{
  "type": "Feature",
  "properties": {
    "gn:admin1_code":"2.0",
    "gn:asciiname":"Kangarouwa",
    "gn:country_code":"NE",
    "gn:dem":304,
    "gn:feature_class":"P",
    "gn:feature_code":"PPL",
    "gn:name":"Kangarouwa",
    "gn:population":0,
    "gn:timezone":"Africa/Niamey",
    "iso:country":"NE",
    "wof:name":"Kangarouwa",
    "wof:placetype":"locality"
},
  "geometry": {"coordinates":[12.63358,13.40117],"type":"Point"}
}