{
  "type": "Feature",
  "properties": {
    "gn:admin1_code":"7.0",
    "gn:asciiname":"Daouda",
    "gn:country_code":"NE",
    "gn:dem":524,
    "gn:feature_class":"P",
    "gn:feature_code":"PPL",
    "gn:name":"Daouda",
    "gn:population":0,
    "gn:timezone":"Africa/Niamey",
    "iso:country":"NE",
    "wof:name":"Daouda",
    "wof:placetype":"locality"
},
  "geometry": {"coordinates":[8.86607,15.04144],"type":"Point"}
}