{
  "type": "Feature",
  "properties": {
    "gn:admin1_code":"3.0",
    "gn:asciiname":"Soroko-Deitegui",
    "gn:country_code":"NE",
    "gn:dem":241,
    "gn:feature_class":"P",
    "gn:feature_code":"PPL",
    "gn:name":"Soroko-De\u00eft\u00e9gui",
    "gn:population":0,
    "gn:timezone":"Africa/Niamey",
    "iso:country":"NE",
    "name:und_x_variant":[
        "Soroko Dey T\u00e9gui",
        "Soroko-De\u00eft\u00e9gui"
    ],
    "wof:name":"Soroko-Deitegui",
    "wof:placetype":"locality"
},
  "geometry": {"coordinates":[3.3016,13.1548],"type":"Point"}
}