{
  "type": "Feature",
  "properties": {
    "gn:admin1_code":"3.0",
    "gn:asciiname":"Koumbo-Koye-Deye",
    "gn:country_code":"NE",
    "gn:dem":220,
    "gn:feature_class":"P",
    "gn:feature_code":"PPL",
    "gn:name":"Koumbo-Koye-D\u00e8ye",
    "gn:population":0,
    "gn:timezone":"Africa/Niamey",
    "iso:country":"NE",
    "name:und_x_variant":[
        "Koumbo-Koy-D\u00e8ye",
        "Koumbo Koy Dey",
        "Koumbo-Koye-D\u00e8ye"
    ],
    "wof:name":"Koumbo-Koye-Deye",
    "wof:placetype":"locality"
},
  "geometry": {"coordinates":[3.14909,12.81173],"type":"Point"}
}