{
  "type": "Feature",
  "properties": {
    "gn:admin1_code":"7.0",
    "gn:asciiname":"Kirla",
    "gn:country_code":"NE",
    "gn:dem":421,
    "gn:feature_class":"P",
    "gn:feature_code":"PPL",
    "gn:name":"Kirla",
    "gn:population":0,
    "gn:timezone":"Africa/Niamey",
    "iso:country":"NE",
    "wof:name":"Kirla",
    "wof:placetype":"locality"
},
  "geometry": {"coordinates":[9.7012,14.084],"type":"Point"}
}