{
  "type": "Feature",
  "properties": {
    "gn:admin1_code":"3.0",
    "gn:asciiname":"Gidadame",
    "gn:country_code":"NE",
    "gn:dem":253,
    "gn:feature_class":"P",
    "gn:feature_code":"PPL",
    "gn:name":"Gidadame",
    "gn:population":0,
    "gn:timezone":"Africa/Niamey",
    "iso:country":"NE",
    "wof:name":"Gidadame",
    "wof:placetype":"locality"
},
  "geometry": {"coordinates":[4.04574,12.97981],"type":"Point"}
}