{
  "type": "Feature",
  "properties": {
    "gn:admin1_code":"2.0",
    "gn:asciiname":"Mankawri",
    "gn:country_code":"NE",
    "gn:dem":313,
    "gn:feature_class":"P",
    "gn:feature_code":"PPL",
    "gn:name":"Mankawri",
    "gn:population":0,
    "gn:timezone":"Africa/Niamey",
    "iso:country":"NE",
    "wof:name":"Mankawri",
    "wof:placetype":"locality"
},
  "geometry": {"coordinates":[12.28451,13.10725],"type":"Point"}
}