{
  "type": "Feature",
  "properties": {
    "gn:admin1_code":"9.0",
    "gn:asciiname":"Lougadian",
    "gn:country_code":"NE",
    "gn:dem":223,
    "gn:feature_class":"P",
    "gn:feature_code":"PPL",
    "gn:name":"Lougadian",
    "gn:population":0,
    "gn:timezone":"Africa/Niamey",
    "iso:country":"NE",
    "name:und_x_variant":[
        "Lougadyam",
        "Lougadian"
    ],
    "wof:name":"Lougadian",
    "wof:placetype":"locality"
},
  "geometry": {"coordinates":[1.98057,13.47464],"type":"Point"}
}