{
  "type": "Feature",
  "properties": {
    "gn:admin1_code":"7.0",
    "gn:asciiname":"Guidan Rigo",
    "gn:country_code":"NE",
    "gn:dem":469,
    "gn:feature_class":"P",
    "gn:feature_code":"PPL",
    "gn:name":"Guidan Rigo",
    "gn:population":0,
    "gn:timezone":"Africa/Niamey",
    "iso:country":"NE",
    "wof:name":"Guidan Rigo",
    "wof:placetype":"locality"
},
  "geometry": {"coordinates":[8.3855,14.6348],"type":"Point"}
}