{
  "type": "Feature",
  "properties": {
    "gn:admin1_code":"3.0",
    "gn:asciiname":"Tombo Guerba",
    "gn:country_code":"NE",
    "gn:dem":218,
    "gn:feature_class":"P",
    "gn:feature_code":"PPL",
    "gn:name":"Tombo Guerba",
    "gn:population":0,
    "gn:timezone":"Africa/Niamey",
    "iso:country":"NE",
    "wof:name":"Tombo Guerba",
    "wof:placetype":"locality"
},
  "geometry": {"coordinates":[3.26591,12.37437],"type":"Point"}
}