{
  "type": "Feature",
  "properties": {
    "gn:admin1_code":"3.0",
    "gn:asciiname":"Massama",
    "gn:country_code":"NE",
    "gn:dem":192,
    "gn:feature_class":"P",
    "gn:feature_code":"PPL",
    "gn:name":"Massama",
    "gn:population":0,
    "gn:timezone":"Africa/Niamey",
    "iso:country":"NE",
    "wof:name":"Massama",
    "wof:placetype":"locality"
},
  "geometry": {"coordinates":[3.64874,12.70418],"type":"Point"}
}