{
  "type": "Feature",
  "properties": {
    "gn:admin1_code":"4.0",
    "gn:asciiname":"Aladji Arou",
    "gn:country_code":"NE",
    "gn:dem":324,
    "gn:feature_class":"P",
    "gn:feature_code":"PPL",
    "gn:name":"Aladji Arou",
    "gn:population":0,
    "gn:timezone":"Africa/Niamey",
    "iso:country":"NE",
    "name:und_x_variant":[
        "Alhadji Arou",
        "Aladji Arou"
    ],
    "wof:name":"Aladji Arou",
    "wof:placetype":"locality"
},
  "geometry": {"coordinates":[6.69646,13.62158],"type":"Point"}
}