{
  "type": "Feature",
  "properties": {
    "gn:admin1_code":"2.0",
    "gn:asciiname":"Boula Berma",
    "gn:country_code":"NE",
    "gn:dem":353,
    "gn:feature_class":"P",
    "gn:feature_code":"PPL",
    "gn:name":"Boula B\u00e9rma",
    "gn:population":0,
    "gn:timezone":"Africa/Niamey",
    "iso:country":"NE",
    "wof:name":"Boula Berma",
    "wof:placetype":"locality"
},
  "geometry": {"coordinates":[10.71169,13.38078],"type":"Point"}
}