{
  "type": "Feature",
  "properties": {
    "gn:admin1_code":"9.0",
    "gn:asciiname":"Sinder",
    "gn:country_code":"NE",
    "gn:dem":215,
    "gn:feature_class":"P",
    "gn:feature_code":"PPL",
    "gn:name":"Sind\u00e8r",
    "gn:population":0,
    "gn:timezone":"Africa/Niamey",
    "iso:country":"NE",
    "name:deu_x_preferred":[
        "Sinder"
    ],
    "name:ita_x_preferred":[
        "Sinder"
    ],
    "name:ron_x_preferred":[
        "Sinder"
    ],
    "name:spa_x_preferred":[
        "Sinder"
    ],
    "name:und_x_variant":[
        "Zinder",
        "Sind\u00e8r"
    ],
    "wof:name":"Sinder",
    "wof:placetype":"locality"
},
  "geometry": {"coordinates":[1.33022,14.23916],"type":"Point"}
}