{
  "type": "Feature",
  "properties": {
    "gn:admin1_code":"4.0",
    "gn:asciiname":"Guidan Nakaora",
    "gn:country_code":"NE",
    "gn:dem":451,
    "gn:feature_class":"P",
    "gn:feature_code":"PPL",
    "gn:name":"Guidan Nakaora",
    "gn:population":0,
    "gn:timezone":"Africa/Niamey",
    "iso:country":"NE",
    "wof:name":"Guidan Nakaora",
    "wof:placetype":"locality"
},
  "geometry": {"coordinates":[7.84476,14.27357],"type":"Point"}
}