{
  "type": "Feature",
  "properties": {
    "gn:admin1_code":"4.0",
    "gn:asciiname":"Goda",
    "gn:country_code":"NE",
    "gn:dem":350,
    "gn:feature_class":"P",
    "gn:feature_code":"PPL",
    "gn:name":"Goda",
    "gn:population":0,
    "gn:timezone":"Africa/Niamey",
    "iso:country":"NE",
    "wof:name":"Goda",
    "wof:placetype":"locality"
},
  "geometry": {"coordinates":[6.81111,13.56349],"type":"Point"}
}