{
  "type": "Feature",
  "properties": {
    "gn:admin1_code":"7.0",
    "gn:asciiname":"Angoal Aya",
    "gn:country_code":"NE",
    "gn:dem":364,
    "gn:feature_class":"P",
    "gn:feature_code":"PPL",
    "gn:name":"Angoal Aya",
    "gn:population":0,
    "gn:timezone":"Africa/Niamey",
    "iso:country":"NE",
    "wof:name":"Angoal Aya",
    "wof:placetype":"locality"
},
  "geometry": {"coordinates":[9.51001,12.89653],"type":"Point"}
}