{
  "type": "Feature",
  "properties": {
    "gn:admin1_code":"7.0",
    "gn:asciiname":"Zougao",
    "gn:country_code":"NE",
    "gn:dem":445,
    "gn:feature_class":"P",
    "gn:feature_code":"PPL",
    "gn:name":"Zougao",
    "gn:population":0,
    "gn:timezone":"Africa/Niamey",
    "iso:country":"NE",
    "wof:name":"Zougao",
    "wof:placetype":"locality"
},
  "geometry": {"coordinates":[7.68915,14.70594],"type":"Point"}
}