{
  "type": "Feature",
  "properties": {
    "gn:admin1_code":"3.0",
    "gn:asciiname":"Waze",
    "gn:country_code":"NE",
    "gn:dem":223,
    "gn:feature_class":"P",
    "gn:feature_code":"PPL",
    "gn:name":"Waz\u00e9",
    "gn:population":0,
    "gn:timezone":"Africa/Niamey",
    "iso:country":"NE",
    "name:ara_x_preferred":[
        "\u0648\u064a\u0632"
    ],
    "name:cat_x_preferred":[
        "Waze"
    ],
    "name:ces_x_preferred":[
        "Waze"
    ],
    "name:deu_x_preferred":[
        "Waze"
    ],
    "name:est_x_preferred":[
        "Waze"
    ],
    "name:fas_x_preferred":[
        "\u0648\u06cc\u0632"
    ],
    "name:fin_x_preferred":[
        "Waze"
    ],
    "name:fra_x_preferred":[
        "Waze"
    ],
    "name:heb_x_preferred":[
        "Waze"
    ],
    "name:hun_x_preferred":[
        "Waze"
    ],
    "name:ind_x_preferred":[
        "Waze"
    ],
    "name:ita_x_preferred":[
        "Waze"
    ],
    "name:jpn_x_preferred":[
        "Waze"
    ],
    "name:kor_x_preferred":[
        "\uc6e8\uc774\uc988"
    ],
    "name:lav_x_preferred":[
        "Waze"
    ],
    "name:msa_x_preferred":[
        "Waze"
    ],
    "name:nld_x_preferred":[
        "Waze"
    ],
    "name:por_x_preferred":[
        "Waze"
    ],
    "name:rus_x_preferred":[
        "Waze"
    ],
    "name:slk_x_preferred":[
        "Waze"
    ],
    "name:spa_x_preferred":[
        "Waze"
    ],
    "name:tur_x_preferred":[
        "Waze"
    ],
    "name:ukr_x_preferred":[
        "Waze"
    ],
    "wof:name":"Waze",
    "wof:placetype":"locality"
},
  "geometry": {"coordinates":[3.16055,13.5294],"type":"Point"}
}