{
  "type": "Feature",
  "properties": {
    "gn:admin1_code":"9.0",
    "gn:asciiname":"Dogaga",
    "gn:country_code":"NE",
    "gn:dem":264,
    "gn:feature_class":"P",
    "gn:feature_code":"PPL",
    "gn:name":"Dogaga",
    "gn:population":0,
    "gn:timezone":"Africa/Niamey",
    "iso:country":"NE",
    "wof:name":"Dogaga",
    "wof:placetype":"locality"
},
  "geometry": {"coordinates":[3.6697,15.0687],"type":"Point"}
}