{
  "type": "Feature",
  "properties": {
    "gn:admin1_code":"6.0",
    "gn:asciiname":"Tira",
    "gn:country_code":"NE",
    "gn:dem":268,
    "gn:feature_class":"P",
    "gn:feature_code":"PPL",
    "gn:name":"Tira",
    "gn:population":0,
    "gn:timezone":"Africa/Niamey",
    "iso:country":"NE",
    "name:ceb_x_preferred":[
        "Tira"
    ],
    "name:ces_x_preferred":[
        "Tira"
    ],
    "name:deu_x_preferred":[
        "Tira"
    ],
    "name:fra_x_preferred":[
        "Tira"
    ],
    "name:heb_x_preferred":[
        "\u05d8\u05d9\u05e8\u05d4"
    ],
    "name:ita_x_preferred":[
        "Tira"
    ],
    "name:lav_x_preferred":[
        "Tira"
    ],
    "name:nld_x_preferred":[
        "Tira"
    ],
    "name:oss_x_preferred":[
        "\u0422\u0438\u0440\u0430"
    ],
    "name:por_x_preferred":[
        "Tira"
    ],
    "name:rus_x_preferred":[
        "\u0422\u0438\u0440\u0430"
    ],
    "name:spa_x_preferred":[
        "Tira"
    ],
    "name:swe_x_preferred":[
        "Tira"
    ],
    "wof:name":"Tira",
    "wof:placetype":"locality"
},
  "geometry": {"coordinates":[4.92568,14.02649],"type":"Point"}
}