{
  "type": "Feature",
  "properties": {
    "gn:admin1_code":"7.0",
    "gn:asciiname":"Gagawa",
    "gn:country_code":"NE",
    "gn:dem":511,
    "gn:feature_class":"P",
    "gn:feature_code":"PPL",
    "gn:name":"Gagawa",
    "gn:population":0,
    "gn:timezone":"Africa/Niamey",
    "iso:country":"NE",
    "name:und_x_variant":[
        "Gagaoua",
        "Gagawa"
    ],
    "wof:name":"Gagawa",
    "wof:placetype":"locality"
},
  "geometry": {"coordinates":[8.62784,14.72256],"type":"Point"}
}