{
  "type": "Feature",
  "properties": {
    "gn:admin1_code":"9.0",
    "gn:asciiname":"Zouragen",
    "gn:country_code":"NE",
    "gn:dem":293,
    "gn:feature_class":"P",
    "gn:feature_code":"PPL",
    "gn:name":"Zourag\u00e8n",
    "gn:population":0,
    "gn:timezone":"Africa/Niamey",
    "iso:country":"NE",
    "name:und_x_variant":[
        "Zouragu\u00e8n",
        "Zourag\u00e8n"
    ],
    "wof:name":"Zouragen",
    "wof:placetype":"locality"
},
  "geometry": {"coordinates":[3.0203,14.3921],"type":"Point"}
}