{
  "type": "Feature",
  "properties": {
    "gn:admin1_code":"9.0",
    "gn:asciiname":"Kanda",
    "gn:country_code":"NE",
    "gn:dem":221,
    "gn:feature_class":"P",
    "gn:feature_code":"PPL",
    "gn:name":"Kanda",
    "gn:population":0,
    "gn:timezone":"Africa/Niamey",
    "iso:country":"NE",
    "name:cat_x_preferred":[
        "Kanda"
    ],
    "name:ceb_x_preferred":[
        "Kanda"
    ],
    "name:deu_x_preferred":[
        "Kanda"
    ],
    "name:epo_x_preferred":[
        "Kanda"
    ],
    "name:fas_x_preferred":[
        "\u06a9\u0627\u0646\u062f\u0627"
    ],
    "name:fra_x_preferred":[
        "Kanda"
    ],
    "name:new_x_preferred":[
        "\u0915\u093e\u0901\u0921\u093e \u0917\u093e\u0935\u093f\u0938"
    ],
    "name:por_x_preferred":[
        "Kanda"
    ],
    "name:rus_x_preferred":[
        "\u041a\u0430\u043d\u0434\u0430"
    ],
    "name:swa_x_preferred":[
        "Kanda"
    ],
    "name:swe_x_preferred":[
        "Kanda"
    ],
    "name:ukr_x_preferred":[
        "\u041a\u0430\u043d\u0434\u0430"
    ],
    "wof:name":"Kanda",
    "wof:placetype":"locality"
},
  "geometry": {"coordinates":[2.22605,14.13046],"type":"Point"}
}