{
  "type": "Feature",
  "properties": {
    "gn:admin1_code":"6.0",
    "gn:asciiname":"Mararafi",
    "gn:country_code":"NE",
    "gn:dem":377,
    "gn:feature_class":"P",
    "gn:feature_code":"PPL",
    "gn:name":"Mararafi",
    "gn:population":0,
    "gn:timezone":"Africa/Niamey",
    "iso:country":"NE",
    "wof:name":"Mararafi",
    "wof:placetype":"locality"
},
  "geometry": {"coordinates":[5.8123,14.2662],"type":"Point"}
}