{
  "type": "Feature",
  "properties": {
    "gn:admin1_code":"4.0",
    "gn:asciiname":"Guidan Kassagui",
    "gn:country_code":"NE",
    "gn:dem":381,
    "gn:feature_class":"P",
    "gn:feature_code":"PPL",
    "gn:name":"Guidan Kassagui",
    "gn:population":0,
    "gn:timezone":"Africa/Niamey",
    "iso:country":"NE",
    "wof:name":"Guidan Kassagui",
    "wof:placetype":"locality"
},
  "geometry": {"coordinates":[7.1761,13.60605],"type":"Point"}
}