{
  "type": "Feature",
  "properties": {
    "gn:admin1_code":"6.0",
    "gn:asciiname":"Kao Data",
    "gn:country_code":"NE",
    "gn:dem":334,
    "gn:feature_class":"P",
    "gn:feature_code":"PPL",
    "gn:name":"Kao Data",
    "gn:population":0,
    "gn:timezone":"Africa/Niamey",
    "iso:country":"NE",
    "wof:name":"Kao Data",
    "wof:placetype":"locality"
},
  "geometry": {"coordinates":[4.8158,15.2875],"type":"Point"}
}