{
  "type": "Feature",
  "properties": {
    "gn:admin1_code":"6.0",
    "gn:asciiname":"Koso",
    "gn:country_code":"NE",
    "gn:dem":515,
    "gn:feature_class":"P",
    "gn:feature_code":"PPL",
    "gn:name":"Koso",
    "gn:population":0,
    "gn:timezone":"Africa/Niamey",
    "iso:country":"NE",
    "name:ceb_x_preferred":[
        "Koso"
    ],
    "name:swe_x_preferred":[
        "Koso"
    ],
    "wof:name":"Koso",
    "wof:placetype":"locality"
},
  "geometry": {"coordinates":[6.02477,14.54722],"type":"Point"}
}