{
  "type": "Feature",
  "properties": {
    "gn:admin1_code":"3.0",
    "gn:asciiname":"Sakari",
    "gn:country_code":"NE",
    "gn:dem":212,
    "gn:feature_class":"P",
    "gn:feature_code":"PPL",
    "gn:name":"Sakari",
    "gn:population":0,
    "gn:timezone":"Africa/Niamey",
    "iso:country":"NE",
    "name:fin_x_preferred":[
        "Sakari"
    ],
    "name:fra_x_preferred":[
        "Sakari"
    ],
    "wof:name":"Sakari",
    "wof:placetype":"locality"
},
  "geometry": {"coordinates":[4.02111,13.11737],"type":"Point"}
}