{
  "type": "Feature",
  "properties": {
    "gn:admin1_code":"3.0",
    "gn:asciiname":"Foulanzam",
    "gn:country_code":"NE",
    "gn:dem":198,
    "gn:feature_class":"P",
    "gn:feature_code":"PPL",
    "gn:name":"Foulanzam",
    "gn:population":0,
    "gn:timezone":"Africa/Niamey",
    "iso:country":"NE",
    "name:und_x_variant":[
        "Foulanza",
        "Foulanzam"
    ],
    "wof:name":"Foulanzam",
    "wof:placetype":"locality"
},
  "geometry": {"coordinates":[2.8809,13.3276],"type":"Point"}
}