{
  "type": "Feature",
  "properties": {
    "gn:admin1_code":"3.0",
    "gn:asciiname":"Waje",
    "gn:country_code":"NE",
    "gn:dem":274,
    "gn:feature_class":"P",
    "gn:feature_code":"PPL",
    "gn:name":"Waj\u00e9",
    "gn:population":0,
    "gn:timezone":"Africa/Niamey",
    "iso:country":"NE",
    "name:fra_x_preferred":[
        "Waje"
    ],
    "name:vie_x_preferred":[
        "Waje"
    ],
    "name:yor_x_preferred":[
        "Waje"
    ],
    "wof:name":"Waje",
    "wof:placetype":"locality"
},
  "geometry": {"coordinates":[4.24315,14.24458],"type":"Point"}
}