{
  "type": "Feature",
  "properties": {
    "gn:admin1_code":"2.0",
    "gn:asciiname":"Lawan Adjiri",
    "gn:country_code":"NE",
    "gn:dem":335,
    "gn:feature_class":"P",
    "gn:feature_code":"PPL",
    "gn:name":"Lawan Adjiri",
    "gn:population":0,
    "gn:timezone":"Africa/Niamey",
    "iso:country":"NE",
    "wof:name":"Lawan Adjiri",
    "wof:placetype":"locality"
},
  "geometry": {"coordinates":[11.7896,13.3584],"type":"Point"}
}