{
  "type": "Feature",
  "properties": {
    "gn:admin1_code":"9.0",
    "gn:asciiname":"Dioubourga",
    "gn:country_code":"NE",
    "gn:dem":223,
    "gn:feature_class":"P",
    "gn:feature_code":"PPL",
    "gn:name":"Dioubourga",
    "gn:population":0,
    "gn:timezone":"Africa/Niamey",
    "iso:country":"NE",
    "name:und_x_variant":[
        "Guibourga",
        "Djibourga",
        "Dioubourga",
        "Dyibourga"
    ],
    "wof:name":"Dioubourga",
    "wof:placetype":"locality"
},
  "geometry": {"coordinates":[1.31793,13.86465],"type":"Point"}
}