{
  "type": "Feature",
  "properties": {
    "gn:admin1_code":"9.0",
    "gn:asciiname":"Tiraou Fandou",
    "gn:country_code":"NE",
    "gn:dem":231,
    "gn:feature_class":"P",
    "gn:feature_code":"PPL",
    "gn:name":"Tiraou Fandou",
    "gn:population":0,
    "gn:timezone":"Africa/Niamey",
    "iso:country":"NE",
    "name:und_x_variant":[
        "Tirofondou",
        "Tiraou Fandou"
    ],
    "wof:name":"Tiraou Fandou",
    "wof:placetype":"locality"
},
  "geometry": {"coordinates":[2.2884,13.1134],"type":"Point"}
}