{
  "type": "Feature",
  "properties": {
    "gn:admin1_code":"8.0",
    "gn:asciiname":"Debon",
    "gn:country_code":"NE",
    "gn:dem":216,
    "gn:feature_class":"P",
    "gn:feature_code":"PPL",
    "gn:name":"Debon",
    "gn:population":0,
    "gn:timezone":"Africa/Niamey",
    "iso:country":"NE",
    "wof:name":"Debon",
    "wof:placetype":"locality"
},
  "geometry": {"coordinates":[2.31667,13.25],"type":"Point"}
}