{
  "type": "Feature",
  "properties": {
    "gn:admin1_code":"6.0",
    "gn:asciiname":"Tale-Zenguina",
    "gn:country_code":"NE",
    "gn:dem":263,
    "gn:feature_class":"P",
    "gn:feature_code":"PPL",
    "gn:name":"Tal\u00e9-Zenguina",
    "gn:population":0,
    "gn:timezone":"Africa/Niamey",
    "iso:country":"NE",
    "name:und_x_variant":[
        "Tal\u00e9-Zengina",
        "Tal\u00e9-Zenguina"
    ],
    "wof:name":"Tale-Zenguina",
    "wof:placetype":"locality"
},
  "geometry": {"coordinates":[5.22909,13.95399],"type":"Point"}
}