{
  "type": "Feature",
  "properties": {
    "gn:admin1_code":"8.0",
    "gn:asciiname":"Bomberi Kwara",
    "gn:cc2":"NE",
    "gn:country_code":"NE",
    "gn:dem":197,
    "gn:feature_class":"P",
    "gn:feature_code":"PPL",
    "gn:name":"Bomb\u00e9ri Kwara",
    "gn:population":0,
    "gn:timezone":"Africa/Niamey",
    "iso:country":"NE",
    "name:und_x_variant":[
        "Bomberi-Koara",
        "Bomb\u00e9ri Kwara"
    ],
    "wof:name":"Bomberi Kwara",
    "wof:placetype":"locality"
},
  "geometry": {"coordinates":[2.81667,13.33333],"type":"Point"}
}