{
  "type": "Feature",
  "properties": {
    "gn:admin1_code":"6.0",
    "gn:asciiname":"Roura",
    "gn:country_code":"NE",
    "gn:dem":390,
    "gn:feature_class":"P",
    "gn:feature_code":"PPL",
    "gn:name":"Roura",
    "gn:population":0,
    "gn:timezone":"Africa/Niamey",
    "iso:country":"NE",
    "wof:name":"Roura",
    "wof:placetype":"locality"
},
  "geometry": {"coordinates":[6.47635,14.44312],"type":"Point"}
}