{
  "type": "Feature",
  "properties": {
    "gn:admin1_code":"9.0",
    "gn:asciiname":"Oulendian",
    "gn:country_code":"NE",
    "gn:dem":238,
    "gn:feature_class":"P",
    "gn:feature_code":"PPL",
    "gn:name":"Oulendian",
    "gn:population":0,
    "gn:timezone":"Africa/Niamey",
    "iso:country":"NE",
    "name:und_x_variant":[
        "Oulendyan"
    ],
    "wof:name":"Oulendian",
    "wof:placetype":"locality"
},
  "geometry": {"coordinates":[1.89138,13.2848],"type":"Point"}
}