{
  "type": "Feature",
  "properties": {
    "gn:admin1_code":"2.0",
    "gn:asciiname":"Fiediga",
    "gn:country_code":"NE",
    "gn:dem":299,
    "gn:feature_class":"P",
    "gn:feature_code":"PPL",
    "gn:name":"Fi\u00e9diga",
    "gn:population":0,
    "gn:timezone":"Africa/Niamey",
    "iso:country":"NE",
    "name:und_x_variant":[
        "Fi\u00e8daga",
        "Fi\u00e9diga"
    ],
    "wof:name":"Fiediga",
    "wof:placetype":"locality"
},
  "geometry": {"coordinates":[13.05059,13.54707],"type":"Point"}
}