{
  "type": "Feature",
  "properties": {
    "gn:admin1_code":"2.0",
    "gn:asciiname":"Garyo",
    "gn:country_code":"NE",
    "gn:dem":348,
    "gn:feature_class":"P",
    "gn:feature_code":"PPL",
    "gn:name":"Garyo",
    "gn:population":0,
    "gn:timezone":"Africa/Niamey",
    "iso:country":"NE",
    "wof:name":"Garyo",
    "wof:placetype":"locality"
},
  "geometry": {"coordinates":[10.85863,13.61079],"type":"Point"}
}