{
  "type": "Feature",
  "properties": {
    "gn:admin1_code":"9.0",
    "gn:asciiname":"Tassa",
    "gn:country_code":"NE",
    "gn:dem":251,
    "gn:feature_class":"P",
    "gn:feature_code":"PPL",
    "gn:name":"Tassa",
    "gn:population":0,
    "gn:timezone":"Africa/Niamey",
    "iso:country":"NE",
    "name:mar_x_preferred":[
        "\u0924\u093e\u0936\u093e"
    ],
    "wof:name":"Tassa",
    "wof:placetype":"locality"
},
  "geometry": {"coordinates":[1.66699,14.31581],"type":"Point"}
}