{
  "type": "Feature",
  "properties": {
    "gn:admin1_code":"7.0",
    "gn:asciiname":"Garine Jebji",
    "gn:country_code":"NE",
    "gn:dem":516,
    "gn:feature_class":"P",
    "gn:feature_code":"PPL",
    "gn:name":"Garine J\u00e8bji",
    "gn:population":0,
    "gn:timezone":"Africa/Niamey",
    "iso:country":"NE",
    "wof:name":"Garine Jebji",
    "wof:placetype":"locality"
},
  "geometry": {"coordinates":[8.86063,15.06652],"type":"Point"}
}