{
  "type": "Feature",
  "properties": {
    "gn:admin1_code":"1.0",
    "gn:asciiname":"Tekokei",
    "gn:country_code":"NE",
    "gn:dem":1430,
    "gn:feature_class":"P",
    "gn:feature_code":"PPL",
    "gn:name":"T\u00e9koke\u00ef",
    "gn:population":0,
    "gn:timezone":"Africa/Niamey",
    "iso:country":"NE",
    "wof:name":"Tekokei",
    "wof:placetype":"locality"
},
  "geometry": {"coordinates":[8.7582,17.6449],"type":"Point"}
}