{
  "type": "Feature",
  "properties": {
    "gn:admin1_code":"8.0",
    "gn:asciiname":"Tioure Fandou",
    "gn:country_code":"NE",
    "gn:dem":210,
    "gn:feature_class":"P",
    "gn:feature_code":"PPL",
    "gn:name":"Tiour\u00e9 Fandou",
    "gn:population":0,
    "gn:timezone":"Africa/Niamey",
    "iso:country":"NE",
    "wof:name":"Tioure Fandou",
    "wof:placetype":"locality"
},
  "geometry": {"coordinates":[2.1775,13.4625],"type":"Point"}
}