{
  "type": "Feature",
  "properties": {
    "gn:admin1_code":"2.0",
    "gn:asciiname":"Kadial",
    "gn:country_code":"NE",
    "gn:dem":346,
    "gn:feature_class":"P",
    "gn:feature_code":"PPL",
    "gn:name":"Kadial",
    "gn:population":0,
    "gn:timezone":"Africa/Niamey",
    "iso:country":"NE",
    "wof:name":"Kadial",
    "wof:placetype":"locality"
},
  "geometry": {"coordinates":[11.3392,13.881],"type":"Point"}
}