{
  "type": "Feature",
  "properties": {
    "gn:admin1_code":"9.0",
    "gn:asciiname":"Bohi Tondi",
    "gn:country_code":"NE",
    "gn:dem":248,
    "gn:feature_class":"P",
    "gn:feature_code":"PPL",
    "gn:name":"Bohi Tondi",
    "gn:population":0,
    "gn:timezone":"Africa/Niamey",
    "iso:country":"NE",
    "name:und_x_variant":[
        "Bohi-Tonndi",
        "Bohi Tondi"
    ],
    "wof:name":"Bohi Tondi",
    "wof:placetype":"locality"
},
  "geometry": {"coordinates":[1.29015,13.75263],"type":"Point"}
}