{
  "type": "Feature",
  "properties": {
    "gn:admin1_code":"4.0",
    "gn:asciiname":"Guidan Bako Chawey",
    "gn:country_code":"NE",
    "gn:dem":399,
    "gn:feature_class":"P",
    "gn:feature_code":"PPL",
    "gn:name":"Guidan Bako Chawey",
    "gn:population":0,
    "gn:timezone":"Africa/Niamey",
    "iso:country":"NE",
    "wof:name":"Guidan Bako Chawey",
    "wof:placetype":"locality"
},
  "geometry": {"coordinates":[7.66381,13.875],"type":"Point"}
}