{
  "type": "Feature",
  "properties": {
    "gn:admin1_code":"8.0",
    "gn:asciiname":"Boukoki",
    "gn:country_code":"NE",
    "gn:dem":214,
    "gn:feature_class":"P",
    "gn:feature_code":"PPL",
    "gn:name":"Boukoki",
    "gn:population":0,
    "gn:timezone":"Africa/Niamey",
    "iso:country":"NE",
    "wof:name":"Boukoki",
    "wof:placetype":"locality"
},
  "geometry": {"coordinates":[2.1194,13.5306],"type":"Point"}
}