{
  "type": "Feature",
  "properties": {
    "gn:admin1_code":"7.0",
    "gn:asciiname":"Dan Barto",
    "gn:country_code":"NE",
    "gn:dem":436,
    "gn:feature_class":"P",
    "gn:feature_code":"PPL",
    "gn:name":"Dan Barto",
    "gn:population":0,
    "gn:timezone":"Africa/Niamey",
    "iso:country":"NE",
    "wof:name":"Dan Barto",
    "wof:placetype":"locality"
},
  "geometry": {"coordinates":[8.32958,13.18074],"type":"Point"}
}