{
  "type": "Feature",
  "properties": {
    "gn:admin1_code":"6.0",
    "gn:asciiname":"Igayawan",
    "gn:country_code":"NE",
    "gn:dem":385,
    "gn:feature_class":"P",
    "gn:feature_code":"PPL",
    "gn:name":"Igayawan",
    "gn:population":0,
    "gn:timezone":"Africa/Niamey",
    "iso:country":"NE",
    "wof:name":"Igayawan",
    "wof:placetype":"locality"
},
  "geometry": {"coordinates":[6.20486,14.00716],"type":"Point"}
}