{
  "type": "Feature",
  "properties": {
    "gn:admin1_code":"4.0",
    "gn:asciiname":"Tabkin Guine",
    "gn:country_code":"NE",
    "gn:dem":451,
    "gn:feature_class":"P",
    "gn:feature_code":"PPL",
    "gn:name":"Tabkin Guin\u00e9",
    "gn:population":0,
    "gn:timezone":"Africa/Niamey",
    "iso:country":"NE",
    "wof:name":"Tabkin Guine",
    "wof:placetype":"locality"
},
  "geometry": {"coordinates":[8.29092,13.86332],"type":"Point"}
}