{
  "type": "Feature",
  "properties": {
    "gn:admin1_code":"9.0",
    "gn:asciiname":"Naouani",
    "gn:country_code":"NE",
    "gn:dem":204,
    "gn:feature_class":"P",
    "gn:feature_code":"PPL",
    "gn:name":"Naouani",
    "gn:population":0,
    "gn:timezone":"Africa/Niamey",
    "iso:country":"NE",
    "name:und_x_variant":[
        "Nawani"
    ],
    "wof:name":"Naouani",
    "wof:placetype":"locality"
},
  "geometry": {"coordinates":[1.42279,14.22387],"type":"Point"}
}