{
  "type": "Feature",
  "properties": {
    "gn:admin1_code":"9.0",
    "gn:asciiname":"Aila Koubo",
    "gn:country_code":"NE",
    "gn:dem":212,
    "gn:feature_class":"P",
    "gn:feature_code":"PPL",
    "gn:name":"A\u00efla Koubo",
    "gn:population":0,
    "gn:timezone":"Africa/Niamey",
    "iso:country":"NE",
    "wof:name":"Aila Koubo",
    "wof:placetype":"locality"
},
  "geometry": {"coordinates":[1.42217,14.19572],"type":"Point"}
}