{
  "type": "Feature",
  "properties": {
    "gn:admin1_code":"7.0",
    "gn:asciiname":"Drikwa",
    "gn:country_code":"NE",
    "gn:dem":377,
    "gn:feature_class":"P",
    "gn:feature_code":"PPL",
    "gn:name":"Drikwa",
    "gn:population":0,
    "gn:timezone":"Africa/Niamey",
    "iso:country":"NE",
    "name:und_x_variant":[
        "Dirikoua",
        "Dirikoa",
        "Drikwa"
    ],
    "wof:name":"Drikwa",
    "wof:placetype":"locality"
},
  "geometry": {"coordinates":[10.31316,13.62549],"type":"Point"}
}