{
  "type": "Feature",
  "properties": {
    "gn:admin1_code":"4.0",
    "gn:asciiname":"Banyi",
    "gn:country_code":"NE",
    "gn:dem":395,
    "gn:feature_class":"P",
    "gn:feature_code":"PPL",
    "gn:name":"Banyi",
    "gn:population":0,
    "gn:timezone":"Africa/Niamey",
    "iso:country":"NE",
    "wof:name":"Banyi",
    "wof:placetype":"locality"
},
  "geometry": {"coordinates":[7.08636,14.0559],"type":"Point"}
}