{
  "type": "Feature",
  "properties": {
    "gn:admin1_code":"7.0",
    "gn:asciiname":"Gazoura Bougaje",
    "gn:country_code":"NE",
    "gn:dem":465,
    "gn:feature_class":"P",
    "gn:feature_code":"PPL",
    "gn:name":"Gazoura Bougaj\u00e9",
    "gn:population":0,
    "gn:timezone":"Africa/Niamey",
    "iso:country":"NE",
    "wof:name":"Gazoura Bougaje",
    "wof:placetype":"locality"
},
  "geometry": {"coordinates":[8.39556,13.5509],"type":"Point"}
}