{
  "type": "Feature",
  "properties": {
    "gn:admin1_code":"3.0",
    "gn:asciiname":"Noma Kwara",
    "gn:country_code":"NE",
    "gn:dem":228,
    "gn:feature_class":"P",
    "gn:feature_code":"PPL",
    "gn:name":"Noma Kwara",
    "gn:population":0,
    "gn:timezone":"Africa/Niamey",
    "iso:country":"NE",
    "name:und_x_variant":[
        "Noma-Koara",
        "Noma Kwara"
    ],
    "wof:name":"Noma Kwara",
    "wof:placetype":"locality"
},
  "geometry": {"coordinates":[3.33917,12.73565],"type":"Point"}
}