{
  "type": "Feature",
  "properties": {
    "gn:admin1_code":"9.0",
    "gn:asciiname":"Gourlea",
    "gn:country_code":"NE",
    "gn:dem":252,
    "gn:feature_class":"P",
    "gn:feature_code":"PPL",
    "gn:name":"Gourl\u00e9a",
    "gn:population":0,
    "gn:timezone":"Africa/Niamey",
    "iso:country":"NE",
    "wof:name":"Gourlea",
    "wof:placetype":"locality"
},
  "geometry": {"coordinates":[1.12122,13.4481],"type":"Point"}
}