{
  "type": "Feature",
  "properties": {
    "gn:admin1_code":"9.0",
    "gn:asciiname":"Kouara Tegui Kolo",
    "gn:country_code":"NE",
    "gn:dem":213,
    "gn:feature_class":"P",
    "gn:feature_code":"PPL",
    "gn:name":"Kouara T\u00e9gui Kolo",
    "gn:population":0,
    "gn:timezone":"Africa/Niamey",
    "iso:country":"NE",
    "wof:name":"Kouara Tegui Kolo",
    "wof:placetype":"locality"
},
  "geometry": {"coordinates":[1.97815,12.93046],"type":"Point"}
}