{
  "type": "Feature",
  "properties": {
    "gn:admin1_code":"3.0",
    "gn:asciiname":"Kobekaina",
    "gn:country_code":"NE",
    "gn:dem":204,
    "gn:feature_class":"P",
    "gn:feature_code":"PPL",
    "gn:name":"Kobeka\u00efna",
    "gn:population":0,
    "gn:timezone":"Africa/Niamey",
    "iso:country":"NE",
    "name:und_x_variant":[
        "Kob\u00e9 Keyna",
        "Kobeka\u00efna"
    ],
    "wof:name":"Kobekaina",
    "wof:placetype":"locality"
},
  "geometry": {"coordinates":[3.01454,13.51981],"type":"Point"}
}