{
  "type": "Feature",
  "properties": {
    "gn:admin1_code":"4.0",
    "gn:asciiname":"Taouray",
    "gn:country_code":"NE",
    "gn:dem":444,
    "gn:feature_class":"P",
    "gn:feature_code":"PPL",
    "gn:name":"Taouray",
    "gn:population":0,
    "gn:timezone":"Africa/Niamey",
    "iso:country":"NE",
    "wof:name":"Taouray",
    "wof:placetype":"locality"
},
  "geometry": {"coordinates":[7.4558,13.37396],"type":"Point"}
}