{
  "type": "Feature",
  "properties": {
    "gn:admin1_code":"9.0",
    "gn:asciiname":"Falanga",
    "gn:country_code":"NE",
    "gn:dem":221,
    "gn:feature_class":"P",
    "gn:feature_code":"PPL",
    "gn:name":"Falanga",
    "gn:population":0,
    "gn:timezone":"Africa/Niamey",
    "iso:country":"NE",
    "name:bul_x_preferred":[
        "\u0424\u0430\u043b\u0430\u043d\u0433\u0430"
    ],
    "name:ces_x_preferred":[
        "Falanga"
    ],
    "name:deu_x_preferred":[
        "Falanga"
    ],
    "name:hrv_x_preferred":[
        "Falanga"
    ],
    "name:lav_x_preferred":[
        "Falanga"
    ],
    "name:pol_x_preferred":[
        "Falanga"
    ],
    "name:rus_x_preferred":[
        "\u0424\u0430\u043b\u0430\u043d\u0433\u0430"
    ],
    "name:slk_x_preferred":[
        "Falanga"
    ],
    "name:slv_x_preferred":[
        "Falanga"
    ],
    "name:srp_x_preferred":[
        "\u0424\u0430\u043b\u0430\u043d\u0433\u0430"
    ],
    "name:ukr_x_preferred":[
        "\u0424\u0430\u043b\u0430\u043d\u0433\u0430"
    ],
    "name:und_x_variant":[
        "Falenga",
        "Falanga"
    ],
    "wof:name":"Falanga",
    "wof:placetype":"locality"
},
  "geometry": {"coordinates":[2.8061,13.426],"type":"Point"}
}