{
  "type": "Feature",
  "properties": {
    "gn:admin1_code":"9.0",
    "gn:asciiname":"Tiaptey Tondo",
    "gn:country_code":"NE",
    "gn:dem":211,
    "gn:feature_class":"P",
    "gn:feature_code":"PPL",
    "gn:name":"Tiaptey Tondo",
    "gn:population":0,
    "gn:timezone":"Africa/Niamey",
    "iso:country":"NE",
    "name:und_x_variant":[
        "Tiaptey Tonndo",
        "Tyaptey Tondo",
        "Tiaptey Tondo"
    ],
    "wof:name":"Tiaptey Tondo",
    "wof:placetype":"locality"
},
  "geometry": {"coordinates":[1.56313,13.69634],"type":"Point"}
}