{
  "type": "Feature",
  "properties": {
    "gn:admin1_code":"7.0",
    "gn:asciiname":"Toundoukou",
    "gn:country_code":"NE",
    "gn:dem":478,
    "gn:feature_class":"P",
    "gn:feature_code":"PPL",
    "gn:name":"Toundoukou",
    "gn:population":0,
    "gn:timezone":"Africa/Niamey",
    "iso:country":"NE",
    "wof:name":"Toundoukou",
    "wof:placetype":"locality"
},
  "geometry": {"coordinates":[8.46123,14.72893],"type":"Point"}
}