{
  "type": "Feature",
  "properties": {
    "gn:admin1_code":"6.0",
    "gn:asciiname":"Tassara",
    "gn:cc2":"NE",
    "gn:country_code":"NE",
    "gn:dem":366,
    "gn:feature_class":"P",
    "gn:feature_code":"PPL",
    "gn:name":"Tassara",
    "gn:population":0,
    "gn:timezone":"Africa/Niamey",
    "iso:country":"NE",
    "name:deu_x_preferred":[
        "Tassara"
    ],
    "name:ita_x_preferred":[
        "Tassara"
    ],
    "name:msa_x_preferred":[
        "Tassara"
    ],
    "name:ron_x_preferred":[
        "Tassara"
    ],
    "name:spa_x_preferred":[
        "Tassara"
    ],
    "name:und_x_variant":[
        "Tasara",
        "Tassara"
    ],
    "wof:name":"Tassara",
    "wof:placetype":"locality"
},
  "geometry": {"coordinates":[5.64417,16.80472],"type":"Point"}
}