{
  "type": "Feature",
  "properties": {
    "gn:admin1_code":"1.0",
    "gn:asciiname":"Akerebreb",
    "gn:country_code":"NE",
    "gn:dem":882,
    "gn:feature_class":"P",
    "gn:feature_code":"PPL",
    "gn:name":"Akerebreb",
    "gn:population":0,
    "gn:timezone":"Africa/Niamey",
    "iso:country":"NE",
    "wof:name":"Akerebreb",
    "wof:placetype":"locality"
},
  "geometry": {"coordinates":[8.65778,18.05972],"type":"Point"}
}