{
  "type": "Feature",
  "properties": {
    "gn:admin1_code":"9.0",
    "gn:asciiname":"Senoubimpo",
    "gn:country_code":"NE",
    "gn:dem":231,
    "gn:feature_class":"P",
    "gn:feature_code":"PPL",
    "gn:name":"S\u00e9noubimpo",
    "gn:population":0,
    "gn:timezone":"Africa/Niamey",
    "iso:country":"NE",
    "wof:name":"Senoubimpo",
    "wof:placetype":"locality"
},
  "geometry": {"coordinates":[1.91178,13.28388],"type":"Point"}
}