{
  "type": "Feature",
  "properties": {
    "gn:admin1_code":"2.0",
    "gn:asciiname":"Gorodi-Birin",
    "gn:country_code":"NE",
    "gn:dem":299,
    "gn:feature_class":"P",
    "gn:feature_code":"PPL",
    "gn:name":"Gorodi-Birin",
    "gn:population":0,
    "gn:timezone":"Africa/Niamey",
    "iso:country":"NE",
    "wof:name":"Gorodi-Birin",
    "wof:placetype":"locality"
},
  "geometry": {"coordinates":[12.71877,13.45681],"type":"Point"}
}