{
  "type": "Feature",
  "properties": {
    "gn:admin1_code":"7.0",
    "gn:asciiname":"Koren Timnia",
    "gn:country_code":"NE",
    "gn:dem":486,
    "gn:feature_class":"P",
    "gn:feature_code":"PPL",
    "gn:name":"Kor\u00e8n Timnia",
    "gn:population":0,
    "gn:timezone":"Africa/Niamey",
    "iso:country":"NE",
    "wof:name":"Koren Timnia",
    "wof:placetype":"locality"
},
  "geometry": {"coordinates":[9.2221,14.3428],"type":"Point"}
}