{
  "type": "Feature",
  "properties": {
    "gn:admin1_code":"4.0",
    "gn:asciiname":"Makouba",
    "gn:country_code":"NE",
    "gn:dem":469,
    "gn:feature_class":"P",
    "gn:feature_code":"PPL",
    "gn:name":"Makouba",
    "gn:population":0,
    "gn:timezone":"Africa/Niamey",
    "iso:country":"NE",
    "wof:name":"Makouba",
    "wof:placetype":"locality"
},
  "geometry": {"coordinates":[8.20191,13.24862],"type":"Point"}
}