{
  "type": "Feature",
  "properties": {
    "gn:admin1_code":"7.0",
    "gn:asciiname":"Jalkasan",
    "gn:country_code":"NE",
    "gn:dem":481,
    "gn:feature_class":"P",
    "gn:feature_code":"PPL",
    "gn:name":"Jalkasan",
    "gn:population":0,
    "gn:timezone":"Africa/Niamey",
    "iso:country":"NE",
    "name:und_x_variant":[
        "Jalkassan",
        "Jalkasan"
    ],
    "wof:name":"Jalkasan",
    "wof:placetype":"locality"
},
  "geometry": {"coordinates":[8.92431,14.67521],"type":"Point"}
}