{
  "type": "Feature",
  "properties": {
    "gn:admin1_code":"3.0",
    "gn:asciiname":"Loma",
    "gn:country_code":"NE",
    "gn:dem":223,
    "gn:feature_class":"P",
    "gn:feature_code":"PPL",
    "gn:name":"Loma",
    "gn:population":0,
    "gn:timezone":"Africa/Niamey",
    "iso:country":"NE",
    "name:ceb_x_preferred":[
        "Loma"
    ],
    "name:deu_x_preferred":[
        "Loma"
    ],
    "name:fra_x_preferred":[
        "Loma"
    ],
    "name:ita_x_preferred":[
        "Loma"
    ],
    "name:nld_x_preferred":[
        "Loma"
    ],
    "name:pol_x_preferred":[
        "Loma"
    ],
    "name:pus_x_preferred":[
        "\u0644\u0648\u0645\u0647"
    ],
    "name:spa_x_preferred":[
        "Loma"
    ],
    "name:srp_x_preferred":[
        "\u041b\u043e\u043c\u0430"
    ],
    "name:swe_x_preferred":[
        "Loma"
    ],
    "name:ukr_x_preferred":[
        "\u041b\u043e\u043c\u0430"
    ],
    "name:vol_x_preferred":[
        "Loma"
    ],
    "wof:name":"Loma",
    "wof:placetype":"locality"
},
  "geometry": {"coordinates":[4.11469,13.30332],"type":"Point"}
}