{
  "type": "Feature",
  "properties": {
    "gn:admin1_code":"3.0",
    "gn:asciiname":"Kountietari-Ama",
    "gn:country_code":"NE",
    "gn:dem":213,
    "gn:feature_class":"P",
    "gn:feature_code":"PPL",
    "gn:name":"Kounti\u00e9tari-Ama",
    "gn:population":0,
    "gn:timezone":"Africa/Niamey",
    "iso:country":"NE",
    "wof:name":"Kountietari-Ama",
    "wof:placetype":"locality"
},
  "geometry": {"coordinates":[3.4763,13.1432],"type":"Point"}
}