{
  "type": "Feature",
  "properties": {
    "gn:admin1_code":"7.0",
    "gn:asciiname":"Jigaymasaka",
    "gn:country_code":"NE",
    "gn:dem":438,
    "gn:feature_class":"P",
    "gn:feature_code":"PPL",
    "gn:name":"Jigaymasaka",
    "gn:population":0,
    "gn:timezone":"Africa/Niamey",
    "iso:country":"NE",
    "wof:name":"Jigaymasaka",
    "wof:placetype":"locality"
},
  "geometry": {"coordinates":[9.1356,13.7544],"type":"Point"}
}