{
  "type": "Feature",
  "properties": {
    "gn:admin1_code":"3.0",
    "gn:asciiname":"Kalgo",
    "gn:country_code":"NE",
    "gn:dem":275,
    "gn:feature_class":"P",
    "gn:feature_code":"PPL",
    "gn:name":"Kalgo",
    "gn:population":0,
    "gn:timezone":"Africa/Niamey",
    "iso:country":"NE",
    "wof:name":"Kalgo",
    "wof:placetype":"locality"
},
  "geometry": {"coordinates":[3.65,13.83333],"type":"Point"}
}