{
  "type": "Feature",
  "properties": {
    "gn:admin1_code":"4.0",
    "gn:asciiname":"Malam Madi",
    "gn:country_code":"NE",
    "gn:dem":426,
    "gn:feature_class":"P",
    "gn:feature_code":"PPL",
    "gn:name":"M\u00e2lam Madi",
    "gn:population":0,
    "gn:timezone":"Africa/Niamey",
    "iso:country":"NE",
    "name:und_x_variant":[
        "Mal\u00e9me Madi",
        "Dan Bad'ada",
        "M\u00e2lam Madi"
    ],
    "wof:name":"Malam Madi",
    "wof:placetype":"locality"
},
  "geometry": {"coordinates":[8.10792,13.35107],"type":"Point"}
}