{
  "type": "Feature",
  "properties": {
    "gn:admin1_code":"6.0",
    "gn:asciiname":"Falalia",
    "gn:country_code":"NE",
    "gn:dem":383,
    "gn:feature_class":"P",
    "gn:feature_code":"PPL",
    "gn:name":"Falalia",
    "gn:population":0,
    "gn:timezone":"Africa/Niamey",
    "iso:country":"NE",
    "wof:name":"Falalia",
    "wof:placetype":"locality"
},
  "geometry": {"coordinates":[6.15197,14.37527],"type":"Point"}
}