{
  "type": "Feature",
  "properties": {
    "gn:admin1_code":"2.0",
    "gn:asciiname":"Biri Boula",
    "gn:country_code":"NE",
    "gn:dem":320,
    "gn:feature_class":"P",
    "gn:feature_code":"PPL",
    "gn:name":"Biri Boula",
    "gn:population":0,
    "gn:timezone":"Africa/Niamey",
    "iso:country":"NE",
    "wof:name":"Biri Boula",
    "wof:placetype":"locality"
},
  "geometry": {"coordinates":[12.35497,13.15916],"type":"Point"}
}