{
  "type": "Feature",
  "properties": {
    "gn:admin1_code":"9.0",
    "gn:asciiname":"Goubogou",
    "gn:country_code":"NE",
    "gn:dem":219,
    "gn:feature_class":"P",
    "gn:feature_code":"PPL",
    "gn:name":"Goubogou",
    "gn:population":0,
    "gn:timezone":"Africa/Niamey",
    "iso:country":"NE",
    "name:und_x_variant":[
        "Goubongou",
        "Goubogou"
    ],
    "wof:name":"Goubogou",
    "wof:placetype":"locality"
},
  "geometry": {"coordinates":[1.64006,13.03782],"type":"Point"}
}