{
  "type": "Feature",
  "properties": {
    "gn:admin1_code":"3.0",
    "gn:asciiname":"Kargui Bangou",
    "gn:country_code":"NE",
    "gn:dem":204,
    "gn:feature_class":"P",
    "gn:feature_code":"PPL",
    "gn:name":"Kargui Bangou",
    "gn:population":0,
    "gn:timezone":"Africa/Niamey",
    "iso:country":"NE",
    "name:und_x_variant":[
        "Kargi Bangou",
        "Karjibengu",
        "Kardjibangou",
        "Karjibengou",
        "Kargui Bangou"
    ],
    "wof:name":"Kargui Bangou",
    "wof:placetype":"locality"
},
  "geometry": {"coordinates":[3.5044,12.94972],"type":"Point"}
}