{
  "type": "Feature",
  "properties": {
    "gn:admin1_code":"7.0",
    "gn:asciiname":"Dan Godi",
    "gn:country_code":"NE",
    "gn:dem":437,
    "gn:feature_class":"P",
    "gn:feature_code":"PPL",
    "gn:name":"Dan Godi",
    "gn:population":0,
    "gn:timezone":"Africa/Niamey",
    "iso:country":"NE",
    "wof:name":"Dan Godi",
    "wof:placetype":"locality"
},
  "geometry": {"coordinates":[7.57121,14.7801],"type":"Point"}
}