{
  "type": "Feature",
  "properties": {
    "gn:admin1_code":"9.0",
    "gn:asciiname":"Dinki",
    "gn:country_code":"NE",
    "gn:dem":262,
    "gn:feature_class":"P",
    "gn:feature_code":"PPL",
    "gn:name":"Dinki",
    "gn:population":0,
    "gn:timezone":"Africa/Niamey",
    "iso:country":"NE",
    "wof:name":"Dinki",
    "wof:placetype":"locality"
},
  "geometry": {"coordinates":[2.0173,13.6905],"type":"Point"}
}