{
  "type": "Feature",
  "properties": {
    "gn:admin1_code":"4.0",
    "gn:asciiname":"Garin Labou",
    "gn:country_code":"NE",
    "gn:dem":390,
    "gn:feature_class":"P",
    "gn:feature_code":"PPL",
    "gn:name":"Garin Labou",
    "gn:population":0,
    "gn:timezone":"Africa/Niamey",
    "iso:country":"NE",
    "wof:name":"Garin Labou",
    "wof:placetype":"locality"
},
  "geometry": {"coordinates":[6.87846,13.35329],"type":"Point"}
}