{
  "type": "Feature",
  "properties": {
    "gn:admin1_code":"4.0",
    "gn:asciiname":"Taka Tieme",
    "gn:country_code":"NE",
    "gn:dem":330,
    "gn:feature_class":"P",
    "gn:feature_code":"PPL",
    "gn:name":"Taka Ti\u00e9m\u00e9",
    "gn:population":0,
    "gn:timezone":"Africa/Niamey",
    "iso:country":"NE",
    "wof:name":"Taka Tieme",
    "wof:placetype":"locality"
},
  "geometry": {"coordinates":[6.66424,13.54748],"type":"Point"}
}