{
  "type": "Feature",
  "properties": {
    "gn:admin1_code":"6.0",
    "gn:asciiname":"Abilo",
    "gn:country_code":"NE",
    "gn:dem":284,
    "gn:feature_class":"P",
    "gn:feature_code":"PPL",
    "gn:name":"Abilo",
    "gn:population":0,
    "gn:timezone":"Africa/Niamey",
    "iso:country":"NE",
    "wof:name":"Abilo",
    "wof:placetype":"locality"
},
  "geometry": {"coordinates":[5.301,14.0328],"type":"Point"}
}