{
  "type": "Feature",
  "properties": {
    "gn:admin1_code":"7.0",
    "gn:asciiname":"Garine Jellou",
    "gn:country_code":"NE",
    "gn:dem":473,
    "gn:feature_class":"P",
    "gn:feature_code":"PPL",
    "gn:name":"Garine J\u00e9llou",
    "gn:population":0,
    "gn:timezone":"Africa/Niamey",
    "iso:country":"NE",
    "wof:name":"Garine Jellou",
    "wof:placetype":"locality"
},
  "geometry": {"coordinates":[8.7023,15.09793],"type":"Point"}
}