{
  "type": "Feature",
  "properties": {
    "gn:admin1_code":"4.0",
    "gn:asciiname":"Sansame",
    "gn:country_code":"NE",
    "gn:dem":452,
    "gn:feature_class":"P",
    "gn:feature_code":"PPL",
    "gn:name":"Sansam\u00e9",
    "gn:population":0,
    "gn:timezone":"Africa/Niamey",
    "iso:country":"NE",
    "wof:name":"Sansame",
    "wof:placetype":"locality"
},
  "geometry": {"coordinates":[7.82684,14.3836],"type":"Point"}
}