{
  "type": "Feature",
  "properties": {
    "gn:admin1_code":"2.0",
    "gn:asciiname":"Digine",
    "gn:country_code":"NE",
    "gn:dem":300,
    "gn:feature_class":"P",
    "gn:feature_code":"PPL",
    "gn:name":"Digin\u00e9",
    "gn:population":0,
    "gn:timezone":"Africa/Niamey",
    "iso:country":"NE",
    "wof:name":"Digine",
    "wof:placetype":"locality"
},
  "geometry": {"coordinates":[12.92877,13.54906],"type":"Point"}
}