{
  "type": "Feature",
  "properties": {
    "gn:admin1_code":"3.0",
    "gn:asciiname":"Bariki",
    "gn:country_code":"NE",
    "gn:dem":228,
    "gn:feature_class":"P",
    "gn:feature_code":"PPL",
    "gn:name":"Bariki",
    "gn:population":0,
    "gn:timezone":"Africa/Niamey",
    "iso:country":"NE",
    "name:ceb_x_preferred":[
        "Bariki"
    ],
    "name:swe_x_preferred":[
        "Bariki"
    ],
    "wof:name":"Bariki",
    "wof:placetype":"locality"
},
  "geometry": {"coordinates":[4.03452,13.89838],"type":"Point"}
}