{
  "type": "Feature",
  "properties": {
    "gn:admin1_code":"3.0",
    "gn:asciiname":"Atara Oubanda Waki Kwara",
    "gn:country_code":"NE",
    "gn:dem":194,
    "gn:feature_class":"P",
    "gn:feature_code":"PPL",
    "gn:name":"Atara Oubanda Waki Kwara",
    "gn:population":0,
    "gn:timezone":"Africa/Niamey",
    "iso:country":"NE",
    "name:und_x_variant":[
        "Atara Oubanda Waki Koara",
        "Attara-Oubanda-Waki-Koara",
        "Attara-Oubanda",
        "Atara Oubanda Waki Kwara"
    ],
    "wof:name":"Atara Oubanda Waki Kwara",
    "wof:placetype":"locality"
},
  "geometry": {"coordinates":[3.4487,12.47746],"type":"Point"}
}