{
  "type": "Feature",
  "properties": {
    "gn:admin1_code":"3.0",
    "gn:asciiname":"Kourokaina",
    "gn:country_code":"NE",
    "gn:dem":237,
    "gn:feature_class":"P",
    "gn:feature_code":"PPL",
    "gn:name":"Kouroka\u00efna",
    "gn:population":0,
    "gn:timezone":"Africa/Niamey",
    "iso:country":"NE",
    "name:und_x_variant":[
        "Kouro Keyna",
        "Kouroka\u00efna"
    ],
    "wof:name":"Kourokaina",
    "wof:placetype":"locality"
},
  "geometry": {"coordinates":[3.5317,13.772],"type":"Point"}
}