{
  "type": "Feature",
  "properties": {
    "gn:admin1_code":"4.0",
    "gn:asciiname":"Agoua Sofoua",
    "gn:country_code":"NE",
    "gn:dem":371,
    "gn:feature_class":"P",
    "gn:feature_code":"PPL",
    "gn:name":"Agoua Sofoua",
    "gn:population":0,
    "gn:timezone":"Africa/Niamey",
    "iso:country":"NE",
    "wof:name":"Agoua Sofoua",
    "wof:placetype":"locality"
},
  "geometry": {"coordinates":[7.09933,13.96034],"type":"Point"}
}