{
  "type": "Feature",
  "properties": {
    "gn:admin1_code":"3.0",
    "gn:asciiname":"Diney Zougou",
    "gn:country_code":"NE",
    "gn:dem":198,
    "gn:feature_class":"P",
    "gn:feature_code":"PPL",
    "gn:name":"Diney Zougou",
    "gn:population":0,
    "gn:timezone":"Africa/Niamey",
    "iso:country":"NE",
    "name:und_x_variant":[
        "Din\u00e9zogo",
        "Diney Zougou"
    ],
    "wof:name":"Diney Zougou",
    "wof:placetype":"locality"
},
  "geometry": {"coordinates":[2.9394,13.388],"type":"Point"}
}