{
  "type": "Feature",
  "properties": {
    "gn:admin1_code":"4.0",
    "gn:asciiname":"Guidan Moullou",
    "gn:country_code":"NE",
    "gn:dem":442,
    "gn:feature_class":"P",
    "gn:feature_code":"PPL",
    "gn:name":"Guidan Moullou",
    "gn:population":0,
    "gn:timezone":"Africa/Niamey",
    "iso:country":"NE",
    "wof:name":"Guidan Moullou",
    "wof:placetype":"locality"
},
  "geometry": {"coordinates":[8.08023,14.25963],"type":"Point"}
}