{
  "type": "Feature",
  "properties": {
    "gn:admin1_code":"7.0",
    "gn:asciiname":"Dagoumba Bougaje",
    "gn:country_code":"NE",
    "gn:dem":418,
    "gn:feature_class":"P",
    "gn:feature_code":"PPL",
    "gn:name":"Dagoumba Bougaj\u00e9",
    "gn:population":0,
    "gn:timezone":"Africa/Niamey",
    "iso:country":"NE",
    "wof:name":"Dagoumba Bougaje",
    "wof:placetype":"locality"
},
  "geometry": {"coordinates":[8.84117,13.24014],"type":"Point"}
}