{
  "type": "Feature",
  "properties": {
    "gn:admin1_code":"7.0",
    "gn:asciiname":"Goubdo",
    "gn:country_code":"NE",
    "gn:dem":536,
    "gn:feature_class":"P",
    "gn:feature_code":"PPL",
    "gn:name":"Goubdo",
    "gn:population":0,
    "gn:timezone":"Africa/Niamey",
    "iso:country":"NE",
    "wof:name":"Goubdo",
    "wof:placetype":"locality"
},
  "geometry": {"coordinates":[10.0021,14.4866],"type":"Point"}
}