{
  "type": "Feature",
  "properties": {
    "gn:admin1_code":"4.0",
    "gn:asciiname":"Guidan Kerki",
    "gn:country_code":"NE",
    "gn:dem":401,
    "gn:feature_class":"P",
    "gn:feature_code":"PPL",
    "gn:name":"Guidan K\u00e8rki",
    "gn:population":0,
    "gn:timezone":"Africa/Niamey",
    "iso:country":"NE",
    "wof:name":"Guidan Kerki",
    "wof:placetype":"locality"
},
  "geometry": {"coordinates":[6.56237,14.193],"type":"Point"}
}