{
  "type": "Feature",
  "properties": {
    "gn:admin1_code":"7.0",
    "gn:asciiname":"Dunari",
    "gn:country_code":"NE",
    "gn:dem":359,
    "gn:feature_class":"P",
    "gn:feature_code":"PPL",
    "gn:name":"Dunari",
    "gn:population":0,
    "gn:timezone":"Africa/Niamey",
    "iso:country":"NE",
    "wof:name":"Dunari",
    "wof:placetype":"locality"
},
  "geometry": {"coordinates":[9.9023,13.0968],"type":"Point"}
}