{
  "type": "Feature",
  "properties": {
    "gn:admin1_code":"7.0",
    "gn:asciiname":"Tay Lafia Bougaje",
    "gn:country_code":"NE",
    "gn:dem":402,
    "gn:feature_class":"P",
    "gn:feature_code":"PPL",
    "gn:name":"Tay Lafia Bougaj\u00e9",
    "gn:population":0,
    "gn:timezone":"Africa/Niamey",
    "iso:country":"NE",
    "wof:name":"Tay Lafia Bougaje",
    "wof:placetype":"locality"
},
  "geometry": {"coordinates":[8.84356,12.98812],"type":"Point"}
}