{
  "type": "Feature",
  "properties": {
    "gn:admin1_code":"7.0",
    "gn:asciiname":"Sarekou",
    "gn:country_code":"NE",
    "gn:dem":455,
    "gn:feature_class":"P",
    "gn:feature_code":"PPL",
    "gn:name":"Sar\u00e9kou",
    "gn:population":0,
    "gn:timezone":"Africa/Niamey",
    "iso:country":"NE",
    "wof:name":"Sarekou",
    "wof:placetype":"locality"
},
  "geometry": {"coordinates":[8.7511,14.0694],"type":"Point"}
}