{
  "type": "Feature",
  "properties": {
    "gn:admin1_code":"6.0",
    "gn:asciiname":"I-n-Kinkaran",
    "gn:country_code":"NE",
    "gn:dem":447,
    "gn:feature_class":"P",
    "gn:feature_code":"PPL",
    "gn:name":"I-n-Kinkaran",
    "gn:population":0,
    "gn:timezone":"Africa/Niamey",
    "iso:country":"NE",
    "name:und_x_variant":[
        "In Kinkaran",
        "I-n-Kinkaran"
    ],
    "wof:name":"I-n-Kinkaran",
    "wof:placetype":"locality"
},
  "geometry": {"coordinates":[5.7704,15.064],"type":"Point"}
}