{
  "type": "Feature",
  "properties": {
    "gn:admin1_code":"9.0",
    "gn:asciiname":"Koubal",
    "gn:country_code":"NE",
    "gn:dem":224,
    "gn:feature_class":"P",
    "gn:feature_code":"PPL",
    "gn:name":"Koubal",
    "gn:population":0,
    "gn:timezone":"Africa/Niamey",
    "iso:country":"NE",
    "wof:name":"Koubal",
    "wof:placetype":"locality"
},
  "geometry": {"coordinates":[1.19324,14.49096],"type":"Point"}
}