{
  "type": "Feature",
  "properties": {
    "gn:admin1_code":"4.0",
    "gn:asciiname":"Garin Dan Ahi",
    "gn:country_code":"NE",
    "gn:dem":368,
    "gn:feature_class":"P",
    "gn:feature_code":"PPL",
    "gn:name":"Garin Dan Ahi",
    "gn:population":0,
    "gn:timezone":"Africa/Niamey",
    "iso:country":"NE",
    "wof:name":"Garin Dan Ahi",
    "wof:placetype":"locality"
},
  "geometry": {"coordinates":[7.12208,13.53735],"type":"Point"}
}