{
  "type": "Feature",
  "properties": {
    "gn:admin1_code":"4.0",
    "gn:asciiname":"Dan Fari",
    "gn:country_code":"NE",
    "gn:dem":445,
    "gn:feature_class":"P",
    "gn:feature_code":"PPL",
    "gn:name":"Dan Fari",
    "gn:population":0,
    "gn:timezone":"Africa/Niamey",
    "iso:country":"NE",
    "wof:name":"Dan Fari",
    "wof:placetype":"locality"
},
  "geometry": {"coordinates":[7.78148,13.64227],"type":"Point"}
}