{
  "type": "Feature",
  "properties": {
    "gn:admin1_code":"4.0",
    "gn:asciiname":"Guidan Illi",
    "gn:country_code":"NE",
    "gn:dem":408,
    "gn:feature_class":"P",
    "gn:feature_code":"PPL",
    "gn:name":"Guidan Illi",
    "gn:population":0,
    "gn:timezone":"Africa/Niamey",
    "iso:country":"NE",
    "wof:name":"Guidan Illi",
    "wof:placetype":"locality"
},
  "geometry": {"coordinates":[7.81765,13.75117],"type":"Point"}
}