{
  "type": "Feature",
  "properties": {
    "gn:admin1_code":"4.0",
    "gn:asciiname":"Tonkourma",
    "gn:country_code":"NE",
    "gn:dem":411,
    "gn:feature_class":"P",
    "gn:feature_code":"PPL",
    "gn:name":"Tonkourma",
    "gn:population":0,
    "gn:timezone":"Africa/Niamey",
    "iso:country":"NE",
    "wof:name":"Tonkourma",
    "wof:placetype":"locality"
},
  "geometry": {"coordinates":[7.47519,13.61158],"type":"Point"}
}