{
  "type": "Feature",
  "properties": {
    "gn:admin1_code":"7.0",
    "gn:asciiname":"Dagoumba Haoussa",
    "gn:country_code":"NE",
    "gn:dem":419,
    "gn:feature_class":"P",
    "gn:feature_code":"PPL",
    "gn:name":"Dagoumba Haoussa",
    "gn:population":0,
    "gn:timezone":"Africa/Niamey",
    "iso:country":"NE",
    "wof:name":"Dagoumba Haoussa",
    "wof:placetype":"locality"
},
  "geometry": {"coordinates":[8.80875,13.25956],"type":"Point"}
}