{
  "type": "Feature",
  "properties": {
    "gn:admin1_code":"2.0",
    "gn:asciiname":"Kouble",
    "gn:country_code":"NE",
    "gn:dem":337,
    "gn:feature_class":"P",
    "gn:feature_code":"PPL",
    "gn:name":"Kouble",
    "gn:population":0,
    "gn:timezone":"Africa/Niamey",
    "iso:country":"NE",
    "wof:name":"Kouble",
    "wof:placetype":"locality"
},
  "geometry": {"coordinates":[11.77685,13.53665],"type":"Point"}
}