{
  "type": "Feature",
  "properties": {
    "gn:country":"NE",
    "gn:fcode":"PPLX",
    "gn:population":0,
    "iso:country":"NE",
    "name:fra_x_colloquial":[
        "Karadje"
    ],
    "name:fra_x_preferred":[
        "Karadj\u00e9"
    ],
    "qs:gn_adm0_cc":"NE",
    "qs:gn_fcode":"PPLX",
    "qs:gn_local":2440485,
    "qs:gn_nam_loc":"Niamey, Niamey, Niamey, NE",
    "qs:gn_namadm1":"08",
    "qs:gn_name":"Karadj\u00e9",
    "qs:local_max":264,
    "qs:local_sum":377,
    "qs:localhoods":2,
    "qs:name":"Karadj\u00e9",
    "qs:name_adm0":"Niger",
    "qs:name_adm1":"Niamey",
    "qs:name_adm2":"Niamey",
    "qs:name_local":"Niamey",
    "qs:photo_max":89,
    "qs:photo_sum":264,
    "qs:placetype":"Suburb",
    "qs:quad_count":12,
    "qs:woe_adm0":23424906,
    "qs:woe_adm1":20069994,
    "qs:woe_adm2":56055506,
    "qs:woe_lau":0,
    "qs:woe_local":1505949,
    "qs:woe_ver":"7.10.0",
    "qs_pg:aaroncc":"NE",
    "qs_pg:gn_country":"NE",
    "qs_pg:gn_fcode":"PPLX",
    "qs_pg:gn_pop":0,
    "qs_pg:name":"Karadj\u00e9",
    "qs_pg:name_adm0":"Niger",
    "qs_pg:name_adm1":"Niamey",
    "qs_pg:photos":118,
    "qs_pg:photos_1k":24,
    "qs_pg:photos_9k":1,
    "qs_pg:photos_9r":3,
    "qs_pg:photos_all":118,
    "qs_pg:photos_sr":3,
    "qs_pg:pop_sr":0,
    "qs_pg:qs_pg_placetype":"neighbourhood",
    "qs_pg:qs_pg_placetype_gp":"Suburb",
    "qs_pg:woe_adm0":23424906,
    "wof:lang":[
        "fre"
    ],
    "wof:name":"Karadj\u00e9",
    "wof:placetype":"neighbourhood"
},
  "geometry": {"coordinates":[2.106379,13.509705],"type":"Point"}
}