{
  "type": "Feature",
  "properties": {
    "gn:admin1_code":"4.0",
    "gn:asciiname":"Garin Bara",
    "gn:country_code":"NE",
    "gn:dem":389,
    "gn:feature_class":"P",
    "gn:feature_code":"PPL",
    "gn:name":"Garin Bara",
    "gn:population":0,
    "gn:timezone":"Africa/Niamey",
    "iso:country":"NE",
    "wof:name":"Garin Bara",
    "wof:placetype":"locality"
},
  "geometry": {"coordinates":[6.62124,14.18091],"type":"Point"}
}