{
  "type": "Feature",
  "properties": {
    "gn:admin1_code":"7.0",
    "gn:asciiname":"Banou Oualki",
    "gn:country_code":"NE",
    "gn:dem":493,
    "gn:feature_class":"P",
    "gn:feature_code":"PPL",
    "gn:name":"Banou Oualki",
    "gn:population":0,
    "gn:timezone":"Africa/Niamey",
    "iso:country":"NE",
    "wof:name":"Banou Oualki",
    "wof:placetype":"locality"
},
  "geometry": {"coordinates":[9.0411,14.7728],"type":"Point"}
}