{
  "type": "Feature",
  "properties": {
    "gn:admin1_code":"4.0",
    "gn:asciiname":"Louga-Arou",
    "gn:country_code":"NE",
    "gn:dem":386,
    "gn:feature_class":"P",
    "gn:feature_code":"PPL",
    "gn:name":"Louga-Arou",
    "gn:population":0,
    "gn:timezone":"Africa/Niamey",
    "iso:country":"NE",
    "wof:name":"Louga-Arou",
    "wof:placetype":"locality"
},
  "geometry": {"coordinates":[7.03715,14.01983],"type":"Point"}
}