{
  "type": "Feature",
  "properties": {
    "gn:admin1_code":"4.0",
    "gn:asciiname":"Labi",
    "gn:country_code":"NE",
    "gn:dem":434,
    "gn:feature_class":"P",
    "gn:feature_code":"PPL",
    "gn:name":"Labi",
    "gn:population":0,
    "gn:timezone":"Africa/Niamey",
    "iso:country":"NE",
    "name:ceb_x_preferred":[
        "Labi"
    ],
    "name:deu_x_preferred":[
        "Labi"
    ],
    "name:swe_x_preferred":[
        "Labi"
    ],
    "name:tgl_x_preferred":[
        "Labi"
    ],
    "wof:name":"Labi",
    "wof:placetype":"locality"
},
  "geometry": {"coordinates":[7.47802,14.5465],"type":"Point"}
}