{
  "type": "Feature",
  "properties": {
    "gn:admin1_code":"3.0",
    "gn:asciiname":"Nguide",
    "gn:country_code":"NE",
    "gn:dem":226,
    "gn:feature_class":"P",
    "gn:feature_code":"PPL",
    "gn:name":"Nguid\u00e9",
    "gn:population":0,
    "gn:timezone":"Africa/Niamey",
    "iso:country":"NE",
    "name:und_x_variant":[
        "Ngid\u00e9",
        "Nguid\u00e9"
    ],
    "wof:name":"Nguide",
    "wof:placetype":"locality"
},
  "geometry": {"coordinates":[3.1184,13.1114],"type":"Point"}
}