{
  "type": "Feature",
  "properties": {
    "gn:admin1_code":"6.0",
    "gn:asciiname":"Makouana",
    "gn:country_code":"NE",
    "gn:dem":310,
    "gn:feature_class":"P",
    "gn:feature_code":"PPL",
    "gn:name":"Makouana",
    "gn:population":0,
    "gn:timezone":"Africa/Niamey",
    "iso:country":"NE",
    "wof:name":"Makouana",
    "wof:placetype":"locality"
},
  "geometry": {"coordinates":[5.1503,14.2243],"type":"Point"}
}