{
  "type": "Feature",
  "properties": {
    "gn:admin1_code":"3.0",
    "gn:asciiname":"Gorou Kaya",
    "gn:country_code":"NE",
    "gn:dem":203,
    "gn:feature_class":"P",
    "gn:feature_code":"PPL",
    "gn:name":"Gorou Kaya",
    "gn:population":0,
    "gn:timezone":"Africa/Niamey",
    "iso:country":"NE",
    "wof:name":"Gorou Kaya",
    "wof:placetype":"locality"
},
  "geometry": {"coordinates":[3.42281,12.92613],"type":"Point"}
}