{
  "type": "Feature",
  "properties": {
    "gn:admin1_code":"4.0",
    "gn:asciiname":"Dan Farou",
    "gn:country_code":"NE",
    "gn:dem":409,
    "gn:feature_class":"P",
    "gn:feature_code":"PPL",
    "gn:name":"Dan F\u00e2ro\u00fb",
    "gn:population":0,
    "gn:timezone":"Africa/Niamey",
    "iso:country":"NE",
    "wof:name":"Dan Farou",
    "wof:placetype":"locality"
},
  "geometry": {"coordinates":[7.33374,13.69648],"type":"Point"}
}