{
  "type": "Feature",
  "properties": {
    "gn:admin1_code":"3.0",
    "gn:asciiname":"Rodji Zarma",
    "gn:country_code":"NE",
    "gn:dem":201,
    "gn:feature_class":"P",
    "gn:feature_code":"PPL",
    "gn:name":"Rodji Zarma",
    "gn:population":0,
    "gn:timezone":"Africa/Niamey",
    "iso:country":"NE",
    "name:und_x_variant":[
        "Rosi",
        "Rossi",
        "Rodji Zarma"
    ],
    "wof:name":"Rodji Zarma",
    "wof:placetype":"locality"
},
  "geometry": {"coordinates":[2.86676,12.84848],"type":"Point"}
}