{
  "type": "Feature",
  "properties": {
    "gn:admin1_code":"4.0",
    "gn:asciiname":"Rijya Gayda",
    "gn:country_code":"NE",
    "gn:dem":421,
    "gn:feature_class":"P",
    "gn:feature_code":"PPL",
    "gn:name":"Rijya Gayda",
    "gn:population":0,
    "gn:timezone":"Africa/Niamey",
    "iso:country":"NE",
    "name:und_x_variant":[
        "Rijia Gayda",
        "Rijya Gayda"
    ],
    "wof:name":"Rijya Gayda",
    "wof:placetype":"locality"
},
  "geometry": {"coordinates":[8.2693,14.2941],"type":"Point"}
}