{
  "type": "Feature",
  "properties": {
    "gn:admin1_code":"9.0",
    "gn:asciiname":"Gata Kouara",
    "gn:country_code":"NE",
    "gn:dem":224,
    "gn:feature_class":"P",
    "gn:feature_code":"PPL",
    "gn:name":"Gata Kouara",
    "gn:population":0,
    "gn:timezone":"Africa/Niamey",
    "iso:country":"NE",
    "name:und_x_variant":[
        "Kouara T\u00e9gui",
        "Gata Kouara"
    ],
    "wof:name":"Gata Kouara",
    "wof:placetype":"locality"
},
  "geometry": {"coordinates":[2.0193,13.9477],"type":"Point"}
}