{
  "type": "Feature",
  "properties": {
    "gn:admin1_code":"9.0",
    "gn:asciiname":"Tigezefen Sabongari",
    "gn:country_code":"NE",
    "gn:dem":284,
    "gn:feature_class":"P",
    "gn:feature_code":"PPL",
    "gn:name":"Tig\u00e9z\u00e9fen Sabongari",
    "gn:population":0,
    "gn:timezone":"Africa/Niamey",
    "iso:country":"NE",
    "wof:name":"Tigezefen Sabongari",
    "wof:placetype":"locality"
},
  "geometry": {"coordinates":[3.3099,15.2314],"type":"Point"}
}