{
  "type": "Feature",
  "properties": {
    "gn:admin1_code":"6.0",
    "gn:asciiname":"Kankara",
    "gn:country_code":"NE",
    "gn:dem":358,
    "gn:feature_class":"P",
    "gn:feature_code":"PPL",
    "gn:name":"Kankara",
    "gn:population":0,
    "gn:timezone":"Africa/Niamey",
    "iso:country":"NE",
    "name:fra_x_preferred":[
        "Kankara"
    ],
    "name:hau_x_preferred":[
        "\u0198an\u0199ara"
    ],
    "name:ita_x_preferred":[
        "Kankara"
    ],
    "name:spa_x_preferred":[
        "Kankara"
    ],
    "wof:name":"Kankara",
    "wof:placetype":"locality"
},
  "geometry": {"coordinates":[6.28424,14.29447],"type":"Point"}
}