{
  "type": "Feature",
  "properties": {
    "gn:admin1_code":"4.0",
    "gn:asciiname":"Guidan Dodo",
    "gn:country_code":"NE",
    "gn:dem":422,
    "gn:feature_class":"P",
    "gn:feature_code":"PPL",
    "gn:name":"Guidan Dodo",
    "gn:population":0,
    "gn:timezone":"Africa/Niamey",
    "iso:country":"NE",
    "wof:name":"Guidan Dodo",
    "wof:placetype":"locality"
},
  "geometry": {"coordinates":[8.01451,13.69339],"type":"Point"}
}