{
  "type": "Feature",
  "properties": {
    "gn:admin1_code":"4.0",
    "gn:asciiname":"May Yara",
    "gn:country_code":"NE",
    "gn:dem":359,
    "gn:feature_class":"P",
    "gn:feature_code":"PPL",
    "gn:name":"May Y\u00e2r\u00e2",
    "gn:population":0,
    "gn:timezone":"Africa/Niamey",
    "iso:country":"NE",
    "name:und_x_variant":[
        "Mayara",
        "May Y\u00e2r\u00e2"
    ],
    "wof:name":"May Yara",
    "wof:placetype":"locality"
},
  "geometry": {"coordinates":[7.21983,13.93538],"type":"Point"}
}