{
  "type": "Feature",
  "properties": {
    "gn:admin1_code":"4.0",
    "gn:asciiname":"Dan Outou",
    "gn:country_code":"NE",
    "gn:dem":405,
    "gn:feature_class":"P",
    "gn:feature_code":"PPL",
    "gn:name":"Dan Outou",
    "gn:population":0,
    "gn:timezone":"Africa/Niamey",
    "iso:country":"NE",
    "wof:name":"Dan Outou",
    "wof:placetype":"locality"
},
  "geometry": {"coordinates":[7.28269,13.69574],"type":"Point"}
}