{
  "type": "Feature",
  "properties": {
    "gn:admin1_code":"3.0",
    "gn:asciiname":"Garin Gora",
    "gn:country_code":"NE",
    "gn:dem":236,
    "gn:feature_class":"P",
    "gn:feature_code":"PPL",
    "gn:name":"Garin Gora",
    "gn:population":0,
    "gn:timezone":"Africa/Niamey",
    "iso:country":"NE",
    "wof:name":"Garin Gora",
    "wof:placetype":"locality"
},
  "geometry": {"coordinates":[3.69138,12.55642],"type":"Point"}
}