{
  "type": "Feature",
  "properties": {
    "gn:admin1_code":"9.0",
    "gn:asciiname":"Boukou",
    "gn:country_code":"NE",
    "gn:dem":201,
    "gn:feature_class":"P",
    "gn:feature_code":"PPL",
    "gn:name":"Boukou",
    "gn:population":0,
    "gn:timezone":"Africa/Niamey",
    "iso:country":"NE",
    "name:azb_x_preferred":[
        "\u0628\u0648\u06a9\u0648"
    ],
    "name:ceb_x_preferred":[
        "Boukou"
    ],
    "name:fas_x_preferred":[
        "\u0628\u0648\u06a9\u0648"
    ],
    "name:fra_x_preferred":[
        "Boukou"
    ],
    "name:swe_x_preferred":[
        "Boukou"
    ],
    "name:und_x_variant":[
        "Bokou"
    ],
    "wof:name":"Boukou",
    "wof:placetype":"locality"
},
  "geometry": {"coordinates":[1.53171,14.08356],"type":"Point"}
}