{
  "type": "Feature",
  "properties": {
    "gn:admin1_code":"2.0",
    "gn:asciiname":"Matawaram",
    "gn:country_code":"NE",
    "gn:dem":350,
    "gn:feature_class":"P",
    "gn:feature_code":"PPL",
    "gn:name":"Matawaram",
    "gn:population":0,
    "gn:timezone":"Africa/Niamey",
    "iso:country":"NE",
    "wof:name":"Matawaram",
    "wof:placetype":"locality"
},
  "geometry": {"coordinates":[11.1149,13.5804],"type":"Point"}
}