{
  "type": "Feature",
  "properties": {
    "gn:admin1_code":"3.0",
    "gn:asciiname":"Doula",
    "gn:country_code":"NE",
    "gn:dem":253,
    "gn:feature_class":"P",
    "gn:feature_code":"PPL",
    "gn:name":"Doula",
    "gn:population":0,
    "gn:timezone":"Africa/Niamey",
    "iso:country":"NE",
    "name:ara_x_preferred":[
        "\u062f\u0648\u0644\u0627"
    ],
    "name:cat_x_preferred":[
        "Doula"
    ],
    "name:ces_x_preferred":[
        "Dula"
    ],
    "name:dan_x_preferred":[
        "Doula"
    ],
    "name:deu_x_preferred":[
        "Doula"
    ],
    "name:est_x_preferred":[
        "S\u00fcnnitoetaja"
    ],
    "name:eus_x_preferred":[
        "Doula"
    ],
    "name:fas_x_preferred":[
        "\u0647\u0645\u0631\u0627\u0647 \u0632\u0627\u0626\u0648"
    ],
    "name:fra_x_preferred":[
        "Doula"
    ],
    "name:heb_x_preferred":[
        "\u05ea\u05de\u05d9\u05db\u05ea \u05dc\u05d9\u05d3\u05d4"
    ],
    "name:ita_x_preferred":[
        "Doula"
    ],
    "name:lit_x_preferred":[
        "Dula"
    ],
    "name:nor_x_preferred":[
        "Doula"
    ],
    "name:pol_x_preferred":[
        "Doula"
    ],
    "name:por_x_preferred":[
        "Doula"
    ],
    "name:rus_x_preferred":[
        "\u0414\u043e\u0443\u043b\u0430"
    ],
    "name:slk_x_preferred":[
        "Dula"
    ],
    "name:spa_x_preferred":[
        "Doula"
    ],
    "name:swe_x_preferred":[
        "Doula"
    ],
    "wof:name":"Doula",
    "wof:placetype":"locality"
},
  "geometry": {"coordinates":[3.898,13.4276],"type":"Point"}
}