{
  "type": "Feature",
  "properties": {
    "gn:admin1_code":"9.0",
    "gn:asciiname":"Gadabo Fetokadie",
    "gn:country_code":"NE",
    "gn:dem":233,
    "gn:feature_class":"P",
    "gn:feature_code":"PPL",
    "gn:name":"Gadabo F\u00e9tok\u00e2di\u00e9",
    "gn:population":0,
    "gn:timezone":"Africa/Niamey",
    "iso:country":"NE",
    "name:und_x_variant":[
        "Gadabo Fatakadi\u00e9",
        "Gadabo F\u00e9tok\u00e2di\u00e9"
    ],
    "wof:name":"Gadabo Fetokadie",
    "wof:placetype":"locality"
},
  "geometry": {"coordinates":[2.3283,13.7681],"type":"Point"}
}