{
  "type": "Feature",
  "properties": {
    "gn:admin1_code":"9.0",
    "gn:asciiname":"Diagoga",
    "gn:country_code":"NE",
    "gn:dem":212,
    "gn:feature_class":"P",
    "gn:feature_code":"PPL",
    "gn:name":"Diagoga",
    "gn:population":0,
    "gn:timezone":"Africa/Niamey",
    "iso:country":"NE",
    "wof:name":"Diagoga",
    "wof:placetype":"locality"
},
  "geometry": {"coordinates":[1.94352,13.13545],"type":"Point"}
}