{
  "type": "Feature",
  "properties": {
    "gn:admin1_code":"4.0",
    "gn:asciiname":"Angoual Mayne Sara",
    "gn:country_code":"NE",
    "gn:dem":465,
    "gn:feature_class":"P",
    "gn:feature_code":"PPL",
    "gn:name":"Angoual Mayn\u00e9 Sara",
    "gn:population":0,
    "gn:timezone":"Africa/Niamey",
    "iso:country":"NE",
    "wof:name":"Angoual Mayne Sara",
    "wof:placetype":"locality"
},
  "geometry": {"coordinates":[8.2932,13.89385],"type":"Point"}
}