{
  "type": "Feature",
  "properties": {
    "gn:admin1_code":"2.0",
    "gn:asciiname":"Alima",
    "gn:country_code":"NE",
    "gn:dem":280,
    "gn:feature_class":"P",
    "gn:feature_code":"PPL",
    "gn:name":"Alima",
    "gn:population":0,
    "gn:timezone":"Africa/Niamey",
    "iso:country":"NE",
    "name:ara_x_preferred":[
        "\u0623\u0644\u064a\u0645\u0627"
    ],
    "name:bel_x_preferred":[
        "\u0410\u043b\u0456\u043c\u0430"
    ],
    "name:ben_x_preferred":[
        "\u0986\u09b2\u09bf\u09ae\u09be"
    ],
    "name:deu_x_preferred":[
        "Alima"
    ],
    "name:ell_x_preferred":[
        "\u0391\u03bb\u03af\u03bc\u03b1"
    ],
    "name:fas_x_preferred":[
        "\u0622\u0644\u06cc\u0645\u0627"
    ],
    "name:fra_x_preferred":[
        "Alima River"
    ],
    "name:fra_x_variant":[
        "Alima"
    ],
    "name:heb_x_preferred":[
        "\u05d0\u05dc\u05d9\u05de\u05d4"
    ],
    "name:hin_x_preferred":[
        "\u0905\u0932\u0940\u092e\u093e"
    ],
    "name:hun_x_preferred":[
        "Alima"
    ],
    "name:ind_x_preferred":[
        "Alima"
    ],
    "name:ita_x_preferred":[
        "Alima"
    ],
    "name:jpn_x_preferred":[
        "\u30a2\u30ea\u30de\u5ddd"
    ],
    "name:kor_x_preferred":[
        "\uc54c\ub9ac\ub9c8"
    ],
    "name:lit_x_preferred":[
        "Alima"
    ],
    "name:nld_x_preferred":[
        "Alima"
    ],
    "name:pol_x_preferred":[
        "Alima"
    ],
    "name:por_x_preferred":[
        "Alima"
    ],
    "name:rus_x_preferred":[
        "\u0410\u043b\u0438\u043c\u0430"
    ],
    "name:spa_x_preferred":[
        "Alima"
    ],
    "name:swe_x_preferred":[
        "Alima"
    ],
    "name:tur_x_preferred":[
        "Alima"
    ],
    "name:ukr_x_preferred":[
        "\u0410\u043b\u0456\u043c\u0430"
    ],
    "name:urd_x_preferred":[
        "\u0639\u0644\u06cc\u0645\u06c1"
    ],
    "name:vie_x_preferred":[
        "S\u00f4ng Alima"
    ],
    "name:zho_cn_x_preferred":[
        "\u963f\u5229\u9a6c\u6cb3"
    ],
    "name:zho_tw_x_preferred":[
        "\u963f\u5229\u99ac\u6cb3"
    ],
    "name:zho_x_preferred":[
        "\u963f\u5229\u99ac\u6cb3"
    ],
    "wof:name":"Alima",
    "wof:placetype":"locality"
},
  "geometry": {"coordinates":[13.28063,13.88323],"type":"Point"}
}