{
  "type": "Feature",
  "properties": {
    "gn:admin1_code":"2.0",
    "gn:asciiname":"Alima",
    "gn:country_code":"NE",
    "gn:dem":280,
    "gn:feature_class":"P",
    "gn:feature_code":"PPL",
    "gn:name":"Alima",
    "gn:population":0,
    "gn:timezone":"Africa/Niamey",
    "iso:country":"NE",
    "name:bel_x_preferred":[
        "\u0410\u043b\u0456\u043c\u0430"
    ],
    "name:fra_x_preferred":[
        "Alima"
    ],
    "name:ita_x_preferred":[
        "Alima"
    ],
    "name:lit_x_preferred":[
        "Alima"
    ],
    "name:rus_x_preferred":[
        "\u0410\u043b\u0438\u043c\u0430"
    ],
    "name:swe_x_preferred":[
        "Alima"
    ],
    "name:zho_x_preferred":[
        "\u963f\u5229\u99ac\u6cb3"
    ],
    "wof:name":"Alima",
    "wof:placetype":"locality"
},
  "geometry": {"coordinates":[13.28063,13.88323],"type":"Point"}
}