{
  "type": "Feature",
  "properties": {
    "gn:admin1_code":"7.0",
    "gn:asciiname":"Dan Goudaou",
    "gn:country_code":"NE",
    "gn:dem":444,
    "gn:feature_class":"P",
    "gn:feature_code":"PPL",
    "gn:name":"Dan Goudaou",
    "gn:population":0,
    "gn:timezone":"Africa/Niamey",
    "iso:country":"NE",
    "name:und_x_variant":[
        "Dan Goudao",
        "Dan Goudaou"
    ],
    "wof:name":"Dan Goudaou",
    "wof:placetype":"locality"
},
  "geometry": {"coordinates":[8.3421,13.6122],"type":"Point"}
}