{
  "type": "Feature",
  "properties": {
    "gn:admin1_code":"7.0",
    "gn:asciiname":"Zengou",
    "gn:country_code":"NE",
    "gn:dem":451,
    "gn:feature_class":"P",
    "gn:feature_code":"PPL",
    "gn:name":"Zengou",
    "gn:population":0,
    "gn:timezone":"Africa/Niamey",
    "iso:country":"NE",
    "wof:name":"Zengou",
    "wof:placetype":"locality"
},
  "geometry": {"coordinates":[8.97761,13.82264],"type":"Point"}
}