{
  "type": "Feature",
  "properties": {
    "gn:admin1_code":"4.0",
    "gn:asciiname":"Jibile",
    "gn:country_code":"NE",
    "gn:dem":425,
    "gn:feature_class":"P",
    "gn:feature_code":"PPL",
    "gn:name":"Jibil\u00e9",
    "gn:population":0,
    "gn:timezone":"Africa/Niamey",
    "iso:country":"NE",
    "wof:name":"Jibile",
    "wof:placetype":"locality"
},
  "geometry": {"coordinates":[7.90336,13.82632],"type":"Point"}
}