{
  "type": "Feature",
  "properties": {
    "gn:admin1_code":"6.0",
    "gn:asciiname":"Tchoron Zakara",
    "gn:country_code":"NE",
    "gn:dem":474,
    "gn:feature_class":"P",
    "gn:feature_code":"PPL",
    "gn:name":"Tchoron Zakara",
    "gn:population":0,
    "gn:timezone":"Africa/Niamey",
    "iso:country":"NE",
    "wof:name":"Tchoron Zakara",
    "wof:placetype":"locality"
},
  "geometry": {"coordinates":[6.14533,14.69806],"type":"Point"}
}