{
  "type": "Feature",
  "properties": {
    "gn:admin1_code":"7.0",
    "gn:asciiname":"Dolli",
    "gn:country_code":"NE",
    "gn:dem":487,
    "gn:feature_class":"P",
    "gn:feature_code":"PPL",
    "gn:name":"Dolli",
    "gn:population":0,
    "gn:timezone":"Africa/Niamey",
    "iso:country":"NE",
    "wof:name":"Dolli",
    "wof:placetype":"locality"
},
  "geometry": {"coordinates":[9.14428,15.10505],"type":"Point"}
}