{
  "type": "Feature",
  "properties": {
    "gn:admin1_code":"4.0",
    "gn:asciiname":"Gawaro Guidan Kane",
    "gn:country_code":"NE",
    "gn:dem":431,
    "gn:feature_class":"P",
    "gn:feature_code":"PPL",
    "gn:name":"Gawaro Guidan Kan\u00e9",
    "gn:population":0,
    "gn:timezone":"Africa/Niamey",
    "iso:country":"NE",
    "name:und_x_variant":[
        "Gidan Kan\u00e9",
        "Guidan Kan\u00e9",
        "Gawaro Guidan Kan\u00e9"
    ],
    "wof:name":"Gawaro Guidan Kane",
    "wof:placetype":"locality"
},
  "geometry": {"coordinates":[7.43256,13.37852],"type":"Point"}
}