{
  "type": "Feature",
  "properties": {
    "gn:admin1_code":"4.0",
    "gn:asciiname":"Dan Koundili",
    "gn:country_code":"NE",
    "gn:dem":462,
    "gn:feature_class":"P",
    "gn:feature_code":"PPL",
    "gn:name":"Dan Koundili",
    "gn:population":0,
    "gn:timezone":"Africa/Niamey",
    "iso:country":"NE",
    "wof:name":"Dan Koundili",
    "wof:placetype":"locality"
},
  "geometry": {"coordinates":[8.22802,13.21902],"type":"Point"}
}