{
  "type": "Feature",
  "properties": {
    "gn:admin1_code":"4.0",
    "gn:asciiname":"Kountoumi",
    "gn:country_code":"NE",
    "gn:dem":373,
    "gn:feature_class":"P",
    "gn:feature_code":"PPL",
    "gn:name":"Kountoumi",
    "gn:population":0,
    "gn:timezone":"Africa/Niamey",
    "iso:country":"NE",
    "wof:name":"Kountoumi",
    "wof:placetype":"locality"
},
  "geometry": {"coordinates":[7.2236,13.27307],"type":"Point"}
}