{
  "type": "Feature",
  "properties": {
    "gn:admin1_code":"6.0",
    "gn:asciiname":"Gamdawa",
    "gn:country_code":"NE",
    "gn:dem":262,
    "gn:feature_class":"P",
    "gn:feature_code":"PPL",
    "gn:name":"Gamdawa",
    "gn:population":0,
    "gn:timezone":"Africa/Niamey",
    "iso:country":"NE",
    "wof:name":"Gamdawa",
    "wof:placetype":"locality"
},
  "geometry": {"coordinates":[5.23579,13.75285],"type":"Point"}
}