{
  "type": "Feature",
  "properties": {
    "gn:admin1_code":"1.0",
    "gn:asciiname":"Seguedine",
    "gn:country_code":"NE",
    "gn:dem":417,
    "gn:feature_class":"P",
    "gn:feature_code":"PPL",
    "gn:name":"S\u00e9gu\u00e9dine",
    "gn:population":0,
    "gn:timezone":"Africa/Niamey",
    "iso:country":"NE",
    "name:und_x_variant":[
        "Sogodem",
        "S\u00e9gu\u00e9dine"
    ],
    "wof:name":"Seguedine",
    "wof:placetype":"locality"
},
  "geometry": {"coordinates":[12.96086,20.19485],"type":"Point"}
}