{
  "type": "Feature",
  "properties": {
    "gn:admin1_code":"7.0",
    "gn:asciiname":"Adjyoumararam",
    "gn:country_code":"NE",
    "gn:dem":373,
    "gn:feature_class":"P",
    "gn:feature_code":"PPL",
    "gn:name":"Adjyoumararam",
    "gn:population":0,
    "gn:timezone":"Africa/Niamey",
    "iso:country":"NE",
    "wof:name":"Adjyoumararam",
    "wof:placetype":"locality"
},
  "geometry": {"coordinates":[10.66446,13.89302],"type":"Point"}
}