{
  "type": "Feature",
  "properties": {
    "gn:admin1_code":"9.0",
    "gn:asciiname":"Dabey",
    "gn:country_code":"NE",
    "gn:dem":228,
    "gn:feature_class":"P",
    "gn:feature_code":"PPL",
    "gn:name":"Dabey",
    "gn:population":0,
    "gn:timezone":"Africa/Niamey",
    "iso:country":"NE",
    "wof:name":"Dabey",
    "wof:placetype":"locality"
},
  "geometry": {"coordinates":[2.6185,13.8685],"type":"Point"}
}