{
  "type": "Feature",
  "properties": {
    "gn:admin1_code":"7.0",
    "gn:asciiname":"Machaya",
    "gn:country_code":"NE",
    "gn:dem":464,
    "gn:feature_class":"P",
    "gn:feature_code":"PPL",
    "gn:name":"Machaya",
    "gn:population":0,
    "gn:timezone":"Africa/Niamey",
    "iso:country":"NE",
    "wof:name":"Machaya",
    "wof:placetype":"locality"
},
  "geometry": {"coordinates":[8.26229,14.44983],"type":"Point"}
}