{
  "type": "Feature",
  "properties": {
    "gn:admin1_code":"7.0",
    "gn:asciiname":"Dan Baki",
    "gn:country_code":"NE",
    "gn:dem":459,
    "gn:feature_class":"P",
    "gn:feature_code":"PPL",
    "gn:name":"Dan Baki",
    "gn:population":0,
    "gn:timezone":"Africa/Niamey",
    "iso:country":"NE",
    "wof:name":"Dan Baki",
    "wof:placetype":"locality"
},
  "geometry": {"coordinates":[8.4584,14.2449],"type":"Point"}
}