{
  "type": "Feature",
  "properties": {
    "gn:admin1_code":"2.0",
    "gn:asciiname":"Seliram",
    "gn:country_code":"NE",
    "gn:dem":341,
    "gn:feature_class":"P",
    "gn:feature_code":"PPL",
    "gn:name":"Seliram",
    "gn:population":0,
    "gn:timezone":"Africa/Niamey",
    "iso:country":"NE",
    "wof:name":"Seliram",
    "wof:placetype":"locality"
},
  "geometry": {"coordinates":[11.37221,13.65136],"type":"Point"}
}