{
  "type": "Feature",
  "properties": {
    "gn:admin1_code":"3.0",
    "gn:asciiname":"Koma Keyna",
    "gn:country_code":"NE",
    "gn:dem":208,
    "gn:feature_class":"P",
    "gn:feature_code":"PPL",
    "gn:name":"Koma Keyna",
    "gn:population":0,
    "gn:timezone":"Africa/Niamey",
    "iso:country":"NE",
    "name:und_x_variant":[
        "Koma Kayna",
        "Koma-Ka\u00efna",
        "Koma Keyna"
    ],
    "wof:name":"Koma Keyna",
    "wof:placetype":"locality"
},
  "geometry": {"coordinates":[3.46526,12.59587],"type":"Point"}
}