{
  "type": "Feature",
  "properties": {
    "gn:admin1_code":"4.0",
    "gn:asciiname":"Kominia",
    "gn:country_code":"NE",
    "gn:dem":324,
    "gn:feature_class":"P",
    "gn:feature_code":"PPL",
    "gn:name":"Kominia",
    "gn:population":0,
    "gn:timezone":"Africa/Niamey",
    "iso:country":"NE",
    "wof:name":"Kominia",
    "wof:placetype":"locality"
},
  "geometry": {"coordinates":[6.56566,13.59966],"type":"Point"}
}