{
  "type": "Feature",
  "properties": {
    "gn:admin1_code":"4.0",
    "gn:asciiname":"Kelkeli",
    "gn:country_code":"NE",
    "gn:dem":359,
    "gn:feature_class":"P",
    "gn:feature_code":"PPL",
    "gn:name":"Kelk\u00e9li",
    "gn:population":0,
    "gn:timezone":"Africa/Niamey",
    "iso:country":"NE",
    "wof:name":"Kelkeli",
    "wof:placetype":"locality"
},
  "geometry": {"coordinates":[6.73468,13.42895],"type":"Point"}
}