{
  "type": "Feature",
  "properties": {
    "gn:admin1_code":"4.0",
    "gn:asciiname":"Linkidim",
    "gn:country_code":"NE",
    "gn:dem":423,
    "gn:feature_class":"P",
    "gn:feature_code":"PPL",
    "gn:name":"Linkidim",
    "gn:population":0,
    "gn:timezone":"Africa/Niamey",
    "iso:country":"NE",
    "wof:name":"Linkidim",
    "wof:placetype":"locality"
},
  "geometry": {"coordinates":[7.29358,14.23075],"type":"Point"}
}