{
  "type": "Feature",
  "properties": {
    "gn:admin1_code":"9.0",
    "gn:asciiname":"Bilal",
    "gn:country_code":"NE",
    "gn:dem":221,
    "gn:feature_class":"P",
    "gn:feature_code":"PPL",
    "gn:name":"Bilal",
    "gn:population":0,
    "gn:timezone":"Africa/Niamey",
    "iso:country":"NE",
    "name:ara_x_preferred":[
        "\u0628\u0644\u0627\u0644"
    ],
    "name:aze_x_preferred":[
        "Bilal"
    ],
    "name:ceb_x_preferred":[
        "Bilal"
    ],
    "name:deu_x_preferred":[
        "Bilal"
    ],
    "name:fra_x_preferred":[
        "Bilal"
    ],
    "name:ita_x_preferred":[
        "Bilal"
    ],
    "name:nld_x_preferred":[
        "Bilal"
    ],
    "name:rus_x_preferred":[
        "\u0411\u0438\u043b\u044f\u043b"
    ],
    "name:swe_x_preferred":[
        "Bilal"
    ],
    "name:tur_x_preferred":[
        "Bilal"
    ],
    "name:und_x_variant":[
        "Bilal Bangou"
    ],
    "wof:name":"Bilal",
    "wof:placetype":"locality"
},
  "geometry": {"coordinates":[3.4378,14.1788],"type":"Point"}
}