{
  "type": "Feature",
  "properties": {
    "gn:admin1_code":"3.0",
    "gn:asciiname":"Bangoubi",
    "gn:country_code":"NE",
    "gn:dem":198,
    "gn:feature_class":"P",
    "gn:feature_code":"PPL",
    "gn:name":"Bangoubi",
    "gn:population":0,
    "gn:timezone":"Africa/Niamey",
    "iso:country":"NE",
    "wof:name":"Bangoubi",
    "wof:placetype":"locality"
},
  "geometry": {"coordinates":[2.9319,13.3275],"type":"Point"}
}