{
  "type": "Feature",
  "properties": {
    "gn:admin1_code":"7.0",
    "gn:asciiname":"Angoual Bayi",
    "gn:country_code":"NE",
    "gn:dem":475,
    "gn:feature_class":"P",
    "gn:feature_code":"PPL",
    "gn:name":"Angoual Bayi",
    "gn:population":0,
    "gn:timezone":"Africa/Niamey",
    "iso:country":"NE",
    "wof:name":"Angoual Bayi",
    "wof:placetype":"locality"
},
  "geometry": {"coordinates":[8.92931,13.86276],"type":"Point"}
}