{
  "type": "Feature",
  "properties": {
    "gn:admin1_code":"9.0",
    "gn:asciiname":"Wani Kalawa",
    "gn:country_code":"NE",
    "gn:dem":272,
    "gn:feature_class":"P",
    "gn:feature_code":"PPL",
    "gn:name":"Wani Kalawa",
    "gn:population":0,
    "gn:timezone":"Africa/Niamey",
    "iso:country":"NE",
    "wof:name":"Wani Kalawa",
    "wof:placetype":"locality"
},
  "geometry": {"coordinates":[4.03511,14.90913],"type":"Point"}
}