{
  "type": "Feature",
  "properties": {
    "gn:admin1_code":"3.0",
    "gn:asciiname":"Mbala",
    "gn:country_code":"NE",
    "gn:dem":266,
    "gn:feature_class":"P",
    "gn:feature_code":"PPL",
    "gn:name":"Mbala",
    "gn:population":0,
    "gn:timezone":"Africa/Niamey",
    "iso:country":"NE",
    "name:ceb_x_preferred":[
        "Mbala"
    ],
    "name:fra_x_preferred":[
        "Mbala"
    ],
    "name:swe_x_preferred":[
        "Mbala"
    ],
    "wof:name":"Mbala",
    "wof:placetype":"locality"
},
  "geometry": {"coordinates":[3.6531,13.6422],"type":"Point"}
}