{
  "type": "Feature",
  "properties": {
    "gn:admin1_code":"9.0",
    "gn:asciiname":"Dioga",
    "gn:country_code":"NE",
    "gn:dem":216,
    "gn:feature_class":"P",
    "gn:feature_code":"PPL",
    "gn:name":"Dioga",
    "gn:population":0,
    "gn:timezone":"Africa/Niamey",
    "iso:country":"NE",
    "name:und_x_variant":[
        "Dyoga",
        "Dioga"
    ],
    "wof:name":"Dioga",
    "wof:placetype":"locality"
},
  "geometry": {"coordinates":[1.75417,13.1242],"type":"Point"}
}