{
  "type": "Feature",
  "properties": {
    "gn:admin1_code":"3.0",
    "gn:asciiname":"Marafo-Koara",
    "gn:country_code":"NE",
    "gn:dem":246,
    "gn:feature_class":"P",
    "gn:feature_code":"PPL",
    "gn:name":"Marafo-Koara",
    "gn:population":0,
    "gn:timezone":"Africa/Niamey",
    "iso:country":"NE",
    "name:und_x_variant":[
        "Marafo Kwara",
        "Marafo-Koara"
    ],
    "wof:name":"Marafo-Koara",
    "wof:placetype":"locality"
},
  "geometry": {"coordinates":[3.451,13.4205],"type":"Point"}
}