{
  "type": "Feature",
  "properties": {
    "gn:admin1_code":"6.0",
    "gn:asciiname":"Tounga Kaka",
    "gn:country_code":"NE",
    "gn:dem":367,
    "gn:feature_class":"P",
    "gn:feature_code":"PPL",
    "gn:name":"Tounga Kaka",
    "gn:population":0,
    "gn:timezone":"Africa/Niamey",
    "iso:country":"NE",
    "wof:name":"Tounga Kaka",
    "wof:placetype":"locality"
},
  "geometry": {"coordinates":[5.4977,14.1991],"type":"Point"}
}