{
  "type": "Feature",
  "properties": {
    "gn:admin1_code":"9.0",
    "gn:asciiname":"Egharghar Oua Zeggueghene",
    "gn:country_code":"NE",
    "gn:dem":205,
    "gn:feature_class":"P",
    "gn:feature_code":"PPL",
    "gn:name":"Egharghar Oua Zeggueghene",
    "gn:population":0,
    "gn:timezone":"Africa/Niamey",
    "iso:country":"NE",
    "wof:name":"Egharghar Oua Zeggueghene",
    "wof:placetype":"locality"
},
  "geometry": {"coordinates":[2.9877,13.7629],"type":"Point"}
}