{
  "type": "Feature",
  "properties": {
    "gn:admin1_code":"4.0",
    "gn:asciiname":"Toza",
    "gn:country_code":"NE",
    "gn:dem":389,
    "gn:feature_class":"P",
    "gn:feature_code":"PPL",
    "gn:name":"Toza",
    "gn:population":0,
    "gn:timezone":"Africa/Niamey",
    "iso:country":"NE",
    "name:ita_x_preferred":[
        "Toza"
    ],
    "name:spa_x_preferred":[
        "Toza"
    ],
    "wof:name":"Toza",
    "wof:placetype":"locality"
},
  "geometry": {"coordinates":[6.86246,13.38457],"type":"Point"}
}