{
  "type": "Feature",
  "properties": {
    "gn:admin1_code":"7.0",
    "gn:asciiname":"Zounkouda",
    "gn:country_code":"NE",
    "gn:dem":414,
    "gn:feature_class":"P",
    "gn:feature_code":"PPL",
    "gn:name":"Zounkouda",
    "gn:population":0,
    "gn:timezone":"Africa/Niamey",
    "iso:country":"NE",
    "wof:name":"Zounkouda",
    "wof:placetype":"locality"
},
  "geometry": {"coordinates":[8.87774,13.47552],"type":"Point"}
}