{
  "type": "Feature",
  "properties": {
    "gn:admin1_code":"3.0",
    "gn:asciiname":"Magarideye",
    "gn:country_code":"NE",
    "gn:dem":243,
    "gn:feature_class":"P",
    "gn:feature_code":"PPL",
    "gn:name":"Magarid\u00e8ye",
    "gn:population":0,
    "gn:timezone":"Africa/Niamey",
    "iso:country":"NE",
    "name:und_x_variant":[
        "Magaridey",
        "Magarid\u00e8ye"
    ],
    "wof:name":"Magarideye",
    "wof:placetype":"locality"
},
  "geometry": {"coordinates":[3.3369,13.2307],"type":"Point"}
}