{
  "type": "Feature",
  "properties": {
    "gn:admin1_code":"7.0",
    "gn:asciiname":"Dan Kouaram",
    "gn:country_code":"NE",
    "gn:dem":439,
    "gn:feature_class":"P",
    "gn:feature_code":"PPL",
    "gn:name":"Dan Kouaram",
    "gn:population":0,
    "gn:timezone":"Africa/Niamey",
    "iso:country":"NE",
    "wof:name":"Dan Kouaram",
    "wof:placetype":"locality"
},
  "geometry": {"coordinates":[9.45079,13.91835],"type":"Point"}
}