{
  "type": "Feature",
  "properties": {
    "gn:admin1_code":"6.0",
    "gn:asciiname":"Dan Totchi",
    "gn:country_code":"NE",
    "gn:dem":314,
    "gn:feature_class":"P",
    "gn:feature_code":"PPL",
    "gn:name":"Dan Totchi",
    "gn:population":0,
    "gn:timezone":"Africa/Niamey",
    "iso:country":"NE",
    "wof:name":"Dan Totchi",
    "wof:placetype":"locality"
},
  "geometry": {"coordinates":[6.13797,13.79997],"type":"Point"}
}