{
  "type": "Feature",
  "properties": {
    "gn:admin1_code":"9.0",
    "gn:asciiname":"Korgom",
    "gn:country_code":"NE",
    "gn:dem":232,
    "gn:feature_class":"P",
    "gn:feature_code":"PPL",
    "gn:name":"Korgom",
    "gn:population":0,
    "gn:timezone":"Africa/Niamey",
    "iso:country":"NE",
    "name:deu_x_preferred":[
        "Korgom"
    ],
    "name:fra_x_preferred":[
        "Korgom"
    ],
    "name:ita_x_preferred":[
        "Korgom"
    ],
    "name:msa_x_preferred":[
        "Korgom"
    ],
    "name:ron_x_preferred":[
        "Korgom"
    ],
    "name:spa_x_preferred":[
        "Korgom"
    ],
    "name:und_x_variant":[
        "Korgam"
    ],
    "wof:name":"Korgom",
    "wof:placetype":"locality"
},
  "geometry": {"coordinates":[3.1876,13.8699],"type":"Point"}
}