{
  "type": "Feature",
  "properties": {
    "gn:admin1_code":"2.0",
    "gn:asciiname":"Madou Koyari",
    "gn:country_code":"NE",
    "gn:dem":351,
    "gn:feature_class":"P",
    "gn:feature_code":"PPL",
    "gn:name":"Madou Koyari",
    "gn:population":0,
    "gn:timezone":"Africa/Niamey",
    "iso:country":"NE",
    "wof:name":"Madou Koyari",
    "wof:placetype":"locality"
},
  "geometry": {"coordinates":[10.73722,13.54931],"type":"Point"}
}