{
  "type": "Feature",
  "properties": {
    "gn:admin1_code":"6.0",
    "gn:asciiname":"Taboukawa",
    "gn:country_code":"NE",
    "gn:dem":363,
    "gn:feature_class":"P",
    "gn:feature_code":"PPL",
    "gn:name":"Taboukawa",
    "gn:population":0,
    "gn:timezone":"Africa/Niamey",
    "iso:country":"NE",
    "wof:name":"Taboukawa",
    "wof:placetype":"locality"
},
  "geometry": {"coordinates":[5.2891,14.7614],"type":"Point"}
}