{
  "type": "Feature",
  "properties": {
    "gn:admin1_code":"4.0",
    "gn:asciiname":"Wala Dan Marke",
    "gn:country_code":"NE",
    "gn:dem":417,
    "gn:feature_class":"P",
    "gn:feature_code":"PPL",
    "gn:name":"Wala Dan Mark\u00e9",
    "gn:population":0,
    "gn:timezone":"Africa/Niamey",
    "iso:country":"NE",
    "name:und_x_variant":[
        "Dan Mark\u00e9",
        "Wala Dan Mark\u00e9"
    ],
    "wof:name":"Wala Dan Marke",
    "wof:placetype":"locality"
},
  "geometry": {"coordinates":[6.54382,14.31987],"type":"Point"}
}