{
  "type": "Feature",
  "properties": {
    "gn:admin1_code":"2.0",
    "gn:asciiname":"Kaya",
    "gn:country_code":"NE",
    "gn:dem":305,
    "gn:feature_class":"P",
    "gn:feature_code":"PPL",
    "gn:name":"Kaya",
    "gn:population":0,
    "gn:timezone":"Africa/Niamey",
    "iso:country":"NE",
    "name:bel_x_preferred":[
        "\u041a\u0430\u044f"
    ],
    "name:ben_x_preferred":[
        "\u0995\u09be\u09df\u09be"
    ],
    "name:ceb_x_preferred":[
        "Kaya"
    ],
    "name:deu_x_preferred":[
        "Kaya"
    ],
    "name:fas_x_preferred":[
        "\u06a9\u0627\u06cc\u0627"
    ],
    "name:fra_x_preferred":[
        "Kaya"
    ],
    "name:heb_x_preferred":[
        "\u05e7\u05d0\u05d9\u05d4"
    ],
    "name:hin_x_preferred":[
        "\u0915\u093e\u092f\u093e"
    ],
    "name:hun_x_preferred":[
        "Kaya"
    ],
    "name:ind_x_preferred":[
        "Kaya"
    ],
    "name:ita_x_preferred":[
        "Kaya"
    ],
    "name:jpn_x_preferred":[
        "\u30ab\u30e4"
    ],
    "name:kaz_x_preferred":[
        "\u041a\u0430\u044f"
    ],
    "name:msa_x_preferred":[
        "Kaya"
    ],
    "name:nld_x_preferred":[
        "Kaya"
    ],
    "name:nor_x_preferred":[
        "Kaya"
    ],
    "name:pol_x_preferred":[
        "Kaya"
    ],
    "name:por_x_preferred":[
        "Kaya"
    ],
    "name:rus_x_preferred":[
        "\u041a\u0430\u044f"
    ],
    "name:spa_x_preferred":[
        "Kaya"
    ],
    "name:srp_x_preferred":[
        "\u041a\u0430\u0458\u0430"
    ],
    "name:swe_x_preferred":[
        "Kaya"
    ],
    "name:ukr_x_preferred":[
        "\u041a\u0430\u044f"
    ],
    "name:vie_x_preferred":[
        "Kaya"
    ],
    "wof:name":"Kaya",
    "wof:placetype":"locality"
},
  "geometry": {"coordinates":[12.68544,13.30642],"type":"Point"}
}