{
  "type": "Feature",
  "properties": {
    "gn:admin1_code":"3.0",
    "gn:asciiname":"Yelou Keyna",
    "gn:country_code":"NE",
    "gn:dem":202,
    "gn:feature_class":"P",
    "gn:feature_code":"PPL",
    "gn:name":"Y\u00e9lou Keyna",
    "gn:population":0,
    "gn:timezone":"Africa/Niamey",
    "iso:country":"NE",
    "name:und_x_variant":[
        "Y\u00e9lou-Ka\u00efna",
        "Y\u00e9lou Keyna"
    ],
    "wof:name":"Yelou Keyna",
    "wof:placetype":"locality"
},
  "geometry": {"coordinates":[3.49431,12.91108],"type":"Point"}
}