{
  "type": "Feature",
  "properties": {
    "gn:admin1_code":"9.0",
    "gn:asciiname":"Bingaro Godie",
    "gn:country_code":"NE",
    "gn:dem":230,
    "gn:feature_class":"P",
    "gn:feature_code":"PPL",
    "gn:name":"Bingaro Godi\u00e9",
    "gn:population":0,
    "gn:timezone":"Africa/Niamey",
    "iso:country":"NE",
    "wof:name":"Bingaro Godie",
    "wof:placetype":"locality"
},
  "geometry": {"coordinates":[2.0338,12.89461],"type":"Point"}
}