{
  "type": "Feature",
  "properties": {
    "gn:admin1_code":"7.0",
    "gn:asciiname":"Bouroum Bouroum",
    "gn:country_code":"NE",
    "gn:dem":433,
    "gn:feature_class":"P",
    "gn:feature_code":"PPL",
    "gn:name":"Bouroum Bouroum",
    "gn:population":0,
    "gn:timezone":"Africa/Niamey",
    "iso:country":"NE",
    "name:und_x_variant":[
        "Ifara",
        "Bouroum Bouroum"
    ],
    "wof:name":"Bouroum Bouroum",
    "wof:placetype":"locality"
},
  "geometry": {"coordinates":[8.88421,13.64032],"type":"Point"}
}