{
  "type": "Feature",
  "properties": {
    "gn:admin1_code":"9.0",
    "gn:asciiname":"Bokey",
    "gn:country_code":"NE",
    "gn:dem":274,
    "gn:feature_class":"P",
    "gn:feature_code":"PPL",
    "gn:name":"Bok\u00e8y",
    "gn:population":0,
    "gn:timezone":"Africa/Niamey",
    "iso:country":"NE",
    "wof:name":"Bokey",
    "wof:placetype":"locality"
},
  "geometry": {"coordinates":[2.39513,14.25107],"type":"Point"}
}