{
  "type": "Feature",
  "properties": {
    "gn:admin1_code":"6.0",
    "gn:asciiname":"Kagam",
    "gn:country_code":"NE",
    "gn:dem":403,
    "gn:feature_class":"P",
    "gn:feature_code":"PPL",
    "gn:name":"Kagam",
    "gn:population":0,
    "gn:timezone":"Africa/Niamey",
    "iso:country":"NE",
    "wof:name":"Kagam",
    "wof:placetype":"locality"
},
  "geometry": {"coordinates":[6.40483,14.71222],"type":"Point"}
}