{
  "type": "Feature",
  "properties": {
    "gn:admin1_code":"2.0",
    "gn:asciiname":"Gabalam",
    "gn:country_code":"NE",
    "gn:dem":344,
    "gn:feature_class":"P",
    "gn:feature_code":"PPL",
    "gn:name":"Gabalam",
    "gn:population":0,
    "gn:timezone":"Africa/Niamey",
    "iso:country":"NE",
    "wof:name":"Gabalam",
    "wof:placetype":"locality"
},
  "geometry": {"coordinates":[11.3684,13.5916],"type":"Point"}
}