{
  "type": "Feature",
  "properties": {
    "gn:admin1_code":"4.0",
    "gn:asciiname":"Dan Faro",
    "gn:country_code":"NE",
    "gn:dem":326,
    "gn:feature_class":"P",
    "gn:feature_code":"PPL",
    "gn:name":"Dan Faro",
    "gn:population":0,
    "gn:timezone":"Africa/Niamey",
    "iso:country":"NE",
    "wof:name":"Dan Faro",
    "wof:placetype":"locality"
},
  "geometry": {"coordinates":[6.47178,13.93987],"type":"Point"}
}