{
  "type": "Feature",
  "properties": {
    "gn:admin1_code":"7.0",
    "gn:asciiname":"Gouzoubouk",
    "gn:country_code":"NE",
    "gn:dem":399,
    "gn:feature_class":"P",
    "gn:feature_code":"PPL",
    "gn:name":"Gouzoubouk",
    "gn:population":0,
    "gn:timezone":"Africa/Niamey",
    "iso:country":"NE",
    "wof:name":"Gouzoubouk",
    "wof:placetype":"locality"
},
  "geometry": {"coordinates":[10.24152,13.64291],"type":"Point"}
}