{
  "type": "Feature",
  "properties": {
    "gn:admin1_code":"9.0",
    "gn:asciiname":"Lele Koynounga",
    "gn:country_code":"NE",
    "gn:dem":192,
    "gn:feature_class":"P",
    "gn:feature_code":"PPL",
    "gn:name":"L\u00e9l\u00e9 Koynounga",
    "gn:population":0,
    "gn:timezone":"Africa/Niamey",
    "iso:country":"NE",
    "name:und_x_variant":[
        "L\u00e9l\u00e9-Ka\u00efna",
        "L\u00e9ley Keyna",
        "L\u00e9l\u00e9 Koynounga"
    ],
    "wof:name":"Lele Koynounga",
    "wof:placetype":"locality"
},
  "geometry": {"coordinates":[2.1531,13.4155],"type":"Point"}
}