{
  "type": "Feature",
  "properties": {
    "gn:admin1_code":"9.0",
    "gn:asciiname":"Zama Kaina",
    "gn:country_code":"NE",
    "gn:dem":220,
    "gn:feature_class":"P",
    "gn:feature_code":"PPL",
    "gn:name":"Zama Kaina",
    "gn:population":0,
    "gn:timezone":"Africa/Niamey",
    "iso:country":"NE",
    "name:und_x_variant":[
        "Zama Keyna",
        "Zama Kaina"
    ],
    "wof:name":"Zama Kaina",
    "wof:placetype":"locality"
},
  "geometry": {"coordinates":[2.83391,14.30018],"type":"Point"}
}