{
  "type": "Feature",
  "properties": {
    "gn:admin1_code":"4.0",
    "gn:asciiname":"Kankari Elhadji Dango",
    "gn:country_code":"NE",
    "gn:dem":380,
    "gn:feature_class":"P",
    "gn:feature_code":"PPL",
    "gn:name":"Kankari Elhadji Dango",
    "gn:population":0,
    "gn:timezone":"Africa/Niamey",
    "iso:country":"NE",
    "name:und_x_variant":[
        "Aladji Dango",
        "Alhadji Dango",
        "Kankari Elhadji Dango"
    ],
    "wof:name":"Kankari Elhadji Dango",
    "wof:placetype":"locality"
},
  "geometry": {"coordinates":[7.09693,13.6873],"type":"Point"}
}