{
  "type": "Feature",
  "properties": {
    "gn:admin1_code":"4.0",
    "gn:asciiname":"Malamey",
    "gn:country_code":"NE",
    "gn:dem":396,
    "gn:feature_class":"P",
    "gn:feature_code":"PPL",
    "gn:name":"M\u00e2lamey",
    "gn:population":0,
    "gn:timezone":"Africa/Niamey",
    "iso:country":"NE",
    "wof:name":"Malamey",
    "wof:placetype":"locality"
},
  "geometry": {"coordinates":[7.36408,13.96769],"type":"Point"}
}