{
  "type": "Feature",
  "properties": {
    "gn:admin1_code":"4.0",
    "gn:asciiname":"Tchibao Bawa",
    "gn:country_code":"NE",
    "gn:dem":318,
    "gn:feature_class":"P",
    "gn:feature_code":"PPL",
    "gn:name":"Tchibao Bawa",
    "gn:population":0,
    "gn:timezone":"Africa/Niamey",
    "iso:country":"NE",
    "wof:name":"Tchibao Bawa",
    "wof:placetype":"locality"
},
  "geometry": {"coordinates":[6.48244,13.83687],"type":"Point"}
}