{
  "type": "Feature",
  "properties": {
    "gn:admin1_code":"3.0",
    "gn:asciiname":"Ngounga Zarma",
    "gn:country_code":"NE",
    "gn:dem":208,
    "gn:feature_class":"P",
    "gn:feature_code":"PPL",
    "gn:name":"Ngounga Zarma",
    "gn:population":0,
    "gn:timezone":"Africa/Niamey",
    "iso:country":"NE",
    "name:und_x_variant":[
        "Go\u00ebnga",
        "Gohenga",
        "Ngounga Zarma"
    ],
    "wof:name":"Ngounga Zarma",
    "wof:placetype":"locality"
},
  "geometry": {"coordinates":[2.8275,13.1794],"type":"Point"}
}