{
  "type": "Feature",
  "properties": {
    "gn:admin1_code":"3.0",
    "gn:asciiname":"Tounga Goube",
    "gn:country_code":"NE",
    "gn:dem":212,
    "gn:feature_class":"P",
    "gn:feature_code":"PPL",
    "gn:name":"Tounga Goub\u00e9",
    "gn:population":0,
    "gn:timezone":"Africa/Niamey",
    "iso:country":"NE",
    "wof:name":"Tounga Goube",
    "wof:placetype":"locality"
},
  "geometry": {"coordinates":[3.94789,12.94724],"type":"Point"}
}