{
  "type": "Feature",
  "properties": {
    "gn:admin1_code":"4.0",
    "gn:asciiname":"Dadeo",
    "gn:country_code":"NE",
    "gn:dem":340,
    "gn:feature_class":"P",
    "gn:feature_code":"PPL",
    "gn:name":"Dad\u00e9o",
    "gn:population":0,
    "gn:timezone":"Africa/Niamey",
    "iso:country":"NE",
    "wof:name":"Dadeo",
    "wof:placetype":"locality"
},
  "geometry": {"coordinates":[6.84507,13.70886],"type":"Point"}
}