{
  "type": "Feature",
  "properties": {
    "gn:admin1_code":"7.0",
    "gn:asciiname":"Baka Doubou",
    "gn:country_code":"NE",
    "gn:dem":463,
    "gn:feature_class":"P",
    "gn:feature_code":"PPL",
    "gn:name":"Baka Doubou",
    "gn:population":0,
    "gn:timezone":"Africa/Niamey",
    "iso:country":"NE",
    "wof:name":"Baka Doubou",
    "wof:placetype":"locality"
},
  "geometry": {"coordinates":[8.35205,13.14288],"type":"Point"}
}