{
  "type": "Feature",
  "properties": {
    "gn:admin1_code":"4.0",
    "gn:asciiname":"Rougawa",
    "gn:country_code":"NE",
    "gn:dem":386,
    "gn:feature_class":"P",
    "gn:feature_code":"PPL",
    "gn:name":"Rougawa",
    "gn:population":0,
    "gn:timezone":"Africa/Niamey",
    "iso:country":"NE",
    "wof:name":"Rougawa",
    "wof:placetype":"locality"
},
  "geometry": {"coordinates":[7.19934,13.60384],"type":"Point"}
}