{
  "type": "Feature",
  "properties": {
    "gn:admin1_code":"6.0",
    "gn:asciiname":"Gisenbiri",
    "gn:country_code":"NE",
    "gn:dem":388,
    "gn:feature_class":"P",
    "gn:feature_code":"PPL",
    "gn:name":"Gisenbiri",
    "gn:population":0,
    "gn:timezone":"Africa/Niamey",
    "iso:country":"NE",
    "wof:name":"Gisenbiri",
    "wof:placetype":"locality"
},
  "geometry": {"coordinates":[5.9877,14.2756],"type":"Point"}
}