{
  "type": "Feature",
  "properties": {
    "gn:admin1_code":"9.0",
    "gn:asciiname":"Talkadabey",
    "gn:country_code":"NE",
    "gn:dem":232,
    "gn:feature_class":"P",
    "gn:feature_code":"PPL",
    "gn:name":"Talkadabey",
    "gn:population":0,
    "gn:timezone":"Africa/Niamey",
    "iso:country":"NE",
    "name:und_x_variant":[
        "Takaldebei",
        "Takaldebey",
        "Talkadabey"
    ],
    "wof:name":"Talkadabey",
    "wof:placetype":"locality"
},
  "geometry": {"coordinates":[2.30004,14.31089],"type":"Point"}
}