{
  "type": "Feature",
  "properties": {
    "gn:admin1_code":"4.0",
    "gn:asciiname":"Yel Guieza",
    "gn:country_code":"NE",
    "gn:dem":423,
    "gn:feature_class":"P",
    "gn:feature_code":"PPL",
    "gn:name":"Yel Gui\u00e9za",
    "gn:population":0,
    "gn:timezone":"Africa/Niamey",
    "iso:country":"NE",
    "name:und_x_variant":[
        "\u00c8l G\u00e8za",
        "El Gu\u00e8za",
        "Yel Gui\u00e9za"
    ],
    "wof:name":"Yel Guieza",
    "wof:placetype":"locality"
},
  "geometry": {"coordinates":[7.91369,13.43077],"type":"Point"}
}