{
  "type": "Feature",
  "properties": {
    "gn:admin1_code":"2.0",
    "gn:asciiname":"Gamaram",
    "gn:country_code":"NE",
    "gn:dem":328,
    "gn:feature_class":"P",
    "gn:feature_code":"PPL",
    "gn:name":"Gamaram",
    "gn:population":0,
    "gn:timezone":"Africa/Niamey",
    "iso:country":"NE",
    "wof:name":"Gamaram",
    "wof:placetype":"locality"
},
  "geometry": {"coordinates":[11.34815,13.57445],"type":"Point"}
}