{
  "type": "Feature",
  "properties": {
    "gn:admin1_code":"7.0",
    "gn:asciiname":"Magaria",
    "gn:country_code":"NE",
    "gn:dem":537,
    "gn:feature_class":"P",
    "gn:feature_code":"PPL",
    "gn:name":"Magaria",
    "gn:population":0,
    "gn:timezone":"Africa/Niamey",
    "iso:country":"NE",
    "wof:name":"Magaria",
    "wof:placetype":"locality"
},
  "geometry": {"coordinates":[9.2344,14.0398],"type":"Point"}
}