{
  "type": "Feature",
  "properties": {
    "gn:admin1_code":"4.0",
    "gn:asciiname":"Oumbouni",
    "gn:country_code":"NE",
    "gn:dem":435,
    "gn:feature_class":"P",
    "gn:feature_code":"PPL",
    "gn:name":"Oumbouni",
    "gn:population":0,
    "gn:timezone":"Africa/Niamey",
    "iso:country":"NE",
    "wof:name":"Oumbouni",
    "wof:placetype":"locality"
},
  "geometry": {"coordinates":[8.19425,13.64938],"type":"Point"}
}