{
  "type": "Feature",
  "properties": {
    "gn:admin1_code":"3.0",
    "gn:asciiname":"Gajita",
    "gn:cc2":"NE",
    "gn:country_code":"NE",
    "gn:dem":196,
    "gn:feature_class":"P",
    "gn:feature_code":"PPL",
    "gn:name":"Gajita",
    "gn:population":0,
    "gn:timezone":"Africa/Niamey",
    "iso:country":"NE",
    "name:und_x_variant":[
        "Gajila",
        "Gajita"
    ],
    "wof:name":"Gajita",
    "wof:placetype":"locality"
},
  "geometry": {"coordinates":[3.51667,12.11667],"type":"Point"}
}