{
  "type": "Feature",
  "properties": {
    "gn:admin1_code":"4.0",
    "gn:asciiname":"Sansanawa Wakili",
    "gn:country_code":"NE",
    "gn:dem":411,
    "gn:feature_class":"P",
    "gn:feature_code":"PPL",
    "gn:name":"Sansanawa Wakili",
    "gn:population":0,
    "gn:timezone":"Africa/Niamey",
    "iso:country":"NE",
    "wof:name":"Sansanawa Wakili",
    "wof:placetype":"locality"
},
  "geometry": {"coordinates":[8.05556,14.06915],"type":"Point"}
}