{
  "type": "Feature",
  "properties": {
    "gn:admin1_code":"7.0",
    "gn:asciiname":"Kaliram",
    "gn:country_code":"NE",
    "gn:dem":495,
    "gn:feature_class":"P",
    "gn:feature_code":"PPL",
    "gn:name":"Kaliram",
    "gn:population":0,
    "gn:timezone":"Africa/Niamey",
    "iso:country":"NE",
    "wof:name":"Kaliram",
    "wof:placetype":"locality"
},
  "geometry": {"coordinates":[9.0621,14.8766],"type":"Point"}
}