{
  "type": "Feature",
  "properties": {
    "gn:admin1_code":"3.0",
    "gn:asciiname":"Koremairoua",
    "gn:country_code":"NE",
    "gn:dem":231,
    "gn:feature_class":"P",
    "gn:feature_code":"PPL",
    "gn:name":"Kor\u00e9ma\u00efroua",
    "gn:population":0,
    "gn:timezone":"Africa/Niamey",
    "iso:country":"NE",
    "name:deu_x_preferred":[
        "Kor\u00e9 Ma\u00efroua"
    ],
    "name:ita_x_preferred":[
        "Kor\u00e9 Ma\u00efroua"
    ],
    "name:msa_x_preferred":[
        "Kor\u00e9 Ma\u00efroua"
    ],
    "name:ron_x_preferred":[
        "Kor\u00e9 Ma\u00efroua"
    ],
    "name:und_x_variant":[
        "Kor\u00e9mairwa",
        "Kor\u00e9",
        "Kor\u00e9 Mayroua",
        "Kor\u00e9-M\u00e9roua",
        "Kor\u00e9ma\u00efroua"
    ],
    "wof:name":"Koremairoua",
    "wof:placetype":"locality"
},
  "geometry": {"coordinates":[3.9079,13.3028],"type":"Point"}
}