{
  "type": "Feature",
  "properties": {
    "gn:admin1_code":"1.0",
    "gn:asciiname":"Tajajaret",
    "gn:country_code":"NE",
    "gn:dem":493,
    "gn:feature_class":"P",
    "gn:feature_code":"PPL",
    "gn:name":"Tajajaret",
    "gn:population":0,
    "gn:timezone":"Africa/Niamey",
    "iso:country":"NE",
    "wof:name":"Tajajaret",
    "wof:placetype":"locality"
},
  "geometry": {"coordinates":[7.96,16.98],"type":"Point"}
}