{
  "type": "Feature",
  "properties": {
    "gn:admin1_code":"3.0",
    "gn:asciiname":"Bombohi Ganda",
    "gn:country_code":"NE",
    "gn:dem":182,
    "gn:feature_class":"P",
    "gn:feature_code":"PPL",
    "gn:name":"Bombohi Ganda",
    "gn:population":0,
    "gn:timezone":"Africa/Niamey",
    "iso:country":"NE",
    "wof:name":"Bombohi Ganda",
    "wof:placetype":"locality"
},
  "geometry": {"coordinates":[2.87681,12.86258],"type":"Point"}
}