{
  "type": "Feature",
  "properties": {
    "gn:admin1_code":"2.0",
    "gn:asciiname":"Malam Kournari",
    "gn:country_code":"NE",
    "gn:dem":312,
    "gn:feature_class":"P",
    "gn:feature_code":"PPL",
    "gn:name":"Malam Kournari",
    "gn:population":0,
    "gn:timezone":"Africa/Niamey",
    "iso:country":"NE",
    "wof:name":"Malam Kournari",
    "wof:placetype":"locality"
},
  "geometry": {"coordinates":[12.29849,13.25747],"type":"Point"}
}