{
  "type": "Feature",
  "properties": {
    "gn:admin1_code":"6.0",
    "gn:asciiname":"Zangon Amisila",
    "gn:country_code":"NE",
    "gn:dem":346,
    "gn:feature_class":"P",
    "gn:feature_code":"PPL",
    "gn:name":"Zangon Amisila",
    "gn:population":0,
    "gn:timezone":"Africa/Niamey",
    "iso:country":"NE",
    "wof:name":"Zangon Amisila",
    "wof:placetype":"locality"
},
  "geometry": {"coordinates":[5.4171,14.3717],"type":"Point"}
}