{
  "type": "Feature",
  "properties": {
    "gn:admin1_code":"9.0",
    "gn:asciiname":"Neyni",
    "gn:country_code":"NE",
    "gn:dem":203,
    "gn:feature_class":"P",
    "gn:feature_code":"PPL",
    "gn:name":"Neyni",
    "gn:population":0,
    "gn:timezone":"Africa/Niamey",
    "iso:country":"NE",
    "wof:name":"Neyni",
    "wof:placetype":"locality"
},
  "geometry": {"coordinates":[1.434,14.21183],"type":"Point"}
}