{
  "type": "Feature",
  "properties": {
    "gn:admin1_code":"6.0",
    "gn:asciiname":"Tapkin Matjiji",
    "gn:country_code":"NE",
    "gn:dem":328,
    "gn:feature_class":"P",
    "gn:feature_code":"PPL",
    "gn:name":"Tapkin Matjiji",
    "gn:population":0,
    "gn:timezone":"Africa/Niamey",
    "iso:country":"NE",
    "name:und_x_variant":[
        "Tabkin Matchiji",
        "Tapkin Matjiji"
    ],
    "wof:name":"Tapkin Matjiji",
    "wof:placetype":"locality"
},
  "geometry": {"coordinates":[6.124,13.90773],"type":"Point"}
}