{
  "type": "Feature",
  "properties": {
    "gn:admin1_code":"2.0",
    "gn:asciiname":"Loutouri",
    "gn:country_code":"NE",
    "gn:dem":321,
    "gn:feature_class":"P",
    "gn:feature_code":"PPL",
    "gn:name":"Loutouri",
    "gn:population":0,
    "gn:timezone":"Africa/Niamey",
    "iso:country":"NE",
    "wof:name":"Loutouri",
    "wof:placetype":"locality"
},
  "geometry": {"coordinates":[12.28083,13.24934],"type":"Point"}
}