{
  "type": "Feature",
  "properties": {
    "gn:admin1_code":"2.0",
    "gn:asciiname":"Ari Arnari",
    "gn:country_code":"NE",
    "gn:dem":308,
    "gn:feature_class":"P",
    "gn:feature_code":"PPL",
    "gn:name":"Ari Arnari",
    "gn:population":0,
    "gn:timezone":"Africa/Niamey",
    "iso:country":"NE",
    "wof:name":"Ari Arnari",
    "wof:placetype":"locality"
},
  "geometry": {"coordinates":[12.52471,13.2188],"type":"Point"}
}