{
  "type": "Feature",
  "properties": {
    "gn:admin1_code":"7.0",
    "gn:asciiname":"Madara",
    "gn:country_code":"NE",
    "gn:dem":447,
    "gn:feature_class":"P",
    "gn:feature_code":"PPL",
    "gn:name":"Madara",
    "gn:population":0,
    "gn:timezone":"Africa/Niamey",
    "iso:country":"NE",
    "name:bul_x_preferred":[
        "\u041c\u0430\u0434\u0430\u0440\u0430"
    ],
    "name:ceb_x_preferred":[
        "Madara"
    ],
    "name:deu_x_preferred":[
        "Madara"
    ],
    "name:fin_x_preferred":[
        "Madara"
    ],
    "name:fra_x_preferred":[
        "Madara"
    ],
    "name:ind_x_preferred":[
        "Madara"
    ],
    "name:ita_x_preferred":[
        "Madara"
    ],
    "name:lav_x_preferred":[
        "Madara"
    ],
    "name:por_x_preferred":[
        "Madara"
    ],
    "name:rus_x_preferred":[
        "\u041c\u0430\u0434\u0430\u0440\u0430"
    ],
    "name:slk_x_preferred":[
        "Madara"
    ],
    "name:spa_x_preferred":[
        "Madara"
    ],
    "name:swe_x_preferred":[
        "Madara"
    ],
    "name:tgl_x_preferred":[
        "Madara"
    ],
    "name:ukr_x_preferred":[
        "\u041c\u0430\u0434\u0430\u0440\u0430"
    ],
    "wof:name":"Madara",
    "wof:placetype":"locality"
},
  "geometry": {"coordinates":[9.02652,13.89922],"type":"Point"}
}