{
  "type": "Feature",
  "properties": {
    "gn:admin1_code":"9.0",
    "gn:asciiname":"Beri",
    "gn:country_code":"NE",
    "gn:dem":192,
    "gn:feature_class":"P",
    "gn:feature_code":"PPL",
    "gn:name":"B\u00e9ri",
    "gn:population":0,
    "gn:timezone":"Africa/Niamey",
    "iso:country":"NE",
    "name:bul_x_preferred":[
        "\u0411\u0435\u0440\u0438"
    ],
    "name:ceb_x_preferred":[
        "Beri"
    ],
    "name:deu_x_preferred":[
        "Beri"
    ],
    "name:fra_x_preferred":[
        "Beri"
    ],
    "name:hin_x_preferred":[
        "\u092c\u0947\u0930\u0940"
    ],
    "name:msa_x_preferred":[
        "Beri"
    ],
    "name:rus_x_preferred":[
        "\u0411\u0435\u0440\u0438"
    ],
    "name:srp_x_preferred":[
        "\u0411\u0435\u0440\u0438"
    ],
    "name:swe_x_preferred":[
        "Beri"
    ],
    "wof:name":"Beri",
    "wof:placetype":"locality"
},
  "geometry": {"coordinates":[1.9196,13.5884],"type":"Point"}
}