{
  "type": "Feature",
  "properties": {
    "gn:admin1_code":"3.0",
    "gn:asciiname":"Goubawa",
    "gn:country_code":"NE",
    "gn:dem":248,
    "gn:feature_class":"P",
    "gn:feature_code":"PPL",
    "gn:name":"Goubawa",
    "gn:population":0,
    "gn:timezone":"Africa/Niamey",
    "iso:country":"NE",
    "wof:name":"Goubawa",
    "wof:placetype":"locality"
},
  "geometry": {"coordinates":[3.7716,12.86777],"type":"Point"}
}