{
  "type": "Feature",
  "properties": {
    "gn:admin1_code":"3.0",
    "gn:asciiname":"Danya",
    "gn:country_code":"NE",
    "gn:dem":267,
    "gn:feature_class":"P",
    "gn:feature_code":"PPL",
    "gn:name":"Danya",
    "gn:population":0,
    "gn:timezone":"Africa/Niamey",
    "iso:country":"NE",
    "wof:name":"Danya",
    "wof:placetype":"locality"
},
  "geometry": {"coordinates":[4.27737,13.96407],"type":"Point"}
}