{
  "type": "Feature",
  "properties": {
    "gn:admin1_code":"7.0",
    "gn:asciiname":"Garin Yerima",
    "gn:country_code":"NE",
    "gn:dem":445,
    "gn:feature_class":"P",
    "gn:feature_code":"PPL",
    "gn:name":"Garin Y\u00e9rima",
    "gn:population":0,
    "gn:timezone":"Africa/Niamey",
    "iso:country":"NE",
    "name:und_x_variant":[
        "Dan Bad\u00e9",
        "Garin Y\u00e9rima"
    ],
    "wof:name":"Garin Yerima",
    "wof:placetype":"locality"
},
  "geometry": {"coordinates":[8.72416,13.60145],"type":"Point"}
}