{
  "type": "Feature",
  "properties": {
    "gn:admin1_code":"9.0",
    "gn:asciiname":"Kassou Kassa",
    "gn:country_code":"NE",
    "gn:dem":200,
    "gn:feature_class":"P",
    "gn:feature_code":"PPL",
    "gn:name":"Kassou Kassa",
    "gn:population":0,
    "gn:timezone":"Africa/Niamey",
    "iso:country":"NE",
    "name:und_x_variant":[
        "Mansar\u00e9",
        "Kassou Kassa"
    ],
    "wof:name":"Kassou Kassa",
    "wof:placetype":"locality"
},
  "geometry": {"coordinates":[1.70171,13.75313],"type":"Point"}
}