{
  "type": "Feature",
  "properties": {
    "gn:admin1_code":"7.0",
    "gn:asciiname":"Kolguidjigaoua",
    "gn:country_code":"NE",
    "gn:dem":514,
    "gn:feature_class":"P",
    "gn:feature_code":"PPL",
    "gn:name":"Kolguidjigaoua",
    "gn:population":0,
    "gn:timezone":"Africa/Niamey",
    "iso:country":"NE",
    "wof:name":"Kolguidjigaoua",
    "wof:placetype":"locality"
},
  "geometry": {"coordinates":[10.0823,14.6174],"type":"Point"}
}