{
  "type": "Feature",
  "properties": {
    "gn:admin1_code":"9.0",
    "gn:asciiname":"Mayanga Gourmantche",
    "gn:country_code":"NE",
    "gn:dem":233,
    "gn:feature_class":"P",
    "gn:feature_code":"PPL",
    "gn:name":"Mayanga Gourmantch\u00e9",
    "gn:population":0,
    "gn:timezone":"Africa/Niamey",
    "iso:country":"NE",
    "name:und_x_variant":[
        "Mayenga",
        "Mayanga Gourmantch\u00e9",
        "Mayanga"
    ],
    "wof:name":"Mayanga Gourmantche",
    "wof:placetype":"locality"
},
  "geometry": {"coordinates":[1.83984,12.80458],"type":"Point"}
}