{
  "type": "Feature",
  "properties": {
    "gn:admin1_code":"7.0",
    "gn:asciiname":"Magara",
    "gn:country_code":"NE",
    "gn:dem":475,
    "gn:feature_class":"P",
    "gn:feature_code":"PPL",
    "gn:name":"Magara",
    "gn:population":0,
    "gn:timezone":"Africa/Niamey",
    "iso:country":"NE",
    "wof:name":"Magara",
    "wof:placetype":"locality"
},
  "geometry": {"coordinates":[9.0173,14.6661],"type":"Point"}
}