{
  "type": "Feature",
  "properties": {
    "gn:admin1_code":"9.0",
    "gn:asciiname":"Guidel",
    "gn:country_code":"NE",
    "gn:dem":232,
    "gn:feature_class":"P",
    "gn:feature_code":"PPL",
    "gn:name":"Guidel",
    "gn:population":0,
    "gn:timezone":"Africa/Niamey",
    "iso:country":"NE",
    "name:als_x_preferred":[
        "Guidel"
    ],
    "name:bre_x_preferred":[
        "Gwidel"
    ],
    "name:cat_x_preferred":[
        "Guidel"
    ],
    "name:ceb_x_preferred":[
        "Guidel"
    ],
    "name:cym_x_preferred":[
        "Gwidel"
    ],
    "name:deu_x_preferred":[
        "Guidel"
    ],
    "name:eus_x_preferred":[
        "Guidel"
    ],
    "name:fin_x_preferred":[
        "Guidel"
    ],
    "name:fra_x_preferred":[
        "Guidel"
    ],
    "name:hun_x_preferred":[
        "Guidel"
    ],
    "name:ita_x_preferred":[
        "Guidel"
    ],
    "name:kaz_x_preferred":[
        "\u0413\u0438\u0434\u0435\u043b\u044c"
    ],
    "name:lat_x_preferred":[
        "Guidel"
    ],
    "name:msa_x_preferred":[
        "Guidel"
    ],
    "name:nld_x_preferred":[
        "Guidel"
    ],
    "name:oci_x_preferred":[
        "Gwidel"
    ],
    "name:pms_x_preferred":[
        "Guidel"
    ],
    "name:pol_x_preferred":[
        "Guidel"
    ],
    "name:por_x_preferred":[
        "Guidel"
    ],
    "name:ron_x_preferred":[
        "Guidel"
    ],
    "name:slk_x_preferred":[
        "Guidel"
    ],
    "name:spa_x_preferred":[
        "Guidel"
    ],
    "name:swe_x_preferred":[
        "Guidel"
    ],
    "name:ukr_x_preferred":[
        "\u0413\u0456\u0434\u0435\u043b\u044c"
    ],
    "name:uzb_x_preferred":[
        "Guidel"
    ],
    "name:vie_x_preferred":[
        "Guidel"
    ],
    "name:vol_x_preferred":[
        "Guidel"
    ],
    "name:war_x_preferred":[
        "Guidel"
    ],
    "wof:name":"Guidel",
    "wof:placetype":"locality"
},
  "geometry": {"coordinates":[1.64216,13.32963],"type":"Point"}
}