{
  "type": "Feature",
  "properties": {
    "gn:admin1_code":"9.0",
    "gn:asciiname":"Guidel",
    "gn:country_code":"NE",
    "gn:dem":232,
    "gn:feature_class":"P",
    "gn:feature_code":"PPL",
    "gn:name":"Guidel",
    "gn:population":0,
    "gn:timezone":"Africa/Niamey",
    "iso:country":"NE",
    "wof:name":"Guidel",
    "wof:placetype":"locality"
},
  "geometry": {"coordinates":[1.64216,13.32963],"type":"Point"}
}