{
  "type": "Feature",
  "properties": {
    "gn:admin1_code":"7.0",
    "gn:asciiname":"Abinouyami",
    "gn:country_code":"NE",
    "gn:dem":534,
    "gn:feature_class":"P",
    "gn:feature_code":"PPL",
    "gn:name":"Abinouyami",
    "gn:population":0,
    "gn:timezone":"Africa/Niamey",
    "iso:country":"NE",
    "wof:name":"Abinouyami",
    "wof:placetype":"locality"
},
  "geometry": {"coordinates":[10.064,14.5187],"type":"Point"}
}