{
  "type": "Feature",
  "properties": {
    "gn:admin1_code":"9.0",
    "gn:asciiname":"Gourberi",
    "gn:country_code":"NE",
    "gn:dem":270,
    "gn:feature_class":"P",
    "gn:feature_code":"PPL",
    "gn:name":"Gourb\u00e9ri",
    "gn:population":0,
    "gn:timezone":"Africa/Niamey",
    "iso:country":"NE",
    "wof:name":"Gourberi",
    "wof:placetype":"locality"
},
  "geometry": {"coordinates":[1.75063,14.15714],"type":"Point"}
}