{
  "type": "Feature",
  "properties": {
    "gn:admin1_code":"4.0",
    "gn:asciiname":"Kaydone",
    "gn:country_code":"NE",
    "gn:dem":316,
    "gn:feature_class":"P",
    "gn:feature_code":"PPL",
    "gn:name":"Kaydon\u00e9",
    "gn:population":0,
    "gn:timezone":"Africa/Niamey",
    "iso:country":"NE",
    "wof:name":"Kaydone",
    "wof:placetype":"locality"
},
  "geometry": {"coordinates":[6.52504,13.59587],"type":"Point"}
}