{
  "type": "Feature",
  "properties": {
    "gn:admin1_code":"4.0",
    "gn:asciiname":"Aderawa",
    "gn:country_code":"NE",
    "gn:dem":365,
    "gn:feature_class":"P",
    "gn:feature_code":"PPL",
    "gn:name":"Ad\u00e9rawa",
    "gn:population":0,
    "gn:timezone":"Africa/Niamey",
    "iso:country":"NE",
    "wof:name":"Aderawa",
    "wof:placetype":"locality"
},
  "geometry": {"coordinates":[7.12463,13.44153],"type":"Point"}
}