{
  "type": "Feature",
  "properties": {
    "gn:admin1_code":"4.0",
    "gn:asciiname":"Gardi",
    "gn:country_code":"NE",
    "gn:dem":421,
    "gn:feature_class":"P",
    "gn:feature_code":"PPL",
    "gn:name":"Gardi",
    "gn:population":0,
    "gn:timezone":"Africa/Niamey",
    "iso:country":"NE",
    "name:mar_x_preferred":[
        "\u092e\u0930\u093e\u0920\u0947 \u0917\u093e\u0930\u0926\u0940"
    ],
    "name:new_x_preferred":[
        "\u0917\u0930\u094d\u0926\u0940"
    ],
    "wof:name":"Gardi",
    "wof:placetype":"locality"
},
  "geometry": {"coordinates":[7.46177,14.21044],"type":"Point"}
}