{
  "type": "Feature",
  "properties": {
    "gn:admin1_code":"3.0",
    "gn:asciiname":"Goulouma-Kadi",
    "gn:country_code":"NE",
    "gn:dem":228,
    "gn:feature_class":"P",
    "gn:feature_code":"PPL",
    "gn:name":"Goulouma-Kadi",
    "gn:population":0,
    "gn:timezone":"Africa/Niamey",
    "iso:country":"NE",
    "wof:name":"Goulouma-Kadi",
    "wof:placetype":"locality"
},
  "geometry": {"coordinates":[3.7047,13.146],"type":"Point"}
}