{
  "type": "Feature",
  "properties": {
    "gn:admin1_code":"6.0",
    "gn:asciiname":"Tounga Abouba",
    "gn:country_code":"NE",
    "gn:dem":292,
    "gn:feature_class":"P",
    "gn:feature_code":"PPL",
    "gn:name":"Tounga Abouba",
    "gn:population":0,
    "gn:timezone":"Africa/Niamey",
    "iso:country":"NE",
    "wof:name":"Tounga Abouba",
    "wof:placetype":"locality"
},
  "geometry": {"coordinates":[5.3289,14.034],"type":"Point"}
}