{
  "type": "Feature",
  "properties": {
    "gn:admin1_code":"9.0",
    "gn:asciiname":"Tondi Habon",
    "gn:country_code":"NE",
    "gn:dem":229,
    "gn:feature_class":"P",
    "gn:feature_code":"PPL",
    "gn:name":"Tondi Habon",
    "gn:population":0,
    "gn:timezone":"Africa/Niamey",
    "iso:country":"NE",
    "wof:name":"Tondi Habon",
    "wof:placetype":"locality"
},
  "geometry": {"coordinates":[1.3952,13.71689],"type":"Point"}
}