{
  "type": "Feature",
  "properties": {
    "gn:admin1_code":"6.0",
    "gn:asciiname":"Taia Koune",
    "gn:country_code":"NE",
    "gn:dem":460,
    "gn:feature_class":"P",
    "gn:feature_code":"PPL",
    "gn:name":"Taia Koune",
    "gn:population":0,
    "gn:timezone":"Africa/Niamey",
    "iso:country":"NE",
    "name:und_x_variant":[
        "Jaja Koum\u00e9",
        "Taia Koune"
    ],
    "wof:name":"Taia Koune",
    "wof:placetype":"locality"
},
  "geometry": {"coordinates":[6.08663,14.72812],"type":"Point"}
}