{
  "type": "Feature",
  "properties": {
    "gn:admin1_code":"7.0",
    "gn:asciiname":"Tassaou Bougaje",
    "gn:country_code":"NE",
    "gn:dem":432,
    "gn:feature_class":"P",
    "gn:feature_code":"PPL",
    "gn:name":"Tassaou Bougaj\u00e9",
    "gn:population":0,
    "gn:timezone":"Africa/Niamey",
    "iso:country":"NE",
    "wof:name":"Tassaou Bougaje",
    "wof:placetype":"locality"
},
  "geometry": {"coordinates":[8.49224,13.52124],"type":"Point"}
}