{
  "type": "Feature",
  "properties": {
    "gn:admin1_code":"3.0",
    "gn:asciiname":"Wonkel-Keini",
    "gn:country_code":"NE",
    "gn:dem":228,
    "gn:feature_class":"P",
    "gn:feature_code":"PPL",
    "gn:name":"Wonkel-K\u00e9\u00efni",
    "gn:population":0,
    "gn:timezone":"Africa/Niamey",
    "iso:country":"NE",
    "name:und_x_variant":[
        "Wonkel Keyni",
        "Wonkel-K\u00e9\u00efni"
    ],
    "wof:name":"Wonkel-Keini",
    "wof:placetype":"locality"
},
  "geometry": {"coordinates":[3.5107,13.3044],"type":"Point"}
}