{
  "type": "Feature",
  "properties": {
    "gn:admin1_code":"4.0",
    "gn:asciiname":"Sourouje",
    "gn:country_code":"NE",
    "gn:dem":420,
    "gn:feature_class":"P",
    "gn:feature_code":"PPL",
    "gn:name":"Sourouj\u00e9",
    "gn:population":0,
    "gn:timezone":"Africa/Niamey",
    "iso:country":"NE",
    "wof:name":"Sourouje",
    "wof:placetype":"locality"
},
  "geometry": {"coordinates":[7.50616,13.46667],"type":"Point"}
}