{
  "type": "Feature",
  "properties": {
    "gn:admin1_code":"7.0",
    "gn:asciiname":"Kaoboul",
    "gn:country_code":"NE",
    "gn:dem":432,
    "gn:feature_class":"P",
    "gn:feature_code":"PPL",
    "gn:name":"Kaoboul",
    "gn:population":0,
    "gn:timezone":"Africa/Niamey",
    "iso:country":"NE",
    "wof:name":"Kaoboul",
    "wof:placetype":"locality"
},
  "geometry": {"coordinates":[9.5307,13.9801],"type":"Point"}
}