{
  "type": "Feature",
  "properties": {
    "gn:admin1_code":"3.0",
    "gn:asciiname":"Niabere Moulay Peul",
    "gn:country_code":"NE",
    "gn:dem":199,
    "gn:feature_class":"P",
    "gn:feature_code":"PPL",
    "gn:name":"Niab\u00e9r\u00e9 Moulay Peul",
    "gn:population":0,
    "gn:timezone":"Africa/Niamey",
    "iso:country":"NE",
    "wof:name":"Niabere Moulay Peul",
    "wof:placetype":"locality"
},
  "geometry": {"coordinates":[2.8369,13.3349],"type":"Point"}
}