{
  "type": "Feature",
  "properties": {
    "iso:country":"NE",
    "name:eng_x_preferred":[
        "Niamey Air Base"
    ],
    "name:eng_x_variant":[
        "NIM",
        "DRRN"
    ],
    "oa:elevation_ft":"732",
    "oa:type":"medium_airport",
    "woe:hierarchy":{
        "country_id":23424906,
        "county_id":56055506,
        "planet_id":1,
        "state_id":20069994
    },
    "wof:name":"Niamey Airport",
    "wof:placetype":"campus"
},
  "geometry": {"coordinates":[2.17028,13.4817],"type":"Point"}
}