{
  "type": "Feature",
  "properties": {
    "gn:admin1_code":"3.0",
    "gn:asciiname":"Boula Fandoga",
    "gn:country_code":"NE",
    "gn:dem":217,
    "gn:feature_class":"P",
    "gn:feature_code":"PPL",
    "gn:name":"Boula Fandoga",
    "gn:population":0,
    "gn:timezone":"Africa/Niamey",
    "iso:country":"NE",
    "wof:name":"Boula Fandoga",
    "wof:placetype":"locality"
},
  "geometry": {"coordinates":[2.8082,13.3328],"type":"Point"}
}