{
  "type": "Feature",
  "properties": {
    "gn:admin1_code":"7.0",
    "gn:asciiname":"Angoual Mak'era",
    "gn:country_code":"NE",
    "gn:dem":473,
    "gn:feature_class":"P",
    "gn:feature_code":"PPL",
    "gn:name":"Angoual Mak'\u00e9ra",
    "gn:population":0,
    "gn:timezone":"Africa/Niamey",
    "iso:country":"NE",
    "wof:name":"Angoual Mak'era",
    "wof:placetype":"locality"
},
  "geometry": {"coordinates":[8.92564,13.7579],"type":"Point"}
}