{
  "type": "Feature",
  "properties": {
    "gn:admin1_code":"3.0",
    "gn:asciiname":"Bassi Zarma",
    "gn:country_code":"NE",
    "gn:dem":211,
    "gn:feature_class":"P",
    "gn:feature_code":"PPL",
    "gn:name":"Bassi Zarma",
    "gn:population":0,
    "gn:timezone":"Africa/Niamey",
    "iso:country":"NE",
    "name:und_x_variant":[
        "Bashi",
        "Baschi",
        "Basi Dy\u00e8rma",
        "Bassi Dyerma",
        "Bassi Djerma",
        "Bassi Zarma"
    ],
    "wof:name":"Bassi Zarma",
    "wof:placetype":"locality"
},
  "geometry": {"coordinates":[2.86789,12.80809],"type":"Point"}
}