{
  "type": "Feature",
  "properties": {
    "gn:admin1_code":"3.0",
    "gn:asciiname":"Angoal Mayaki",
    "gn:country_code":"NE",
    "gn:dem":210,
    "gn:feature_class":"P",
    "gn:feature_code":"PPL",
    "gn:name":"Angoal Mayaki",
    "gn:population":0,
    "gn:timezone":"Africa/Niamey",
    "iso:country":"NE",
    "wof:name":"Angoal Mayaki",
    "wof:placetype":"locality"
},
  "geometry": {"coordinates":[4.06384,13.17719],"type":"Point"}
}