{
  "type": "Feature",
  "properties": {
    "gn:admin1_code":"3.0",
    "gn:asciiname":"Deitegui-Amani",
    "gn:country_code":"NE",
    "gn:dem":214,
    "gn:feature_class":"P",
    "gn:feature_code":"PPL",
    "gn:name":"De\u00eft\u00e9gui-Amani",
    "gn:population":0,
    "gn:timezone":"Africa/Niamey",
    "iso:country":"NE",
    "name:und_x_variant":[
        "Dey T\u00e9gui Amani",
        "De\u00eft\u00e9gui-Amani"
    ],
    "wof:name":"Deitegui-Amani",
    "wof:placetype":"locality"
},
  "geometry": {"coordinates":[3.5857,13.0913],"type":"Point"}
}