{
  "type": "Feature",
  "properties": {
    "gn:admin1_code":"9.0",
    "gn:asciiname":"Winde Boulay",
    "gn:country_code":"NE",
    "gn:dem":229,
    "gn:feature_class":"P",
    "gn:feature_code":"PPL",
    "gn:name":"Wind\u00e9 Boulay",
    "gn:population":0,
    "gn:timezone":"Africa/Niamey",
    "iso:country":"NE",
    "name:und_x_variant":[
        "Nindiboula\u00ef",
        "Wind\u00e9 Boulay"
    ],
    "wof:name":"Winde Boulay",
    "wof:placetype":"locality"
},
  "geometry": {"coordinates":[2.0778,13.0791],"type":"Point"}
}