{
  "type": "Feature",
  "properties": {
    "gn:admin1_code":"2.0",
    "gn:asciiname":"Fieboula",
    "gn:country_code":"NE",
    "gn:dem":275,
    "gn:feature_class":"P",
    "gn:feature_code":"PPL",
    "gn:name":"Fi\u00e9boula",
    "gn:population":0,
    "gn:timezone":"Africa/Niamey",
    "iso:country":"NE",
    "wof:name":"Fieboula",
    "wof:placetype":"locality"
},
  "geometry": {"coordinates":[13.26551,14.10196],"type":"Point"}
}