{
  "type": "Feature",
  "properties": {
    "gn:admin1_code":"9.0",
    "gn:asciiname":"Boulkass",
    "gn:country_code":"NE",
    "gn:dem":218,
    "gn:feature_class":"P",
    "gn:feature_code":"PPL",
    "gn:name":"Boulkass",
    "gn:population":0,
    "gn:timezone":"Africa/Niamey",
    "iso:country":"NE",
    "name:und_x_variant":[
        "Boulkas",
        "Boulkass"
    ],
    "wof:name":"Boulkass",
    "wof:placetype":"locality"
},
  "geometry": {"coordinates":[3.0835,13.8288],"type":"Point"}
}