{
  "type": "Feature",
  "properties": {
    "gn:admin1_code":"6.0",
    "gn:asciiname":"Magaria",
    "gn:country_code":"NE",
    "gn:dem":376,
    "gn:feature_class":"P",
    "gn:feature_code":"PPL",
    "gn:name":"Magaria",
    "gn:population":0,
    "gn:timezone":"Africa/Niamey",
    "iso:country":"NE",
    "name:rus_x_preferred":[
        "\u041c\u0430\u0433\u0430\u0440\u0438\u0430"
    ],
    "name:und_x_variant":[
        "Magarla",
        "Magaria"
    ],
    "wof:name":"Magaria",
    "wof:placetype":"locality"
},
  "geometry": {"coordinates":[5.7872,14.027],"type":"Point"}
}