{
  "type": "Feature",
  "properties": {
    "gn:admin1_code":"6.0",
    "gn:asciiname":"Magaria",
    "gn:country_code":"NE",
    "gn:dem":376,
    "gn:feature_class":"P",
    "gn:feature_code":"PPL",
    "gn:name":"Magaria",
    "gn:population":0,
    "gn:timezone":"Africa/Niamey",
    "iso:country":"NE",
    "name:ara_x_preferred":[
        "\u0645\u0627\u063a\u0627\u0631\u064a\u0627"
    ],
    "name:ceb_x_preferred":[
        "Magaria"
    ],
    "name:deu_x_preferred":[
        "Magaria"
    ],
    "name:fra_x_preferred":[
        "Magaria"
    ],
    "name:ita_x_preferred":[
        "Magaria"
    ],
    "name:jpn_x_preferred":[
        "\u30de\u30ac\u30ea\u30a2"
    ],
    "name:msa_x_preferred":[
        "Magaria"
    ],
    "name:pol_x_preferred":[
        "Magaria"
    ],
    "name:ron_x_preferred":[
        "Magaria"
    ],
    "name:rus_x_preferred":[
        "\u041c\u0430\u0433\u0430\u0440\u0438\u0430"
    ],
    "name:spa_x_preferred":[
        "Magaria"
    ],
    "name:und_x_variant":[
        "Magarla"
    ],
    "name:urd_x_preferred":[
        "\u0645\u0627\u06af\u0627\u0631\u06cc\u0627"
    ],
    "wof:name":"Magaria",
    "wof:placetype":"locality"
},
  "geometry": {"coordinates":[5.7872,14.027],"type":"Point"}
}