{
  "type": "Feature",
  "properties": {
    "gn:admin1_code":"9.0",
    "gn:asciiname":"Tintiba",
    "gn:country_code":"NE",
    "gn:dem":237,
    "gn:feature_class":"P",
    "gn:feature_code":"PPL",
    "gn:name":"Tintiba",
    "gn:population":0,
    "gn:timezone":"Africa/Niamey",
    "iso:country":"NE",
    "wof:name":"Tintiba",
    "wof:placetype":"locality"
},
  "geometry": {"coordinates":[1.93784,13.32683],"type":"Point"}
}