{
  "type": "Feature",
  "properties": {
    "gn:admin1_code":"9.0",
    "gn:asciiname":"Danyan",
    "gn:country_code":"NE",
    "gn:dem":258,
    "gn:feature_class":"P",
    "gn:feature_code":"PPL",
    "gn:name":"Danyan",
    "gn:population":0,
    "gn:timezone":"Africa/Niamey",
    "iso:country":"NE",
    "wof:name":"Danyan",
    "wof:placetype":"locality"
},
  "geometry": {"coordinates":[3.3259,14.9934],"type":"Point"}
}