{
  "type": "Feature",
  "properties": {
    "gn:admin1_code":"4.0",
    "gn:asciiname":"Makou",
    "gn:country_code":"NE",
    "gn:dem":377,
    "gn:feature_class":"P",
    "gn:feature_code":"PPL",
    "gn:name":"Makou",
    "gn:population":0,
    "gn:timezone":"Africa/Niamey",
    "iso:country":"NE",
    "wof:name":"Makou",
    "wof:placetype":"locality"
},
  "geometry": {"coordinates":[7.25101,13.95235],"type":"Point"}
}