{
  "type": "Feature",
  "properties": {
    "gn:admin1_code":"6.0",
    "gn:asciiname":"Tyaba",
    "gn:country_code":"NE",
    "gn:dem":378,
    "gn:feature_class":"P",
    "gn:feature_code":"PPL",
    "gn:name":"Tyaba",
    "gn:population":0,
    "gn:timezone":"Africa/Niamey",
    "iso:country":"NE",
    "wof:name":"Tyaba",
    "wof:placetype":"locality"
},
  "geometry": {"coordinates":[5.8032,14.1216],"type":"Point"}
}