{
  "type": "Feature",
  "properties": {
    "gn:admin1_code":"9.0",
    "gn:asciiname":"Diagorou",
    "gn:country_code":"NE",
    "gn:dem":234,
    "gn:feature_class":"P",
    "gn:feature_code":"PPL",
    "gn:name":"Diagorou",
    "gn:population":0,
    "gn:timezone":"Africa/Niamey",
    "iso:country":"NE",
    "name:und_x_variant":[
        "Dyagorou",
        "Diagorou"
    ],
    "wof:name":"Diagorou",
    "wof:placetype":"locality"
},
  "geometry": {"coordinates":[0.81167,13.90745],"type":"Point"}
}