{
  "type": "Feature",
  "properties": {
    "gn:admin1_code":"6.0",
    "gn:asciiname":"Tatawasen",
    "gn:country_code":"NE",
    "gn:dem":524,
    "gn:feature_class":"P",
    "gn:feature_code":"PPL",
    "gn:name":"Tatawasen",
    "gn:population":0,
    "gn:timezone":"Africa/Niamey",
    "iso:country":"NE",
    "wof:name":"Tatawasen",
    "wof:placetype":"locality"
},
  "geometry": {"coordinates":[6.05356,14.97255],"type":"Point"}
}