{
  "type": "Feature",
  "properties": {
    "gn:admin1_code":"9.0",
    "gn:asciiname":"Sandire",
    "gn:country_code":"NE",
    "gn:dem":207,
    "gn:feature_class":"P",
    "gn:feature_code":"PPL",
    "gn:name":"Sandir\u00e9",
    "gn:population":0,
    "gn:timezone":"Africa/Niamey",
    "iso:country":"NE",
    "wof:name":"Sandire",
    "wof:placetype":"locality"
},
  "geometry": {"coordinates":[2.8952,13.65],"type":"Point"}
}