{
  "type": "Feature",
  "properties": {
    "gn:admin1_code":"7.0",
    "gn:asciiname":"Wam",
    "gn:country_code":"NE",
    "gn:dem":379,
    "gn:feature_class":"P",
    "gn:feature_code":"PPL",
    "gn:name":"Wam",
    "gn:population":0,
    "gn:timezone":"Africa/Niamey",
    "iso:country":"NE",
    "wof:name":"Wam",
    "wof:placetype":"locality"
},
  "geometry": {"coordinates":[10.52183,13.92625],"type":"Point"}
}