{
  "type": "Feature",
  "properties": {
    "gn:admin1_code":"9.0",
    "gn:asciiname":"Gangani",
    "gn:country_code":"NE",
    "gn:dem":242,
    "gn:feature_class":"P",
    "gn:feature_code":"PPL",
    "gn:name":"Gangani",
    "gn:population":0,
    "gn:timezone":"Africa/Niamey",
    "iso:country":"NE",
    "name:bre_x_preferred":[
        "Gangani"
    ],
    "name:cat_x_preferred":[
        "Gangani"
    ],
    "name:cym_x_preferred":[
        "Gangani"
    ],
    "name:fra_x_preferred":[
        "Gangani"
    ],
    "name:spa_x_preferred":[
        "Gangani"
    ],
    "wof:name":"Gangani",
    "wof:placetype":"locality"
},
  "geometry": {"coordinates":[1.91395,14.60256],"type":"Point"}
}