{
  "type": "Feature",
  "properties": {
    "gn:admin1_code":"3.0",
    "gn:asciiname":"Sabarou",
    "gn:country_code":"NE",
    "gn:dem":237,
    "gn:feature_class":"P",
    "gn:feature_code":"PPL",
    "gn:name":"Sabarou",
    "gn:population":0,
    "gn:timezone":"Africa/Niamey",
    "iso:country":"NE",
    "name:und_x_variant":[
        "Sabrou",
        "Sabarou"
    ],
    "wof:name":"Sabarou",
    "wof:placetype":"locality"
},
  "geometry": {"coordinates":[4.07752,13.16859],"type":"Point"}
}