{
  "type": "Feature",
  "properties": {
    "gn:admin1_code":"6.0",
    "gn:asciiname":"Guidan-Adamou",
    "gn:country_code":"NE",
    "gn:dem":302,
    "gn:feature_class":"P",
    "gn:feature_code":"PPL",
    "gn:name":"Guidan-Adamou",
    "gn:population":0,
    "gn:timezone":"Africa/Niamey",
    "iso:country":"NE",
    "name:und_x_variant":[
        "Gidan-Adamou",
        "Guidan-Adamou"
    ],
    "wof:name":"Guidan-Adamou",
    "wof:placetype":"locality"
},
  "geometry": {"coordinates":[5.93523,13.83033],"type":"Point"}
}