{
  "type": "Feature",
  "properties": {
    "gn:admin1_code":"2.0",
    "gn:asciiname":"Sargeram",
    "gn:country_code":"NE",
    "gn:dem":348,
    "gn:feature_class":"P",
    "gn:feature_code":"PPL",
    "gn:name":"Sarg\u00e9ram",
    "gn:population":0,
    "gn:timezone":"Africa/Niamey",
    "iso:country":"NE",
    "wof:name":"Sargeram",
    "wof:placetype":"locality"
},
  "geometry": {"coordinates":[11.3286,13.8445],"type":"Point"}
}