{
  "type": "Feature",
  "properties": {
    "gn:admin1_code":"3.0",
    "gn:asciiname":"Ziamazoubi",
    "gn:country_code":"NE",
    "gn:dem":235,
    "gn:feature_class":"P",
    "gn:feature_code":"PPL",
    "gn:name":"Ziamazoubi",
    "gn:population":0,
    "gn:timezone":"Africa/Niamey",
    "iso:country":"NE",
    "name:und_x_variant":[
        "Zammazoubi",
        "Ziamazoubi"
    ],
    "wof:name":"Ziamazoubi",
    "wof:placetype":"locality"
},
  "geometry": {"coordinates":[3.7328,13.0541],"type":"Point"}
}