{
  "type": "Feature",
  "properties": {
    "gn:admin1_code":"3.0",
    "gn:asciiname":"Ladan Kwara",
    "gn:country_code":"NE",
    "gn:dem":162,
    "gn:feature_class":"P",
    "gn:feature_code":"PPL",
    "gn:name":"Ladan Kwara",
    "gn:population":0,
    "gn:timezone":"Africa/Niamey",
    "iso:country":"NE",
    "name:und_x_variant":[
        "Ladankpira",
        "Ladan Kwara"
    ],
    "wof:name":"Ladan Kwara",
    "wof:placetype":"locality"
},
  "geometry": {"coordinates":[3.63162,11.74566],"type":"Point"}
}