{
  "type": "Feature",
  "properties": {
    "gn:admin1_code":"6.0",
    "gn:asciiname":"Tsernawa",
    "gn:country_code":"NE",
    "gn:dem":283,
    "gn:feature_class":"P",
    "gn:feature_code":"PPL",
    "gn:name":"Tsernawa",
    "gn:population":0,
    "gn:timezone":"Africa/Niamey",
    "iso:country":"NE",
    "name:ceb_x_preferred":[
        "Tsernawa"
    ],
    "name:deu_x_preferred":[
        "Tsernaoua"
    ],
    "name:ita_x_preferred":[
        "Tsernaoua"
    ],
    "name:msa_x_preferred":[
        "Tsernaoua"
    ],
    "name:ron_x_preferred":[
        "Tsernaoua"
    ],
    "name:spa_x_preferred":[
        "Tsernaoua"
    ],
    "name:und_x_variant":[
        "Isarnaoua",
        "Tsarnaua",
        "Tsarnaoua",
        "Tsernaoua",
        "Tsernawa"
    ],
    "wof:name":"Tsernawa",
    "wof:placetype":"locality"
},
  "geometry": {"coordinates":[5.34758,13.88536],"type":"Point"}
}