{
  "type": "Feature",
  "properties": {
    "gn:admin1_code":"6.0",
    "gn:asciiname":"Akoirori",
    "gn:country_code":"NE",
    "gn:dem":317,
    "gn:feature_class":"P",
    "gn:feature_code":"PPL",
    "gn:name":"Akoirori",
    "gn:population":0,
    "gn:timezone":"Africa/Niamey",
    "iso:country":"NE",
    "name:und_x_variant":[
        "Akoyrori",
        "Akoirori"
    ],
    "wof:name":"Akoirori",
    "wof:placetype":"locality"
},
  "geometry": {"coordinates":[6.07713,13.83553],"type":"Point"}
}