{
  "type": "Feature",
  "properties": {
    "gn:admin1_code":"3.0",
    "gn:asciiname":"Banizoumbou",
    "gn:country_code":"NE",
    "gn:dem":235,
    "gn:feature_class":"P",
    "gn:feature_code":"PPL",
    "gn:name":"Banizoumbou",
    "gn:population":0,
    "gn:timezone":"Africa/Niamey",
    "iso:country":"NE",
    "wof:name":"Banizoumbou",
    "wof:placetype":"locality"
},
  "geometry": {"coordinates":[3.8926,13.2602],"type":"Point"}
}