{
  "type": "Feature",
  "properties": {
    "gn:admin1_code":"6.0",
    "gn:asciiname":"Mayki",
    "gn:country_code":"NE",
    "gn:dem":426,
    "gn:feature_class":"P",
    "gn:feature_code":"PPL",
    "gn:name":"Mayki",
    "gn:population":0,
    "gn:timezone":"Africa/Niamey",
    "iso:country":"NE",
    "wof:name":"Mayki",
    "wof:placetype":"locality"
},
  "geometry": {"coordinates":[6.5035,14.28013],"type":"Point"}
}