{
  "type": "Feature",
  "properties": {
    "gn:admin1_code":"6.0",
    "gn:asciiname":"Garin Abdelkader",
    "gn:country_code":"NE",
    "gn:dem":484,
    "gn:feature_class":"P",
    "gn:feature_code":"PPL",
    "gn:name":"Garin Abd\u00e9lkad\u00e9r",
    "gn:population":0,
    "gn:timezone":"Africa/Niamey",
    "iso:country":"NE",
    "wof:name":"Garin Abdelkader",
    "wof:placetype":"locality"
},
  "geometry": {"coordinates":[6.25383,14.79105],"type":"Point"}
}