{
  "type": "Feature",
  "properties": {
    "gn:admin1_code":"7.0",
    "gn:asciiname":"Baouchiri",
    "gn:country_code":"NE",
    "gn:dem":456,
    "gn:feature_class":"P",
    "gn:feature_code":"PPL",
    "gn:name":"Baouchiri",
    "gn:population":0,
    "gn:timezone":"Africa/Niamey",
    "iso:country":"NE",
    "wof:name":"Baouchiri",
    "wof:placetype":"locality"
},
  "geometry": {"coordinates":[9.0648,13.7105],"type":"Point"}
}