{
  "type": "Feature",
  "properties": {
    "gn:admin1_code":"7.0",
    "gn:asciiname":"Seloum",
    "gn:country_code":"NE",
    "gn:dem":469,
    "gn:feature_class":"P",
    "gn:feature_code":"PPL",
    "gn:name":"S\u00e9loum",
    "gn:population":0,
    "gn:timezone":"Africa/Niamey",
    "iso:country":"NE",
    "wof:name":"Seloum",
    "wof:placetype":"locality"
},
  "geometry": {"coordinates":[8.7318,14.3665],"type":"Point"}
}