{
  "type": "Feature",
  "properties": {
    "gn:admin1_code":"4.0",
    "gn:asciiname":"Oubandawaki",
    "gn:country_code":"NE",
    "gn:dem":330,
    "gn:feature_class":"P",
    "gn:feature_code":"PPL",
    "gn:name":"Oubandawaki",
    "gn:population":0,
    "gn:timezone":"Africa/Niamey",
    "iso:country":"NE",
    "wof:name":"Oubandawaki",
    "wof:placetype":"locality"
},
  "geometry": {"coordinates":[6.40885,13.6906],"type":"Point"}
}