{
  "type": "Feature",
  "properties": {
    "gn:admin1_code":"2.0",
    "gn:asciiname":"Fourdia",
    "gn:country_code":"NE",
    "gn:dem":341,
    "gn:feature_class":"P",
    "gn:feature_code":"PPL",
    "gn:name":"Fourdia",
    "gn:population":0,
    "gn:timezone":"Africa/Niamey",
    "iso:country":"NE",
    "wof:name":"Fourdia",
    "wof:placetype":"locality"
},
  "geometry": {"coordinates":[11.7093,13.4822],"type":"Point"}
}