{
  "type": "Feature",
  "properties": {
    "gn:admin1_code":"7.0",
    "gn:asciiname":"Baregou",
    "gn:country_code":"NE",
    "gn:dem":404,
    "gn:feature_class":"P",
    "gn:feature_code":"PPL",
    "gn:name":"Baregou",
    "gn:population":0,
    "gn:timezone":"Africa/Niamey",
    "iso:country":"NE",
    "wof:name":"Baregou",
    "wof:placetype":"locality"
},
  "geometry": {"coordinates":[9.0977,13.52102],"type":"Point"}
}