{
  "type": "Feature",
  "properties": {
    "gn:admin1_code":"9.0",
    "gn:asciiname":"Bole",
    "gn:country_code":"NE",
    "gn:dem":237,
    "gn:feature_class":"P",
    "gn:feature_code":"PPL",
    "gn:name":"Bol\u00e9",
    "gn:population":0,
    "gn:timezone":"Africa/Niamey",
    "iso:country":"NE",
    "name:ceb_x_preferred":[
        "Bole"
    ],
    "name:deu_x_preferred":[
        "Bole"
    ],
    "name:fra_x_preferred":[
        "Bole"
    ],
    "name:ita_x_preferred":[
        "Bole"
    ],
    "name:nld_x_preferred":[
        "Bole"
    ],
    "name:pol_x_preferred":[
        "Bole"
    ],
    "name:swe_x_preferred":[
        "Bole"
    ],
    "name:wln_x_preferred":[
        "Bole"
    ],
    "wof:name":"Bole",
    "wof:placetype":"locality"
},
  "geometry": {"coordinates":[2.12931,14.29156],"type":"Point"}
}