{
  "type": "Feature",
  "properties": {
    "gn:admin1_code":"4.0",
    "gn:asciiname":"Guidan Dialo",
    "gn:country_code":"NE",
    "gn:dem":342,
    "gn:feature_class":"P",
    "gn:feature_code":"PPL",
    "gn:name":"Guidan Dialo",
    "gn:population":0,
    "gn:timezone":"Africa/Niamey",
    "iso:country":"NE",
    "name:und_x_variant":[
        "Gidan Dialo",
        "Guidan Dialo"
    ],
    "wof:name":"Guidan Dialo",
    "wof:placetype":"locality"
},
  "geometry": {"coordinates":[6.98376,13.57805],"type":"Point"}
}