{
  "type": "Feature",
  "properties": {
    "gn:admin1_code":"7.0",
    "gn:asciiname":"Daba Massabki",
    "gn:country_code":"NE",
    "gn:dem":432,
    "gn:feature_class":"P",
    "gn:feature_code":"PPL",
    "gn:name":"Daba Massabki",
    "gn:population":0,
    "gn:timezone":"Africa/Niamey",
    "iso:country":"NE",
    "wof:name":"Daba Massabki",
    "wof:placetype":"locality"
},
  "geometry": {"coordinates":[8.90923,13.62992],"type":"Point"}
}