{
  "type": "Feature",
  "properties": {
    "gn:admin1_code":"3.0",
    "gn:asciiname":"Boundouga",
    "gn:country_code":"NE",
    "gn:dem":210,
    "gn:feature_class":"P",
    "gn:feature_code":"PPL",
    "gn:name":"Boundouga",
    "gn:population":0,
    "gn:timezone":"Africa/Niamey",
    "iso:country":"NE",
    "name:und_x_variant":[
        "Boudounga",
        "Boundouga"
    ],
    "wof:name":"Boundouga",
    "wof:placetype":"locality"
},
  "geometry": {"coordinates":[2.68544,12.80073],"type":"Point"}
}