{
  "type": "Feature",
  "properties": {
    "gn:admin1_code":"7.0",
    "gn:asciiname":"Nguibiri",
    "gn:country_code":"NE",
    "gn:dem":511,
    "gn:feature_class":"P",
    "gn:feature_code":"PPL",
    "gn:name":"Nguibiri",
    "gn:population":0,
    "gn:timezone":"Africa/Niamey",
    "iso:country":"NE",
    "wof:name":"Nguibiri",
    "wof:placetype":"locality"
},
  "geometry": {"coordinates":[10.1034,14.4967],"type":"Point"}
}