{
  "type": "Feature",
  "properties": {
    "gn:admin1_code":"4.0",
    "gn:asciiname":"Zangon Mahama",
    "gn:country_code":"NE",
    "gn:dem":432,
    "gn:feature_class":"P",
    "gn:feature_code":"PPL",
    "gn:name":"Zangon Mahama",
    "gn:population":0,
    "gn:timezone":"Africa/Niamey",
    "iso:country":"NE",
    "wof:name":"Zangon Mahama",
    "wof:placetype":"locality"
},
  "geometry": {"coordinates":[7.15282,14.47866],"type":"Point"}
}