{
  "type": "Feature",
  "properties": {
    "gn:admin1_code":"3.0",
    "gn:asciiname":"Dabkoudeye",
    "gn:country_code":"NE",
    "gn:dem":219,
    "gn:feature_class":"P",
    "gn:feature_code":"PPL",
    "gn:name":"Dabkoudeye",
    "gn:population":0,
    "gn:timezone":"Africa/Niamey",
    "iso:country":"NE",
    "name:und_x_variant":[
        "Dabkoudey",
        "Dabkoudeye"
    ],
    "wof:name":"Dabkoudeye",
    "wof:placetype":"locality"
},
  "geometry": {"coordinates":[3.0214,13.5036],"type":"Point"}
}