{
  "type": "Feature",
  "properties": {
    "gn:admin1_code":"4.0",
    "gn:asciiname":"Tekwalou",
    "gn:country_code":"NE",
    "gn:dem":372,
    "gn:feature_class":"P",
    "gn:feature_code":"PPL",
    "gn:name":"Tekwalou",
    "gn:population":0,
    "gn:timezone":"Africa/Niamey",
    "iso:country":"NE",
    "wof:name":"Tekwalou",
    "wof:placetype":"locality"
},
  "geometry": {"coordinates":[6.99128,13.80772],"type":"Point"}
}