{
  "type": "Feature",
  "properties": {
    "gn:admin1_code":"3.0",
    "gn:asciiname":"Fadama",
    "gn:country_code":"NE",
    "gn:dem":214,
    "gn:feature_class":"P",
    "gn:feature_code":"PPL",
    "gn:name":"Fadama",
    "gn:population":0,
    "gn:timezone":"Africa/Niamey",
    "iso:country":"NE",
    "wof:name":"Fadama",
    "wof:placetype":"locality"
},
  "geometry": {"coordinates":[3.9016,13.0354],"type":"Point"}
}