{
  "type": "Feature",
  "properties": {
    "gn:admin1_code":"4.0",
    "gn:asciiname":"Andale",
    "gn:country_code":"NE",
    "gn:dem":342,
    "gn:feature_class":"P",
    "gn:feature_code":"PPL",
    "gn:name":"Andal\u00e9",
    "gn:population":0,
    "gn:timezone":"Africa/Niamey",
    "iso:country":"NE",
    "name:nld_x_preferred":[
        "Andale"
    ],
    "wof:name":"Andale",
    "wof:placetype":"locality"
},
  "geometry": {"coordinates":[6.86417,13.58857],"type":"Point"}
}