{
  "type": "Feature",
  "properties": {
    "gn:admin1_code":"3.0",
    "gn:asciiname":"Ganawa",
    "gn:country_code":"NE",
    "gn:dem":167,
    "gn:feature_class":"P",
    "gn:feature_code":"PPL",
    "gn:name":"Ganawa",
    "gn:population":0,
    "gn:timezone":"Africa/Niamey",
    "iso:country":"NE",
    "wof:name":"Ganawa",
    "wof:placetype":"locality"
},
  "geometry": {"coordinates":[3.57615,11.99403],"type":"Point"}
}