{
  "type": "Feature",
  "properties": {
    "gn:admin1_code":"7.0",
    "gn:asciiname":"Memeni",
    "gn:country_code":"NE",
    "gn:dem":493,
    "gn:feature_class":"P",
    "gn:feature_code":"PPL",
    "gn:name":"M\u00e9m\u00e9ni",
    "gn:population":0,
    "gn:timezone":"Africa/Niamey",
    "iso:country":"NE",
    "wof:name":"Memeni",
    "wof:placetype":"locality"
},
  "geometry": {"coordinates":[9.3887,14.4409],"type":"Point"}
}