{
  "type": "Feature",
  "properties": {
    "gn:admin1_code":"4.0",
    "gn:asciiname":"Zongouna Aza",
    "gn:country_code":"NE",
    "gn:dem":438,
    "gn:feature_class":"P",
    "gn:feature_code":"PPL",
    "gn:name":"Zongouna Aza",
    "gn:population":0,
    "gn:timezone":"Africa/Niamey",
    "iso:country":"NE",
    "wof:name":"Zongouna Aza",
    "wof:placetype":"locality"
},
  "geometry": {"coordinates":[8.3535,14.25399],"type":"Point"}
}