{
  "type": "Feature",
  "properties": {
    "gn:admin1_code":"6.0",
    "gn:asciiname":"Doney",
    "gn:country_code":"NE",
    "gn:dem":363,
    "gn:feature_class":"P",
    "gn:feature_code":"PPL",
    "gn:name":"Don\u00e9y",
    "gn:population":0,
    "gn:timezone":"Africa/Niamey",
    "iso:country":"NE",
    "name:und_x_variant":[
        "Donei",
        "Don\u00e8ye",
        "Don\u00e9y"
    ],
    "wof:name":"Doney",
    "wof:placetype":"locality"
},
  "geometry": {"coordinates":[6.13138,14.09451],"type":"Point"}
}