{
  "type": "Feature",
  "properties": {
    "gn:admin1_code":"7.0",
    "gn:asciiname":"Guidan Bagala",
    "gn:country_code":"NE",
    "gn:dem":497,
    "gn:feature_class":"P",
    "gn:feature_code":"PPL",
    "gn:name":"Guidan Bagala",
    "gn:population":0,
    "gn:timezone":"Africa/Niamey",
    "iso:country":"NE",
    "name:und_x_variant":[
        "Gidan Bagala",
        "Guidan Bagala"
    ],
    "wof:name":"Guidan Bagala",
    "wof:placetype":"locality"
},
  "geometry": {"coordinates":[8.77671,14.6734],"type":"Point"}
}