{
  "type": "Feature",
  "properties": {
    "gn:admin1_code":"6.0",
    "gn:asciiname":"Zangarata",
    "gn:country_code":"NE",
    "gn:dem":383,
    "gn:feature_class":"P",
    "gn:feature_code":"PPL",
    "gn:name":"Zangarata",
    "gn:population":0,
    "gn:timezone":"Africa/Niamey",
    "iso:country":"NE",
    "wof:name":"Zangarata",
    "wof:placetype":"locality"
},
  "geometry": {"coordinates":[5.6571,14.7999],"type":"Point"}
}