{
  "type": "Feature",
  "properties": {
    "gn:admin1_code":"7.0",
    "gn:asciiname":"Idrissari",
    "gn:country_code":"NE",
    "gn:dem":500,
    "gn:feature_class":"P",
    "gn:feature_code":"PPL",
    "gn:name":"Idrissari",
    "gn:population":0,
    "gn:timezone":"Africa/Niamey",
    "iso:country":"NE",
    "wof:name":"Idrissari",
    "wof:placetype":"locality"
},
  "geometry": {"coordinates":[9.1635,14.69],"type":"Point"}
}