{
  "type": "Feature",
  "properties": {
    "gn:admin1_code":"3.0",
    "gn:asciiname":"Tombo Tessa",
    "gn:country_code":"NE",
    "gn:dem":227,
    "gn:feature_class":"P",
    "gn:feature_code":"PPL",
    "gn:name":"Tombo Tessa",
    "gn:population":0,
    "gn:timezone":"Africa/Niamey",
    "iso:country":"NE",
    "name:und_x_variant":[
        "Tombo",
        "Tombo Tessa"
    ],
    "wof:name":"Tombo Tessa",
    "wof:placetype":"locality"
},
  "geometry": {"coordinates":[3.44819,12.7426],"type":"Point"}
}