{
  "type": "Feature",
  "properties": {
    "gn:admin1_code":"3.0",
    "gn:asciiname":"Tiandewa",
    "gn:country_code":"NE",
    "gn:dem":233,
    "gn:feature_class":"P",
    "gn:feature_code":"PPL",
    "gn:name":"Tiandewa",
    "gn:population":0,
    "gn:timezone":"Africa/Niamey",
    "iso:country":"NE",
    "wof:name":"Tiandewa",
    "wof:placetype":"locality"
},
  "geometry": {"coordinates":[3.208,13.5148],"type":"Point"}
}