{
  "type": "Feature",
  "properties": {
    "gn:admin1_code":"7.0",
    "gn:asciiname":"Daneki",
    "gn:country_code":"NE",
    "gn:dem":439,
    "gn:feature_class":"P",
    "gn:feature_code":"PPL",
    "gn:name":"Dan\u00e9ki",
    "gn:population":0,
    "gn:timezone":"Africa/Niamey",
    "iso:country":"NE",
    "wof:name":"Daneki",
    "wof:placetype":"locality"
},
  "geometry": {"coordinates":[8.40855,13.63134],"type":"Point"}
}