{
  "type": "Feature",
  "properties": {
    "gn:admin1_code":"7.0",
    "gn:asciiname":"Mahoum",
    "gn:country_code":"NE",
    "gn:dem":512,
    "gn:feature_class":"P",
    "gn:feature_code":"PPL",
    "gn:name":"Mahoum",
    "gn:population":0,
    "gn:timezone":"Africa/Niamey",
    "iso:country":"NE",
    "wof:name":"Mahoum",
    "wof:placetype":"locality"
},
  "geometry": {"coordinates":[10.1233,14.5182],"type":"Point"}
}