{
  "type": "Feature",
  "properties": {
    "gn:admin1_code":"4.0",
    "gn:asciiname":"Aekao",
    "gn:country_code":"NE",
    "gn:dem":385,
    "gn:feature_class":"P",
    "gn:feature_code":"PPL",
    "gn:name":"A\u00e9kao",
    "gn:population":0,
    "gn:timezone":"Africa/Niamey",
    "iso:country":"NE",
    "wof:name":"Aekao",
    "wof:placetype":"locality"
},
  "geometry": {"coordinates":[6.8767,13.36927],"type":"Point"}
}