{
  "type": "Feature",
  "properties": {
    "gn:admin1_code":"7.0",
    "gn:asciiname":"Barkatalale",
    "gn:country_code":"NE",
    "gn:dem":396,
    "gn:feature_class":"P",
    "gn:feature_code":"PPL",
    "gn:name":"Barkatalal\u00e9",
    "gn:population":0,
    "gn:timezone":"Africa/Niamey",
    "iso:country":"NE",
    "wof:name":"Barkatalale",
    "wof:placetype":"locality"
},
  "geometry": {"coordinates":[9.61433,13.5859],"type":"Point"}
}