{
  "type": "Feature",
  "properties": {
    "gn:admin1_code":"6.0",
    "gn:asciiname":"Kalgo",
    "gn:country_code":"NE",
    "gn:dem":346,
    "gn:feature_class":"P",
    "gn:feature_code":"PPL",
    "gn:name":"Kalgo",
    "gn:population":0,
    "gn:timezone":"Africa/Niamey",
    "iso:country":"NE",
    "name:fra_x_preferred":[
        "Kalgo"
    ],
    "name:hau_x_preferred":[
        "Kalgo"
    ],
    "name:ita_x_preferred":[
        "Kalgo"
    ],
    "name:spa_x_preferred":[
        "Kalgo"
    ],
    "wof:name":"Kalgo",
    "wof:placetype":"locality"
},
  "geometry": {"coordinates":[5.0738,14.9952],"type":"Point"}
}