{
  "type": "Feature",
  "properties": {
    "gn:admin1_code":"4.0",
    "gn:asciiname":"Dan Falke",
    "gn:country_code":"NE",
    "gn:dem":329,
    "gn:feature_class":"P",
    "gn:feature_code":"PPL",
    "gn:name":"Dan Falk\u00e9",
    "gn:population":0,
    "gn:timezone":"Africa/Niamey",
    "iso:country":"NE",
    "wof:name":"Dan Falke",
    "wof:placetype":"locality"
},
  "geometry": {"coordinates":[6.60029,13.96812],"type":"Point"}
}