{
  "type": "Feature",
  "properties": {
    "gn:admin1_code":"2.0",
    "gn:asciiname":"Basa",
    "gn:country_code":"NE",
    "gn:dem":298,
    "gn:feature_class":"P",
    "gn:feature_code":"PPL",
    "gn:name":"Basa",
    "gn:population":0,
    "gn:timezone":"Africa/Niamey",
    "iso:country":"NE",
    "name:ceb_x_preferred":[
        "Basa"
    ],
    "name:ces_x_preferred":[
        "Basa"
    ],
    "name:deu_x_preferred":[
        "Basa"
    ],
    "name:fra_x_preferred":[
        "Basa"
    ],
    "name:heb_x_preferred":[
        "\u05d1\u05d0\u05e1\u05d4"
    ],
    "name:lmo_x_preferred":[
        "Basa"
    ],
    "name:slk_x_preferred":[
        "Basa"
    ],
    "name:swe_x_preferred":[
        "Basa"
    ],
    "name:tgl_x_preferred":[
        "Basa"
    ],
    "name:und_x_variant":[
        "Wassa",
        "Basa"
    ],
    "wof:name":"Basa",
    "wof:placetype":"locality"
},
  "geometry": {"coordinates":[12.96229,13.52053],"type":"Point"}
}