{
  "type": "Feature",
  "properties": {
    "gn:admin1_code":"3.0",
    "gn:asciiname":"Garin Zaroumay",
    "gn:country_code":"NE",
    "gn:dem":247,
    "gn:feature_class":"P",
    "gn:feature_code":"PPL",
    "gn:name":"Garin Zaroumay",
    "gn:population":0,
    "gn:timezone":"Africa/Niamey",
    "iso:country":"NE",
    "wof:name":"Garin Zaroumay",
    "wof:placetype":"locality"
},
  "geometry": {"coordinates":[4.02189,13.32345],"type":"Point"}
}