{
  "type": "Feature",
  "properties": {
    "gn:admin1_code":"9.0",
    "gn:asciiname":"Dinkildimi",
    "gn:country_code":"NE",
    "gn:dem":249,
    "gn:feature_class":"P",
    "gn:feature_code":"PPL",
    "gn:name":"Dinkildimi",
    "gn:population":0,
    "gn:timezone":"Africa/Niamey",
    "iso:country":"NE",
    "name:und_x_variant":[
        "Dinkilmi",
        "Dinkildimi"
    ],
    "wof:name":"Dinkildimi",
    "wof:placetype":"locality"
},
  "geometry": {"coordinates":[3.6542,14.4879],"type":"Point"}
}