{
  "type": "Feature",
  "properties": {
    "gn:admin1_code":"3.0",
    "gn:asciiname":"Moubena",
    "gn:country_code":"NE",
    "gn:dem":199,
    "gn:feature_class":"P",
    "gn:feature_code":"PPL",
    "gn:name":"Moub\u00e9na",
    "gn:population":0,
    "gn:timezone":"Africa/Niamey",
    "iso:country":"NE",
    "name:und_x_variant":[
        "Mounb\u00e9na",
        "Notinguel",
        "Moub\u00e9na"
    ],
    "wof:name":"Moubena",
    "wof:placetype":"locality"
},
  "geometry": {"coordinates":[2.9324,13.458],"type":"Point"}
}