{
  "type": "Feature",
  "properties": {
    "gn:admin1_code":"6.0",
    "gn:asciiname":"Guidan Maygojya",
    "gn:country_code":"NE",
    "gn:dem":425,
    "gn:feature_class":"P",
    "gn:feature_code":"PPL",
    "gn:name":"Guidan Maygojya",
    "gn:population":0,
    "gn:timezone":"Africa/Niamey",
    "iso:country":"NE",
    "wof:name":"Guidan Maygojya",
    "wof:placetype":"locality"
},
  "geometry": {"coordinates":[6.34517,14.70534],"type":"Point"}
}