{
  "type": "Feature",
  "properties": {
    "gn:admin1_code":"4.0",
    "gn:asciiname":"Kouka Dan Wada",
    "gn:country_code":"NE",
    "gn:dem":384,
    "gn:feature_class":"P",
    "gn:feature_code":"PPL",
    "gn:name":"Kouka Dan Wada",
    "gn:population":0,
    "gn:timezone":"Africa/Niamey",
    "iso:country":"NE",
    "wof:name":"Kouka Dan Wada",
    "wof:placetype":"locality"
},
  "geometry": {"coordinates":[7.39998,13.66521],"type":"Point"}
}