{
  "type": "Feature",
  "properties": {
    "gn:admin1_code":"7.0",
    "gn:asciiname":"Gamori",
    "gn:country_code":"NE",
    "gn:dem":485,
    "gn:feature_class":"P",
    "gn:feature_code":"PPL",
    "gn:name":"Gamori",
    "gn:population":0,
    "gn:timezone":"Africa/Niamey",
    "iso:country":"NE",
    "wof:name":"Gamori",
    "wof:placetype":"locality"
},
  "geometry": {"coordinates":[9.1478,14.7011],"type":"Point"}
}