{
  "type": "Feature",
  "properties": {
    "gn:admin1_code":"2.0",
    "gn:asciiname":"Meleri",
    "gn:country_code":"NE",
    "gn:dem":329,
    "gn:feature_class":"P",
    "gn:feature_code":"PPL",
    "gn:name":"M\u00e9l\u00e9ri",
    "gn:population":0,
    "gn:timezone":"Africa/Niamey",
    "iso:country":"NE",
    "wof:name":"Meleri",
    "wof:placetype":"locality"
},
  "geometry": {"coordinates":[12.13857,13.44841],"type":"Point"}
}