{
  "type": "Feature",
  "properties": {
    "gn:admin1_code":"4.0",
    "gn:asciiname":"Koroumgosou",
    "gn:country_code":"NE",
    "gn:dem":394,
    "gn:feature_class":"P",
    "gn:feature_code":"PPL",
    "gn:name":"Koroumgosou",
    "gn:population":0,
    "gn:timezone":"Africa/Niamey",
    "iso:country":"NE",
    "wof:name":"Koroumgosou",
    "wof:placetype":"locality"
},
  "geometry": {"coordinates":[6.64114,14.56007],"type":"Point"}
}