{
  "type": "Feature",
  "properties": {
    "gn:admin1_code":"3.0",
    "gn:asciiname":"Tassiel",
    "gn:country_code":"NE",
    "gn:dem":180,
    "gn:feature_class":"P",
    "gn:feature_code":"PPL",
    "gn:name":"Tassi\u00e8l",
    "gn:population":0,
    "gn:timezone":"Africa/Niamey",
    "iso:country":"NE",
    "name:und_x_variant":[
        "Tasi\u00e8l",
        "Tassi\u00e8l"
    ],
    "wof:name":"Tassiel",
    "wof:placetype":"locality"
},
  "geometry": {"coordinates":[2.89017,12.45614],"type":"Point"}
}