{
  "type": "Feature",
  "properties": {
    "gn:admin1_code":"7.0",
    "gn:asciiname":"Aloulouba",
    "gn:country_code":"NE",
    "gn:dem":481,
    "gn:feature_class":"P",
    "gn:feature_code":"PPL",
    "gn:name":"Aloulouba",
    "gn:population":0,
    "gn:timezone":"Africa/Niamey",
    "iso:country":"NE",
    "wof:name":"Aloulouba",
    "wof:placetype":"locality"
},
  "geometry": {"coordinates":[8.90232,14.05908],"type":"Point"}
}