{
  "type": "Feature",
  "properties": {
    "gn:admin1_code":"7.0",
    "gn:asciiname":"Mwala",
    "gn:country_code":"NE",
    "gn:dem":421,
    "gn:feature_class":"P",
    "gn:feature_code":"PPL",
    "gn:name":"Mwala",
    "gn:population":0,
    "gn:timezone":"Africa/Niamey",
    "iso:country":"NE",
    "wof:name":"Mwala",
    "wof:placetype":"locality"
},
  "geometry": {"coordinates":[8.00599,14.49181],"type":"Point"}
}