{
  "type": "Feature",
  "properties": {
    "gn:admin1_code":"3.0",
    "gn:asciiname":"Barkire Kwara",
    "gn:country_code":"NE",
    "gn:dem":184,
    "gn:feature_class":"P",
    "gn:feature_code":"PPL",
    "gn:name":"Barkir\u00e9 Kwara",
    "gn:population":0,
    "gn:timezone":"Africa/Niamey",
    "iso:country":"NE",
    "name:und_x_variant":[
        "Barkir\u00e9koara",
        "Barkir\u00e9 Kwara"
    ],
    "wof:name":"Barkire Kwara",
    "wof:placetype":"locality"
},
  "geometry": {"coordinates":[2.91063,12.56305],"type":"Point"}
}