{
  "type": "Feature",
  "properties": {
    "gn:admin1_code":"9.0",
    "gn:asciiname":"Soley Tonka",
    "gn:country_code":"NE",
    "gn:dem":219,
    "gn:feature_class":"P",
    "gn:feature_code":"PPL",
    "gn:name":"Sol\u00e8y Tonka",
    "gn:population":0,
    "gn:timezone":"Africa/Niamey",
    "iso:country":"NE",
    "name:und_x_variant":[
        "Sole\u00ef",
        "Sol\u00e8y Tonka"
    ],
    "wof:name":"Soley Tonka",
    "wof:placetype":"locality"
},
  "geometry": {"coordinates":[2.85585,14.13847],"type":"Point"}
}