{
  "type": "Feature",
  "properties": {
    "gn:admin1_code":"6.0",
    "gn:asciiname":"Abdouga",
    "gn:country_code":"NE",
    "gn:dem":307,
    "gn:feature_class":"P",
    "gn:feature_code":"PPL",
    "gn:name":"Abdouga",
    "gn:population":0,
    "gn:timezone":"Africa/Niamey",
    "iso:country":"NE",
    "wof:name":"Abdouga",
    "wof:placetype":"locality"
},
  "geometry": {"coordinates":[4.79278,14.56523],"type":"Point"}
}