{
  "type": "Feature",
  "properties": {
    "gn:admin1_code":"7.0",
    "gn:asciiname":"Koumari",
    "gn:country_code":"NE",
    "gn:dem":462,
    "gn:feature_class":"P",
    "gn:feature_code":"PPL",
    "gn:name":"Koumari",
    "gn:population":0,
    "gn:timezone":"Africa/Niamey",
    "iso:country":"NE",
    "wof:name":"Koumari",
    "wof:placetype":"locality"
},
  "geometry": {"coordinates":[9.2953,13.8834],"type":"Point"}
}