{
  "type": "Feature",
  "properties": {
    "gn:admin1_code":"3.0",
    "gn:asciiname":"Bossadji",
    "gn:country_code":"NE",
    "gn:dem":241,
    "gn:feature_class":"P",
    "gn:feature_code":"PPL",
    "gn:name":"Bossadji",
    "gn:population":0,
    "gn:timezone":"Africa/Niamey",
    "iso:country":"NE",
    "wof:name":"Bossadji",
    "wof:placetype":"locality"
},
  "geometry": {"coordinates":[2.7545,13.0736],"type":"Point"}
}