{
  "type": "Feature",
  "properties": {
    "gn:admin1_code":"7.0",
    "gn:asciiname":"Garin Masaji",
    "gn:country_code":"NE",
    "gn:dem":377,
    "gn:feature_class":"P",
    "gn:feature_code":"PPL",
    "gn:name":"Garin Masaji",
    "gn:population":0,
    "gn:timezone":"Africa/Niamey",
    "iso:country":"NE",
    "wof:name":"Garin Masaji",
    "wof:placetype":"locality"
},
  "geometry": {"coordinates":[9.2718,13.0426],"type":"Point"}
}