{
  "type": "Feature",
  "properties": {
    "gn:admin1_code":"9.0",
    "gn:asciiname":"Dougou Saro",
    "gn:country_code":"NE",
    "gn:dem":231,
    "gn:feature_class":"P",
    "gn:feature_code":"PPL",
    "gn:name":"Dougou Saro",
    "gn:population":0,
    "gn:timezone":"Africa/Niamey",
    "iso:country":"NE",
    "name:und_x_variant":[
        "Doukou",
        "Dougou Saro",
        "Dougou"
    ],
    "wof:name":"Dougou Saro",
    "wof:placetype":"locality"
},
  "geometry": {"coordinates":[1.27886,14.43511],"type":"Point"}
}