{
  "type": "Feature",
  "properties": {
    "gn:admin1_code":"4.0",
    "gn:asciiname":"Badeta",
    "gn:country_code":"NE",
    "gn:dem":370,
    "gn:feature_class":"P",
    "gn:feature_code":"PPL",
    "gn:name":"Bad\u00e8ta",
    "gn:population":0,
    "gn:timezone":"Africa/Niamey",
    "iso:country":"NE",
    "wof:name":"Badeta",
    "wof:placetype":"locality"
},
  "geometry": {"coordinates":[6.82654,13.51068],"type":"Point"}
}