{
  "type": "Feature",
  "properties": {
    "gn:admin1_code":"9.0",
    "gn:asciiname":"Bobal",
    "gn:country_code":"NE",
    "gn:dem":248,
    "gn:feature_class":"P",
    "gn:feature_code":"PPL",
    "gn:name":"Bobal",
    "gn:population":0,
    "gn:timezone":"Africa/Niamey",
    "iso:country":"NE",
    "name:cat_x_preferred":[
        "Boval"
    ],
    "name:chv_x_preferred":[
        "\u0411\u043e\u0431\u0430\u043b\u044c"
    ],
    "name:deu_x_preferred":[
        "Bobal"
    ],
    "name:fra_x_preferred":[
        "Bobal"
    ],
    "name:nld_x_preferred":[
        "Bobal"
    ],
    "name:rus_x_preferred":[
        "\u0411\u043e\u0431\u0430\u043b\u044c"
    ],
    "name:spa_x_preferred":[
        "Bobal"
    ],
    "name:ukr_x_preferred":[
        "\u0411\u043e\u0431\u0430\u043b\u044c"
    ],
    "wof:name":"Bobal",
    "wof:placetype":"locality"
},
  "geometry": {"coordinates":[2.56724,14.07904],"type":"Point"}
}