{
  "type": "Feature",
  "properties": {
    "gn:admin1_code":"6.0",
    "gn:asciiname":"Madata",
    "gn:country_code":"NE",
    "gn:dem":284,
    "gn:feature_class":"P",
    "gn:feature_code":"PPL",
    "gn:name":"Madata",
    "gn:population":0,
    "gn:timezone":"Africa/Niamey",
    "iso:country":"NE",
    "name:und_x_variant":[
        "Mandata",
        "Mandaba",
        "Madata",
        "Mandatta"
    ],
    "wof:name":"Madata",
    "wof:placetype":"locality"
},
  "geometry": {"coordinates":[5.2382,14.0083],"type":"Point"}
}