{
  "type": "Feature",
  "properties": {
    "gn:admin1_code":"3.0",
    "gn:asciiname":"Angoa Dobi",
    "gn:country_code":"NE",
    "gn:dem":201,
    "gn:feature_class":"P",
    "gn:feature_code":"PPL",
    "gn:name":"Angoa Dobi",
    "gn:population":0,
    "gn:timezone":"Africa/Niamey",
    "iso:country":"NE",
    "wof:name":"Angoa Dobi",
    "wof:placetype":"locality"
},
  "geometry": {"coordinates":[3.90478,12.9568],"type":"Point"}
}