{
  "type": "Feature",
  "properties": {
    "gn:admin1_code":"7.0",
    "gn:asciiname":"Nafouta",
    "gn:country_code":"NE",
    "gn:dem":549,
    "gn:feature_class":"P",
    "gn:feature_code":"PPL",
    "gn:name":"Nafouta",
    "gn:population":0,
    "gn:timezone":"Africa/Niamey",
    "iso:country":"NE",
    "wof:name":"Nafouta",
    "wof:placetype":"locality"
},
  "geometry": {"coordinates":[8.92239,14.92535],"type":"Point"}
}