{
  "type": "Feature",
  "properties": {
    "gn:admin1_code":"7.0",
    "gn:asciiname":"Na-tirje",
    "gn:country_code":"NE",
    "gn:dem":460,
    "gn:feature_class":"P",
    "gn:feature_code":"PPL",
    "gn:name":"N\u00e2-tirj\u00e9",
    "gn:population":0,
    "gn:timezone":"Africa/Niamey",
    "iso:country":"NE",
    "wof:name":"Na-tirje",
    "wof:placetype":"locality"
},
  "geometry": {"coordinates":[8.86325,13.83048],"type":"Point"}
}