{
  "type": "Feature",
  "properties": {
    "gn:admin1_code":"3.0",
    "gn:asciiname":"Kotaye",
    "gn:country_code":"NE",
    "gn:dem":276,
    "gn:feature_class":"P",
    "gn:feature_code":"PPL",
    "gn:name":"Kotay\u00e9",
    "gn:population":0,
    "gn:timezone":"Africa/Niamey",
    "iso:country":"NE",
    "wof:name":"Kotaye",
    "wof:placetype":"locality"
},
  "geometry": {"coordinates":[3.9303,14.2975],"type":"Point"}
}