{
  "type": "Feature",
  "properties": {
    "gn:admin1_code":"9.0",
    "gn:asciiname":"Dinti Bangou",
    "gn:country_code":"NE",
    "gn:dem":234,
    "gn:feature_class":"P",
    "gn:feature_code":"PPL",
    "gn:name":"Dinti Bangou",
    "gn:population":0,
    "gn:timezone":"Africa/Niamey",
    "iso:country":"NE",
    "wof:name":"Dinti Bangou",
    "wof:placetype":"locality"
},
  "geometry": {"coordinates":[1.36625,13.92934],"type":"Point"}
}