{
  "type": "Feature",
  "properties": {
    "gn:admin1_code":"6.0",
    "gn:asciiname":"Foura",
    "gn:country_code":"NE",
    "gn:dem":301,
    "gn:feature_class":"P",
    "gn:feature_code":"PPL",
    "gn:name":"Foura",
    "gn:population":0,
    "gn:timezone":"Africa/Niamey",
    "iso:country":"NE",
    "wof:name":"Foura",
    "wof:placetype":"locality"
},
  "geometry": {"coordinates":[6.20773,13.67766],"type":"Point"}
}