{
  "type": "Feature",
  "properties": {
    "gn:admin1_code":"6.0",
    "gn:asciiname":"Guidan Mayboube",
    "gn:country_code":"NE",
    "gn:dem":424,
    "gn:feature_class":"P",
    "gn:feature_code":"PPL",
    "gn:name":"Guidan Mayboub\u00e9",
    "gn:population":0,
    "gn:timezone":"Africa/Niamey",
    "iso:country":"NE",
    "wof:name":"Guidan Mayboube",
    "wof:placetype":"locality"
},
  "geometry": {"coordinates":[6.45131,14.25602],"type":"Point"}
}