{
  "type": "Feature",
  "properties": {
    "gn:admin1_code":"7.0",
    "gn:asciiname":"Tchaba",
    "gn:country_code":"NE",
    "gn:dem":429,
    "gn:feature_class":"P",
    "gn:feature_code":"PPL",
    "gn:name":"Tchaba",
    "gn:population":0,
    "gn:timezone":"Africa/Niamey",
    "iso:country":"NE",
    "wof:name":"Tchaba",
    "wof:placetype":"locality"
},
  "geometry": {"coordinates":[8.74929,13.25291],"type":"Point"}
}