{
  "type": "Feature",
  "properties": {
    "gn:admin1_code":"6.0",
    "gn:asciiname":"Guidan Maykayderi",
    "gn:country_code":"NE",
    "gn:dem":404,
    "gn:feature_class":"P",
    "gn:feature_code":"PPL",
    "gn:name":"Guidan Maykayd\u00e9ri",
    "gn:population":0,
    "gn:timezone":"Africa/Niamey",
    "iso:country":"NE",
    "name:und_x_variant":[
        "Gidan Maykayd\u00e9ri",
        "Guidan Maykayd\u00e9ri"
    ],
    "wof:name":"Guidan Maykayderi",
    "wof:placetype":"locality"
},
  "geometry": {"coordinates":[5.71801,13.87818],"type":"Point"}
}