{
  "type": "Feature",
  "properties": {
    "gn:admin1_code":"3.0",
    "gn:asciiname":"Deyteguifandou",
    "gn:country_code":"NE",
    "gn:dem":251,
    "gn:feature_class":"P",
    "gn:feature_code":"PPL",
    "gn:name":"Deyt\u00e9guifandou",
    "gn:population":0,
    "gn:timezone":"Africa/Niamey",
    "iso:country":"NE",
    "wof:name":"Deyteguifandou",
    "wof:placetype":"locality"
},
  "geometry": {"coordinates":[3.1321,13.6509],"type":"Point"}
}