{
  "type": "Feature",
  "properties": {
    "gn:admin1_code":"4.0",
    "gn:asciiname":"Guidan Kane Katsinawa",
    "gn:country_code":"NE",
    "gn:dem":387,
    "gn:feature_class":"P",
    "gn:feature_code":"PPL",
    "gn:name":"Guidan Kan\u00e9 Katsinawa",
    "gn:population":0,
    "gn:timezone":"Africa/Niamey",
    "iso:country":"NE",
    "name:und_x_variant":[
        "Guidan Kan\u00e9 Kats\u00e9nawa",
        "Guidan Kan\u00e9 Katsinawa"
    ],
    "wof:name":"Guidan Kane Katsinawa",
    "wof:placetype":"locality"
},
  "geometry": {"coordinates":[7.40658,13.62687],"type":"Point"}
}