{
  "type": "Feature",
  "properties": {
    "gn:admin1_code":"6.0",
    "gn:asciiname":"Kolarawa",
    "gn:country_code":"NE",
    "gn:dem":308,
    "gn:feature_class":"P",
    "gn:feature_code":"PPL",
    "gn:name":"Kolarawa",
    "gn:population":0,
    "gn:timezone":"Africa/Niamey",
    "iso:country":"NE",
    "wof:name":"Kolarawa",
    "wof:placetype":"locality"
},
  "geometry": {"coordinates":[6.07867,13.82485],"type":"Point"}
}