{
  "type": "Feature",
  "properties": {
    "gn:admin1_code":"7.0",
    "gn:asciiname":"Maitafassa",
    "gn:country_code":"NE",
    "gn:dem":483,
    "gn:feature_class":"P",
    "gn:feature_code":"PPL",
    "gn:name":"Ma\u00eftafassa",
    "gn:population":0,
    "gn:timezone":"Africa/Niamey",
    "iso:country":"NE",
    "wof:name":"Maitafassa",
    "wof:placetype":"locality"
},
  "geometry": {"coordinates":[8.66411,15.05778],"type":"Point"}
}