{
  "type": "Feature",
  "properties": {
    "gn:admin1_code":"9.0",
    "gn:asciiname":"Birimpeni",
    "gn:country_code":"NE",
    "gn:dem":250,
    "gn:feature_class":"P",
    "gn:feature_code":"PPL",
    "gn:name":"Birimp\u00e9ni",
    "gn:population":0,
    "gn:timezone":"Africa/Niamey",
    "iso:country":"NE",
    "wof:name":"Birimpeni",
    "wof:placetype":"locality"
},
  "geometry": {"coordinates":[1.44862,13.14163],"type":"Point"}
}