{
  "type": "Feature",
  "properties": {
    "gn:admin1_code":"7.0",
    "gn:asciiname":"Kakara",
    "gn:country_code":"NE",
    "gn:dem":432,
    "gn:feature_class":"P",
    "gn:feature_code":"PPL",
    "gn:name":"Kakara",
    "gn:population":0,
    "gn:timezone":"Africa/Niamey",
    "iso:country":"NE",
    "name:ceb_x_preferred":[
        "Kakara"
    ],
    "name:swe_x_preferred":[
        "Kakara"
    ],
    "name:und_x_variant":[
        "Karkara"
    ],
    "wof:name":"Kakara",
    "wof:placetype":"locality"
},
  "geometry": {"coordinates":[9.5881,13.8995],"type":"Point"}
}