{
  "type": "Feature",
  "properties": {
    "gn:admin1_code":"9.0",
    "gn:asciiname":"Komo Bangou",
    "gn:country_code":"NE",
    "gn:dem":244,
    "gn:feature_class":"P",
    "gn:feature_code":"PPL",
    "gn:name":"Komo Bangou",
    "gn:population":0,
    "gn:timezone":"Africa/Niamey",
    "iso:country":"NE",
    "wof:name":"Komo Bangou",
    "wof:placetype":"locality"
},
  "geometry": {"coordinates":[2.01522,14.4149],"type":"Point"}
}