{
  "type": "Feature",
  "properties": {
    "gn:admin1_code":"4.0",
    "gn:asciiname":"D'akora Harouna",
    "gn:country_code":"NE",
    "gn:dem":409,
    "gn:feature_class":"P",
    "gn:feature_code":"PPL",
    "gn:name":"D'akora Harouna",
    "gn:population":0,
    "gn:timezone":"Africa/Niamey",
    "iso:country":"NE",
    "name:und_x_variant":[
        "Dakoro",
        "D'akora Harouna"
    ],
    "wof:name":"D'akora Harouna",
    "wof:placetype":"locality"
},
  "geometry": {"coordinates":[7.76024,13.80499],"type":"Point"}
}