{
  "type": "Feature",
  "properties": {
    "gn:admin1_code":"6.0",
    "gn:asciiname":"Tougo Gala",
    "gn:country_code":"NE",
    "gn:dem":510,
    "gn:feature_class":"P",
    "gn:feature_code":"PPL",
    "gn:name":"Tougo Gala",
    "gn:population":0,
    "gn:timezone":"Africa/Niamey",
    "iso:country":"NE",
    "wof:name":"Tougo Gala",
    "wof:placetype":"locality"
},
  "geometry": {"coordinates":[5.8867,14.9317],"type":"Point"}
}