{
  "type": "Feature",
  "properties": {
    "gn:admin1_code":"9.0",
    "gn:asciiname":"Dolbel",
    "gn:country_code":"NE",
    "gn:dem":253,
    "gn:feature_class":"P",
    "gn:feature_code":"PPL",
    "gn:name":"Dolb\u00e8l",
    "gn:population":0,
    "gn:timezone":"Africa/Niamey",
    "iso:country":"NE",
    "name:und_x_variant":[
        "Golbel",
        "Dolb\u00e8l"
    ],
    "wof:name":"Dolbel",
    "wof:placetype":"locality"
},
  "geometry": {"coordinates":[0.27645,14.61194],"type":"Point"}
}