{
  "type": "Feature",
  "properties": {
    "gn:admin1_code":"7.0",
    "gn:asciiname":"Talia",
    "gn:country_code":"NE",
    "gn:dem":427,
    "gn:feature_class":"P",
    "gn:feature_code":"PPL",
    "gn:name":"Talia",
    "gn:population":0,
    "gn:timezone":"Africa/Niamey",
    "iso:country":"NE",
    "wof:name":"Talia",
    "wof:placetype":"locality"
},
  "geometry": {"coordinates":[8.1312,14.6942],"type":"Point"}
}