{
  "type": "Feature",
  "properties": {
    "gn:admin1_code":"7.0",
    "gn:asciiname":"Talia",
    "gn:country_code":"NE",
    "gn:dem":427,
    "gn:feature_class":"P",
    "gn:feature_code":"PPL",
    "gn:name":"Talia",
    "gn:population":0,
    "gn:timezone":"Africa/Niamey",
    "iso:country":"NE",
    "name:cat_x_preferred":[
        "Talia"
    ],
    "name:ceb_x_preferred":[
        "Talia"
    ],
    "name:deu_x_preferred":[
        "Talia"
    ],
    "name:fra_x_preferred":[
        "Talia"
    ],
    "name:glg_x_preferred":[
        "Tal\u00eda"
    ],
    "name:heb_x_preferred":[
        "\u05d8\u05dc\u05d9\u05d4"
    ],
    "name:ita_x_preferred":[
        "Talia"
    ],
    "name:jpn_x_preferred":[
        "\u30bf\u30ea\u30a2"
    ],
    "name:pol_x_preferred":[
        "Talia"
    ],
    "name:por_x_preferred":[
        "T\u00e1lia"
    ],
    "name:scn_x_preferred":[
        "Talia"
    ],
    "name:slk_x_preferred":[
        "T\u00e1lia"
    ],
    "name:spa_x_preferred":[
        "Tal\u00eda"
    ],
    "name:swe_x_preferred":[
        "Talia"
    ],
    "wof:name":"Talia",
    "wof:placetype":"locality"
},
  "geometry": {"coordinates":[8.1312,14.6942],"type":"Point"}
}