{
  "type": "Feature",
  "properties": {
    "gn:admin1_code":"4.0",
    "gn:asciiname":"Dangali",
    "gn:country_code":"NE",
    "gn:dem":386,
    "gn:feature_class":"P",
    "gn:feature_code":"PPL",
    "gn:name":"Dangali",
    "gn:population":0,
    "gn:timezone":"Africa/Niamey",
    "iso:country":"NE",
    "wof:name":"Dangali",
    "wof:placetype":"locality"
},
  "geometry": {"coordinates":[7.62447,13.90991],"type":"Point"}
}