{
  "type": "Feature",
  "properties": {
    "gn:admin1_code":"4.0",
    "gn:asciiname":"Moudougou",
    "gn:country_code":"NE",
    "gn:dem":399,
    "gn:feature_class":"P",
    "gn:feature_code":"PPL",
    "gn:name":"Moudougou",
    "gn:population":0,
    "gn:timezone":"Africa/Niamey",
    "iso:country":"NE",
    "wof:name":"Moudougou",
    "wof:placetype":"locality"
},
  "geometry": {"coordinates":[6.5469,14.74933],"type":"Point"}
}