{
  "type": "Feature",
  "properties": {
    "gn:admin1_code":"4.0",
    "gn:asciiname":"Koubdo Saboa",
    "gn:country_code":"NE",
    "gn:dem":400,
    "gn:feature_class":"P",
    "gn:feature_code":"PPL",
    "gn:name":"Koubdo Saboa",
    "gn:population":0,
    "gn:timezone":"Africa/Niamey",
    "iso:country":"NE",
    "wof:name":"Koubdo Saboa",
    "wof:placetype":"locality"
},
  "geometry": {"coordinates":[7.91081,13.73943],"type":"Point"}
}