{
  "type": "Feature",
  "properties": {
    "gn:admin1_code":"6.0",
    "gn:asciiname":"Zoukouta",
    "gn:country_code":"NE",
    "gn:dem":352,
    "gn:feature_class":"P",
    "gn:feature_code":"PPL",
    "gn:name":"Zoukouta",
    "gn:population":0,
    "gn:timezone":"Africa/Niamey",
    "iso:country":"NE",
    "wof:name":"Zoukouta",
    "wof:placetype":"locality"
},
  "geometry": {"coordinates":[5.4766,14.1378],"type":"Point"}
}