{
  "type": "Feature",
  "properties": {
    "gn:admin1_code":"6.0",
    "gn:asciiname":"Mahawa",
    "gn:country_code":"NE",
    "gn:dem":300,
    "gn:feature_class":"P",
    "gn:feature_code":"PPL",
    "gn:name":"Mahawa",
    "gn:population":0,
    "gn:timezone":"Africa/Niamey",
    "iso:country":"NE",
    "wof:name":"Mahawa",
    "wof:placetype":"locality"
},
  "geometry": {"coordinates":[6.18157,13.77971],"type":"Point"}
}