{
  "type": "Feature",
  "properties": {
    "gn:admin1_code":"3.0",
    "gn:asciiname":"Sakari-Koara",
    "gn:country_code":"NE",
    "gn:dem":238,
    "gn:feature_class":"P",
    "gn:feature_code":"PPL",
    "gn:name":"Sakari-Koara",
    "gn:population":0,
    "gn:timezone":"Africa/Niamey",
    "iso:country":"NE",
    "name:und_x_variant":[
        "Sakari Kwara",
        "Sakari-Koara"
    ],
    "wof:name":"Sakari-Koara",
    "wof:placetype":"locality"
},
  "geometry": {"coordinates":[3.6198,13.1849],"type":"Point"}
}