{
  "type": "Feature",
  "properties": {
    "gn:admin1_code":"9.0",
    "gn:asciiname":"Lmoudaka Kogane",
    "gn:country_code":"NE",
    "gn:dem":279,
    "gn:feature_class":"P",
    "gn:feature_code":"PPL",
    "gn:name":"Lmoudaka Kogan\u00e9",
    "gn:population":0,
    "gn:timezone":"Africa/Niamey",
    "iso:country":"NE",
    "name:und_x_variant":[
        "Kogan\u00e9",
        "Imoudaka",
        "Lmoudaka Kogan\u00e9"
    ],
    "wof:name":"Lmoudaka Kogane",
    "wof:placetype":"locality"
},
  "geometry": {"coordinates":[0.53268,13.89626],"type":"Point"}
}