{
  "type": "Feature",
  "properties": {
    "gn:admin1_code":"7.0",
    "gn:asciiname":"Deloua",
    "gn:country_code":"NE",
    "gn:dem":537,
    "gn:feature_class":"P",
    "gn:feature_code":"PPL",
    "gn:name":"D\u00e9loua",
    "gn:population":0,
    "gn:timezone":"Africa/Niamey",
    "iso:country":"NE",
    "wof:name":"Deloua",
    "wof:placetype":"locality"
},
  "geometry": {"coordinates":[10.201,14.4329],"type":"Point"}
}