{
  "type": "Feature",
  "properties": {
    "gn:admin1_code":"9.0",
    "gn:asciiname":"Reyrabanza",
    "gn:country_code":"NE",
    "gn:dem":220,
    "gn:feature_class":"P",
    "gn:feature_code":"PPL",
    "gn:name":"Reyrabanza",
    "gn:population":0,
    "gn:timezone":"Africa/Niamey",
    "iso:country":"NE",
    "wof:name":"Reyrabanza",
    "wof:placetype":"locality"
},
  "geometry": {"coordinates":[3.4323,14.1383],"type":"Point"}
}