{
  "type": "Feature",
  "properties": {
    "gn:admin1_code":"6.0",
    "gn:asciiname":"Fotingel",
    "gn:country_code":"NE",
    "gn:dem":395,
    "gn:feature_class":"P",
    "gn:feature_code":"PPL",
    "gn:name":"Fotingel",
    "gn:population":0,
    "gn:timezone":"Africa/Niamey",
    "iso:country":"NE",
    "name:und_x_variant":[
        "Fotinguel",
        "Fotingel"
    ],
    "wof:name":"Fotingel",
    "wof:placetype":"locality"
},
  "geometry": {"coordinates":[6.33724,14.36148],"type":"Point"}
}