{
  "type": "Feature",
  "properties": {
    "gn:admin1_code":"4.0",
    "gn:asciiname":"Samia Ketao",
    "gn:country_code":"NE",
    "gn:dem":434,
    "gn:feature_class":"P",
    "gn:feature_code":"PPL",
    "gn:name":"Samia K\u00e9tao",
    "gn:population":0,
    "gn:timezone":"Africa/Niamey",
    "iso:country":"NE",
    "wof:name":"Samia Ketao",
    "wof:placetype":"locality"
},
  "geometry": {"coordinates":[8.25643,13.28165],"type":"Point"}
}