{
  "type": "Feature",
  "properties": {
    "gn:admin1_code":"6.0",
    "gn:asciiname":"Zangon Moujia",
    "gn:country_code":"NE",
    "gn:dem":324,
    "gn:feature_class":"P",
    "gn:feature_code":"PPL",
    "gn:name":"Zangon Moujia",
    "gn:population":0,
    "gn:timezone":"Africa/Niamey",
    "iso:country":"NE",
    "wof:name":"Zangon Moujia",
    "wof:placetype":"locality"
},
  "geometry": {"coordinates":[5.3715,14.3569],"type":"Point"}
}