{
  "type": "Feature",
  "properties": {
    "gn:admin1_code":"7.0",
    "gn:asciiname":"Sada K'aram",
    "gn:country_code":"NE",
    "gn:dem":456,
    "gn:feature_class":"P",
    "gn:feature_code":"PPL",
    "gn:name":"Sada K'aram",
    "gn:population":0,
    "gn:timezone":"Africa/Niamey",
    "iso:country":"NE",
    "wof:name":"Sada K'aram",
    "wof:placetype":"locality"
},
  "geometry": {"coordinates":[8.98917,13.91459],"type":"Point"}
}