{
  "type": "Feature",
  "properties": {
    "gn:admin1_code":"3.0",
    "gn:asciiname":"Dineguidi",
    "gn:country_code":"NE",
    "gn:dem":256,
    "gn:feature_class":"P",
    "gn:feature_code":"PPL",
    "gn:name":"Din\u00e9guidi",
    "gn:population":0,
    "gn:timezone":"Africa/Niamey",
    "iso:country":"NE",
    "wof:name":"Dineguidi",
    "wof:placetype":"locality"
},
  "geometry": {"coordinates":[3.7801,13.3882],"type":"Point"}
}