{
  "type": "Feature",
  "properties": {
    "gn:admin1_code":"8.0",
    "gn:asciiname":"Banidyoumbou",
    "gn:country_code":"NE",
    "gn:dem":218,
    "gn:feature_class":"P",
    "gn:feature_code":"PPL",
    "gn:name":"Banidyoumbou",
    "gn:population":0,
    "gn:timezone":"Africa/Niamey",
    "iso:country":"NE",
    "wof:name":"Banidyoumbou",
    "wof:placetype":"locality"
},
  "geometry": {"coordinates":[1.86667,13.11667],"type":"Point"}
}