{
  "type": "Feature",
  "properties": {
    "gn:admin1_code":"9.0",
    "gn:asciiname":"Siankore Bambara",
    "gn:country_code":"NE",
    "gn:dem":220,
    "gn:feature_class":"P",
    "gn:feature_code":"PPL",
    "gn:name":"Siankor\u00e9 Bambara",
    "gn:population":0,
    "gn:timezone":"Africa/Niamey",
    "iso:country":"NE",
    "name:und_x_variant":[
        "Siankor\u00e9 Bambara",
        "Siankol\u00e9"
    ],
    "wof:name":"Siankore Bambara",
    "wof:placetype":"locality"
},
  "geometry": {"coordinates":[1.87663,12.86649],"type":"Point"}
}