{
  "type": "Feature",
  "properties": {
    "gn:admin1_code":"6.0",
    "gn:asciiname":"Guidan Arouna",
    "gn:country_code":"NE",
    "gn:dem":351,
    "gn:feature_class":"P",
    "gn:feature_code":"PPL",
    "gn:name":"Guidan Arouna",
    "gn:population":0,
    "gn:timezone":"Africa/Niamey",
    "iso:country":"NE",
    "wof:name":"Guidan Arouna",
    "wof:placetype":"locality"
},
  "geometry": {"coordinates":[6.46399,14.07436],"type":"Point"}
}