{
  "type": "Feature",
  "properties": {
    "gn:admin1_code":"7.0",
    "gn:asciiname":"Yachima",
    "gn:country_code":"NE",
    "gn:dem":482,
    "gn:feature_class":"P",
    "gn:feature_code":"PPL",
    "gn:name":"Yachima",
    "gn:population":0,
    "gn:timezone":"Africa/Niamey",
    "iso:country":"NE",
    "wof:name":"Yachima",
    "wof:placetype":"locality"
},
  "geometry": {"coordinates":[8.8827,14.5855],"type":"Point"}
}