{
  "type": "Feature",
  "properties": {
    "gn:admin1_code":"6.0",
    "gn:asciiname":"Mayeroufa",
    "gn:country_code":"NE",
    "gn:dem":391,
    "gn:feature_class":"P",
    "gn:feature_code":"PPL",
    "gn:name":"May\u00e9roufa",
    "gn:population":0,
    "gn:timezone":"Africa/Niamey",
    "iso:country":"NE",
    "wof:name":"Mayeroufa",
    "wof:placetype":"locality"
},
  "geometry": {"coordinates":[6.36083,14.32974],"type":"Point"}
}