{
  "type": "Feature",
  "properties": {
    "gn:admin1_code":"9.0",
    "gn:asciiname":"Sefala",
    "gn:country_code":"NE",
    "gn:dem":274,
    "gn:feature_class":"P",
    "gn:feature_code":"PPL",
    "gn:name":"S\u00e9fala",
    "gn:population":0,
    "gn:timezone":"Africa/Niamey",
    "iso:country":"NE",
    "wof:name":"Sefala",
    "wof:placetype":"locality"
},
  "geometry": {"coordinates":[3.6654,14.9395],"type":"Point"}
}