{
  "type": "Feature",
  "properties": {
    "gn:admin1_code":"4.0",
    "gn:asciiname":"Katare",
    "gn:country_code":"NE",
    "gn:dem":413,
    "gn:feature_class":"P",
    "gn:feature_code":"PPL",
    "gn:name":"Katar\u00e9",
    "gn:population":0,
    "gn:timezone":"Africa/Niamey",
    "iso:country":"NE",
    "name:und_x_variant":[
        "Katir\u00e9",
        "Katar\u00e9"
    ],
    "wof:name":"Katare",
    "wof:placetype":"locality"
},
  "geometry": {"coordinates":[7.41955,14.18485],"type":"Point"}
}