{
  "type": "Feature",
  "properties": {
    "gn:admin1_code":"2.0",
    "gn:asciiname":"Sayam",
    "gn:country_code":"NE",
    "gn:dem":315,
    "gn:feature_class":"P",
    "gn:feature_code":"PPL",
    "gn:name":"Sayam",
    "gn:population":0,
    "gn:timezone":"Africa/Niamey",
    "iso:country":"NE",
    "name:und_x_variant":[
        "Sagam",
        "Sayam"
    ],
    "wof:name":"Sayam",
    "wof:placetype":"locality"
},
  "geometry": {"coordinates":[12.50667,13.6284],"type":"Point"}
}