{
  "type": "Feature",
  "properties": {
    "gn:admin1_code":"9.0",
    "gn:asciiname":"Touloubi",
    "gn:country_code":"NE",
    "gn:dem":221,
    "gn:feature_class":"P",
    "gn:feature_code":"PPL",
    "gn:name":"Touloubi",
    "gn:population":0,
    "gn:timezone":"Africa/Niamey",
    "iso:country":"NE",
    "wof:name":"Touloubi",
    "wof:placetype":"locality"
},
  "geometry": {"coordinates":[3.1402,14.0839],"type":"Point"}
}