{
  "type": "Feature",
  "properties": {
    "gn:admin1_code":"7.0",
    "gn:asciiname":"Medjiga",
    "gn:country_code":"NE",
    "gn:dem":512,
    "gn:feature_class":"P",
    "gn:feature_code":"PPL",
    "gn:name":"M\u00e9djiga",
    "gn:population":0,
    "gn:timezone":"Africa/Niamey",
    "iso:country":"NE",
    "wof:name":"Medjiga",
    "wof:placetype":"locality"
},
  "geometry": {"coordinates":[9.1392,14.0892],"type":"Point"}
}