{
  "type": "Feature",
  "properties": {
    "gn:admin1_code":"4.0",
    "gn:asciiname":"Dan Rabi",
    "gn:country_code":"NE",
    "gn:dem":453,
    "gn:feature_class":"P",
    "gn:feature_code":"PPL",
    "gn:name":"Dan Rabi",
    "gn:population":0,
    "gn:timezone":"Africa/Niamey",
    "iso:country":"NE",
    "wof:name":"Dan Rabi",
    "wof:placetype":"locality"
},
  "geometry": {"coordinates":[8.29415,13.28291],"type":"Point"}
}