{
  "type": "Feature",
  "properties": {
    "gn:admin1_code":"7.0",
    "gn:asciiname":"Yari",
    "gn:country_code":"NE",
    "gn:dem":364,
    "gn:feature_class":"P",
    "gn:feature_code":"PPL",
    "gn:name":"Yari",
    "gn:population":0,
    "gn:timezone":"Africa/Niamey",
    "iso:country":"NE",
    "wof:name":"Yari",
    "wof:placetype":"locality"
},
  "geometry": {"coordinates":[10.73219,13.83955],"type":"Point"}
}