{
  "type": "Feature",
  "properties": {
    "gn:admin1_code":"7.0",
    "gn:asciiname":"Foura Girke",
    "gn:country_code":"NE",
    "gn:dem":467,
    "gn:feature_class":"P",
    "gn:feature_code":"PPL",
    "gn:name":"Foura Girk\u00e9",
    "gn:population":0,
    "gn:timezone":"Africa/Niamey",
    "iso:country":"NE",
    "name:und_x_variant":[
        "Foura Guirk\u00e9",
        "Foura Girk\u00e9"
    ],
    "wof:name":"Foura Girke",
    "wof:placetype":"locality"
},
  "geometry": {"coordinates":[8.92164,14.3065],"type":"Point"}
}