{
  "type": "Feature",
  "properties": {
    "gn:admin1_code":"9.0",
    "gn:asciiname":"Kirtachi Seybou",
    "gn:country_code":"NE",
    "gn:dem":180,
    "gn:feature_class":"P",
    "gn:feature_code":"PPL",
    "gn:name":"Kirtachi Seybou",
    "gn:population":0,
    "gn:timezone":"Africa/Niamey",
    "iso:country":"NE",
    "name:deu_x_preferred":[
        "Kirtachi"
    ],
    "name:ita_x_preferred":[
        "Kirtachi"
    ],
    "name:msa_x_preferred":[
        "Kirtachi"
    ],
    "name:ron_x_preferred":[
        "Kirtachi"
    ],
    "name:spa_x_preferred":[
        "Kirtachi"
    ],
    "name:und_x_variant":[
        "Kirtachi",
        "Kirtachi Seybou"
    ],
    "wof:name":"Kirtachi Seybou",
    "wof:placetype":"locality"
},
  "geometry": {"coordinates":[2.47557,12.79519],"type":"Point"}
}