{
  "type": "Feature",
  "properties": {
    "gn:admin1_code":"9.0",
    "gn:asciiname":"Boundou",
    "gn:country_code":"NE",
    "gn:dem":207,
    "gn:feature_class":"P",
    "gn:feature_code":"PPL",
    "gn:name":"Boundou",
    "gn:population":0,
    "gn:timezone":"Africa/Niamey",
    "iso:country":"NE",
    "wof:name":"Boundou",
    "wof:placetype":"locality"
},
  "geometry": {"coordinates":[2.6421,13.5446],"type":"Point"}
}