{
  "type": "Feature",
  "properties": {
    "gn:admin1_code":"7.0",
    "gn:asciiname":"Magaria Tounkour",
    "gn:country_code":"NE",
    "gn:dem":438,
    "gn:feature_class":"P",
    "gn:feature_code":"PPL",
    "gn:name":"Magaria Tounkour",
    "gn:population":0,
    "gn:timezone":"Africa/Niamey",
    "iso:country":"NE",
    "wof:name":"Magaria Tounkour",
    "wof:placetype":"locality"
},
  "geometry": {"coordinates":[8.70627,13.54636],"type":"Point"}
}