{
  "type": "Feature",
  "properties": {
    "gn:admin1_code":"3.0",
    "gn:asciiname":"Koron Gomey",
    "gn:country_code":"NE",
    "gn:dem":244,
    "gn:feature_class":"P",
    "gn:feature_code":"PPL",
    "gn:name":"Koron Gom\u00e8y",
    "gn:population":0,
    "gn:timezone":"Africa/Niamey",
    "iso:country":"NE",
    "name:und_x_variant":[
        "Kuarangami",
        "Koron Gom\u00e8y"
    ],
    "wof:name":"Koron Gomey",
    "wof:placetype":"locality"
},
  "geometry": {"coordinates":[4.3819,13.69273],"type":"Point"}
}