{
  "type": "Feature",
  "properties": {
    "gn:admin1_code":"6.0",
    "gn:asciiname":"Awanchela",
    "gn:country_code":"NE",
    "gn:dem":304,
    "gn:feature_class":"P",
    "gn:feature_code":"PPL",
    "gn:name":"Awanch\u00e9la",
    "gn:population":0,
    "gn:timezone":"Africa/Niamey",
    "iso:country":"NE",
    "wof:name":"Awanchela",
    "wof:placetype":"locality"
},
  "geometry": {"coordinates":[4.50721,14.5748],"type":"Point"}
}