{
  "type": "Feature",
  "properties": {
    "gn:admin1_code":"7.0",
    "gn:asciiname":"Artey",
    "gn:country_code":"NE",
    "gn:dem":458,
    "gn:feature_class":"P",
    "gn:feature_code":"PPL",
    "gn:name":"Artey",
    "gn:population":0,
    "gn:timezone":"Africa/Niamey",
    "iso:country":"NE",
    "wof:name":"Artey",
    "wof:placetype":"locality"
},
  "geometry": {"coordinates":[8.59246,13.27589],"type":"Point"}
}