{
  "type": "Feature",
  "properties": {
    "gn:admin1_code":"3.0",
    "gn:asciiname":"Touhore",
    "gn:country_code":"NE",
    "gn:dem":223,
    "gn:feature_class":"P",
    "gn:feature_code":"PPL",
    "gn:name":"Touhor\u00e9",
    "gn:population":0,
    "gn:timezone":"Africa/Niamey",
    "iso:country":"NE",
    "name:und_x_variant":[
        "Tihore",
        "Tikor\u00e9",
        "Touhor\u00e9"
    ],
    "wof:name":"Touhore",
    "wof:placetype":"locality"
},
  "geometry": {"coordinates":[2.63334,12.86828],"type":"Point"}
}