{
  "type": "Feature",
  "properties": {
    "gn:admin1_code":"4.0",
    "gn:asciiname":"Guidan Bagouari",
    "gn:country_code":"NE",
    "gn:dem":412,
    "gn:feature_class":"P",
    "gn:feature_code":"PPL",
    "gn:name":"Guidan Bagou\u00e2r\u00ee",
    "gn:population":0,
    "gn:timezone":"Africa/Niamey",
    "iso:country":"NE",
    "name:und_x_variant":[
        "Gidan Bogori",
        "Guidan Bogori",
        "Guidan Bagou\u00e2r\u00ee"
    ],
    "wof:name":"Guidan Bagouari",
    "wof:placetype":"locality"
},
  "geometry": {"coordinates":[7.53943,13.7112],"type":"Point"}
}