{
  "type": "Feature",
  "properties": {
    "gn:admin1_code":"7.0",
    "gn:asciiname":"Kinoa",
    "gn:country_code":"NE",
    "gn:dem":434,
    "gn:feature_class":"P",
    "gn:feature_code":"PPL",
    "gn:name":"Kinoa",
    "gn:population":0,
    "gn:timezone":"Africa/Niamey",
    "iso:country":"NE",
    "wof:name":"Kinoa",
    "wof:placetype":"locality"
},
  "geometry": {"coordinates":[9.507,13.94057],"type":"Point"}
}