{
  "type": "Feature",
  "properties": {
    "gn:admin1_code":"6.0",
    "gn:asciiname":"Souraka",
    "gn:country_code":"NE",
    "gn:dem":356,
    "gn:feature_class":"P",
    "gn:feature_code":"PPL",
    "gn:name":"Souraka",
    "gn:population":0,
    "gn:timezone":"Africa/Niamey",
    "iso:country":"NE",
    "wof:name":"Souraka",
    "wof:placetype":"locality"
},
  "geometry": {"coordinates":[6.49844,14.57619],"type":"Point"}
}