{
  "type": "Feature",
  "properties": {
    "gn:admin1_code":"4.0",
    "gn:asciiname":"Alforma Bogwari",
    "gn:country_code":"NE",
    "gn:dem":398,
    "gn:feature_class":"P",
    "gn:feature_code":"PPL",
    "gn:name":"Alforma Bogwari",
    "gn:population":0,
    "gn:timezone":"Africa/Niamey",
    "iso:country":"NE",
    "wof:name":"Alforma Bogwari",
    "wof:placetype":"locality"
},
  "geometry": {"coordinates":[7.31473,14.02703],"type":"Point"}
}