{
  "type": "Feature",
  "properties": {
    "gn:admin1_code":"9.0",
    "gn:asciiname":"Debiel",
    "gn:country_code":"NE",
    "gn:dem":219,
    "gn:feature_class":"P",
    "gn:feature_code":"PPL",
    "gn:name":"D\u00e9biel",
    "gn:population":0,
    "gn:timezone":"Africa/Niamey",
    "iso:country":"NE",
    "wof:name":"Debiel",
    "wof:placetype":"locality"
},
  "geometry": {"coordinates":[2.322,13.0611],"type":"Point"}
}