{
  "type": "Feature",
  "properties": {
    "gn:admin1_code":"9.0",
    "gn:asciiname":"Firinkin",
    "gn:country_code":"NE",
    "gn:dem":239,
    "gn:feature_class":"P",
    "gn:feature_code":"PPLL",
    "gn:name":"Firinkin",
    "gn:population":0,
    "gn:timezone":"Africa/Niamey",
    "iso:country":"NE",
    "wof:name":"Firinkin",
    "wof:placetype":"locality"
},
  "geometry": {"coordinates":[1.32353,13.95645],"type":"Point"}
}