{
  "type": "Feature",
  "properties": {
    "gn:admin1_code":"9.0",
    "gn:asciiname":"Basawa",
    "gn:country_code":"NE",
    "gn:dem":276,
    "gn:feature_class":"P",
    "gn:feature_code":"PPL",
    "gn:name":"Basawa",
    "gn:population":0,
    "gn:timezone":"Africa/Niamey",
    "iso:country":"NE",
    "wof:name":"Basawa",
    "wof:placetype":"locality"
},
  "geometry": {"coordinates":[0.60841,13.93298],"type":"Point"}
}