{
  "type": "Feature",
  "properties": {
    "gn:admin1_code":"7.0",
    "gn:asciiname":"Kwatokom",
    "gn:country_code":"NE",
    "gn:dem":520,
    "gn:feature_class":"P",
    "gn:feature_code":"PPL",
    "gn:name":"Kwatokom",
    "gn:population":0,
    "gn:timezone":"Africa/Niamey",
    "iso:country":"NE",
    "wof:name":"Kwatokom",
    "wof:placetype":"locality"
},
  "geometry": {"coordinates":[8.6895,14.8985],"type":"Point"}
}