{
  "type": "Feature",
  "properties": {
    "gn:admin1_code":"4.0",
    "gn:asciiname":"Awa Kansara",
    "gn:country_code":"NE",
    "gn:dem":327,
    "gn:feature_class":"P",
    "gn:feature_code":"PPL",
    "gn:name":"Awa Kansara",
    "gn:population":0,
    "gn:timezone":"Africa/Niamey",
    "iso:country":"NE",
    "wof:name":"Awa Kansara",
    "wof:placetype":"locality"
},
  "geometry": {"coordinates":[6.47649,13.65883],"type":"Point"}
}