{
  "type": "Feature",
  "properties": {
    "gn:admin1_code":"7.0",
    "gn:asciiname":"Telemida",
    "gn:country_code":"NE",
    "gn:dem":419,
    "gn:feature_class":"P",
    "gn:feature_code":"PPL",
    "gn:name":"T\u00e9l\u00e9mida",
    "gn:population":0,
    "gn:timezone":"Africa/Niamey",
    "iso:country":"NE",
    "wof:name":"Telemida",
    "wof:placetype":"locality"
},
  "geometry": {"coordinates":[9.9576,14.1244],"type":"Point"}
}