{
  "type": "Feature",
  "properties": {
    "gn:admin1_code":"7.0",
    "gn:asciiname":"Zangon Katourge",
    "gn:country_code":"NE",
    "gn:dem":407,
    "gn:feature_class":"P",
    "gn:feature_code":"PPL",
    "gn:name":"Zangon Katourge",
    "gn:population":0,
    "gn:timezone":"Africa/Niamey",
    "iso:country":"NE",
    "wof:name":"Zangon Katourge",
    "wof:placetype":"locality"
},
  "geometry": {"coordinates":[9.26,13.39],"type":"Point"}
}