{
  "type": "Feature",
  "properties": {
    "gn:admin1_code":"3.0",
    "gn:asciiname":"Tyenga Siminti",
    "gn:country_code":"NE",
    "gn:dem":194,
    "gn:feature_class":"P",
    "gn:feature_code":"PPL",
    "gn:name":"Ty\u00e8nga Siminti",
    "gn:population":0,
    "gn:timezone":"Africa/Niamey",
    "iso:country":"NE",
    "wof:name":"Tyenga Siminti",
    "wof:placetype":"locality"
},
  "geometry": {"coordinates":[2.9827,12.68435],"type":"Point"}
}