{
  "type": "Feature",
  "properties": {
    "gn:admin1_code":"9.0",
    "gn:asciiname":"Bangou Banda",
    "gn:country_code":"NE",
    "gn:dem":226,
    "gn:feature_class":"P",
    "gn:feature_code":"PPL",
    "gn:name":"Bangou Banda",
    "gn:population":0,
    "gn:timezone":"Africa/Niamey",
    "iso:country":"NE",
    "wof:name":"Bangou Banda",
    "wof:placetype":"locality"
},
  "geometry": {"coordinates":[2.60397,13.84832],"type":"Point"}
}