{
  "type": "Feature",
  "properties": {
    "gn:admin1_code":"2.0",
    "gn:asciiname":"Youwa",
    "gn:country_code":"NE",
    "gn:dem":303,
    "gn:feature_class":"P",
    "gn:feature_code":"PPL",
    "gn:name":"Youwa",
    "gn:population":0,
    "gn:timezone":"Africa/Niamey",
    "iso:country":"NE",
    "wof:name":"Youwa",
    "wof:placetype":"locality"
},
  "geometry": {"coordinates":[12.82317,13.46749],"type":"Point"}
}