{
  "type": "Feature",
  "properties": {
    "gn:admin1_code":"7.0",
    "gn:asciiname":"Reynadadi",
    "gn:country_code":"NE",
    "gn:dem":471,
    "gn:feature_class":"P",
    "gn:feature_code":"PPL",
    "gn:name":"Reynadadi",
    "gn:population":0,
    "gn:timezone":"Africa/Niamey",
    "iso:country":"NE",
    "wof:name":"Reynadadi",
    "wof:placetype":"locality"
},
  "geometry": {"coordinates":[8.58553,15.0631],"type":"Point"}
}