{
  "type": "Feature",
  "properties": {
    "gn:admin1_code":"7.0",
    "gn:asciiname":"Biri",
    "gn:country_code":"NE",
    "gn:dem":518,
    "gn:feature_class":"P",
    "gn:feature_code":"PPL",
    "gn:name":"Biri",
    "gn:population":0,
    "gn:timezone":"Africa/Niamey",
    "iso:country":"NE",
    "name:ceb_x_preferred":[
        "Biri"
    ],
    "name:ces_x_preferred":[
        "Biri"
    ],
    "name:deu_x_preferred":[
        "Biri"
    ],
    "name:fra_x_preferred":[
        "Biri"
    ],
    "name:hun_x_preferred":[
        "Biri"
    ],
    "name:ita_x_preferred":[
        "Biri"
    ],
    "name:swe_x_preferred":[
        "Biri"
    ],
    "name:tgl_x_preferred":[
        "Biri"
    ],
    "wof:name":"Biri",
    "wof:placetype":"locality"
},
  "geometry": {"coordinates":[8.5023,14.6571],"type":"Point"}
}