{
  "type": "Feature",
  "properties": {
    "gn:admin1_code":"9.0",
    "gn:asciiname":"Boubon",
    "gn:country_code":"NE",
    "gn:dem":195,
    "gn:feature_class":"P",
    "gn:feature_code":"PPL",
    "gn:name":"Boubon",
    "gn:population":0,
    "gn:timezone":"Africa/Niamey",
    "iso:country":"NE",
    "wof:name":"Boubon",
    "wof:placetype":"locality"
},
  "geometry": {"coordinates":[1.92731,13.60181],"type":"Point"}
}