{
  "type": "Feature",
  "properties": {
    "gn:admin1_code":"4.0",
    "gn:asciiname":"Dan Tchiako",
    "gn:country_code":"NE",
    "gn:dem":416,
    "gn:feature_class":"P",
    "gn:feature_code":"PPL",
    "gn:name":"Dan Tchiako",
    "gn:population":0,
    "gn:timezone":"Africa/Niamey",
    "iso:country":"NE",
    "name:und_x_variant":[
        "Dan Tchako",
        "Dan Tchiako"
    ],
    "wof:name":"Dan Tchiako",
    "wof:placetype":"locality"
},
  "geometry": {"coordinates":[6.97438,14.41311],"type":"Point"}
}