{
  "type": "Feature",
  "properties": {
    "gn:admin1_code":"6.0",
    "gn:asciiname":"Takoukout",
    "gn:country_code":"NE",
    "gn:dem":395,
    "gn:feature_class":"P",
    "gn:feature_code":"PPL",
    "gn:name":"Takoukout",
    "gn:population":0,
    "gn:timezone":"Africa/Niamey",
    "iso:country":"NE",
    "wof:name":"Takoukout",
    "wof:placetype":"locality"
},
  "geometry": {"coordinates":[5.3763,15.0459],"type":"Point"}
}