{
  "type": "Feature",
  "properties": {
    "gn:admin1_code":"2.0",
    "gn:asciiname":"Tanamiram",
    "gn:country_code":"NE",
    "gn:dem":347,
    "gn:feature_class":"P",
    "gn:feature_code":"PPL",
    "gn:name":"Tanamiram",
    "gn:population":0,
    "gn:timezone":"Africa/Niamey",
    "iso:country":"NE",
    "wof:name":"Tanamiram",
    "wof:placetype":"locality"
},
  "geometry": {"coordinates":[11.3671,13.8505],"type":"Point"}
}