{
  "type": "Feature",
  "properties": {
    "gn:admin1_code":"6.0",
    "gn:asciiname":"Farasaouna",
    "gn:country_code":"NE",
    "gn:dem":274,
    "gn:feature_class":"P",
    "gn:feature_code":"PPL",
    "gn:name":"Farasaouna",
    "gn:population":0,
    "gn:timezone":"Africa/Niamey",
    "iso:country":"NE",
    "name:und_x_variant":[
        "Farassaouna",
        "Farasaouna"
    ],
    "wof:name":"Farasaouna",
    "wof:placetype":"locality"
},
  "geometry": {"coordinates":[5.0717,13.75963],"type":"Point"}
}