{
  "type": "Feature",
  "properties": {
    "gn:admin1_code":"3.0",
    "gn:asciiname":"Batako",
    "gn:country_code":"NE",
    "gn:dem":255,
    "gn:feature_class":"P",
    "gn:feature_code":"PPL",
    "gn:name":"Batako",
    "gn:population":0,
    "gn:timezone":"Africa/Niamey",
    "iso:country":"NE",
    "wof:name":"Batako",
    "wof:placetype":"locality"
},
  "geometry": {"coordinates":[3.33333,13.48333],"type":"Point"}
}