{
  "type": "Feature",
  "properties": {
    "gn:admin1_code":"7.0",
    "gn:asciiname":"Ngaarbya",
    "gn:country_code":"NE",
    "gn:dem":423,
    "gn:feature_class":"P",
    "gn:feature_code":"PPL",
    "gn:name":"Ngaarbya",
    "gn:population":0,
    "gn:timezone":"Africa/Niamey",
    "iso:country":"NE",
    "wof:name":"Ngaarbya",
    "wof:placetype":"locality"
},
  "geometry": {"coordinates":[10.2143,13.78518],"type":"Point"}
}