{
  "type": "Feature",
  "properties": {
    "gn:admin1_code":"6.0",
    "gn:asciiname":"Allela II Peulh",
    "gn:country_code":"NE",
    "gn:dem":256,
    "gn:feature_class":"P",
    "gn:feature_code":"PPL",
    "gn:name":"Allela II Peulh",
    "gn:population":0,
    "gn:timezone":"Africa/Niamey",
    "iso:country":"NE",
    "wof:name":"Allela II Peulh",
    "wof:placetype":"locality"
},
  "geometry": {"coordinates":[4.82,13.92],"type":"Point"}
}