{
  "type": "Feature",
  "properties": {
    "gn:admin1_code":"9.0",
    "gn:asciiname":"Gorotye",
    "gn:country_code":"NE",
    "gn:dem":269,
    "gn:feature_class":"P",
    "gn:feature_code":"PPL",
    "gn:name":"Goroty\u00e9",
    "gn:population":0,
    "gn:timezone":"Africa/Niamey",
    "iso:country":"NE",
    "wof:name":"Gorotye",
    "wof:placetype":"locality"
},
  "geometry": {"coordinates":[2.7678,15.1563],"type":"Point"}
}