{
  "type": "Feature",
  "properties": {
    "gn:admin1_code":"3.0",
    "gn:asciiname":"Gounoubi Kouara",
    "gn:country_code":"NE",
    "gn:dem":192,
    "gn:feature_class":"P",
    "gn:feature_code":"PPL",
    "gn:name":"Gounoubi Kouara",
    "gn:population":0,
    "gn:timezone":"Africa/Niamey",
    "iso:country":"NE",
    "name:und_x_variant":[
        "Gounoubi",
        "Gounoubi Kouara"
    ],
    "wof:name":"Gounoubi Kouara",
    "wof:placetype":"locality"
},
  "geometry": {"coordinates":[2.9126,13.3237],"type":"Point"}
}