{
  "type": "Feature",
  "properties": {
    "gn:admin1_code":"4.0",
    "gn:asciiname":"Maylawa",
    "gn:country_code":"NE",
    "gn:dem":419,
    "gn:feature_class":"P",
    "gn:feature_code":"PPL",
    "gn:name":"Maylawa",
    "gn:population":0,
    "gn:timezone":"Africa/Niamey",
    "iso:country":"NE",
    "wof:name":"Maylawa",
    "wof:placetype":"locality"
},
  "geometry": {"coordinates":[7.06119,14.43187],"type":"Point"}
}