{
  "type": "Feature",
  "properties": {
    "gn:admin1_code":"9.0",
    "gn:asciiname":"Sabargorou",
    "gn:country_code":"NE",
    "gn:dem":277,
    "gn:feature_class":"P",
    "gn:feature_code":"PPL",
    "gn:name":"Sabargorou",
    "gn:population":0,
    "gn:timezone":"Africa/Niamey",
    "iso:country":"NE",
    "wof:name":"Sabargorou",
    "wof:placetype":"locality"
},
  "geometry": {"coordinates":[2.36845,14.27873],"type":"Point"}
}