{
  "type": "Feature",
  "properties": {
    "gn:admin1_code":"4.0",
    "gn:asciiname":"Guidan Bassou",
    "gn:country_code":"NE",
    "gn:dem":439,
    "gn:feature_class":"P",
    "gn:feature_code":"PPL",
    "gn:name":"Guidan Bassou",
    "gn:population":0,
    "gn:timezone":"Africa/Niamey",
    "iso:country":"NE",
    "name:und_x_variant":[
        "Gidan Basou",
        "Guidan Bassou"
    ],
    "wof:name":"Guidan Bassou",
    "wof:placetype":"locality"
},
  "geometry": {"coordinates":[7.42814,13.32416],"type":"Point"}
}