{
  "type": "Feature",
  "properties": {
    "gn:admin1_code":"1.0",
    "gn:asciiname":"Sidaouet",
    "gn:cc2":"NE",
    "gn:country_code":"NE",
    "gn:dem":584,
    "gn:feature_class":"P",
    "gn:feature_code":"PPL",
    "gn:name":"Sidaouet",
    "gn:population":0,
    "gn:timezone":"Africa/Niamey",
    "iso:country":"NE",
    "name:und_x_variant":[
        "Sidawet",
        "Sidaouet"
    ],
    "wof:name":"Sidaouet",
    "wof:placetype":"locality"
},
  "geometry": {"coordinates":[8.08556,18.51833],"type":"Point"}
}