{
  "type": "Feature",
  "properties": {
    "gn:admin1_code":"7.0",
    "gn:asciiname":"Gamouga",
    "gn:country_code":"NE",
    "gn:dem":435,
    "gn:feature_class":"P",
    "gn:feature_code":"PPL",
    "gn:name":"Gamouga",
    "gn:population":0,
    "gn:timezone":"Africa/Niamey",
    "iso:country":"NE",
    "wof:name":"Gamouga",
    "wof:placetype":"locality"
},
  "geometry": {"coordinates":[9.5178,14.023],"type":"Point"}
}