{
  "type": "Feature",
  "properties": {
    "gn:admin1_code":"6.0",
    "gn:asciiname":"Zouragan",
    "gn:country_code":"NE",
    "gn:dem":309,
    "gn:feature_class":"P",
    "gn:feature_code":"PPL",
    "gn:name":"Zouragan",
    "gn:population":0,
    "gn:timezone":"Africa/Niamey",
    "iso:country":"NE",
    "wof:name":"Zouragan",
    "wof:placetype":"locality"
},
  "geometry": {"coordinates":[5.1837,14.503],"type":"Point"}
}