{
  "type": "Feature",
  "properties": {
    "gn:admin1_code":"7.0",
    "gn:asciiname":"Birjin Zaoure",
    "gn:country_code":"NE",
    "gn:dem":487,
    "gn:feature_class":"P",
    "gn:feature_code":"PPL",
    "gn:name":"Birj\u00een Zaour\u00e9",
    "gn:population":0,
    "gn:timezone":"Africa/Niamey",
    "iso:country":"NE",
    "wof:name":"Birjin Zaoure",
    "wof:placetype":"locality"
},
  "geometry": {"coordinates":[8.5026,13.24977],"type":"Point"}
}