{
  "type": "Feature",
  "properties": {
    "gn:admin1_code":"2.0",
    "gn:asciiname":"Miskindi",
    "gn:country_code":"NE",
    "gn:dem":359,
    "gn:feature_class":"P",
    "gn:feature_code":"PPL",
    "gn:name":"Miskindi",
    "gn:population":0,
    "gn:timezone":"Africa/Niamey",
    "iso:country":"NE",
    "wof:name":"Miskindi",
    "wof:placetype":"locality"
},
  "geometry": {"coordinates":[10.84413,13.46735],"type":"Point"}
}