{
  "type": "Feature",
  "properties": {
    "gn:admin1_code":"6.0",
    "gn:asciiname":"Maymourafou",
    "gn:country_code":"NE",
    "gn:dem":301,
    "gn:feature_class":"P",
    "gn:feature_code":"PPL",
    "gn:name":"Maymourafou",
    "gn:population":0,
    "gn:timezone":"Africa/Niamey",
    "iso:country":"NE",
    "wof:name":"Maymourafou",
    "wof:placetype":"locality"
},
  "geometry": {"coordinates":[4.30204,14.76525],"type":"Point"}
}