{
  "type": "Feature",
  "properties": {
    "gn:admin1_code":"9.0",
    "gn:asciiname":"Gabo Baba Kouara",
    "gn:country_code":"NE",
    "gn:dem":244,
    "gn:feature_class":"P",
    "gn:feature_code":"PPL",
    "gn:name":"Gabo Baba Kouara",
    "gn:population":0,
    "gn:timezone":"Africa/Niamey",
    "iso:country":"NE",
    "name:und_x_variant":[
        "Nazey-Gadobabo-Koara",
        "Nazey Gadobado Kwara",
        "Gabo Baba Kouara"
    ],
    "wof:name":"Gabo Baba Kouara",
    "wof:placetype":"locality"
},
  "geometry": {"coordinates":[2.5491,13.833],"type":"Point"}
}