{
  "type": "Feature",
  "properties": {
    "gn:admin1_code":"9.0",
    "gn:asciiname":"Hayni Simorou",
    "gn:country_code":"NE",
    "gn:dem":231,
    "gn:feature_class":"P",
    "gn:feature_code":"PPL",
    "gn:name":"Hayni Simorou",
    "gn:population":0,
    "gn:timezone":"Africa/Niamey",
    "iso:country":"NE",
    "name:und_x_variant":[
        "A\u00efnsimourou",
        "Hayni Simorou"
    ],
    "wof:name":"Hayni Simorou",
    "wof:placetype":"locality"
},
  "geometry": {"coordinates":[2.8056,13.983],"type":"Point"}
}