{
  "type": "Feature",
  "properties": {
    "gn:admin1_code":"7.0",
    "gn:asciiname":"Changi",
    "gn:country_code":"NE",
    "gn:dem":471,
    "gn:feature_class":"P",
    "gn:feature_code":"PPL",
    "gn:name":"Changi",
    "gn:population":0,
    "gn:timezone":"Africa/Niamey",
    "iso:country":"NE",
    "name:ast_x_preferred":[
        "Changi"
    ],
    "name:bul_x_preferred":[
        "\u0427\u0430\u043d\u0433\u0438"
    ],
    "name:fas_x_preferred":[
        "\u0686\u0627\u0646\u06af\u06cc"
    ],
    "name:fin_x_preferred":[
        "Changi"
    ],
    "name:ind_x_preferred":[
        "Changi"
    ],
    "name:jpn_x_preferred":[
        "\u30c1\u30e3\u30f3\u30ae"
    ],
    "name:mar_x_preferred":[
        "\u091a\u093e\u0902\u0917\u0940"
    ],
    "name:msa_x_preferred":[
        "Changi"
    ],
    "name:nld_x_preferred":[
        "Changi"
    ],
    "name:nor_x_preferred":[
        "Changi"
    ],
    "name:pol_x_preferred":[
        "Changi"
    ],
    "name:spa_x_preferred":[
        "Changi"
    ],
    "name:swe_x_preferred":[
        "Changi"
    ],
    "name:tam_x_preferred":[
        "\u0b9a\u0bbe\u0b99\u0bcd\u0b95\u0bbf"
    ],
    "name:und_x_variant":[
        "Changui",
        "Changi"
    ],
    "name:urd_x_preferred":[
        "\u0686\u0627\u0646\u06af\u06cc"
    ],
    "wof:name":"Changi",
    "wof:placetype":"locality"
},
  "geometry": {"coordinates":[8.94001,14.18561],"type":"Point"}
}