{
  "type": "Feature",
  "properties": {
    "gn:admin1_code":"9.0",
    "gn:asciiname":"Tiota",
    "gn:country_code":"NE",
    "gn:dem":234,
    "gn:feature_class":"P",
    "gn:feature_code":"PPL",
    "gn:name":"Tiota",
    "gn:population":0,
    "gn:timezone":"Africa/Niamey",
    "iso:country":"NE",
    "name:und_x_variant":[
        "Tyota",
        "Tiota"
    ],
    "wof:name":"Tiota",
    "wof:placetype":"locality"
},
  "geometry": {"coordinates":[1.42395,13.06496],"type":"Point"}
}