{
  "type": "Feature",
  "properties": {
    "gn:admin1_code":"7.0",
    "gn:asciiname":"Nguel",
    "gn:country_code":"NE",
    "gn:dem":421,
    "gn:feature_class":"P",
    "gn:feature_code":"PPL",
    "gn:name":"Ngu\u00e8l",
    "gn:population":0,
    "gn:timezone":"Africa/Niamey",
    "iso:country":"NE",
    "wof:name":"Nguel",
    "wof:placetype":"locality"
},
  "geometry": {"coordinates":[9.5829,14.0179],"type":"Point"}
}