{
  "type": "Feature",
  "properties": {
    "gn:admin1_code":"4.0",
    "gn:asciiname":"Tabkin Gao",
    "gn:country_code":"NE",
    "gn:dem":440,
    "gn:feature_class":"P",
    "gn:feature_code":"PPL",
    "gn:name":"Tabkin Gao",
    "gn:population":0,
    "gn:timezone":"Africa/Niamey",
    "iso:country":"NE",
    "wof:name":"Tabkin Gao",
    "wof:placetype":"locality"
},
  "geometry": {"coordinates":[7.87039,13.38152],"type":"Point"}
}