{
  "type": "Feature",
  "properties": {
    "gn:admin1_code":"3.0",
    "gn:asciiname":"Katababa-Koara",
    "gn:country_code":"NE",
    "gn:dem":208,
    "gn:feature_class":"P",
    "gn:feature_code":"PPL",
    "gn:name":"Katababa-Koara",
    "gn:population":0,
    "gn:timezone":"Africa/Niamey",
    "iso:country":"NE",
    "name:und_x_variant":[
        "Katababa Kwara",
        "Katababa-Koara"
    ],
    "wof:name":"Katababa-Koara",
    "wof:placetype":"locality"
},
  "geometry": {"coordinates":[3.461,13.0427],"type":"Point"}
}