{
  "type": "Feature",
  "properties": {
    "gn:admin1_code":"2.0",
    "gn:asciiname":"Kogouri",
    "gn:country_code":"NE",
    "gn:dem":318,
    "gn:feature_class":"P",
    "gn:feature_code":"PPL",
    "gn:name":"Kogouri",
    "gn:population":0,
    "gn:timezone":"Africa/Niamey",
    "iso:country":"NE",
    "wof:name":"Kogouri",
    "wof:placetype":"locality"
},
  "geometry": {"coordinates":[12.29385,13.21677],"type":"Point"}
}