{
  "type": "Feature",
  "properties": {
    "gn:admin1_code":"7.0",
    "gn:asciiname":"Kadi Dan Salifou",
    "gn:country_code":"NE",
    "gn:dem":389,
    "gn:feature_class":"P",
    "gn:feature_code":"PPL",
    "gn:name":"Kadi Dan Salifou",
    "gn:population":0,
    "gn:timezone":"Africa/Niamey",
    "iso:country":"NE",
    "wof:name":"Kadi Dan Salifou",
    "wof:placetype":"locality"
},
  "geometry": {"coordinates":[9.1411,13.4158],"type":"Point"}
}