{
  "type": "Feature",
  "properties": {
    "gn:admin1_code":"7.0",
    "gn:asciiname":"Kekeni",
    "gn:country_code":"NE",
    "gn:dem":463,
    "gn:feature_class":"P",
    "gn:feature_code":"PPL",
    "gn:name":"K\u00e9k\u00e9ni",
    "gn:population":0,
    "gn:timezone":"Africa/Niamey",
    "iso:country":"NE",
    "wof:name":"Kekeni",
    "wof:placetype":"locality"
},
  "geometry": {"coordinates":[8.4064,14.91111],"type":"Point"}
}