{
  "type": "Feature",
  "properties": {
    "gn:admin1_code":"4.0",
    "gn:asciiname":"Djiratawa",
    "gn:country_code":"NE",
    "gn:dem":357,
    "gn:feature_class":"P",
    "gn:feature_code":"PPL",
    "gn:name":"Djiratawa",
    "gn:population":0,
    "gn:timezone":"Africa/Niamey",
    "iso:country":"NE",
    "name:deu_x_preferred":[
        "Djiratawa"
    ],
    "name:ita_x_preferred":[
        "Djiratawa"
    ],
    "name:msa_x_preferred":[
        "Djiratawa"
    ],
    "name:ron_x_preferred":[
        "Djiratawa"
    ],
    "name:spa_x_preferred":[
        "Djiratawa"
    ],
    "name:und_x_variant":[
        "Djirataoua",
        "Djiratawa"
    ],
    "wof:name":"Djiratawa",
    "wof:placetype":"locality"
},
  "geometry": {"coordinates":[7.13887,13.40717],"type":"Point"}
}