{
  "type": "Feature",
  "properties": {
    "gn:admin1_code":"9.0",
    "gn:asciiname":"Adamou Kouara",
    "gn:country_code":"NE",
    "gn:dem":226,
    "gn:feature_class":"P",
    "gn:feature_code":"PPL",
    "gn:name":"Adamou Kouara",
    "gn:population":0,
    "gn:timezone":"Africa/Niamey",
    "iso:country":"NE",
    "wof:name":"Adamou Kouara",
    "wof:placetype":"locality"
},
  "geometry": {"coordinates":[2.4737,13.3146],"type":"Point"}
}