{
  "type": "Feature",
  "properties": {
    "gn:admin1_code":"2.0",
    "gn:asciiname":"Goursoungoumiram",
    "gn:country_code":"NE",
    "gn:dem":324,
    "gn:feature_class":"P",
    "gn:feature_code":"PPL",
    "gn:name":"Goursoungoumiram",
    "gn:population":0,
    "gn:timezone":"Africa/Niamey",
    "iso:country":"NE",
    "wof:name":"Goursoungoumiram",
    "wof:placetype":"locality"
},
  "geometry": {"coordinates":[12.08023,13.16122],"type":"Point"}
}