{
  "type": "Feature",
  "properties": {
    "gn:admin1_code":"3.0",
    "gn:asciiname":"Sabou-Koara",
    "gn:country_code":"NE",
    "gn:dem":226,
    "gn:feature_class":"P",
    "gn:feature_code":"PPL",
    "gn:name":"Sabou-Koara",
    "gn:population":0,
    "gn:timezone":"Africa/Niamey",
    "iso:country":"NE",
    "name:und_x_variant":[
        "Sabou Kwara",
        "Sabou-Koara"
    ],
    "wof:name":"Sabou-Koara",
    "wof:placetype":"locality"
},
  "geometry": {"coordinates":[3.6822,13.232],"type":"Point"}
}