{
  "type": "Feature",
  "properties": {
    "gn:admin1_code":"6.0",
    "gn:asciiname":"Katangorya",
    "gn:country_code":"NE",
    "gn:dem":300,
    "gn:feature_class":"P",
    "gn:feature_code":"PPL",
    "gn:name":"Katangorya",
    "gn:population":0,
    "gn:timezone":"Africa/Niamey",
    "iso:country":"NE",
    "wof:name":"Katangorya",
    "wof:placetype":"locality"
},
  "geometry": {"coordinates":[5.1578,14.44],"type":"Point"}
}