{
  "type": "Feature",
  "properties": {
    "gn:admin1_code":"9.0",
    "gn:asciiname":"Gassikeyna",
    "gn:country_code":"NE",
    "gn:dem":208,
    "gn:feature_class":"P",
    "gn:feature_code":"PPL",
    "gn:name":"Gassikeyna",
    "gn:population":0,
    "gn:timezone":"Africa/Niamey",
    "iso:country":"NE",
    "name:und_x_variant":[
        "Gassik\u00e9na"
    ],
    "wof:name":"Gassikeyna",
    "wof:placetype":"locality"
},
  "geometry": {"coordinates":[1.5642,14.01446],"type":"Point"}
}