{
  "type": "Feature",
  "properties": {
    "gn:admin1_code":"4.0",
    "gn:asciiname":"Meydi",
    "gn:country_code":"NE",
    "gn:dem":356,
    "gn:feature_class":"P",
    "gn:feature_code":"PPL",
    "gn:name":"Meydi",
    "gn:population":0,
    "gn:timezone":"Africa/Niamey",
    "iso:country":"NE",
    "wof:name":"Meydi",
    "wof:placetype":"locality"
},
  "geometry": {"coordinates":[6.86886,13.56402],"type":"Point"}
}