{
  "type": "Feature",
  "properties": {
    "gn:admin1_code":"9.0",
    "gn:asciiname":"Wari",
    "gn:country_code":"NE",
    "gn:dem":214,
    "gn:feature_class":"P",
    "gn:feature_code":"PPL",
    "gn:name":"Wari",
    "gn:population":0,
    "gn:timezone":"Africa/Niamey",
    "iso:country":"NE",
    "name:ceb_x_preferred":[
        "Wari"
    ],
    "name:deu_x_preferred":[
        "Wari"
    ],
    "name:fra_x_preferred":[
        "Wari"
    ],
    "name:jpn_x_preferred":[
        "\u30ef\u30ea"
    ],
    "name:mkd_x_preferred":[
        "\u0412\u0430\u0440\u0438"
    ],
    "name:pol_x_preferred":[
        "Wari"
    ],
    "name:rus_x_preferred":[
        "\u0412\u0430\u0440\u0438"
    ],
    "name:spa_x_preferred":[
        "Wari"
    ],
    "name:swe_x_preferred":[
        "Wari"
    ],
    "wof:name":"Wari",
    "wof:placetype":"locality"
},
  "geometry": {"coordinates":[2.24578,13.61925],"type":"Point"}
}