{
  "type": "Feature",
  "properties": {
    "gn:admin1_code":"9.0",
    "gn:asciiname":"Chinagodrar",
    "gn:country_code":"NE",
    "gn:dem":269,
    "gn:feature_class":"P",
    "gn:feature_code":"PPL",
    "gn:name":"Chinagodrar",
    "gn:population":0,
    "gn:timezone":"Africa/Niamey",
    "iso:country":"NE",
    "wof:name":"Chinagodrar",
    "wof:placetype":"locality"
},
  "geometry": {"coordinates":[3.0014,15.2276],"type":"Point"}
}