{
  "type": "Feature",
  "properties": {
    "gn:admin1_code":"4.0",
    "gn:asciiname":"Alhazey",
    "gn:country_code":"NE",
    "gn:dem":349,
    "gn:feature_class":"P",
    "gn:feature_code":"PPL",
    "gn:name":"Alhazey",
    "gn:population":0,
    "gn:timezone":"Africa/Niamey",
    "iso:country":"NE",
    "wof:name":"Alhazey",
    "wof:placetype":"locality"
},
  "geometry": {"coordinates":[7.06531,13.95565],"type":"Point"}
}