{
  "type": "Feature",
  "properties": {
    "gn:admin1_code":"4.0",
    "gn:asciiname":"Dan Ahi",
    "gn:country_code":"NE",
    "gn:dem":457,
    "gn:feature_class":"P",
    "gn:feature_code":"PPL",
    "gn:name":"Dan Ahi",
    "gn:population":0,
    "gn:timezone":"Africa/Niamey",
    "iso:country":"NE",
    "wof:name":"Dan Ahi",
    "wof:placetype":"locality"
},
  "geometry": {"coordinates":[8.21256,14.33439],"type":"Point"}
}