{
  "type": "Feature",
  "properties": {
    "gn:admin1_code":"6.0",
    "gn:asciiname":"Edir",
    "gn:country_code":"NE",
    "gn:dem":329,
    "gn:feature_class":"P",
    "gn:feature_code":"PPL",
    "gn:name":"Edir",
    "gn:population":0,
    "gn:timezone":"Africa/Niamey",
    "iso:country":"NE",
    "wof:name":"Edir",
    "wof:placetype":"locality"
},
  "geometry": {"coordinates":[4.77794,14.81238],"type":"Point"}
}