{
  "type": "Feature",
  "properties": {
    "gn:admin1_code":"4.0",
    "gn:asciiname":"Tchololoua",
    "gn:country_code":"NE",
    "gn:dem":410,
    "gn:feature_class":"P",
    "gn:feature_code":"PPL",
    "gn:name":"Tchololoua",
    "gn:population":0,
    "gn:timezone":"Africa/Niamey",
    "iso:country":"NE",
    "name:und_x_variant":[
        "Tchololoy",
        "Tchololoua"
    ],
    "wof:name":"Tchololoua",
    "wof:placetype":"locality"
},
  "geometry": {"coordinates":[7.43854,13.79343],"type":"Point"}
}