{
  "type": "Feature",
  "properties": {
    "gn:admin1_code":"3.0",
    "gn:asciiname":"Alfaize-Koara",
    "gn:country_code":"NE",
    "gn:dem":227,
    "gn:feature_class":"P",
    "gn:feature_code":"PPL",
    "gn:name":"Alfa\u00efz\u00e9-Koara",
    "gn:population":0,
    "gn:timezone":"Africa/Niamey",
    "iso:country":"NE",
    "name:und_x_variant":[
        "Alfa\u00efz\u00e9 Kwara",
        "Alfa\u00efz\u00e9-Koara"
    ],
    "wof:name":"Alfaize-Koara",
    "wof:placetype":"locality"
},
  "geometry": {"coordinates":[3.643,13.1619],"type":"Point"}
}