{
  "type": "Feature",
  "properties": {
    "gn:admin1_code":"4.0",
    "gn:asciiname":"Guidan Sami",
    "gn:country_code":"NE",
    "gn:dem":322,
    "gn:feature_class":"P",
    "gn:feature_code":"PPL",
    "gn:name":"Guidan Sami",
    "gn:population":0,
    "gn:timezone":"Africa/Niamey",
    "iso:country":"NE",
    "wof:name":"Guidan Sami",
    "wof:placetype":"locality"
},
  "geometry": {"coordinates":[6.66114,13.65302],"type":"Point"}
}