{
  "type": "Feature",
  "properties": {
    "gn:admin1_code":"9.0",
    "gn:asciiname":"Aray",
    "gn:country_code":"NE",
    "gn:dem":268,
    "gn:feature_class":"P",
    "gn:feature_code":"PPL",
    "gn:name":"Aray",
    "gn:population":0,
    "gn:timezone":"Africa/Niamey",
    "iso:country":"NE",
    "name:rus_x_preferred":[
        "\u0410\u0440\u0430\u0439"
    ],
    "wof:name":"Aray",
    "wof:placetype":"locality"
},
  "geometry": {"coordinates":[3.9442,15.057],"type":"Point"}
}