{
  "type": "Feature",
  "properties": {
    "gn:admin1_code":"3.0",
    "gn:asciiname":"Dounme",
    "gn:country_code":"NE",
    "gn:dem":291,
    "gn:feature_class":"P",
    "gn:feature_code":"PPL",
    "gn:name":"Dounm\u00e9",
    "gn:population":0,
    "gn:timezone":"Africa/Niamey",
    "iso:country":"NE",
    "wof:name":"Dounme",
    "wof:placetype":"locality"
},
  "geometry": {"coordinates":[4.13457,14.00915],"type":"Point"}
}