{
  "type": "Feature",
  "properties": {
    "gn:admin1_code":"2.0",
    "gn:asciiname":"Tamsougoua",
    "gn:country_code":"NE",
    "gn:dem":319,
    "gn:feature_class":"P",
    "gn:feature_code":"PPL",
    "gn:name":"Tamsougoua",
    "gn:population":0,
    "gn:timezone":"Africa/Niamey",
    "iso:country":"NE",
    "wof:name":"Tamsougoua",
    "wof:placetype":"locality"
},
  "geometry": {"coordinates":[12.28539,13.51862],"type":"Point"}
}