{
  "type": "Feature",
  "properties": {
    "gn:admin1_code":"4.0",
    "gn:asciiname":"Zango Baghe",
    "gn:country_code":"NE",
    "gn:dem":327,
    "gn:feature_class":"P",
    "gn:feature_code":"PPL",
    "gn:name":"Zango Bagh\u00e9",
    "gn:population":0,
    "gn:timezone":"Africa/Niamey",
    "iso:country":"NE",
    "name:und_x_variant":[
        "Zango Barh\u00e9",
        "Zango Bagh\u00e9"
    ],
    "wof:name":"Zango Baghe",
    "wof:placetype":"locality"
},
  "geometry": {"coordinates":[6.35868,13.71332],"type":"Point"}
}