{
  "type": "Feature",
  "properties": {
    "gn:admin1_code":"4.0",
    "gn:asciiname":"Gada Serkin Bak'a",
    "gn:country_code":"NE",
    "gn:dem":463,
    "gn:feature_class":"P",
    "gn:feature_code":"PPL",
    "gn:name":"Gada Serkin Bak'a",
    "gn:population":0,
    "gn:timezone":"Africa/Niamey",
    "iso:country":"NE",
    "wof:name":"Gada Serkin Bak'a",
    "wof:placetype":"locality"
},
  "geometry": {"coordinates":[8.20923,13.50784],"type":"Point"}
}