{
  "type": "Feature",
  "properties": {
    "gn:admin1_code":"6.0",
    "gn:asciiname":"Roumbouki",
    "gn:country_code":"NE",
    "gn:dem":309,
    "gn:feature_class":"P",
    "gn:feature_code":"PPL",
    "gn:name":"Roumbouki",
    "gn:population":0,
    "gn:timezone":"Africa/Niamey",
    "iso:country":"NE",
    "wof:name":"Roumbouki",
    "wof:placetype":"locality"
},
  "geometry": {"coordinates":[5.3618,14.0611],"type":"Point"}
}