{
  "type": "Feature",
  "properties": {
    "gn:admin1_code":"9.0",
    "gn:asciiname":"Finfetou",
    "gn:country_code":"NE",
    "gn:dem":221,
    "gn:feature_class":"P",
    "gn:feature_code":"PPL",
    "gn:name":"Finf\u00e9tou",
    "gn:population":0,
    "gn:timezone":"Africa/Niamey",
    "iso:country":"NE",
    "name:und_x_variant":[
        "Fenf\u00e9tou",
        "Finf\u00e9tou"
    ],
    "wof:name":"Finfetou",
    "wof:placetype":"locality"
},
  "geometry": {"coordinates":[1.84281,13.27429],"type":"Point"}
}