{
  "type": "Feature",
  "properties": {
    "gn:admin1_code":"9.0",
    "gn:asciiname":"Koure",
    "gn:country_code":"NE",
    "gn:dem":231,
    "gn:feature_class":"P",
    "gn:feature_code":"PPL",
    "gn:name":"Kour\u00e9",
    "gn:population":0,
    "gn:timezone":"Africa/Niamey",
    "iso:country":"NE",
    "name:und_x_variant":[
        "Kure",
        "Kour",
        "Kour\u00e9"
    ],
    "wof:name":"Koure",
    "wof:placetype":"locality"
},
  "geometry": {"coordinates":[2.576,13.3106],"type":"Point"}
}