{
  "type": "Feature",
  "properties": {
    "gn:admin1_code":"4.0",
    "gn:asciiname":"Ba-rana",
    "gn:country_code":"NE",
    "gn:dem":408,
    "gn:feature_class":"P",
    "gn:feature_code":"PPL",
    "gn:name":"B\u00e2-r\u00e2n\u00e2",
    "gn:population":0,
    "gn:timezone":"Africa/Niamey",
    "iso:country":"NE",
    "wof:name":"Ba-rana",
    "wof:placetype":"locality"
},
  "geometry": {"coordinates":[7.9888,13.48561],"type":"Point"}
}