{
  "type": "Feature",
  "properties": {
    "gn:admin1_code":"9.0",
    "gn:asciiname":"Dinagha",
    "gn:country_code":"NE",
    "gn:dem":289,
    "gn:feature_class":"P",
    "gn:feature_code":"PPL",
    "gn:name":"Dinagha",
    "gn:population":0,
    "gn:timezone":"Africa/Niamey",
    "iso:country":"NE",
    "name:und_x_variant":[
        "Dinarha",
        "Dinagha"
    ],
    "wof:name":"Dinagha",
    "wof:placetype":"locality"
},
  "geometry": {"coordinates":[1.9691,15.2188],"type":"Point"}
}