{
  "type": "Feature",
  "properties": {
    "gn:admin1_code":"3.0",
    "gn:asciiname":"Madawaki",
    "gn:country_code":"NE",
    "gn:dem":187,
    "gn:feature_class":"P",
    "gn:feature_code":"PPL",
    "gn:name":"Madawaki",
    "gn:population":0,
    "gn:timezone":"Africa/Niamey",
    "iso:country":"NE",
    "wof:name":"Madawaki",
    "wof:placetype":"locality"
},
  "geometry": {"coordinates":[3.58852,12.63242],"type":"Point"}
}