{
  "type": "Feature",
  "properties": {
    "gn:admin1_code":"4.0",
    "gn:asciiname":"Guidan Dan Maygari",
    "gn:country_code":"NE",
    "gn:dem":374,
    "gn:feature_class":"P",
    "gn:feature_code":"PPL",
    "gn:name":"Guidan Dan Maygari",
    "gn:population":0,
    "gn:timezone":"Africa/Niamey",
    "iso:country":"NE",
    "wof:name":"Guidan Dan Maygari",
    "wof:placetype":"locality"
},
  "geometry": {"coordinates":[6.60966,14.16062],"type":"Point"}
}