{
  "type": "Feature",
  "properties": {
    "gn:admin1_code":"4.0",
    "gn:asciiname":"Maski",
    "gn:country_code":"NE",
    "gn:dem":418,
    "gn:feature_class":"P",
    "gn:feature_code":"PPL",
    "gn:name":"Maski",
    "gn:population":0,
    "gn:timezone":"Africa/Niamey",
    "iso:country":"NE",
    "name:ceb_x_preferred":[
        "Maski"
    ],
    "name:hin_x_preferred":[
        "\u092e\u0938\u094d\u0915\u0940"
    ],
    "name:kan_x_preferred":[
        "\u0cae\u0cb8\u0ccd\u0c95\u0cbf"
    ],
    "name:nor_x_preferred":[
        "Maski"
    ],
    "name:spa_x_preferred":[
        "Maski"
    ],
    "name:swe_x_preferred":[
        "Maski"
    ],
    "wof:name":"Maski",
    "wof:placetype":"locality"
},
  "geometry": {"coordinates":[7.26823,14.38535],"type":"Point"}
}