{
  "type": "Feature",
  "properties": {
    "gn:admin1_code":"4.0",
    "gn:asciiname":"Yachin Gila",
    "gn:country_code":"NE",
    "gn:dem":441,
    "gn:feature_class":"P",
    "gn:feature_code":"PPL",
    "gn:name":"Yachin Gila",
    "gn:population":0,
    "gn:timezone":"Africa/Niamey",
    "iso:country":"NE",
    "name:und_x_variant":[
        "Yachin Guila",
        "Yachin Gila"
    ],
    "wof:name":"Yachin Gila",
    "wof:placetype":"locality"
},
  "geometry": {"coordinates":[8.2952,14.1301],"type":"Point"}
}