{
  "type": "Feature",
  "properties": {
    "gn:admin1_code":"4.0",
    "gn:asciiname":"Chipkao",
    "gn:country_code":"NE",
    "gn:dem":410,
    "gn:feature_class":"P",
    "gn:feature_code":"PPL",
    "gn:name":"Chipkao",
    "gn:population":0,
    "gn:timezone":"Africa/Niamey",
    "iso:country":"NE",
    "wof:name":"Chipkao",
    "wof:placetype":"locality"
},
  "geometry": {"coordinates":[6.77956,14.52648],"type":"Point"}
}