{
  "type": "Feature",
  "properties": {
    "gn:admin1_code":"7.0",
    "gn:asciiname":"Brandi",
    "gn:country_code":"NE",
    "gn:dem":426,
    "gn:feature_class":"P",
    "gn:feature_code":"PPL",
    "gn:name":"Brandi",
    "gn:population":0,
    "gn:timezone":"Africa/Niamey",
    "iso:country":"NE",
    "wof:name":"Brandi",
    "wof:placetype":"locality"
},
  "geometry": {"coordinates":[9.7217,14.1328],"type":"Point"}
}