{
  "type": "Feature",
  "properties": {
    "gn:admin1_code":"3.0",
    "gn:asciiname":"Daniare",
    "gn:country_code":"NE",
    "gn:dem":207,
    "gn:feature_class":"P",
    "gn:feature_code":"PPL",
    "gn:name":"Daniar\u00e9",
    "gn:population":0,
    "gn:timezone":"Africa/Niamey",
    "iso:country":"NE",
    "name:und_x_variant":[
        "Niakar\u00e9",
        "Daniar\u00e9"
    ],
    "wof:name":"Daniare",
    "wof:placetype":"locality"
},
  "geometry": {"coordinates":[2.8377,13.2432],"type":"Point"}
}