{
  "type": "Feature",
  "properties": {
    "gn:admin1_code":"6.0",
    "gn:asciiname":"Edikin Ibrina",
    "gn:country_code":"NE",
    "gn:dem":410,
    "gn:feature_class":"P",
    "gn:feature_code":"PPL",
    "gn:name":"Edikin Ibrina",
    "gn:population":0,
    "gn:timezone":"Africa/Niamey",
    "iso:country":"NE",
    "wof:name":"Edikin Ibrina",
    "wof:placetype":"locality"
},
  "geometry": {"coordinates":[5.6657,14.7378],"type":"Point"}
}