{
  "type": "Feature",
  "properties": {
    "gn:admin1_code":"9.0",
    "gn:asciiname":"Tiandadji",
    "gn:country_code":"NE",
    "gn:dem":205,
    "gn:feature_class":"P",
    "gn:feature_code":"PPL",
    "gn:name":"Tiandadji",
    "gn:population":0,
    "gn:timezone":"Africa/Niamey",
    "iso:country":"NE",
    "name:und_x_variant":[
        "Tilagadji"
    ],
    "wof:name":"Tiandadji",
    "wof:placetype":"locality"
},
  "geometry": {"coordinates":[1.40578,14.22885],"type":"Point"}
}