{
  "type": "Feature",
  "properties": {
    "gn:admin1_code":"9.0",
    "gn:asciiname":"Girbiye",
    "gn:country_code":"NE",
    "gn:dem":240,
    "gn:feature_class":"P",
    "gn:feature_code":"PPL",
    "gn:name":"Girbiy\u00e9",
    "gn:population":0,
    "gn:timezone":"Africa/Niamey",
    "iso:country":"NE",
    "name:und_x_variant":[
        "Gu\u00edrbiy\u00e9",
        "Girbiy\u00e9"
    ],
    "wof:name":"Girbiye",
    "wof:placetype":"locality"
},
  "geometry": {"coordinates":[2.55335,14.01295],"type":"Point"}
}