{
  "type": "Feature",
  "properties": {
    "gn:admin1_code":"3.0",
    "gn:asciiname":"Mazar Kola",
    "gn:country_code":"NE",
    "gn:dem":224,
    "gn:feature_class":"P",
    "gn:feature_code":"PPL",
    "gn:name":"Mazar Kola",
    "gn:population":0,
    "gn:timezone":"Africa/Niamey",
    "iso:country":"NE",
    "wof:name":"Mazar Kola",
    "wof:placetype":"locality"
},
  "geometry": {"coordinates":[4.0269,13.80618],"type":"Point"}
}