{
  "type": "Feature",
  "properties": {
    "gn:admin1_code":"9.0",
    "gn:asciiname":"Bossa",
    "gn:country_code":"NE",
    "gn:dem":217,
    "gn:feature_class":"P",
    "gn:feature_code":"PPL",
    "gn:name":"Bossa",
    "gn:population":0,
    "gn:timezone":"Africa/Niamey",
    "iso:country":"NE",
    "wof:name":"Bossa",
    "wof:placetype":"locality"
},
  "geometry": {"coordinates":[1.9158,13.11924],"type":"Point"}
}