{
  "type": "Feature",
  "properties": {
    "gn:admin1_code":"2.0",
    "gn:asciiname":"Birandi",
    "gn:country_code":"NE",
    "gn:dem":351,
    "gn:feature_class":"P",
    "gn:feature_code":"PPL",
    "gn:name":"Birandi",
    "gn:population":0,
    "gn:timezone":"Africa/Niamey",
    "iso:country":"NE",
    "wof:name":"Birandi",
    "wof:placetype":"locality"
},
  "geometry": {"coordinates":[11.9872,13.3903],"type":"Point"}
}