{
  "type": "Feature",
  "properties": {
    "gn:admin1_code":"9.0",
    "gn:asciiname":"Metelekiya",
    "gn:country_code":"NE",
    "gn:dem":231,
    "gn:feature_class":"P",
    "gn:feature_code":"PPL",
    "gn:name":"M\u00e9t\u00e9l\u00e9kiya",
    "gn:population":0,
    "gn:timezone":"Africa/Niamey",
    "iso:country":"NE",
    "wof:name":"Metelekiya",
    "wof:placetype":"locality"
},
  "geometry": {"coordinates":[3.2749,14.6567],"type":"Point"}
}