{
  "type": "Feature",
  "properties": {
    "gn:admin1_code":"7.0",
    "gn:asciiname":"Rapsori",
    "gn:country_code":"NE",
    "gn:dem":443,
    "gn:feature_class":"P",
    "gn:feature_code":"PPL",
    "gn:name":"Rapsori",
    "gn:population":0,
    "gn:timezone":"Africa/Niamey",
    "iso:country":"NE",
    "wof:name":"Rapsori",
    "wof:placetype":"locality"
},
  "geometry": {"coordinates":[8.5494,14.3143],"type":"Point"}
}