{
  "type": "Feature",
  "properties": {
    "gn:admin1_code":"3.0",
    "gn:asciiname":"Dantoulou",
    "gn:country_code":"NE",
    "gn:dem":265,
    "gn:feature_class":"P",
    "gn:feature_code":"PPL",
    "gn:name":"Dantoulou",
    "gn:population":0,
    "gn:timezone":"Africa/Niamey",
    "iso:country":"NE",
    "wof:name":"Dantoulou",
    "wof:placetype":"locality"
},
  "geometry": {"coordinates":[3.8869,13.2282],"type":"Point"}
}