{
  "type": "Feature",
  "properties": {
    "gn:admin1_code":"9.0",
    "gn:asciiname":"Deli Tondi Atou Kouara",
    "gn:country_code":"NE",
    "gn:dem":248,
    "gn:feature_class":"P",
    "gn:feature_code":"PPL",
    "gn:name":"D\u00e9li Tondi Atou Kouara",
    "gn:population":0,
    "gn:timezone":"Africa/Niamey",
    "iso:country":"NE",
    "name:und_x_variant":[
        "Delli-Tondi-Atou-Koara",
        "Delli Tondi Atou Kwara",
        "Delifondi",
        "D\u00e9li Tondi",
        "D\u00e9li Tondi Atou Kouara"
    ],
    "wof:name":"Deli Tondi Atou Kouara",
    "wof:placetype":"locality"
},
  "geometry": {"coordinates":[2.205,13.9955],"type":"Point"}
}