{
  "type": "Feature",
  "properties": {
    "gn:admin1_code":"2.0",
    "gn:asciiname":"Koa Lealidi",
    "gn:country_code":"NE",
    "gn:dem":349,
    "gn:feature_class":"P",
    "gn:feature_code":"PPL",
    "gn:name":"Koa L\u00e9alidi",
    "gn:population":0,
    "gn:timezone":"Africa/Niamey",
    "iso:country":"NE",
    "wof:name":"Koa Lealidi",
    "wof:placetype":"locality"
},
  "geometry": {"coordinates":[11.1103,13.5987],"type":"Point"}
}