{
  "type": "Feature",
  "properties": {
    "gn:admin1_code":"6.0",
    "gn:asciiname":"Kyara",
    "gn:country_code":"NE",
    "gn:dem":269,
    "gn:feature_class":"P",
    "gn:feature_code":"PPL",
    "gn:name":"Kyara",
    "gn:population":0,
    "gn:timezone":"Africa/Niamey",
    "iso:country":"NE",
    "wof:name":"Kyara",
    "wof:placetype":"locality"
},
  "geometry": {"coordinates":[4.51408,14.20045],"type":"Point"}
}