{
  "type": "Feature",
  "properties": {
    "gn:admin1_code":"4.0",
    "gn:asciiname":"Bongounji",
    "gn:country_code":"NE",
    "gn:dem":353,
    "gn:feature_class":"P",
    "gn:feature_code":"PPL",
    "gn:name":"Bongounji",
    "gn:population":0,
    "gn:timezone":"Africa/Niamey",
    "iso:country":"NE",
    "wof:name":"Bongounji",
    "wof:placetype":"locality"
},
  "geometry": {"coordinates":[6.96358,13.65535],"type":"Point"}
}