{
  "type": "Feature",
  "properties": {
    "gn:admin1_code":"4.0",
    "gn:asciiname":"Maylayou",
    "gn:country_code":"NE",
    "gn:dem":432,
    "gn:feature_class":"P",
    "gn:feature_code":"PPL",
    "gn:name":"Maylayou",
    "gn:population":0,
    "gn:timezone":"Africa/Niamey",
    "iso:country":"NE",
    "wof:name":"Maylayou",
    "wof:placetype":"locality"
},
  "geometry": {"coordinates":[7.94793,14.43787],"type":"Point"}
}