{
  "type": "Feature",
  "properties": {
    "gn:admin1_code":"9.0",
    "gn:asciiname":"Katanga",
    "gn:country_code":"NE",
    "gn:dem":251,
    "gn:feature_class":"P",
    "gn:feature_code":"PPL",
    "gn:name":"Katanga",
    "gn:population":0,
    "gn:timezone":"Africa/Niamey",
    "iso:country":"NE",
    "wof:name":"Katanga",
    "wof:placetype":"locality"
},
  "geometry": {"coordinates":[2.8153,13.5361],"type":"Point"}
}