{
  "type": "Feature",
  "properties": {
    "gn:admin1_code":"9.0",
    "gn:asciiname":"Dak Dakey Sabo Koara",
    "gn:country_code":"NE",
    "gn:dem":246,
    "gn:feature_class":"P",
    "gn:feature_code":"PPL",
    "gn:name":"Dak Dak\u00e8y Sabo Koara",
    "gn:population":0,
    "gn:timezone":"Africa/Niamey",
    "iso:country":"NE",
    "name:und_x_variant":[
        "Dak Dakey Sabo Kwara",
        "Dak Dak\u00e8y Sabo Koara"
    ],
    "wof:name":"Dak Dakey Sabo Koara",
    "wof:placetype":"locality"
},
  "geometry": {"coordinates":[2.08422,14.41092],"type":"Point"}
}