{
  "type": "Feature",
  "properties": {
    "gn:admin1_code":"3.0",
    "gn:asciiname":"Makieri",
    "gn:country_code":"NE",
    "gn:dem":182,
    "gn:feature_class":"P",
    "gn:feature_code":"PPL",
    "gn:name":"Maki\u00e9ri",
    "gn:population":0,
    "gn:timezone":"Africa/Niamey",
    "iso:country":"NE",
    "name:und_x_variant":[
        "Maky\u00e9ri",
        "Maki\u00e9ri"
    ],
    "wof:name":"Makieri",
    "wof:placetype":"locality"
},
  "geometry": {"coordinates":[3.54864,12.56118],"type":"Point"}
}