{
  "type": "Feature",
  "properties": {
    "gn:admin1_code":"7.0",
    "gn:asciiname":"May Zakara",
    "gn:country_code":"NE",
    "gn:dem":454,
    "gn:feature_class":"P",
    "gn:feature_code":"PPL",
    "gn:name":"May Zakara",
    "gn:population":0,
    "gn:timezone":"Africa/Niamey",
    "iso:country":"NE",
    "wof:name":"May Zakara",
    "wof:placetype":"locality"
},
  "geometry": {"coordinates":[8.30173,13.64218],"type":"Point"}
}