{
  "type": "Feature",
  "properties": {
    "gn:admin1_code":"2.0",
    "gn:asciiname":"Bouloswa",
    "gn:country_code":"NE",
    "gn:dem":349,
    "gn:feature_class":"P",
    "gn:feature_code":"PPL",
    "gn:name":"Bouloswa",
    "gn:population":0,
    "gn:timezone":"Africa/Niamey",
    "iso:country":"NE",
    "wof:name":"Bouloswa",
    "wof:placetype":"locality"
},
  "geometry": {"coordinates":[11.0561,13.5415],"type":"Point"}
}