{
  "type": "Feature",
  "properties": {
    "gn:admin1_code":"4.0",
    "gn:asciiname":"Rijial Dadji",
    "gn:country_code":"NE",
    "gn:dem":369,
    "gn:feature_class":"P",
    "gn:feature_code":"PPL",
    "gn:name":"Rijial Dadji",
    "gn:population":0,
    "gn:timezone":"Africa/Niamey",
    "iso:country":"NE",
    "name:und_x_variant":[
        "Match\u00e9ri",
        "Rijial Dadji"
    ],
    "wof:name":"Rijial Dadji",
    "wof:placetype":"locality"
},
  "geometry": {"coordinates":[7.31957,13.81308],"type":"Point"}
}