{
  "type": "Feature",
  "properties": {
    "gn:admin1_code":"9.0",
    "gn:asciiname":"Bonfeba",
    "gn:country_code":"NE",
    "gn:dem":211,
    "gn:feature_class":"P",
    "gn:feature_code":"PPL",
    "gn:name":"Bonf\u00e9ba",
    "gn:population":0,
    "gn:timezone":"Africa/Niamey",
    "iso:country":"NE",
    "wof:name":"Bonfeba",
    "wof:placetype":"locality"
},
  "geometry": {"coordinates":[1.20044,14.38376],"type":"Point"}
}