{
  "type": "Feature",
  "properties": {
    "gn:admin1_code":"4.0",
    "gn:asciiname":"Gangara",
    "gn:country_code":"NE",
    "gn:dem":413,
    "gn:feature_class":"P",
    "gn:feature_code":"PPL",
    "gn:name":"Gangara",
    "gn:population":0,
    "gn:timezone":"Africa/Niamey",
    "iso:country":"NE",
    "name:deu_x_preferred":[
        "Gangara"
    ],
    "name:fra_x_preferred":[
        "Gangara"
    ],
    "name:ita_x_preferred":[
        "Gangara"
    ],
    "name:msa_x_preferred":[
        "Gangara"
    ],
    "name:ron_x_preferred":[
        "Gangara"
    ],
    "name:spa_x_preferred":[
        "Gangara"
    ],
    "wof:name":"Gangara",
    "wof:placetype":"locality"
},
  "geometry": {"coordinates":[7.84314,13.42579],"type":"Point"}
}