{
  "type": "Feature",
  "properties": {
    "gn:admin1_code":"4.0",
    "gn:asciiname":"Dillo",
    "gn:country_code":"NE",
    "gn:dem":420,
    "gn:feature_class":"P",
    "gn:feature_code":"PPL",
    "gn:name":"Dillo",
    "gn:population":0,
    "gn:timezone":"Africa/Niamey",
    "iso:country":"NE",
    "wof:name":"Dillo",
    "wof:placetype":"locality"
},
  "geometry": {"coordinates":[7.3164,14.86868],"type":"Point"}
}