{
  "type": "Feature",
  "properties": {
    "gn:admin1_code":"4.0",
    "gn:asciiname":"Dillo",
    "gn:country_code":"NE",
    "gn:dem":420,
    "gn:feature_class":"P",
    "gn:feature_code":"PPL",
    "gn:name":"Dillo",
    "gn:population":0,
    "gn:timezone":"Africa/Niamey",
    "iso:country":"NE",
    "name:ara_x_preferred":[
        "\u062f\u06cc\u0644\u0648"
    ],
    "name:cat_x_preferred":[
        "Dillo"
    ],
    "name:ces_x_preferred":[
        "Dillo"
    ],
    "name:csb_x_preferred":[
        "Dillo"
    ],
    "name:deu_x_preferred":[
        "Dillo"
    ],
    "name:est_x_preferred":[
        "Dillo"
    ],
    "name:fas_x_preferred":[
        "\u062f\u06cc\u0644\u0648"
    ],
    "name:fin_x_preferred":[
        "Dillo"
    ],
    "name:fra_x_preferred":[
        "Dillo"
    ],
    "name:hun_x_preferred":[
        "Dillo"
    ],
    "name:ind_x_preferred":[
        "Dillo"
    ],
    "name:ita_x_preferred":[
        "Dillo"
    ],
    "name:jpn_x_preferred":[
        "Dillo"
    ],
    "name:lit_x_preferred":[
        "Dillo"
    ],
    "name:nld_x_preferred":[
        "Dillo"
    ],
    "name:nno_x_preferred":[
        "Dillo"
    ],
    "name:pol_x_preferred":[
        "Dillo"
    ],
    "name:por_x_preferred":[
        "Dillo"
    ],
    "name:rus_x_preferred":[
        "Dillo"
    ],
    "name:spa_x_preferred":[
        "Dillo"
    ],
    "name:swe_x_preferred":[
        "Dillo"
    ],
    "name:vie_x_preferred":[
        "Dillo"
    ],
    "name:zho_x_preferred":[
        "Dillo"
    ],
    "wof:name":"Dillo",
    "wof:placetype":"locality"
},
  "geometry": {"coordinates":[7.3164,14.86868],"type":"Point"}
}