{
  "type": "Feature",
  "properties": {
    "gn:admin1_code":"3.0",
    "gn:asciiname":"Daniaro",
    "gn:country_code":"NE",
    "gn:dem":190,
    "gn:feature_class":"P",
    "gn:feature_code":"PPL",
    "gn:name":"Daniaro",
    "gn:population":0,
    "gn:timezone":"Africa/Niamey",
    "iso:country":"NE",
    "wof:name":"Daniaro",
    "wof:placetype":"locality"
},
  "geometry": {"coordinates":[2.96861,12.83483],"type":"Point"}
}