{
  "type": "Feature",
  "properties": {
    "gn:admin1_code":"6.0",
    "gn:asciiname":"Guidan Dougounawa",
    "gn:country_code":"NE",
    "gn:dem":427,
    "gn:feature_class":"P",
    "gn:feature_code":"PPL",
    "gn:name":"Guidan Dougounawa",
    "gn:population":0,
    "gn:timezone":"Africa/Niamey",
    "iso:country":"NE",
    "wof:name":"Guidan Dougounawa",
    "wof:placetype":"locality"
},
  "geometry": {"coordinates":[6.21797,14.61835],"type":"Point"}
}