{
  "type": "Feature",
  "properties": {
    "gn:admin1_code":"9.0",
    "gn:asciiname":"Kokorbe",
    "gn:country_code":"NE",
    "gn:dem":240,
    "gn:feature_class":"P",
    "gn:feature_code":"PPL",
    "gn:name":"Kokorb\u00e9",
    "gn:population":0,
    "gn:timezone":"Africa/Niamey",
    "iso:country":"NE",
    "wof:name":"Kokorbe",
    "wof:placetype":"locality"
},
  "geometry": {"coordinates":[1.91916,14.56735],"type":"Point"}
}