{
  "type": "Feature",
  "properties": {
    "gn:admin1_code":"3.0",
    "gn:asciiname":"Kousou",
    "gn:country_code":"NE",
    "gn:dem":275,
    "gn:feature_class":"P",
    "gn:feature_code":"PPL",
    "gn:name":"Kousou",
    "gn:population":0,
    "gn:timezone":"Africa/Niamey",
    "iso:country":"NE",
    "wof:name":"Kousou",
    "wof:placetype":"locality"
},
  "geometry": {"coordinates":[4.39539,14.19612],"type":"Point"}
}