{
  "type": "Feature",
  "properties": {
    "gn:admin1_code":"7.0",
    "gn:asciiname":"Chiriaou",
    "gn:country_code":"NE",
    "gn:dem":401,
    "gn:feature_class":"P",
    "gn:feature_code":"PPL",
    "gn:name":"Chiriaou",
    "gn:population":0,
    "gn:timezone":"Africa/Niamey",
    "iso:country":"NE",
    "wof:name":"Chiriaou",
    "wof:placetype":"locality"
},
  "geometry": {"coordinates":[8.83927,12.88989],"type":"Point"}
}