{
  "type": "Feature",
  "properties": {
    "gn:admin1_code":"7.0",
    "gn:asciiname":"Tamaraoulo",
    "gn:country_code":"NE",
    "gn:dem":471,
    "gn:feature_class":"P",
    "gn:feature_code":"PPL",
    "gn:name":"Tamaraoulo",
    "gn:population":0,
    "gn:timezone":"Africa/Niamey",
    "iso:country":"NE",
    "wof:name":"Tamaraoulo",
    "wof:placetype":"locality"
},
  "geometry": {"coordinates":[8.74666,15.23419],"type":"Point"}
}