{
  "type": "Feature",
  "properties": {
    "gn:admin1_code":"9.0",
    "gn:asciiname":"Goundey",
    "gn:country_code":"NE",
    "gn:dem":232,
    "gn:feature_class":"P",
    "gn:feature_code":"PPL",
    "gn:name":"Gound\u00e8y",
    "gn:population":0,
    "gn:timezone":"Africa/Niamey",
    "iso:country":"NE",
    "wof:name":"Goundey",
    "wof:placetype":"locality"
},
  "geometry": {"coordinates":[2.39665,14.02718],"type":"Point"}
}