{
  "type": "Feature",
  "properties": {
    "gn:admin1_code":"7.0",
    "gn:asciiname":"Foudi",
    "gn:country_code":"NE",
    "gn:dem":384,
    "gn:feature_class":"P",
    "gn:feature_code":"PPL",
    "gn:name":"Foudi",
    "gn:population":0,
    "gn:timezone":"Africa/Niamey",
    "iso:country":"NE",
    "wof:name":"Foudi",
    "wof:placetype":"locality"
},
  "geometry": {"coordinates":[10.37112,13.83013],"type":"Point"}
}