{
  "type": "Feature",
  "properties": {
    "gn:gn_country":"NE",
    "gn:gn_fcode":"PPLX",
    "gn:gn_pop":0,
    "iso:country":"NE",
    "name:fra_x_colloquial":[
        "Gaweye"
    ],
    "name:fra_x_preferred":[
        "Gaw\u00e9ye"
    ],
    "name:unk_x_variant":[
        "Gaw\u00e9ye"
    ],
    "qs_pg:aaroncc":"NE",
    "qs_pg:gn_country":"NE",
    "qs_pg:gn_fcode":"PPLX",
    "qs_pg:gn_pop":0,
    "qs_pg:name":"Gaw\u00e9ye",
    "qs_pg:name_adm0":"Niger",
    "qs_pg:name_adm1":"Niamey",
    "qs_pg:photos":257,
    "qs_pg:photos_1k":52,
    "qs_pg:photos_9k":1,
    "qs_pg:photos_9r":4,
    "qs_pg:photos_all":257,
    "qs_pg:photos_sr":5,
    "qs_pg:pop_sr":0,
    "qs_pg:qs_pg_placetype":"neighbourhood",
    "qs_pg:qs_pg_placetype_gp":"Suburb",
    "qs_pg:woe_adm0":23424906,
    "woe:adm0_id":23424906,
    "woe:name_adm0":"Niger",
    "woe:name_adm1":"Niamey",
    "woe:placetype":"Suburb",
    "wof:name":"Gaw\u00e9ye",
    "wof:placetype":"neighbourhood"
},
  "geometry": {"coordinates":[2.10056,13.48778],"type":"Point"}
}