{
  "type": "Feature",
  "properties": {
    "gn:admin1_code":"3.0",
    "gn:asciiname":"Seti Birni",
    "gn:country_code":"NE",
    "gn:dem":210,
    "gn:feature_class":"P",
    "gn:feature_code":"PPL",
    "gn:name":"S\u00e9ti Birni",
    "gn:population":0,
    "gn:timezone":"Africa/Niamey",
    "iso:country":"NE",
    "name:und_x_variant":[
        "Se\u00efti Berni",
        "S\u00e9ti Birni"
    ],
    "wof:name":"Seti Birni",
    "wof:placetype":"locality"
},
  "geometry": {"coordinates":[2.9792,13.1218],"type":"Point"}
}