{
  "type": "Feature",
  "properties": {
    "gn:admin1_code":"4.0",
    "gn:asciiname":"Guidan Tambari Bako",
    "gn:country_code":"NE",
    "gn:dem":442,
    "gn:feature_class":"P",
    "gn:feature_code":"PPL",
    "gn:name":"Guidan Tambari Bako",
    "gn:population":0,
    "gn:timezone":"Africa/Niamey",
    "iso:country":"NE",
    "wof:name":"Guidan Tambari Bako",
    "wof:placetype":"locality"
},
  "geometry": {"coordinates":[7.36707,13.33555],"type":"Point"}
}