{
  "type": "Feature",
  "properties": {
    "gn:admin1_code":"4.0",
    "gn:asciiname":"Adagoy",
    "gn:country_code":"NE",
    "gn:dem":438,
    "gn:feature_class":"P",
    "gn:feature_code":"PPL",
    "gn:name":"Adagoy",
    "gn:population":0,
    "gn:timezone":"Africa/Niamey",
    "iso:country":"NE",
    "wof:name":"Adagoy",
    "wof:placetype":"locality"
},
  "geometry": {"coordinates":[8.11252,13.4043],"type":"Point"}
}