{
  "type": "Feature",
  "properties": {
    "gn:admin1_code":"6.0",
    "gn:asciiname":"Guidan Ataba",
    "gn:country_code":"NE",
    "gn:dem":389,
    "gn:feature_class":"P",
    "gn:feature_code":"PPL",
    "gn:name":"Guidan Ataba",
    "gn:population":0,
    "gn:timezone":"Africa/Niamey",
    "iso:country":"NE",
    "wof:name":"Guidan Ataba",
    "wof:placetype":"locality"
},
  "geometry": {"coordinates":[6.3678,14.66123],"type":"Point"}
}