{
  "type": "Feature",
  "properties": {
    "gn:admin1_code":"3.0",
    "gn:asciiname":"Guillare Peul",
    "gn:country_code":"NE",
    "gn:dem":189,
    "gn:feature_class":"P",
    "gn:feature_code":"PPL",
    "gn:name":"Guillar\u00e9 Peul",
    "gn:population":0,
    "gn:timezone":"Africa/Niamey",
    "iso:country":"NE",
    "name:und_x_variant":[
        "Guilar\u00e9 Peul",
        "Guillar\u00e9 Peul"
    ],
    "wof:name":"Guillare Peul",
    "wof:placetype":"locality"
},
  "geometry": {"coordinates":[2.86663,13.13081],"type":"Point"}
}