{
  "type": "Feature",
  "properties": {
    "gn:admin1_code":"3.0",
    "gn:asciiname":"Kademdami",
    "gn:country_code":"NE",
    "gn:dem":304,
    "gn:feature_class":"P",
    "gn:feature_code":"PPL",
    "gn:name":"Kademdami",
    "gn:population":0,
    "gn:timezone":"Africa/Niamey",
    "iso:country":"NE",
    "wof:name":"Kademdami",
    "wof:placetype":"locality"
},
  "geometry": {"coordinates":[4.2931,13.88884],"type":"Point"}
}