{
  "type": "Feature",
  "properties": {
    "gn:admin1_code":"3.0",
    "gn:asciiname":"Tounga-Adoua",
    "gn:country_code":"NE",
    "gn:dem":237,
    "gn:feature_class":"P",
    "gn:feature_code":"PPL",
    "gn:name":"Tounga-Adoua",
    "gn:population":0,
    "gn:timezone":"Africa/Niamey",
    "iso:country":"NE",
    "wof:name":"Tounga-Adoua",
    "wof:placetype":"locality"
},
  "geometry": {"coordinates":[3.8851,13.0708],"type":"Point"}
}