{
  "type": "Feature",
  "properties": {
    "gn:admin1_code":"7.0",
    "gn:asciiname":"Kirba",
    "gn:country_code":"NE",
    "gn:dem":390,
    "gn:feature_class":"P",
    "gn:feature_code":"PPL",
    "gn:name":"Kirba",
    "gn:population":0,
    "gn:timezone":"Africa/Niamey",
    "iso:country":"NE",
    "wof:name":"Kirba",
    "wof:placetype":"locality"
},
  "geometry": {"coordinates":[9.0826,13.0836],"type":"Point"}
}