{
  "type": "Feature",
  "properties": {
    "gn:admin1_code":"3.0",
    "gn:asciiname":"Kosseye",
    "gn:country_code":"NE",
    "gn:dem":260,
    "gn:feature_class":"P",
    "gn:feature_code":"PPL",
    "gn:name":"Koss\u00e8ye",
    "gn:population":0,
    "gn:timezone":"Africa/Niamey",
    "iso:country":"NE",
    "name:und_x_variant":[
        "Kos\u00e8y",
        "Kossey",
        "Koss\u00e8ye"
    ],
    "wof:name":"Kosseye",
    "wof:placetype":"locality"
},
  "geometry": {"coordinates":[3.4072,13.5803],"type":"Point"}
}