{
  "type": "Feature",
  "properties": {
    "gn:admin1_code":"4.0",
    "gn:asciiname":"Guidan Kalgo",
    "gn:country_code":"NE",
    "gn:dem":418,
    "gn:feature_class":"P",
    "gn:feature_code":"PPL",
    "gn:name":"Guidan Kalg\u00f4",
    "gn:population":0,
    "gn:timezone":"Africa/Niamey",
    "iso:country":"NE",
    "name:und_x_variant":[
        "Gidan Kalgo",
        "Guidan Kalg\u00f4"
    ],
    "wof:name":"Guidan Kalgo",
    "wof:placetype":"locality"
},
  "geometry": {"coordinates":[7.30896,13.66403],"type":"Point"}
}