{
  "type": "Feature",
  "properties": {
    "gn:admin1_code":"7.0",
    "gn:asciiname":"Kania",
    "gn:country_code":"NE",
    "gn:dem":447,
    "gn:feature_class":"P",
    "gn:feature_code":"PPL",
    "gn:name":"Kania",
    "gn:population":0,
    "gn:timezone":"Africa/Niamey",
    "iso:country":"NE",
    "name:ceb_x_preferred":[
        "Kania"
    ],
    "name:ces_x_preferred":[
        "Kania"
    ],
    "name:deu_x_preferred":[
        "Kania"
    ],
    "name:fra_x_preferred":[
        "Kania"
    ],
    "name:ita_x_preferred":[
        "Kania"
    ],
    "name:nld_x_preferred":[
        "Kania"
    ],
    "name:pol_x_preferred":[
        "Kania"
    ],
    "name:rus_x_preferred":[
        "\u041a\u0430\u043d\u044f"
    ],
    "name:swe_x_preferred":[
        "Kania"
    ],
    "name:ukr_x_preferred":[
        "\u041a\u0430\u043d\u044f"
    ],
    "name:und_x_variant":[
        "Kanya",
        "Kania"
    ],
    "wof:name":"Kania",
    "wof:placetype":"locality"
},
  "geometry": {"coordinates":[8.99072,13.90869],"type":"Point"}
}