{
  "type": "Feature",
  "properties": {
    "gn:admin1_code":"7.0",
    "gn:asciiname":"Bagal",
    "gn:country_code":"NE",
    "gn:dem":483,
    "gn:feature_class":"P",
    "gn:feature_code":"PPL",
    "gn:name":"Bagal",
    "gn:population":0,
    "gn:timezone":"Africa/Niamey",
    "iso:country":"NE",
    "wof:name":"Bagal",
    "wof:placetype":"locality"
},
  "geometry": {"coordinates":[8.46474,13.24008],"type":"Point"}
}