{
  "type": "Feature",
  "properties": {
    "gn:admin1_code":"3.0",
    "gn:asciiname":"Bawada",
    "gn:country_code":"NE",
    "gn:dem":261,
    "gn:feature_class":"P",
    "gn:feature_code":"PPL",
    "gn:name":"Bawada",
    "gn:population":0,
    "gn:timezone":"Africa/Niamey",
    "iso:country":"NE",
    "name:und_x_variant":[
        "Baouada",
        "Bawada"
    ],
    "wof:name":"Bawada",
    "wof:placetype":"locality"
},
  "geometry": {"coordinates":[3.83762,12.7866],"type":"Point"}
}