{
  "type": "Feature",
  "properties": {
    "gn:admin1_code":"6.0",
    "gn:asciiname":"Karkamat",
    "gn:country_code":"NE",
    "gn:dem":548,
    "gn:feature_class":"P",
    "gn:feature_code":"PPL",
    "gn:name":"Karkamat",
    "gn:population":0,
    "gn:timezone":"Africa/Niamey",
    "iso:country":"NE",
    "wof:name":"Karkamat",
    "wof:placetype":"locality"
},
  "geometry": {"coordinates":[6.08294,14.94004],"type":"Point"}
}