{
  "type": "Feature",
  "properties": {
    "gn:admin1_code":"4.0",
    "gn:asciiname":"Djali",
    "gn:country_code":"NE",
    "gn:dem":396,
    "gn:feature_class":"P",
    "gn:feature_code":"PPL",
    "gn:name":"Djali",
    "gn:population":0,
    "gn:timezone":"Africa/Niamey",
    "iso:country":"NE",
    "name:und_x_variant":[
        "Jali",
        "Djali"
    ],
    "wof:name":"Djali",
    "wof:placetype":"locality"
},
  "geometry": {"coordinates":[7.3983,14.0674],"type":"Point"}
}