{
  "type": "Feature",
  "properties": {
    "gn:admin1_code":"3.0",
    "gn:asciiname":"Sakara",
    "gn:country_code":"NE",
    "gn:dem":182,
    "gn:feature_class":"P",
    "gn:feature_code":"PPL",
    "gn:name":"Sakara",
    "gn:population":0,
    "gn:timezone":"Africa/Niamey",
    "iso:country":"NE",
    "name:ceb_x_preferred":[
        "Sakara"
    ],
    "name:fin_x_preferred":[
        "Sakara"
    ],
    "name:swe_x_preferred":[
        "Sakara"
    ],
    "wof:name":"Sakara",
    "wof:placetype":"locality"
},
  "geometry": {"coordinates":[2.83749,12.64959],"type":"Point"}
}