{
  "type": "Feature",
  "properties": {
    "gn:admin1_code":"4.0",
    "gn:asciiname":"Kankaren Kaka",
    "gn:country_code":"NE",
    "gn:dem":399,
    "gn:feature_class":"P",
    "gn:feature_code":"PPL",
    "gn:name":"Kankar\u00e9n Kaka",
    "gn:population":0,
    "gn:timezone":"Africa/Niamey",
    "iso:country":"NE",
    "name:und_x_variant":[
        "Kankari",
        "Kankar\u00e9n Kaka"
    ],
    "wof:name":"Kankaren Kaka",
    "wof:placetype":"locality"
},
  "geometry": {"coordinates":[7.13884,13.72327],"type":"Point"}
}