{
  "type": "Feature",
  "properties": {
    "gn:admin1_code":"4.0",
    "gn:asciiname":"Kayfin Gatari",
    "gn:country_code":"NE",
    "gn:dem":443,
    "gn:feature_class":"P",
    "gn:feature_code":"PPL",
    "gn:name":"Kayfin Gatari",
    "gn:population":0,
    "gn:timezone":"Africa/Niamey",
    "iso:country":"NE",
    "wof:name":"Kayfin Gatari",
    "wof:placetype":"locality"
},
  "geometry": {"coordinates":[8.0298,14.2142],"type":"Point"}
}