{
  "type": "Feature",
  "properties": {
    "gn:admin1_code":"3.0",
    "gn:asciiname":"Sarikinedadji",
    "gn:country_code":"NE",
    "gn:dem":242,
    "gn:feature_class":"P",
    "gn:feature_code":"PPL",
    "gn:name":"Sarikin\u00e9dadji",
    "gn:population":0,
    "gn:timezone":"Africa/Niamey",
    "iso:country":"NE",
    "wof:name":"Sarikinedadji",
    "wof:placetype":"locality"
},
  "geometry": {"coordinates":[3.8649,13.3659],"type":"Point"}
}