{
  "type": "Feature",
  "properties": {
    "gn:admin1_code":"4.0",
    "gn:asciiname":"Tankarawa",
    "gn:country_code":"NE",
    "gn:dem":415,
    "gn:feature_class":"P",
    "gn:feature_code":"PPL",
    "gn:name":"Tankarawa",
    "gn:population":0,
    "gn:timezone":"Africa/Niamey",
    "iso:country":"NE",
    "name:und_x_variant":[
        "Tankaraoua",
        "Tankarawa"
    ],
    "wof:name":"Tankarawa",
    "wof:placetype":"locality"
},
  "geometry": {"coordinates":[6.62198,14.27746],"type":"Point"}
}