{
  "type": "Feature",
  "properties": {
    "gn:admin1_code":"7.0",
    "gn:asciiname":"Mare",
    "gn:country_code":"NE",
    "gn:dem":508,
    "gn:feature_class":"P",
    "gn:feature_code":"PPL",
    "gn:name":"Mar\u00e9",
    "gn:population":0,
    "gn:timezone":"Africa/Niamey",
    "iso:country":"NE",
    "name:aze_x_preferred":[
        "Madyan"
    ],
    "name:bel_x_preferred":[
        "\u041a\u0430\u0431\u044b\u043b\u0430"
    ],
    "name:bre_x_preferred":[
        "Kazeg"
    ],
    "name:bul_x_preferred":[
        "\u041a\u043e\u0431\u0438\u043b\u0430"
    ],
    "name:deu_x_preferred":[
        "Stute"
    ],
    "name:est_x_preferred":[
        "M\u00e4ra"
    ],
    "name:fas_x_preferred":[
        "\u0645\u0627\u062f\u06cc\u0627\u0646"
    ],
    "name:fra_x_preferred":[
        "Jument"
    ],
    "name:hun_x_preferred":[
        "Kanca"
    ],
    "name:kir_x_preferred":[
        "\u0411\u044d\u044d"
    ],
    "name:lav_x_preferred":[
        "\u0136\u0113ve"
    ],
    "name:nds_x_preferred":[
        "M\u00e4hr"
    ],
    "name:nld_x_preferred":[
        "Merrie"
    ],
    "name:nno_x_preferred":[
        "Hoppe"
    ],
    "name:nor_x_preferred":[
        "Hoppe"
    ],
    "name:pol_x_preferred":[
        "Klacz"
    ],
    "name:por_x_preferred":[
        "\u00c9gua"
    ],
    "name:scn_x_preferred":[
        "Jumenta"
    ],
    "name:sco_x_preferred":[
        "Meir"
    ],
    "name:slk_x_preferred":[
        "Kobyla"
    ],
    "name:swe_x_preferred":[
        "Sto"
    ],
    "name:tgk_x_preferred":[
        "\u0411\u0430\u0439\u0442\u0430\u043b"
    ],
    "name:uzb_x_preferred":[
        "Biya"
    ],
    "name:yid_x_preferred":[
        "\u05e7\u05dc\u05d9\u05d0\u05d8\u05e9\u05e2"
    ],
    "wof:name":"Mare",
    "wof:placetype":"locality"
},
  "geometry": {"coordinates":[8.9874,14.89907],"type":"Point"}
}