{
  "type": "Feature",
  "properties": {
    "gn:admin1_code":"6.0",
    "gn:asciiname":"Guidan Zabeyrau",
    "gn:country_code":"NE",
    "gn:dem":388,
    "gn:feature_class":"P",
    "gn:feature_code":"PPL",
    "gn:name":"Guidan Zab\u00e9yrau",
    "gn:population":0,
    "gn:timezone":"Africa/Niamey",
    "iso:country":"NE",
    "wof:name":"Guidan Zabeyrau",
    "wof:placetype":"locality"
},
  "geometry": {"coordinates":[6.41444,14.23536],"type":"Point"}
}