{
  "type": "Feature",
  "properties": {
    "gn:admin1_code":"6.0",
    "gn:asciiname":"Chanyasou",
    "gn:country_code":"NE",
    "gn:dem":272,
    "gn:feature_class":"P",
    "gn:feature_code":"PPL",
    "gn:name":"Chanyasou",
    "gn:population":0,
    "gn:timezone":"Africa/Niamey",
    "iso:country":"NE",
    "wof:name":"Chanyasou",
    "wof:placetype":"locality"
},
  "geometry": {"coordinates":[5.1144,14.1443],"type":"Point"}
}