{
  "type": "Feature",
  "properties": {
    "gn:admin1_code":"2.0",
    "gn:asciiname":"Boulousou",
    "gn:country_code":"NE",
    "gn:dem":357,
    "gn:feature_class":"P",
    "gn:feature_code":"PPL",
    "gn:name":"Boulousou",
    "gn:population":0,
    "gn:timezone":"Africa/Niamey",
    "iso:country":"NE",
    "wof:name":"Boulousou",
    "wof:placetype":"locality"
},
  "geometry": {"coordinates":[10.85183,13.8076],"type":"Point"}
}