{
  "type": "Feature",
  "properties": {
    "gn:admin1_code":"9.0",
    "gn:asciiname":"Toudou",
    "gn:country_code":"NE",
    "gn:dem":238,
    "gn:feature_class":"P",
    "gn:feature_code":"PPL",
    "gn:name":"Toudou",
    "gn:population":0,
    "gn:timezone":"Africa/Niamey",
    "iso:country":"NE",
    "name:azb_x_preferred":[
        "\u062a\u0648\u062f\u0648"
    ],
    "name:ceb_x_preferred":[
        "Toudou"
    ],
    "name:fas_x_preferred":[
        "\u062a\u0648\u062f\u0648"
    ],
    "name:swe_x_preferred":[
        "Toudou"
    ],
    "wof:name":"Toudou",
    "wof:placetype":"locality"
},
  "geometry": {"coordinates":[3.2796,14.2291],"type":"Point"}
}