{
  "type": "Feature",
  "properties": {
    "gn:admin1_code":"7.0",
    "gn:asciiname":"Poulatari",
    "gn:country_code":"NE",
    "gn:dem":405,
    "gn:feature_class":"P",
    "gn:feature_code":"PPL",
    "gn:name":"Poulatari",
    "gn:population":0,
    "gn:timezone":"Africa/Niamey",
    "iso:country":"NE",
    "wof:name":"Poulatari",
    "wof:placetype":"locality"
},
  "geometry": {"coordinates":[9.9587,14.2447],"type":"Point"}
}