{
  "type": "Feature",
  "properties": {
    "gn:admin1_code":"6.0",
    "gn:asciiname":"Dan Kadou",
    "gn:country_code":"NE",
    "gn:dem":283,
    "gn:feature_class":"P",
    "gn:feature_code":"PPL",
    "gn:name":"Dan Kadou",
    "gn:population":0,
    "gn:timezone":"Africa/Niamey",
    "iso:country":"NE",
    "wof:name":"Dan Kadou",
    "wof:placetype":"locality"
},
  "geometry": {"coordinates":[5.24141,13.95043],"type":"Point"}
}