{
  "type": "Feature",
  "properties": {
    "gn:admin1_code":"9.0",
    "gn:asciiname":"Kirib Beri",
    "gn:country_code":"NE",
    "gn:dem":236,
    "gn:feature_class":"P",
    "gn:feature_code":"PPL",
    "gn:name":"Kirib B\u00e9ri",
    "gn:population":0,
    "gn:timezone":"Africa/Niamey",
    "iso:country":"NE",
    "name:und_x_variant":[
        "Kiri",
        "Kirib",
        "Kirib B\u00e9ri"
    ],
    "wof:name":"Kirib Beri",
    "wof:placetype":"locality"
},
  "geometry": {"coordinates":[2.6808,13.8837],"type":"Point"}
}