{
  "type": "Feature",
  "properties": {
    "gn:admin1_code":"3.0",
    "gn:asciiname":"Zanloa Tounga",
    "gn:country_code":"NE",
    "gn:dem":160,
    "gn:feature_class":"P",
    "gn:feature_code":"PPL",
    "gn:name":"Zanloa Tounga",
    "gn:population":0,
    "gn:timezone":"Africa/Niamey",
    "iso:country":"NE",
    "wof:name":"Zanloa Tounga",
    "wof:placetype":"locality"
},
  "geometry": {"coordinates":[3.60333,11.73586],"type":"Point"}
}