{
  "type": "Feature",
  "properties": {
    "gn:admin1_code":"9.0",
    "gn:asciiname":"Kounam Mane Koara",
    "gn:country_code":"NE",
    "gn:dem":253,
    "gn:feature_class":"P",
    "gn:feature_code":"PPL",
    "gn:name":"Kounam Mane Koara",
    "gn:population":0,
    "gn:timezone":"Africa/Niamey",
    "iso:country":"NE",
    "wof:name":"Kounam Mane Koara",
    "wof:placetype":"locality"
},
  "geometry": {"coordinates":[2.29825,14.07539],"type":"Point"}
}