{
  "type": "Feature",
  "properties": {
    "gn:admin1_code":"9.0",
    "gn:asciiname":"Giliman",
    "gn:country_code":"NE",
    "gn:dem":246,
    "gn:feature_class":"P",
    "gn:feature_code":"PPL",
    "gn:name":"Giliman",
    "gn:population":0,
    "gn:timezone":"Africa/Niamey",
    "iso:country":"NE",
    "name:und_x_variant":[
        "Guillima",
        "Guiliman",
        "Giliman"
    ],
    "wof:name":"Giliman",
    "wof:placetype":"locality"
},
  "geometry": {"coordinates":[2.32453,14.14132],"type":"Point"}
}