{
  "type": "Feature",
  "properties": {
    "gn:admin1_code":"7.0",
    "gn:asciiname":"May Toumbi Bougaje",
    "gn:country_code":"NE",
    "gn:dem":395,
    "gn:feature_class":"P",
    "gn:feature_code":"PPL",
    "gn:name":"May Toumb\u00ee Bougaj\u00e9",
    "gn:population":0,
    "gn:timezone":"Africa/Niamey",
    "iso:country":"NE",
    "wof:name":"May Toumbi Bougaje",
    "wof:placetype":"locality"
},
  "geometry": {"coordinates":[8.92383,12.94942],"type":"Point"}
}