{
  "type": "Feature",
  "properties": {
    "gn:admin1_code":"9.0",
    "gn:asciiname":"Iboy",
    "gn:country_code":"NE",
    "gn:dem":246,
    "gn:feature_class":"P",
    "gn:feature_code":"PPL",
    "gn:name":"Iboy",
    "gn:population":0,
    "gn:timezone":"Africa/Niamey",
    "iso:country":"NE",
    "name:und_x_variant":[
        "Tooye",
        "Iboye",
        "Iboy"
    ],
    "wof:name":"Iboy",
    "wof:placetype":"locality"
},
  "geometry": {"coordinates":[1.89613,13.37602],"type":"Point"}
}