{
  "type": "Feature",
  "properties": {
    "gn:admin1_code":"6.0",
    "gn:asciiname":"Karame",
    "gn:country_code":"NE",
    "gn:dem":367,
    "gn:feature_class":"P",
    "gn:feature_code":"PPL",
    "gn:name":"Karam\u00e9",
    "gn:population":0,
    "gn:timezone":"Africa/Niamey",
    "iso:country":"NE",
    "wof:name":"Karame",
    "wof:placetype":"locality"
},
  "geometry": {"coordinates":[6.42084,14.14034],"type":"Point"}
}