{
  "type": "Feature",
  "properties": {
    "gn:admin1_code":"2.0",
    "gn:asciiname":"Bana",
    "gn:country_code":"NE",
    "gn:dem":344,
    "gn:feature_class":"P",
    "gn:feature_code":"PPL",
    "gn:name":"Bana",
    "gn:population":0,
    "gn:timezone":"Africa/Niamey",
    "iso:country":"NE",
    "wof:name":"Bana",
    "wof:placetype":"locality"
},
  "geometry": {"coordinates":[11.2559,13.5699],"type":"Point"}
}