{
  "type": "Feature",
  "properties": {
    "gn:admin1_code":"2.0",
    "gn:asciiname":"Bana",
    "gn:country_code":"NE",
    "gn:dem":344,
    "gn:feature_class":"P",
    "gn:feature_code":"PPL",
    "gn:name":"Bana",
    "gn:population":0,
    "gn:timezone":"Africa/Niamey",
    "iso:country":"NE",
    "name:cat_x_preferred":[
        "Bana"
    ],
    "name:ceb_x_preferred":[
        "Bana"
    ],
    "name:deu_x_preferred":[
        "Bana"
    ],
    "name:fas_x_preferred":[
        "\u0628\u0627\u0646\u0627"
    ],
    "name:fra_x_preferred":[
        "Bana"
    ],
    "name:ind_x_preferred":[
        "Bana"
    ],
    "name:ita_x_preferred":[
        "Bana"
    ],
    "name:jpn_x_preferred":[
        "\u30d0\u30fc\u30ca"
    ],
    "name:new_x_preferred":[
        "\u092c\u0928\u093e"
    ],
    "name:nld_x_preferred":[
        "Bana"
    ],
    "name:oci_x_preferred":[
        "Bana"
    ],
    "name:por_x_preferred":[
        "Bana"
    ],
    "name:rus_x_preferred":[
        "\u0411\u0430\u043d\u0430"
    ],
    "name:spa_x_preferred":[
        "Bana"
    ],
    "name:swe_x_preferred":[
        "Bana"
    ],
    "wof:name":"Bana",
    "wof:placetype":"locality"
},
  "geometry": {"coordinates":[11.2559,13.5699],"type":"Point"}
}