{
  "type": "Feature",
  "properties": {
    "gn:admin1_code":"6.0",
    "gn:asciiname":"Tounga Doudou",
    "gn:country_code":"NE",
    "gn:dem":310,
    "gn:feature_class":"P",
    "gn:feature_code":"PPL",
    "gn:name":"Tounga Doudou",
    "gn:population":0,
    "gn:timezone":"Africa/Niamey",
    "iso:country":"NE",
    "wof:name":"Tounga Doudou",
    "wof:placetype":"locality"
},
  "geometry": {"coordinates":[5.3853,14.0256],"type":"Point"}
}