{
  "type": "Feature",
  "properties": {
    "gn:admin1_code":"3.0",
    "gn:asciiname":"Fabidji",
    "gn:country_code":"NE",
    "gn:dem":215,
    "gn:feature_class":"P",
    "gn:feature_code":"PPL",
    "gn:name":"Fabidji",
    "gn:population":0,
    "gn:timezone":"Africa/Niamey",
    "iso:country":"NE",
    "name:und_x_variant":[
        "Fabeidji\u00e9",
        "Fabidji"
    ],
    "wof:name":"Fabidji",
    "wof:placetype":"locality"
},
  "geometry": {"coordinates":[2.86474,12.9094],"type":"Point"}
}