{
  "type": "Feature",
  "properties": {
    "gn:admin1_code":"7.0",
    "gn:asciiname":"Kasari",
    "gn:country_code":"NE",
    "gn:dem":406,
    "gn:feature_class":"P",
    "gn:feature_code":"PPL",
    "gn:name":"Kasari",
    "gn:population":0,
    "gn:timezone":"Africa/Niamey",
    "iso:country":"NE",
    "wof:name":"Kasari",
    "wof:placetype":"locality"
},
  "geometry": {"coordinates":[9.16123,13.54889],"type":"Point"}
}