{
  "type": "Feature",
  "properties": {
    "gn:admin1_code":"9.0",
    "gn:asciiname":"Dey Tegui",
    "gn:country_code":"NE",
    "gn:dem":215,
    "gn:feature_class":"P",
    "gn:feature_code":"PPL",
    "gn:name":"Dey T\u00e9gui",
    "gn:population":0,
    "gn:timezone":"Africa/Niamey",
    "iso:country":"NE",
    "name:und_x_variant":[
        "D\u00e9yetagui",
        "Dey Tagui",
        "Dey T\u00e9gui"
    ],
    "wof:name":"Dey Tegui",
    "wof:placetype":"locality"
},
  "geometry": {"coordinates":[2.7904,13.4493],"type":"Point"}
}