{
  "type": "Feature",
  "properties": {
    "gn:admin1_code":"9.0",
    "gn:asciiname":"Koulme Tondi",
    "gn:country_code":"NE",
    "gn:dem":256,
    "gn:feature_class":"P",
    "gn:feature_code":"PPL",
    "gn:name":"Koulm\u00e9 Tondi",
    "gn:population":0,
    "gn:timezone":"Africa/Niamey",
    "iso:country":"NE",
    "wof:name":"Koulme Tondi",
    "wof:placetype":"locality"
},
  "geometry": {"coordinates":[1.95224,13.98298],"type":"Point"}
}