{
  "type": "Feature",
  "properties": {
    "gn:admin1_code":"7.0",
    "gn:asciiname":"Kabikibou",
    "gn:country_code":"NE",
    "gn:dem":382,
    "gn:feature_class":"P",
    "gn:feature_code":"PPL",
    "gn:name":"Kabikibou",
    "gn:population":0,
    "gn:timezone":"Africa/Niamey",
    "iso:country":"NE",
    "wof:name":"Kabikibou",
    "wof:placetype":"locality"
},
  "geometry": {"coordinates":[10.63964,13.99584],"type":"Point"}
}