{
  "type": "Feature",
  "properties": {
    "gn:admin1_code":"6.0",
    "gn:asciiname":"Guidan Segi",
    "gn:country_code":"NE",
    "gn:dem":417,
    "gn:feature_class":"P",
    "gn:feature_code":"PPL",
    "gn:name":"Guidan S\u00e9gi",
    "gn:population":0,
    "gn:timezone":"Africa/Niamey",
    "iso:country":"NE",
    "wof:name":"Guidan Segi",
    "wof:placetype":"locality"
},
  "geometry": {"coordinates":[6.00488,14.32058],"type":"Point"}
}