{
  "type": "Feature",
  "properties": {
    "gn:admin1_code":"7.0",
    "gn:asciiname":"Matata",
    "gn:country_code":"NE",
    "gn:dem":366,
    "gn:feature_class":"P",
    "gn:feature_code":"PPL",
    "gn:name":"Matata",
    "gn:population":0,
    "gn:timezone":"Africa/Niamey",
    "iso:country":"NE",
    "wof:name":"Matata",
    "wof:placetype":"locality"
},
  "geometry": {"coordinates":[9.7119,13.2007],"type":"Point"}
}