{
  "type": "Feature",
  "properties": {
    "gn:admin1_code":"3.0",
    "gn:asciiname":"Dogo Kouara",
    "gn:country_code":"NE",
    "gn:dem":185,
    "gn:feature_class":"P",
    "gn:feature_code":"PPL",
    "gn:name":"Dogo Kouara",
    "gn:population":0,
    "gn:timezone":"Africa/Niamey",
    "iso:country":"NE",
    "wof:name":"Dogo Kouara",
    "wof:placetype":"locality"
},
  "geometry": {"coordinates":[2.97272,12.85091],"type":"Point"}
}