{
  "type": "Feature",
  "properties": {
    "gn:admin1_code":"6.0",
    "gn:asciiname":"Metekane",
    "gn:country_code":"NE",
    "gn:dem":431,
    "gn:feature_class":"P",
    "gn:feature_code":"PPL",
    "gn:name":"M\u00e9t\u00e9kan\u00e9",
    "gn:population":0,
    "gn:timezone":"Africa/Niamey",
    "iso:country":"NE",
    "wof:name":"Metekane",
    "wof:placetype":"locality"
},
  "geometry": {"coordinates":[5.5593,15.0333],"type":"Point"}
}