{
  "type": "Feature",
  "properties": {
    "gn:admin1_code":"7.0",
    "gn:asciiname":"Maykerawa",
    "gn:country_code":"NE",
    "gn:dem":434,
    "gn:feature_class":"P",
    "gn:feature_code":"PPL",
    "gn:name":"Mayk\u00e9rawa",
    "gn:population":0,
    "gn:timezone":"Africa/Niamey",
    "iso:country":"NE",
    "wof:name":"Maykerawa",
    "wof:placetype":"locality"
},
  "geometry": {"coordinates":[8.2758,14.8022],"type":"Point"}
}