{
  "type": "Feature",
  "properties": {
    "gn:admin1_code":"9.0",
    "gn:asciiname":"Bangario",
    "gn:country_code":"NE",
    "gn:dem":231,
    "gn:feature_class":"P",
    "gn:feature_code":"PPL",
    "gn:name":"Bangario",
    "gn:population":0,
    "gn:timezone":"Africa/Niamey",
    "iso:country":"NE",
    "wof:name":"Bangario",
    "wof:placetype":"locality"
},
  "geometry": {"coordinates":[3.0681,13.7451],"type":"Point"}
}