{
  "type": "Feature",
  "properties": {
    "gn:admin1_code":"7.0",
    "gn:asciiname":"Aley",
    "gn:country_code":"NE",
    "gn:dem":454,
    "gn:feature_class":"P",
    "gn:feature_code":"PPL",
    "gn:name":"Al\u00e9y",
    "gn:population":0,
    "gn:timezone":"Africa/Niamey",
    "iso:country":"NE",
    "wof:name":"Aley",
    "wof:placetype":"locality"
},
  "geometry": {"coordinates":[8.5767,14.334],"type":"Point"}
}