{
  "type": "Feature",
  "properties": {
    "gn:admin1_code":"9.0",
    "gn:asciiname":"Moli Haoussa",
    "gn:country_code":"NE",
    "gn:dem":252,
    "gn:feature_class":"P",
    "gn:feature_code":"PPL",
    "gn:name":"Moli Haoussa",
    "gn:population":0,
    "gn:timezone":"Africa/Niamey",
    "iso:country":"NE",
    "name:und_x_variant":[
        "Moli Haousa",
        "Moli Haoussa"
    ],
    "wof:name":"Moli Haoussa",
    "wof:placetype":"locality"
},
  "geometry": {"coordinates":[2.32021,12.53385],"type":"Point"}
}