{
  "type": "Feature",
  "properties": {
    "gn:admin1_code":"9.0",
    "gn:asciiname":"Bazeyze Koara",
    "gn:country_code":"NE",
    "gn:dem":239,
    "gn:feature_class":"P",
    "gn:feature_code":"PPL",
    "gn:name":"Baz\u00e8yz\u00e8 Koara",
    "gn:population":0,
    "gn:timezone":"Africa/Niamey",
    "iso:country":"NE",
    "name:und_x_variant":[
        "Baz\u00e8\u00efz\u00e9 Kwara",
        "Baz\u00e8yz\u00e8 Koara"
    ],
    "wof:name":"Bazeyze Koara",
    "wof:placetype":"locality"
},
  "geometry": {"coordinates":[2.72399,14.87603],"type":"Point"}
}