{
  "type": "Feature",
  "properties": {
    "gn:admin1_code":"9.0",
    "gn:asciiname":"Dantiandou",
    "gn:country_code":"NE",
    "gn:dem":201,
    "gn:feature_class":"P",
    "gn:feature_code":"PPL",
    "gn:name":"Dantiandou",
    "gn:population":0,
    "gn:timezone":"Africa/Niamey",
    "iso:country":"NE",
    "name:und_x_variant":[
        "Dantyandou",
        "Dochandu",
        "Dentchandou",
        "Dantandiou",
        "Dantiandou"
    ],
    "wof:name":"Dantiandou",
    "wof:placetype":"locality"
},
  "geometry": {"coordinates":[2.7576,13.4118],"type":"Point"}
}