{
  "type": "Feature",
  "properties": {
    "gn:admin1_code":"4.0",
    "gn:asciiname":"Yani Takane",
    "gn:country_code":"NE",
    "gn:dem":408,
    "gn:feature_class":"P",
    "gn:feature_code":"PPL",
    "gn:name":"Yani Takan\u00e9",
    "gn:population":0,
    "gn:timezone":"Africa/Niamey",
    "iso:country":"NE",
    "wof:name":"Yani Takane",
    "wof:placetype":"locality"
},
  "geometry": {"coordinates":[6.8995,14.35442],"type":"Point"}
}