{
  "type": "Feature",
  "properties": {
    "gn:admin1_code":"9.0",
    "gn:asciiname":"Korogoussou",
    "gn:country_code":"NE",
    "gn:dem":221,
    "gn:feature_class":"P",
    "gn:feature_code":"PPL",
    "gn:name":"Korogoussou",
    "gn:population":0,
    "gn:timezone":"Africa/Niamey",
    "iso:country":"NE",
    "name:und_x_variant":[
        "Lilo",
        "Korogoussou"
    ],
    "wof:name":"Korogoussou",
    "wof:placetype":"locality"
},
  "geometry": {"coordinates":[1.62503,13.03751],"type":"Point"}
}