{
  "type": "Feature",
  "properties": {
    "gn:admin1_code":"3.0",
    "gn:asciiname":"Fandou-Dodo",
    "gn:country_code":"NE",
    "gn:dem":212,
    "gn:feature_class":"P",
    "gn:feature_code":"PPL",
    "gn:name":"Fandou-Dodo",
    "gn:population":0,
    "gn:timezone":"Africa/Niamey",
    "iso:country":"NE",
    "wof:name":"Fandou-Dodo",
    "wof:placetype":"locality"
},
  "geometry": {"coordinates":[3.16848,12.76516],"type":"Point"}
}