{
  "type": "Feature",
  "properties": {
    "gn:admin1_code":"7.0",
    "gn:asciiname":"Garin Makad'a",
    "gn:country_code":"NE",
    "gn:dem":408,
    "gn:feature_class":"P",
    "gn:feature_code":"PPL",
    "gn:name":"Garin Makad'\u00e2",
    "gn:population":0,
    "gn:timezone":"Africa/Niamey",
    "iso:country":"NE",
    "name:und_x_variant":[
        "Angoual Hassam",
        "Garin Makad'\u00e2"
    ],
    "wof:name":"Garin Makad'a",
    "wof:placetype":"locality"
},
  "geometry": {"coordinates":[8.96938,13.20846],"type":"Point"}
}