{
  "type": "Feature",
  "properties": {
    "gn:admin1_code":"9.0",
    "gn:asciiname":"Garbey Kourou",
    "gn:country_code":"NE",
    "gn:dem":204,
    "gn:feature_class":"P",
    "gn:feature_code":"PPL",
    "gn:name":"Garbey Kourou",
    "gn:population":0,
    "gn:timezone":"Africa/Niamey",
    "iso:country":"NE",
    "name:und_x_variant":[
        "Garbay-Kourou",
        "Garbey Kourou"
    ],
    "wof:name":"Garbey Kourou",
    "wof:placetype":"locality"
},
  "geometry": {"coordinates":[1.60962,13.74054],"type":"Point"}
}