{
  "type": "Feature",
  "properties": {
    "gn:admin1_code":"3.0",
    "gn:asciiname":"Kounkouroutou Kwara",
    "gn:country_code":"NE",
    "gn:dem":170,
    "gn:feature_class":"P",
    "gn:feature_code":"PPL",
    "gn:name":"Kounkouroutou Kwara",
    "gn:population":0,
    "gn:timezone":"Africa/Niamey",
    "iso:country":"NE",
    "name:und_x_variant":[
        "Kounkouroutou-Koara",
        "Kounkourotou-Koara",
        "Kounkouroutou Kwara"
    ],
    "wof:name":"Kounkouroutou Kwara",
    "wof:placetype":"locality"
},
  "geometry": {"coordinates":[3.06506,12.23746],"type":"Point"}
}