{
  "type": "Feature",
  "properties": {
    "gn:admin1_code":"3.0",
    "gn:asciiname":"Donoudibi",
    "gn:country_code":"NE",
    "gn:dem":190,
    "gn:feature_class":"P",
    "gn:feature_code":"PPL",
    "gn:name":"Donoudibi",
    "gn:population":0,
    "gn:timezone":"Africa/Niamey",
    "iso:country":"NE",
    "name:und_x_variant":[
        "Dodibi",
        "Donoudibi"
    ],
    "wof:name":"Donoudibi",
    "wof:placetype":"locality"
},
  "geometry": {"coordinates":[2.9227,13.0978],"type":"Point"}
}