{
  "type": "Feature",
  "properties": {
    "gn:admin1_code":"7.0",
    "gn:asciiname":"Bagari",
    "gn:country_code":"NE",
    "gn:dem":393,
    "gn:feature_class":"P",
    "gn:feature_code":"PPL",
    "gn:name":"Bagari",
    "gn:population":0,
    "gn:timezone":"Africa/Niamey",
    "iso:country":"NE",
    "wof:name":"Bagari",
    "wof:placetype":"locality"
},
  "geometry": {"coordinates":[8.92383,12.88716],"type":"Point"}
}