{
  "type": "Feature",
  "properties": {
    "gn:admin1_code":"7.0",
    "gn:asciiname":"Ichirnawa Leko",
    "gn:country_code":"NE",
    "gn:dem":458,
    "gn:feature_class":"P",
    "gn:feature_code":"PPL",
    "gn:name":"Ichirnawa L\u00e9ko",
    "gn:population":0,
    "gn:timezone":"Africa/Niamey",
    "iso:country":"NE",
    "name:und_x_variant":[
        "Ichirnawa",
        "Ichirnawa L\u00e9ko"
    ],
    "wof:name":"Ichirnawa Leko",
    "wof:placetype":"locality"
},
  "geometry": {"coordinates":[8.34085,13.53196],"type":"Point"}
}