{
  "type": "Feature",
  "properties": {
    "gn:admin1_code":"2.0",
    "gn:asciiname":"Boulamari Kyari",
    "gn:country_code":"NE",
    "gn:dem":319,
    "gn:feature_class":"P",
    "gn:feature_code":"PPL",
    "gn:name":"Boulamari Kyari",
    "gn:population":0,
    "gn:timezone":"Africa/Niamey",
    "iso:country":"NE",
    "wof:name":"Boulamari Kyari",
    "wof:placetype":"locality"
},
  "geometry": {"coordinates":[12.32385,13.12824],"type":"Point"}
}