{
  "type": "Feature",
  "properties": {
    "gn:admin1_code":"4.0",
    "gn:asciiname":"Na-k'i K'arfi",
    "gn:country_code":"NE",
    "gn:dem":429,
    "gn:feature_class":"P",
    "gn:feature_code":"PPL",
    "gn:name":"Na-k'i K'arf\u00ee",
    "gn:population":0,
    "gn:timezone":"Africa/Niamey",
    "iso:country":"NE",
    "wof:name":"Na-k'i K'arfi",
    "wof:placetype":"locality"
},
  "geometry": {"coordinates":[7.71913,13.64259],"type":"Point"}
}