{
  "type": "Feature",
  "properties": {
    "gn:admin1_code":"3.0",
    "gn:asciiname":"Debe Debe Zarma",
    "gn:country_code":"NE",
    "gn:dem":183,
    "gn:feature_class":"P",
    "gn:feature_code":"PPL",
    "gn:name":"D\u00e9b\u00e9 D\u00e9b\u00e9 Zarma",
    "gn:population":0,
    "gn:timezone":"Africa/Niamey",
    "iso:country":"NE",
    "name:und_x_variant":[
        "Dab\u00e9d\u00e9b\u00e9",
        "D\u00e9b\u00e9 D\u00e9b\u00e9 Dyerma",
        "D\u00e9b\u00e9 D\u00e9b\u00e9 Djerma",
        "D\u00e9b\u00e9 D\u00e9b\u00e9 Zarma"
    ],
    "wof:name":"Debe Debe Zarma",
    "wof:placetype":"locality"
},
  "geometry": {"coordinates":[2.96382,12.78935],"type":"Point"}
}