{
  "type": "Feature",
  "properties": {
    "gn:admin1_code":"7.0",
    "gn:asciiname":"Malam Gantari",
    "gn:country_code":"NE",
    "gn:dem":374,
    "gn:feature_class":"P",
    "gn:feature_code":"PPL",
    "gn:name":"Malam Gantari",
    "gn:population":0,
    "gn:timezone":"Africa/Niamey",
    "iso:country":"NE",
    "wof:name":"Malam Gantari",
    "wof:placetype":"locality"
},
  "geometry": {"coordinates":[10.51864,13.84865],"type":"Point"}
}