{
  "type": "Feature",
  "properties": {
    "gn:admin1_code":"3.0",
    "gn:asciiname":"Ourdao",
    "gn:country_code":"NE",
    "gn:dem":216,
    "gn:feature_class":"P",
    "gn:feature_code":"PPL",
    "gn:name":"Ourdao",
    "gn:population":0,
    "gn:timezone":"Africa/Niamey",
    "iso:country":"NE",
    "wof:name":"Ourdao",
    "wof:placetype":"locality"
},
  "geometry": {"coordinates":[4.06607,13.47317],"type":"Point"}
}