{
  "type": "Feature",
  "properties": {
    "gn:admin1_code":"7.0",
    "gn:asciiname":"Harna",
    "gn:country_code":"NE",
    "gn:dem":440,
    "gn:feature_class":"P",
    "gn:feature_code":"PPL",
    "gn:name":"Harna",
    "gn:population":0,
    "gn:timezone":"Africa/Niamey",
    "iso:country":"NE",
    "name:ceb_x_preferred":[
        "H\u0101rn\u0101"
    ],
    "name:fas_x_preferred":[
        "\u0647\u0627\u0631\u0646\u0627"
    ],
    "name:msa_x_preferred":[
        "Harna"
    ],
    "name:swe_x_preferred":[
        "H\u0101rn\u0101"
    ],
    "wof:name":"Harna",
    "wof:placetype":"locality"
},
  "geometry": {"coordinates":[8.45889,14.33558],"type":"Point"}
}