{
  "type": "Feature",
  "properties": {
    "gn:admin1_code":"7.0",
    "gn:asciiname":"Harna",
    "gn:country_code":"NE",
    "gn:dem":440,
    "gn:feature_class":"P",
    "gn:feature_code":"PPL",
    "gn:name":"Harna",
    "gn:population":0,
    "gn:timezone":"Africa/Niamey",
    "iso:country":"NE",
    "wof:name":"Harna",
    "wof:placetype":"locality"
},
  "geometry": {"coordinates":[8.45889,14.33558],"type":"Point"}
}