{
  "type": "Feature",
  "properties": {
    "gn:admin1_code":"4.0",
    "gn:asciiname":"Afaram",
    "gn:country_code":"NE",
    "gn:dem":481,
    "gn:feature_class":"P",
    "gn:feature_code":"PPL",
    "gn:name":"Afaram",
    "gn:population":0,
    "gn:timezone":"Africa/Niamey",
    "iso:country":"NE",
    "wof:name":"Afaram",
    "wof:placetype":"locality"
},
  "geometry": {"coordinates":[8.33231,13.45891],"type":"Point"}
}