{
  "type": "Feature",
  "properties": {
    "gn:admin1_code":"6.0",
    "gn:asciiname":"Gabara",
    "gn:country_code":"NE",
    "gn:dem":421,
    "gn:feature_class":"P",
    "gn:feature_code":"PPL",
    "gn:name":"Gabara",
    "gn:population":0,
    "gn:timezone":"Africa/Niamey",
    "iso:country":"NE",
    "name:jpn_x_preferred":[
        "\u30ac\u30d0\u30e9"
    ],
    "name:nld_x_preferred":[
        "Gabara"
    ],
    "name:por_x_preferred":[
        "Gabara"
    ],
    "wof:name":"Gabara",
    "wof:placetype":"locality"
},
  "geometry": {"coordinates":[6.13967,14.53527],"type":"Point"}
}