{
  "type": "Feature",
  "properties": {
    "gn:admin1_code":"7.0",
    "gn:asciiname":"Gouagourzo",
    "gn:country_code":"NE",
    "gn:dem":495,
    "gn:feature_class":"P",
    "gn:feature_code":"PPL",
    "gn:name":"Gouagourzo",
    "gn:population":0,
    "gn:timezone":"Africa/Niamey",
    "iso:country":"NE",
    "wof:name":"Gouagourzo",
    "wof:placetype":"locality"
},
  "geometry": {"coordinates":[8.44087,14.73269],"type":"Point"}
}