{
  "type": "Feature",
  "properties": {
    "gn:admin1_code":"9.0",
    "gn:asciiname":"Tondyakangue",
    "gn:country_code":"NE",
    "gn:dem":251,
    "gn:feature_class":"P",
    "gn:feature_code":"PPL",
    "gn:name":"Tondyakangu\u00e9",
    "gn:population":0,
    "gn:timezone":"Africa/Niamey",
    "iso:country":"NE",
    "wof:name":"Tondyakangue",
    "wof:placetype":"locality"
},
  "geometry": {"coordinates":[0.93644,13.85064],"type":"Point"}
}