{
  "type": "Feature",
  "properties": {
    "gn:admin1_code":"7.0",
    "gn:asciiname":"Kouabo",
    "gn:country_code":"NE",
    "gn:dem":459,
    "gn:feature_class":"P",
    "gn:feature_code":"PPL",
    "gn:name":"Kouabo",
    "gn:population":0,
    "gn:timezone":"Africa/Niamey",
    "iso:country":"NE",
    "name:und_x_variant":[
        "Kwabo",
        "Kouabo"
    ],
    "wof:name":"Kouabo",
    "wof:placetype":"locality"
},
  "geometry": {"coordinates":[8.59384,13.08034],"type":"Point"}
}