{
  "type": "Feature",
  "properties": {
    "gn:admin1_code":"4.0",
    "gn:asciiname":"Akali",
    "gn:country_code":"NE",
    "gn:dem":321,
    "gn:feature_class":"P",
    "gn:feature_code":"PPL",
    "gn:name":"Akali",
    "gn:population":0,
    "gn:timezone":"Africa/Niamey",
    "iso:country":"NE",
    "name:mal_x_preferred":[
        "\u0d05\u0d15\u0d3e\u0d32\u0d3f"
    ],
    "wof:name":"Akali",
    "wof:placetype":"locality"
},
  "geometry": {"coordinates":[6.60041,13.60354],"type":"Point"}
}