{
  "type": "Feature",
  "properties": {
    "gn:admin1_code":"8.0",
    "gn:asciiname":"Tafa Kouara",
    "gn:cc2":"NE",
    "gn:country_code":"NE",
    "gn:dem":189,
    "gn:feature_class":"P",
    "gn:feature_code":"PPL",
    "gn:name":"Tafa Kouara",
    "gn:population":0,
    "gn:timezone":"Africa/Niamey",
    "iso:country":"NE",
    "name:und_x_variant":[
        "Tafa-Koara",
        "Tafa Kwara",
        "Tafa Kouara"
    ],
    "wof:name":"Tafa Kouara",
    "wof:placetype":"locality"
},
  "geometry": {"coordinates":[2.1675,13.45694],"type":"Point"}
}