{
  "type": "Feature",
  "properties": {
    "gn:admin1_code":"8.0",
    "gn:asciiname":"Assanni",
    "gn:country_code":"NE",
    "gn:dem":197,
    "gn:feature_class":"P",
    "gn:feature_code":"PPL",
    "gn:name":"Assanni",
    "gn:population":0,
    "gn:timezone":"Africa/Niamey",
    "iso:country":"NE",
    "wof:name":"Assanni",
    "wof:placetype":"locality"
},
  "geometry": {"coordinates":[1.55,13.86667],"type":"Point"}
}