{
  "type": "Feature",
  "properties": {
    "gn:admin1_code":"4.0",
    "gn:asciiname":"Zaourami",
    "gn:country_code":"NE",
    "gn:dem":375,
    "gn:feature_class":"P",
    "gn:feature_code":"PPL",
    "gn:name":"Zaourami",
    "gn:population":0,
    "gn:timezone":"Africa/Niamey",
    "iso:country":"NE",
    "name:und_x_variant":[
        "Gidan Zaourami",
        "Guidan Zaourami",
        "Zaourami"
    ],
    "wof:name":"Zaourami",
    "wof:placetype":"locality"
},
  "geometry": {"coordinates":[7.12086,13.68093],"type":"Point"}
}