{
  "type": "Feature",
  "properties": {
    "gn:admin1_code":"2.0",
    "gn:asciiname":"Ngoudo Boulam",
    "gn:country_code":"NE",
    "gn:dem":284,
    "gn:feature_class":"P",
    "gn:feature_code":"PPL",
    "gn:name":"Ngoudo Boulam",
    "gn:population":0,
    "gn:timezone":"Africa/Niamey",
    "iso:country":"NE",
    "name:und_x_variant":[
        "Kouray\u00e9",
        "Ngoudo Boulam"
    ],
    "wof:name":"Ngoudo Boulam",
    "wof:placetype":"locality"
},
  "geometry": {"coordinates":[13.43302,14.34373],"type":"Point"}
}