{
  "type": "Feature",
  "properties": {
    "gn:admin1_code":"4.0",
    "gn:asciiname":"Ajia Mijiniawa",
    "gn:country_code":"NE",
    "gn:dem":357,
    "gn:feature_class":"P",
    "gn:feature_code":"PPL",
    "gn:name":"Ajia Mijiniawa",
    "gn:population":0,
    "gn:timezone":"Africa/Niamey",
    "iso:country":"NE",
    "wof:name":"Ajia Mijiniawa",
    "wof:placetype":"locality"
},
  "geometry": {"coordinates":[6.97933,13.53681],"type":"Point"}
}