{
  "type": "Feature",
  "properties": {
    "gn:admin1_code":"9.0",
    "gn:asciiname":"Dingoaba",
    "gn:country_code":"NE",
    "gn:dem":262,
    "gn:feature_class":"P",
    "gn:feature_code":"PPL",
    "gn:name":"Dingoaba",
    "gn:population":0,
    "gn:timezone":"Africa/Niamey",
    "iso:country":"NE",
    "name:und_x_variant":[
        "Dourobia",
        "Dingoaba"
    ],
    "wof:name":"Dingoaba",
    "wof:placetype":"locality"
},
  "geometry": {"coordinates":[0.85141,14.04707],"type":"Point"}
}