{
  "type": "Feature",
  "properties": {
    "gn:admin1_code":"3.0",
    "gn:asciiname":"Kogorou",
    "gn:country_code":"NE",
    "gn:dem":246,
    "gn:feature_class":"P",
    "gn:feature_code":"PPL",
    "gn:name":"Kogorou",
    "gn:population":0,
    "gn:timezone":"Africa/Niamey",
    "iso:country":"NE",
    "wof:name":"Kogorou",
    "wof:placetype":"locality"
},
  "geometry": {"coordinates":[3.1674,13.7152],"type":"Point"}
}