{
  "type": "Feature",
  "properties": {
    "gn:admin1_code":"4.0",
    "gn:asciiname":"Zagavoa",
    "gn:country_code":"NE",
    "gn:dem":361,
    "gn:feature_class":"P",
    "gn:feature_code":"PPL",
    "gn:name":"Zagavoa",
    "gn:population":0,
    "gn:timezone":"Africa/Niamey",
    "iso:country":"NE",
    "name:und_x_variant":[
        "Zagawa",
        "Zagavoa"
    ],
    "wof:name":"Zagavoa",
    "wof:placetype":"locality"
},
  "geometry": {"coordinates":[6.92535,13.94212],"type":"Point"}
}