{
  "type": "Feature",
  "properties": {
    "gn:admin1_code":"4.0",
    "gn:asciiname":"Karabaguie",
    "gn:country_code":"NE",
    "gn:dem":406,
    "gn:feature_class":"P",
    "gn:feature_code":"PPL",
    "gn:name":"Karabagui\u00e9",
    "gn:population":0,
    "gn:timezone":"Africa/Niamey",
    "iso:country":"NE",
    "wof:name":"Karabaguie",
    "wof:placetype":"locality"
},
  "geometry": {"coordinates":[7.89585,13.57019],"type":"Point"}
}