{
  "type": "Feature",
  "properties": {
    "gn:admin1_code":"3.0",
    "gn:asciiname":"Kountoudeye",
    "gn:country_code":"NE",
    "gn:dem":218,
    "gn:feature_class":"P",
    "gn:feature_code":"PPL",
    "gn:name":"Kountoud\u00e8ye",
    "gn:population":0,
    "gn:timezone":"Africa/Niamey",
    "iso:country":"NE",
    "name:und_x_variant":[
        "Kountoudey",
        "Kountoud\u00e8ye"
    ],
    "wof:name":"Kountoudeye",
    "wof:placetype":"locality"
},
  "geometry": {"coordinates":[3.2883,13.0468],"type":"Point"}
}