{
  "type": "Feature",
  "properties": {
    "gn:admin1_code":"4.0",
    "gn:asciiname":"Gaja",
    "gn:country_code":"NE",
    "gn:dem":322,
    "gn:feature_class":"P",
    "gn:feature_code":"PPL",
    "gn:name":"Gaja",
    "gn:population":0,
    "gn:timezone":"Africa/Niamey",
    "iso:country":"NE",
    "name:ori_x_preferred":[
        "\u0b17\u0b1c\u0b3e"
    ],
    "wof:name":"Gaja",
    "wof:placetype":"locality"
},
  "geometry": {"coordinates":[6.50689,13.59117],"type":"Point"}
}