{
  "type": "Feature",
  "properties": {
    "gn:admin1_code":"3.0",
    "gn:asciiname":"Kolfa",
    "gn:country_code":"NE",
    "gn:dem":235,
    "gn:feature_class":"P",
    "gn:feature_code":"PPL",
    "gn:name":"Kolfa",
    "gn:population":0,
    "gn:timezone":"Africa/Lagos",
    "iso:country":"NE",
    "wof:name":"Kolfa",
    "wof:placetype":"locality"
},
  "geometry": {"coordinates":[4.351,13.59983],"type":"Point"}
}