{
  "type": "Feature",
  "properties": {
    "gn:admin1_code":"2.0",
    "gn:asciiname":"Ngorgalo",
    "gn:country_code":"NE",
    "gn:dem":334,
    "gn:feature_class":"P",
    "gn:feature_code":"PPL",
    "gn:name":"Ngorgalo",
    "gn:population":0,
    "gn:timezone":"Africa/Niamey",
    "iso:country":"NE",
    "wof:name":"Ngorgalo",
    "wof:placetype":"locality"
},
  "geometry": {"coordinates":[12.09949,13.57219],"type":"Point"}
}