{
  "type": "Feature",
  "properties": {
    "gn:admin1_code":"3.0",
    "gn:asciiname":"Tounga Bahaoche",
    "gn:country_code":"NE",
    "gn:dem":186,
    "gn:feature_class":"P",
    "gn:feature_code":"PPL",
    "gn:name":"Tounga Bahaoch\u00e9",
    "gn:population":0,
    "gn:timezone":"Africa/Niamey",
    "iso:country":"NE",
    "wof:name":"Tounga Bahaoche",
    "wof:placetype":"locality"
},
  "geometry": {"coordinates":[3.44236,12.39701],"type":"Point"}
}