{
  "type": "Feature",
  "properties": {
    "gn:admin1_code":"3.0",
    "gn:asciiname":"Gardie",
    "gn:country_code":"NE",
    "gn:dem":259,
    "gn:feature_class":"P",
    "gn:feature_code":"PPL",
    "gn:name":"Gardi\u00e9",
    "gn:population":0,
    "gn:timezone":"Africa/Niamey",
    "iso:country":"NE",
    "name:swe_x_preferred":[
        "Gardie"
    ],
    "wof:name":"Gardie",
    "wof:placetype":"locality"
},
  "geometry": {"coordinates":[3.59451,13.58273],"type":"Point"}
}