{
  "type": "Feature",
  "properties": {
    "gn:admin1_code":"9.0",
    "gn:asciiname":"Koka",
    "gn:country_code":"NE",
    "gn:dem":239,
    "gn:feature_class":"P",
    "gn:feature_code":"PPL",
    "gn:name":"Koka",
    "gn:population":0,
    "gn:timezone":"Africa/Niamey",
    "iso:country":"NE",
    "wof:name":"Koka",
    "wof:placetype":"locality"
},
  "geometry": {"coordinates":[1.7428,13.4105],"type":"Point"}
}