{
  "type": "Feature",
  "properties": {
    "gn:admin1_code":"6.0",
    "gn:asciiname":"Tabanni",
    "gn:country_code":"NE",
    "gn:dem":289,
    "gn:feature_class":"P",
    "gn:feature_code":"PPL",
    "gn:name":"Tabanni",
    "gn:population":0,
    "gn:timezone":"Africa/Niamey",
    "iso:country":"NE",
    "wof:name":"Tabanni",
    "wof:placetype":"locality"
},
  "geometry": {"coordinates":[5.3315,13.81084],"type":"Point"}
}