{
  "type": "Feature",
  "properties": {
    "gn:admin1_code":"7.0",
    "gn:asciiname":"Toumbi",
    "gn:country_code":"NE",
    "gn:dem":423,
    "gn:feature_class":"P",
    "gn:feature_code":"PPL",
    "gn:name":"Toumbi",
    "gn:population":0,
    "gn:timezone":"Africa/Niamey",
    "iso:country":"NE",
    "wof:name":"Toumbi",
    "wof:placetype":"locality"
},
  "geometry": {"coordinates":[8.00901,14.69677],"type":"Point"}
}