{
  "type": "Feature",
  "properties": {
    "gn:admin1_code":"9.0",
    "gn:asciiname":"Boura",
    "gn:country_code":"NE",
    "gn:dem":236,
    "gn:feature_class":"P",
    "gn:feature_code":"PPL",
    "gn:name":"Boura",
    "gn:population":0,
    "gn:timezone":"Africa/Niamey",
    "iso:country":"NE",
    "name:ceb_x_preferred":[
        "Boura"
    ],
    "name:fra_x_preferred":[
        "Boura"
    ],
    "name:ita_x_preferred":[
        "Boura"
    ],
    "name:swe_x_preferred":[
        "Boura"
    ],
    "wof:name":"Boura",
    "wof:placetype":"locality"
},
  "geometry": {"coordinates":[1.04083,13.9007],"type":"Point"}
}