{
  "type": "Feature",
  "properties": {
    "gn:admin1_code":"7.0",
    "gn:asciiname":"Nguel Waye",
    "gn:country_code":"NE",
    "gn:dem":354,
    "gn:feature_class":"P",
    "gn:feature_code":"PPL",
    "gn:name":"Ngu\u00e8l Waye",
    "gn:population":0,
    "gn:timezone":"Africa/Niamey",
    "iso:country":"NE",
    "wof:name":"Nguel Waye",
    "wof:placetype":"locality"
},
  "geometry": {"coordinates":[11.03176,14.14426],"type":"Point"}
}