{
  "type": "Feature",
  "properties": {
    "gn:admin1_code":"3.0",
    "gn:asciiname":"Tounga Magaji",
    "gn:country_code":"NE",
    "gn:dem":171,
    "gn:feature_class":"P",
    "gn:feature_code":"PPL",
    "gn:name":"Tounga Magaji",
    "gn:population":0,
    "gn:timezone":"Africa/Niamey",
    "iso:country":"NE",
    "name:und_x_variant":[
        "Tungan Magaji",
        "Tounga Magaji"
    ],
    "wof:name":"Tounga Magaji",
    "wof:placetype":"locality"
},
  "geometry": {"coordinates":[3.58172,11.95091],"type":"Point"}
}