{
  "type": "Feature",
  "properties": {
    "gn:admin1_code":"4.0",
    "gn:asciiname":"Farga",
    "gn:country_code":"NE",
    "gn:dem":424,
    "gn:feature_class":"P",
    "gn:feature_code":"PPL",
    "gn:name":"Farg\u00e2",
    "gn:population":0,
    "gn:timezone":"Africa/Niamey",
    "iso:country":"NE",
    "wof:name":"Farga",
    "wof:placetype":"locality"
},
  "geometry": {"coordinates":[7.41742,13.39338],"type":"Point"}
}