{
  "type": "Feature",
  "properties": {
    "gn:admin1_code":"3.0",
    "gn:asciiname":"Yeda",
    "gn:country_code":"NE",
    "gn:dem":253,
    "gn:feature_class":"P",
    "gn:feature_code":"PPL",
    "gn:name":"Y\u00e9da",
    "gn:population":0,
    "gn:timezone":"Africa/Niamey",
    "iso:country":"NE",
    "name:ceb_x_preferred":[
        "Yeda"
    ],
    "name:deu_x_preferred":[
        "Yeda"
    ],
    "name:swe_x_preferred":[
        "Yeda"
    ],
    "name:und_x_variant":[
        "H\u00e9da",
        "Y\u00e9da"
    ],
    "wof:name":"Yeda",
    "wof:placetype":"locality"
},
  "geometry": {"coordinates":[2.7639,13.1948],"type":"Point"}
}