{
  "type": "Feature",
  "properties": {
    "gn:admin1_code":"7.0",
    "gn:asciiname":"Niango Kanamdi",
    "gn:country_code":"NE",
    "gn:dem":409,
    "gn:feature_class":"P",
    "gn:feature_code":"PPL",
    "gn:name":"Niango Kanamdi",
    "gn:population":0,
    "gn:timezone":"Africa/Niamey",
    "iso:country":"NE",
    "wof:name":"Niango Kanamdi",
    "wof:placetype":"locality"
},
  "geometry": {"coordinates":[10.6138,14.3518],"type":"Point"}
}