{
  "type": "Feature",
  "properties": {
    "gn:admin1_code":"7.0",
    "gn:asciiname":"Ngel Kefale",
    "gn:country_code":"NE",
    "gn:dem":360,
    "gn:feature_class":"P",
    "gn:feature_code":"PPL",
    "gn:name":"Ngel K\u00e9fal\u00e9",
    "gn:population":0,
    "gn:timezone":"Africa/Niamey",
    "iso:country":"NE",
    "wof:name":"Ngel Kefale",
    "wof:placetype":"locality"
},
  "geometry": {"coordinates":[10.68011,13.76712],"type":"Point"}
}