{
  "type": "Feature",
  "properties": {
    "gn:admin1_code":"7.0",
    "gn:asciiname":"Daouaraya",
    "gn:country_code":"NE",
    "gn:dem":480,
    "gn:feature_class":"P",
    "gn:feature_code":"PPL",
    "gn:name":"Daouaraya",
    "gn:population":0,
    "gn:timezone":"Africa/Niamey",
    "iso:country":"NE",
    "wof:name":"Daouaraya",
    "wof:placetype":"locality"
},
  "geometry": {"coordinates":[9.1479,14.4412],"type":"Point"}
}