{
  "type": "Feature",
  "properties": {
    "gn:admin1_code":"6.0",
    "gn:asciiname":"Magaya",
    "gn:country_code":"NE",
    "gn:dem":362,
    "gn:feature_class":"P",
    "gn:feature_code":"PPL",
    "gn:name":"Magaya",
    "gn:population":0,
    "gn:timezone":"Africa/Niamey",
    "iso:country":"NE",
    "wof:name":"Magaya",
    "wof:placetype":"locality"
},
  "geometry": {"coordinates":[6.38695,14.02929],"type":"Point"}
}