{
  "type": "Feature",
  "properties": {
    "gn:admin1_code":"2.0",
    "gn:asciiname":"Koseiri",
    "gn:country_code":"NE",
    "gn:dem":345,
    "gn:feature_class":"P",
    "gn:feature_code":"PPL",
    "gn:name":"Kos\u00e9iri",
    "gn:population":0,
    "gn:timezone":"Africa/Niamey",
    "iso:country":"NE",
    "wof:name":"Koseiri",
    "wof:placetype":"locality"
},
  "geometry": {"coordinates":[11.3994,13.6981],"type":"Point"}
}