{
  "type": "Feature",
  "properties": {
    "gn:admin1_code":"6.0",
    "gn:asciiname":"Kile",
    "gn:country_code":"NE",
    "gn:dem":492,
    "gn:feature_class":"P",
    "gn:feature_code":"PPL",
    "gn:name":"Kil\u00e9",
    "gn:population":0,
    "gn:timezone":"Africa/Niamey",
    "iso:country":"NE",
    "name:ara_x_preferred":[
        "\u0643\u0627\u064a\u0644"
    ],
    "name:cat_x_preferred":[
        "Kile"
    ],
    "name:deu_x_preferred":[
        "Kile"
    ],
    "name:eus_x_preferred":[
        "Kile"
    ],
    "name:fas_x_preferred":[
        "\u06a9\u0627\u06cc\u0644"
    ],
    "name:fra_x_preferred":[
        "Kile"
    ],
    "name:ita_x_preferred":[
        "Kile"
    ],
    "name:jpn_x_preferred":[
        "Kile"
    ],
    "name:pol_x_preferred":[
        "Kile"
    ],
    "name:por_x_preferred":[
        "Kile"
    ],
    "name:rus_x_preferred":[
        "Kile"
    ],
    "name:spa_x_preferred":[
        "Kile"
    ],
    "name:swe_x_preferred":[
        "Kile"
    ],
    "name:tur_x_preferred":[
        "Kile"
    ],
    "name:ukr_x_preferred":[
        "Kile"
    ],
    "name:zho_x_preferred":[
        "Kile"
    ],
    "wof:name":"Kile",
    "wof:placetype":"locality"
},
  "geometry": {"coordinates":[5.8486,14.5213],"type":"Point"}
}