{
  "type": "Feature",
  "properties": {
    "gn:admin1_code":"3.0",
    "gn:asciiname":"Kobio",
    "gn:country_code":"NE",
    "gn:dem":259,
    "gn:feature_class":"P",
    "gn:feature_code":"PPL",
    "gn:name":"Kobio",
    "gn:population":0,
    "gn:timezone":"Africa/Niamey",
    "iso:country":"NE",
    "wof:name":"Kobio",
    "wof:placetype":"locality"
},
  "geometry": {"coordinates":[3.83806,12.68943],"type":"Point"}
}