{
  "type": "Feature",
  "properties": {
    "gn:admin1_code":"9.0",
    "gn:asciiname":"Tientiergou",
    "gn:country_code":"NE",
    "gn:dem":222,
    "gn:feature_class":"P",
    "gn:feature_code":"PPL",
    "gn:name":"Tientiergou",
    "gn:population":0,
    "gn:timezone":"Africa/Niamey",
    "iso:country":"NE",
    "name:und_x_variant":[
        "Tient\u00e9rogou",
        "Tient\u00e9rougou",
        "Tiantargou",
        "Tientergu",
        "Tientergou",
        "Tientiergou"
    ],
    "wof:name":"Tientiergou",
    "wof:placetype":"locality"
},
  "geometry": {"coordinates":[2.1705,13.0348],"type":"Point"}
}