{
  "type": "Feature",
  "properties": {
    "gn:admin1_code":"4.0",
    "gn:asciiname":"Eloum",
    "gn:country_code":"NE",
    "gn:dem":437,
    "gn:feature_class":"P",
    "gn:feature_code":"PPL",
    "gn:name":"\u00c9loum",
    "gn:population":0,
    "gn:timezone":"Africa/Niamey",
    "iso:country":"NE",
    "wof:name":"Eloum",
    "wof:placetype":"locality"
},
  "geometry": {"coordinates":[7.50644,13.39014],"type":"Point"}
}