{
  "type": "Feature",
  "properties": {
    "gn:admin1_code":"4.0",
    "gn:asciiname":"Chawey",
    "gn:country_code":"NE",
    "gn:dem":370,
    "gn:feature_class":"P",
    "gn:feature_code":"PPL",
    "gn:name":"Chawey",
    "gn:population":0,
    "gn:timezone":"Africa/Niamey",
    "iso:country":"NE",
    "wof:name":"Chawey",
    "wof:placetype":"locality"
},
  "geometry": {"coordinates":[6.75194,13.27421],"type":"Point"}
}