{
  "type": "Feature",
  "properties": {
    "gn:admin1_code":"4.0",
    "gn:asciiname":"Tchadoua",
    "gn:country_code":"NE",
    "gn:dem":396,
    "gn:feature_class":"P",
    "gn:feature_code":"PPL",
    "gn:name":"Tchadoua",
    "gn:population":0,
    "gn:timezone":"Africa/Niamey",
    "iso:country":"NE",
    "name:deu_x_preferred":[
        "Tchadoua"
    ],
    "name:ita_x_preferred":[
        "Tchadoua"
    ],
    "name:msa_x_preferred":[
        "Tchadoua"
    ],
    "name:ron_x_preferred":[
        "Tchadoua"
    ],
    "name:spa_x_preferred":[
        "Tchadoua"
    ],
    "name:und_x_variant":[
        "Tchadwa",
        "Tchadaoua"
    ],
    "wof:name":"Tchadoua",
    "wof:placetype":"locality"
},
  "geometry": {"coordinates":[7.44614,13.54643],"type":"Point"}
}