{
  "type": "Feature",
  "properties": {
    "gn:admin1_code":"3.0",
    "gn:asciiname":"Kanare",
    "gn:country_code":"NE",
    "gn:dem":222,
    "gn:feature_class":"P",
    "gn:feature_code":"PPL",
    "gn:name":"Kanar\u00e9",
    "gn:population":0,
    "gn:timezone":"Africa/Niamey",
    "iso:country":"NE",
    "wof:name":"Kanare",
    "wof:placetype":"locality"
},
  "geometry": {"coordinates":[2.7637,13.2445],"type":"Point"}
}