{
  "type": "Feature",
  "properties": {
    "gn:admin1_code":"9.0",
    "gn:asciiname":"Djiliki Foulbe",
    "gn:country_code":"NE",
    "gn:dem":210,
    "gn:feature_class":"P",
    "gn:feature_code":"PPL",
    "gn:name":"Djiliki Foulb\u00e9",
    "gn:population":0,
    "gn:timezone":"Africa/Niamey",
    "iso:country":"NE",
    "name:und_x_variant":[
        "Djiliki",
        "Guilouki",
        "Djiliki Foulb\u00e9"
    ],
    "wof:name":"Djiliki Foulbe",
    "wof:placetype":"locality"
},
  "geometry": {"coordinates":[1.84525,13.09973],"type":"Point"}
}