{
  "type": "Feature",
  "properties": {
    "gn:admin1_code":"3.0",
    "gn:asciiname":"Serkin Noma Kwara",
    "gn:country_code":"NE",
    "gn:dem":199,
    "gn:feature_class":"P",
    "gn:feature_code":"PPL",
    "gn:name":"Serkin Noma Kwara",
    "gn:population":0,
    "gn:timezone":"Africa/Niamey",
    "iso:country":"NE",
    "name:und_x_variant":[
        "Serkine-Noma-Koara",
        "Serkin Noma Kwara"
    ],
    "wof:name":"Serkin Noma Kwara",
    "wof:placetype":"locality"
},
  "geometry": {"coordinates":[3.14779,12.21702],"type":"Point"}
}