{
  "type": "Feature",
  "properties": {
    "gn:admin1_code":"7.0",
    "gn:asciiname":"May Yak'i",
    "gn:country_code":"NE",
    "gn:dem":424,
    "gn:feature_class":"P",
    "gn:feature_code":"PPL",
    "gn:name":"May Y\u00e2k'i",
    "gn:population":0,
    "gn:timezone":"Africa/Niamey",
    "iso:country":"NE",
    "name:und_x_variant":[
        "Mayaki",
        "May Y\u00e2k'i"
    ],
    "wof:name":"May Yak'i",
    "wof:placetype":"locality"
},
  "geometry": {"coordinates":[8.68932,12.95995],"type":"Point"}
}