{
  "type": "Feature",
  "properties": {
    "gn:admin1_code":"2.0",
    "gn:asciiname":"Dabogoum-Kayawa",
    "gn:country_code":"NE",
    "gn:dem":307,
    "gn:feature_class":"P",
    "gn:feature_code":"PPL",
    "gn:name":"Dabogoum-Kayawa",
    "gn:population":0,
    "gn:timezone":"Africa/Niamey",
    "iso:country":"NE",
    "wof:name":"Dabogoum-Kayawa",
    "wof:placetype":"locality"
},
  "geometry": {"coordinates":[12.52668,13.21404],"type":"Point"}
}