{
  "type": "Feature",
  "properties": {
    "gn:admin1_code":"9.0",
    "gn:asciiname":"Bada",
    "gn:country_code":"NE",
    "gn:dem":247,
    "gn:feature_class":"P",
    "gn:feature_code":"PPL",
    "gn:name":"Bada",
    "gn:population":0,
    "gn:timezone":"Africa/Niamey",
    "iso:country":"NE",
    "name:ara_x_preferred":[
        "\u0628\u0627\u062f\u0627"
    ],
    "name:aze_x_preferred":[
        "Bada"
    ],
    "name:ces_x_preferred":[
        "Bada"
    ],
    "name:ckb_x_preferred":[
        "\u0628\u0627\u062f\u0627"
    ],
    "name:deu_x_preferred":[
        "Bada"
    ],
    "name:fas_x_preferred":[
        "\u0628\u0627\u062f\u0627"
    ],
    "name:fin_x_preferred":[
        "Bada"
    ],
    "name:fra_x_preferred":[
        "Bada"
    ],
    "name:heb_x_preferred":[
        "Bada"
    ],
    "name:hun_x_preferred":[
        "Bada"
    ],
    "name:hye_x_preferred":[
        "\u0532\u0561\u0564\u0561"
    ],
    "name:ind_x_preferred":[
        "Samsung bada"
    ],
    "name:ita_x_preferred":[
        "Bada"
    ],
    "name:jpn_x_preferred":[
        "Bada"
    ],
    "name:kor_x_preferred":[
        "\ubc14\ub2e4"
    ],
    "name:nep_x_preferred":[
        "\u092c\u0921\u093e"
    ],
    "name:nld_x_preferred":[
        "Bada"
    ],
    "name:pol_x_preferred":[
        "Bada"
    ],
    "name:por_x_preferred":[
        "Bada"
    ],
    "name:rus_x_preferred":[
        "Bada"
    ],
    "name:spa_x_preferred":[
        "Bada"
    ],
    "name:swe_x_preferred":[
        "Bada"
    ],
    "name:tam_x_preferred":[
        "\u0baa\u0b9f\u0bbe"
    ],
    "name:tha_x_preferred":[
        "\u0e1a\u0e32\u0e14\u0e32"
    ],
    "name:tur_x_preferred":[
        "Bada"
    ],
    "name:ukr_x_preferred":[
        "Bada"
    ],
    "name:urd_x_preferred":[
        "\u0628\u0627\u0688\u0627"
    ],
    "name:vie_x_preferred":[
        "Bada"
    ],
    "name:zho_x_preferred":[
        "Bada"
    ],
    "wof:name":"Bada",
    "wof:placetype":"locality"
},
  "geometry": {"coordinates":[3.575,14.7922],"type":"Point"}
}