{
  "type": "Feature",
  "properties": {
    "gn:admin1_code":"9.0",
    "gn:asciiname":"Ko Kouarey Zarma",
    "gn:country_code":"NE",
    "gn:dem":236,
    "gn:feature_class":"P",
    "gn:feature_code":"PPL",
    "gn:name":"Ko Kouarey Zarma",
    "gn:population":0,
    "gn:timezone":"Africa/Niamey",
    "iso:country":"NE",
    "name:und_x_variant":[
        "Kokoar\u00e9-Djerma",
        "Kokwar\u00e9 Djerma",
        "Ko Kouarey Zarma"
    ],
    "wof:name":"Ko Kouarey Zarma",
    "wof:placetype":"locality"
},
  "geometry": {"coordinates":[2.4501,13.4137],"type":"Point"}
}