{
  "type": "Feature",
  "properties": {
    "gn:admin1_code":"9.0",
    "gn:asciiname":"Diambala",
    "gn:country_code":"NE",
    "gn:dem":215,
    "gn:feature_class":"P",
    "gn:feature_code":"PPL",
    "gn:name":"Diambala",
    "gn:population":0,
    "gn:timezone":"Africa/Niamey",
    "iso:country":"NE",
    "name:und_x_variant":[
        "Diombala",
        "Dangala",
        "Diambala"
    ],
    "wof:name":"Diambala",
    "wof:placetype":"locality"
},
  "geometry": {"coordinates":[1.29965,14.31376],"type":"Point"}
}