{
  "type": "Feature",
  "properties": {
    "gn:admin1_code":"9.0",
    "gn:asciiname":"Tiouridi",
    "gn:country_code":"NE",
    "gn:dem":222,
    "gn:feature_class":"P",
    "gn:feature_code":"PPL",
    "gn:name":"Tiouridi",
    "gn:population":0,
    "gn:timezone":"Africa/Niamey",
    "iso:country":"NE",
    "name:und_x_variant":[
        "Tyourio",
        "Tiouridi"
    ],
    "wof:name":"Tiouridi",
    "wof:placetype":"locality"
},
  "geometry": {"coordinates":[1.77554,13.30772],"type":"Point"}
}