{
  "type": "Feature",
  "properties": {
    "gn:admin1_code":"4.0",
    "gn:asciiname":"Dargaza",
    "gn:country_code":"NE",
    "gn:dem":447,
    "gn:feature_class":"P",
    "gn:feature_code":"PPL",
    "gn:name":"Dargaza",
    "gn:population":0,
    "gn:timezone":"Africa/Niamey",
    "iso:country":"NE",
    "wof:name":"Dargaza",
    "wof:placetype":"locality"
},
  "geometry": {"coordinates":[8.33226,13.84853],"type":"Point"}
}