{
  "type": "Feature",
  "properties": {
    "gn:admin1_code":"2.0",
    "gn:asciiname":"Kabasia",
    "gn:country_code":"NE",
    "gn:dem":339,
    "gn:feature_class":"P",
    "gn:feature_code":"PPL",
    "gn:name":"Kabasia",
    "gn:population":0,
    "gn:timezone":"Africa/Niamey",
    "iso:country":"NE",
    "wof:name":"Kabasia",
    "wof:placetype":"locality"
},
  "geometry": {"coordinates":[11.7014,13.6283],"type":"Point"}
}