{
  "type": "Feature",
  "properties": {
    "gn:admin1_code":"2.0",
    "gn:asciiname":"Likaridi",
    "gn:country_code":"NE",
    "gn:dem":343,
    "gn:feature_class":"P",
    "gn:feature_code":"PPL",
    "gn:name":"Likaridi",
    "gn:population":0,
    "gn:timezone":"Africa/Niamey",
    "iso:country":"NE",
    "wof:name":"Likaridi",
    "wof:placetype":"locality"
},
  "geometry": {"coordinates":[11.0761,13.3827],"type":"Point"}
}