{
  "type": "Feature",
  "properties": {
    "gn:admin1_code":"4.0",
    "gn:asciiname":"Daboubou",
    "gn:country_code":"NE",
    "gn:dem":435,
    "gn:feature_class":"P",
    "gn:feature_code":"PPL",
    "gn:name":"Daboubou",
    "gn:population":0,
    "gn:timezone":"Africa/Niamey",
    "iso:country":"NE",
    "wof:name":"Daboubou",
    "wof:placetype":"locality"
},
  "geometry": {"coordinates":[7.76079,14.3882],"type":"Point"}
}