{
  "type": "Feature",
  "properties": {
    "gn:admin1_code":"4.0",
    "gn:asciiname":"Kondala",
    "gn:country_code":"NE",
    "gn:dem":440,
    "gn:feature_class":"P",
    "gn:feature_code":"PPL",
    "gn:name":"Kondala",
    "gn:population":0,
    "gn:timezone":"Africa/Niamey",
    "iso:country":"NE",
    "name:und_x_variant":[
        "Koundala",
        "Kondala"
    ],
    "wof:name":"Kondala",
    "wof:placetype":"locality"
},
  "geometry": {"coordinates":[6.84864,14.39158],"type":"Point"}
}