{
  "type": "Feature",
  "properties": {
    "gn:admin1_code":"9.0",
    "gn:asciiname":"Bolsou",
    "gn:country_code":"NE",
    "gn:dem":251,
    "gn:feature_class":"P",
    "gn:feature_code":"PPL",
    "gn:name":"Bolsou",
    "gn:population":0,
    "gn:timezone":"Africa/Niamey",
    "iso:country":"NE",
    "wof:name":"Bolsou",
    "wof:placetype":"locality"
},
  "geometry": {"coordinates":[0.94955,14.37801],"type":"Point"}
}