{
  "type": "Feature",
  "properties": {
    "gn:admin1_code":"4.0",
    "gn:asciiname":"Sansana Wada",
    "gn:country_code":"NE",
    "gn:dem":424,
    "gn:feature_class":"P",
    "gn:feature_code":"PPL",
    "gn:name":"Sansana Wada",
    "gn:population":0,
    "gn:timezone":"Africa/Niamey",
    "iso:country":"NE",
    "name:und_x_variant":[
        "Sansanaoua",
        "Sansana Wada"
    ],
    "wof:name":"Sansana Wada",
    "wof:placetype":"locality"
},
  "geometry": {"coordinates":[8.24291,14.09125],"type":"Point"}
}