{
  "type": "Feature",
  "properties": {
    "gn:admin1_code":"4.0",
    "gn:asciiname":"Malamay",
    "gn:country_code":"NE",
    "gn:dem":309,
    "gn:feature_class":"P",
    "gn:feature_code":"PPL",
    "gn:name":"Malamay",
    "gn:population":0,
    "gn:timezone":"Africa/Niamey",
    "iso:country":"NE",
    "wof:name":"Malamay",
    "wof:placetype":"locality"
},
  "geometry": {"coordinates":[6.54997,13.61994],"type":"Point"}
}