{
  "type": "Feature",
  "properties": {
    "gn:admin1_code":"7.0",
    "gn:asciiname":"Goudcheke",
    "gn:country_code":"NE",
    "gn:dem":371,
    "gn:feature_class":"P",
    "gn:feature_code":"PPL",
    "gn:name":"Goudch\u00e9ke",
    "gn:population":0,
    "gn:timezone":"Africa/Niamey",
    "iso:country":"NE",
    "wof:name":"Goudcheke",
    "wof:placetype":"locality"
},
  "geometry": {"coordinates":[9.34052,12.96452],"type":"Point"}
}