{
  "type": "Feature",
  "properties": {
    "gn:admin1_code":"4.0",
    "gn:asciiname":"K'ouran Mota",
    "gn:country_code":"NE",
    "gn:dem":410,
    "gn:feature_class":"P",
    "gn:feature_code":"PPL",
    "gn:name":"K'o\u00fbran M\u00f4ta",
    "gn:population":0,
    "gn:timezone":"Africa/Niamey",
    "iso:country":"NE",
    "wof:name":"K'ouran Mota",
    "wof:placetype":"locality"
},
  "geometry": {"coordinates":[7.52139,13.55998],"type":"Point"}
}