{
  "type": "Feature",
  "properties": {
    "gn:admin1_code":"4.0",
    "gn:asciiname":"Ta-tchi",
    "gn:country_code":"NE",
    "gn:dem":433,
    "gn:feature_class":"P",
    "gn:feature_code":"PPL",
    "gn:name":"T\u00e2-tchi",
    "gn:population":0,
    "gn:timezone":"Africa/Niamey",
    "iso:country":"NE",
    "wof:name":"Ta-tchi",
    "wof:placetype":"locality"
},
  "geometry": {"coordinates":[7.38879,13.26307],"type":"Point"}
}