{
  "type": "Feature",
  "properties": {
    "gn:admin1_code":"4.0",
    "gn:asciiname":"Guidan Bara Dangaji",
    "gn:country_code":"NE",
    "gn:dem":404,
    "gn:feature_class":"P",
    "gn:feature_code":"PPL",
    "gn:name":"Guidan Bara Dangaji",
    "gn:population":0,
    "gn:timezone":"Africa/Niamey",
    "iso:country":"NE",
    "wof:name":"Guidan Bara Dangaji",
    "wof:placetype":"locality"
},
  "geometry": {"coordinates":[7.02629,14.21161],"type":"Point"}
}