{
  "type": "Feature",
  "properties": {
    "gn:admin1_code":"4.0",
    "gn:asciiname":"Maine Sara",
    "gn:country_code":"NE",
    "gn:dem":394,
    "gn:feature_class":"P",
    "gn:feature_code":"PPL",
    "gn:name":"Main\u00e9 Sara",
    "gn:population":0,
    "gn:timezone":"Africa/Niamey",
    "iso:country":"NE",
    "wof:name":"Maine Sara",
    "wof:placetype":"locality"
},
  "geometry": {"coordinates":[7.37999,14.73205],"type":"Point"}
}