{
  "type": "Feature",
  "properties": {
    "gn:admin1_code":"2.0",
    "gn:asciiname":"Jaji Ganaram",
    "gn:country_code":"NE",
    "gn:dem":347,
    "gn:feature_class":"P",
    "gn:feature_code":"PPL",
    "gn:name":"Jaji Ganaram",
    "gn:population":0,
    "gn:timezone":"Africa/Niamey",
    "iso:country":"NE",
    "wof:name":"Jaji Ganaram",
    "wof:placetype":"locality"
},
  "geometry": {"coordinates":[11.4301,13.8208],"type":"Point"}
}