{
  "type": "Feature",
  "properties": {
    "gn:admin1_code":"4.0",
    "gn:asciiname":"Guidan Mousa",
    "gn:country_code":"NE",
    "gn:dem":405,
    "gn:feature_class":"P",
    "gn:feature_code":"PPL",
    "gn:name":"Guidan Mousa",
    "gn:population":0,
    "gn:timezone":"Africa/Niamey",
    "iso:country":"NE",
    "name:und_x_variant":[
        "Guidan Moussa",
        "Guidan Mousa"
    ],
    "wof:name":"Guidan Mousa",
    "wof:placetype":"locality"
},
  "geometry": {"coordinates":[6.52453,14.37021],"type":"Point"}
}