{
  "type": "Feature",
  "properties": {
    "gn:admin1_code":"3.0",
    "gn:asciiname":"Maoureydo",
    "gn:country_code":"NE",
    "gn:dem":187,
    "gn:feature_class":"P",
    "gn:feature_code":"PPL",
    "gn:name":"Maoureydo",
    "gn:population":0,
    "gn:timezone":"Africa/Niamey",
    "iso:country":"NE",
    "wof:name":"Maoureydo",
    "wof:placetype":"locality"
},
  "geometry": {"coordinates":[2.88508,12.92718],"type":"Point"}
}