{
  "type": "Feature",
  "properties": {
    "gn:admin1_code":"6.0",
    "gn:asciiname":"Areoua",
    "gn:country_code":"NE",
    "gn:dem":312,
    "gn:feature_class":"P",
    "gn:feature_code":"PPL",
    "gn:name":"Ar\u00e9oua",
    "gn:population":0,
    "gn:timezone":"Africa/Niamey",
    "iso:country":"NE",
    "name:und_x_variant":[
        "Arioua",
        "Ar\u00e9oua"
    ],
    "wof:name":"Areoua",
    "wof:placetype":"locality"
},
  "geometry": {"coordinates":[5.645,14.058],"type":"Point"}
}