{
  "type": "Feature",
  "properties": {
    "gn:admin1_code":"4.0",
    "gn:asciiname":"Touringoukou",
    "gn:country_code":"NE",
    "gn:dem":317,
    "gn:feature_class":"P",
    "gn:feature_code":"PPL",
    "gn:name":"Touringoukou",
    "gn:population":0,
    "gn:timezone":"Africa/Niamey",
    "iso:country":"NE",
    "wof:name":"Touringoukou",
    "wof:placetype":"locality"
},
  "geometry": {"coordinates":[6.52746,13.6252],"type":"Point"}
}