{
  "type": "Feature",
  "properties": {
    "gn:admin1_code":"7.0",
    "gn:asciiname":"Mehanoye",
    "gn:country_code":"NE",
    "gn:dem":485,
    "gn:feature_class":"P",
    "gn:feature_code":"PPL",
    "gn:name":"M\u00e9hanoye",
    "gn:population":0,
    "gn:timezone":"Africa/Niamey",
    "iso:country":"NE",
    "wof:name":"Mehanoye",
    "wof:placetype":"locality"
},
  "geometry": {"coordinates":[9.0077,14.2096],"type":"Point"}
}