{
  "type": "Feature",
  "properties": {
    "gn:admin1_code":"2.0",
    "gn:asciiname":"Kanya",
    "gn:country_code":"NE",
    "gn:dem":353,
    "gn:feature_class":"P",
    "gn:feature_code":"PPL",
    "gn:name":"Kanya",
    "gn:population":0,
    "gn:timezone":"Africa/Niamey",
    "iso:country":"NE",
    "name:tel_x_preferred":[
        "\u0c15\u0c28\u0c4d\u0c2f\u0c3e \u0c32\u0c17\u0c4d\u0c28\u0c2e\u0c41"
    ],
    "name:und_x_variant":[
        "Kagniouakoura",
        "Kaniua",
        "Kanioua",
        "Kanya"
    ],
    "wof:name":"Kanya",
    "wof:placetype":"locality"
},
  "geometry": {"coordinates":[11.1896,13.8066],"type":"Point"}
}