{
  "type": "Feature",
  "properties": {
    "gn:admin1_code":"3.0",
    "gn:asciiname":"Babourey Kouara",
    "gn:country_code":"NE",
    "gn:dem":184,
    "gn:feature_class":"P",
    "gn:feature_code":"PPL",
    "gn:name":"Babourey Kouara",
    "gn:population":0,
    "gn:timezone":"Africa/Niamey",
    "iso:country":"NE",
    "wof:name":"Babourey Kouara",
    "wof:placetype":"locality"
},
  "geometry": {"coordinates":[2.94565,12.75415],"type":"Point"}
}