{
  "type": "Feature",
  "properties": {
    "gn:admin1_code":"9.0",
    "gn:asciiname":"Dare",
    "gn:country_code":"NE",
    "gn:dem":249,
    "gn:feature_class":"P",
    "gn:feature_code":"PPL",
    "gn:name":"Dar\u00e9",
    "gn:population":0,
    "gn:timezone":"Africa/Niamey",
    "iso:country":"NE",
    "name:ceb_x_preferred":[
        "Dare"
    ],
    "name:deu_x_preferred":[
        "Dare"
    ],
    "name:fra_x_preferred":[
        "Dare"
    ],
    "name:ita_x_preferred":[
        "Dare"
    ],
    "name:nld_x_preferred":[
        "Dare"
    ],
    "name:pol_x_preferred":[
        "Dare"
    ],
    "name:por_x_preferred":[
        "Dare"
    ],
    "name:rus_x_preferred":[
        "\u0414\u044d\u0439\u0440"
    ],
    "name:spa_x_preferred":[
        "Dare"
    ],
    "name:swe_x_preferred":[
        "Dare"
    ],
    "wof:name":"Dare",
    "wof:placetype":"locality"
},
  "geometry": {"coordinates":[3.1151,13.6477],"type":"Point"}
}