{
  "type": "Feature",
  "properties": {
    "gn:admin1_code":"6.0",
    "gn:asciiname":"Birni",
    "gn:country_code":"NE",
    "gn:dem":489,
    "gn:feature_class":"P",
    "gn:feature_code":"PPL",
    "gn:name":"Birni",
    "gn:population":0,
    "gn:timezone":"Africa/Niamey",
    "iso:country":"NE",
    "name:ceb_x_preferred":[
        "Birni"
    ],
    "name:ita_x_preferred":[
        "Birni"
    ],
    "name:msa_x_preferred":[
        "Birni"
    ],
    "name:swe_x_preferred":[
        "Birni"
    ],
    "wof:name":"Birni",
    "wof:placetype":"locality"
},
  "geometry": {"coordinates":[5.6811,14.6121],"type":"Point"}
}