{
  "type": "Feature",
  "properties": {
    "gn:admin1_code":"9.0",
    "gn:asciiname":"Kossey",
    "gn:country_code":"NE",
    "gn:dem":187,
    "gn:feature_class":"P",
    "gn:feature_code":"PPL",
    "gn:name":"Kossey",
    "gn:population":0,
    "gn:timezone":"Africa/Niamey",
    "iso:country":"NE",
    "name:und_x_variant":[
        "Koss\u00e9y\u00e9",
        "Kossey"
    ],
    "wof:name":"Kossey",
    "wof:placetype":"locality"
},
  "geometry": {"coordinates":[2.0444,13.5118],"type":"Point"}
}