{
  "type": "Feature",
  "properties": {
    "gn:admin1_code":"7.0",
    "gn:asciiname":"Dad'in Kowa",
    "gn:country_code":"NE",
    "gn:dem":464,
    "gn:feature_class":"P",
    "gn:feature_code":"PPL",
    "gn:name":"D\u00e2d'in K\u00f4w\u00e2",
    "gn:population":0,
    "gn:timezone":"Africa/Niamey",
    "iso:country":"NE",
    "wof:name":"Dad'in Kowa",
    "wof:placetype":"locality"
},
  "geometry": {"coordinates":[8.41932,13.29163],"type":"Point"}
}