{
  "type": "Feature",
  "properties": {
    "gn:admin1_code":"9.0",
    "gn:asciiname":"Eguebango",
    "gn:country_code":"NE",
    "gn:dem":260,
    "gn:feature_class":"P",
    "gn:feature_code":"PPL",
    "gn:name":"Egu\u00e9bango",
    "gn:population":0,
    "gn:timezone":"Africa/Niamey",
    "iso:country":"NE",
    "wof:name":"Eguebango",
    "wof:placetype":"locality"
},
  "geometry": {"coordinates":[0.24206,14.56055],"type":"Point"}
}