{
  "type": "Feature",
  "properties": {
    "gn:admin1_code":"3.0",
    "gn:asciiname":"Tokoye",
    "gn:country_code":"NE",
    "gn:dem":252,
    "gn:feature_class":"P",
    "gn:feature_code":"PPL",
    "gn:name":"Tokoye",
    "gn:population":0,
    "gn:timezone":"Africa/Niamey",
    "iso:country":"NE",
    "name:und_x_variant":[
        "Tokoy",
        "Tokoye"
    ],
    "wof:name":"Tokoye",
    "wof:placetype":"locality"
},
  "geometry": {"coordinates":[3.3675,13.3977],"type":"Point"}
}