{
  "type": "Feature",
  "properties": {
    "gn:admin1_code":"4.0",
    "gn:asciiname":"Dan Gouiwa",
    "gn:country_code":"NE",
    "gn:dem":407,
    "gn:feature_class":"P",
    "gn:feature_code":"PPL",
    "gn:name":"Dan Gouiwa",
    "gn:population":0,
    "gn:timezone":"Africa/Niamey",
    "iso:country":"NE",
    "name:und_x_variant":[
        "Dan Gwywa",
        "Dan Gwiwa",
        "Dan Gouiwa"
    ],
    "wof:name":"Dan Gouiwa",
    "wof:placetype":"locality"
},
  "geometry": {"coordinates":[7.75291,13.78908],"type":"Point"}
}