{
  "type": "Feature",
  "properties": {
    "gn:admin1_code":"3.0",
    "gn:asciiname":"Gongamakare",
    "gn:country_code":"NE",
    "gn:dem":240,
    "gn:feature_class":"P",
    "gn:feature_code":"PPL",
    "gn:name":"Gongamakar\u00e9",
    "gn:population":0,
    "gn:timezone":"Africa/Niamey",
    "iso:country":"NE",
    "wof:name":"Gongamakare",
    "wof:placetype":"locality"
},
  "geometry": {"coordinates":[3.225,13.2033],"type":"Point"}
}