{
  "type": "Feature",
  "properties": {
    "gn:admin1_code":"2.0",
    "gn:asciiname":"Argoun",
    "gn:country_code":"NE",
    "gn:dem":301,
    "gn:feature_class":"P",
    "gn:feature_code":"PPL",
    "gn:name":"Argoun",
    "gn:population":0,
    "gn:timezone":"Africa/Niamey",
    "iso:country":"NE",
    "wof:name":"Argoun",
    "wof:placetype":"locality"
},
  "geometry": {"coordinates":[12.94339,13.60078],"type":"Point"}
}