{
  "type": "Feature",
  "properties": {
    "gn:admin1_code":"6.0",
    "gn:asciiname":"Balgaya",
    "gn:country_code":"NE",
    "gn:dem":314,
    "gn:feature_class":"P",
    "gn:feature_code":"PPL",
    "gn:name":"Balgaya",
    "gn:population":0,
    "gn:timezone":"Africa/Niamey",
    "iso:country":"NE",
    "wof:name":"Balgaya",
    "wof:placetype":"locality"
},
  "geometry": {"coordinates":[5.62818,13.90353],"type":"Point"}
}