{
  "type": "Feature",
  "properties": {
    "gn:admin1_code":"4.0",
    "gn:asciiname":"Guidan Kiata",
    "gn:country_code":"NE",
    "gn:dem":464,
    "gn:feature_class":"P",
    "gn:feature_code":"PPL",
    "gn:name":"Guidan Kiata",
    "gn:population":0,
    "gn:timezone":"Africa/Niamey",
    "iso:country":"NE",
    "name:und_x_variant":[
        "Gidan Kyata",
        "Guidan Kyata",
        "Guidan Kiata"
    ],
    "wof:name":"Guidan Kiata",
    "wof:placetype":"locality"
},
  "geometry": {"coordinates":[7.72154,13.36755],"type":"Point"}
}