{
  "type": "Feature",
  "properties": {
    "gn:admin1_code":"9.0",
    "gn:asciiname":"Kongou Peul",
    "gn:country_code":"NE",
    "gn:dem":213,
    "gn:feature_class":"P",
    "gn:feature_code":"PPL",
    "gn:name":"Kongou Peul",
    "gn:population":0,
    "gn:timezone":"Africa/Niamey",
    "iso:country":"NE",
    "wof:name":"Kongou Peul",
    "wof:placetype":"locality"
},
  "geometry": {"coordinates":[2.3761,13.3098],"type":"Point"}
}