{
  "type": "Feature",
  "properties": {
    "gn:admin1_code":"9.0",
    "gn:asciiname":"Gari Miza",
    "gn:country_code":"NE",
    "gn:dem":224,
    "gn:feature_class":"P",
    "gn:feature_code":"PPL",
    "gn:name":"Gari Miza",
    "gn:population":0,
    "gn:timezone":"Africa/Niamey",
    "iso:country":"NE",
    "wof:name":"Gari Miza",
    "wof:placetype":"locality"
},
  "geometry": {"coordinates":[3.3382,14.2896],"type":"Point"}
}