{
  "type": "Feature",
  "properties": {
    "gn:admin1_code":"2.0",
    "gn:asciiname":"Garoumia",
    "gn:country_code":"NE",
    "gn:dem":342,
    "gn:feature_class":"P",
    "gn:feature_code":"PPL",
    "gn:name":"Garoumia",
    "gn:population":0,
    "gn:timezone":"Africa/Niamey",
    "iso:country":"NE",
    "name:und_x_variant":[
        "Garoumiga",
        "Garumagi",
        "Garoumaji",
        "Garoumia"
    ],
    "wof:name":"Garoumia",
    "wof:placetype":"locality"
},
  "geometry": {"coordinates":[11.2233,13.6598],"type":"Point"}
}