{
  "type": "Feature",
  "properties": {
    "gn:admin1_code":"2.0",
    "gn:asciiname":"Wogom",
    "gn:country_code":"NE",
    "gn:dem":318,
    "gn:feature_class":"P",
    "gn:feature_code":"PPL",
    "gn:name":"Wogom",
    "gn:population":0,
    "gn:timezone":"Africa/Niamey",
    "iso:country":"NE",
    "wof:name":"Wogom",
    "wof:placetype":"locality"
},
  "geometry": {"coordinates":[12.27213,13.22128],"type":"Point"}
}