{
  "type": "Feature",
  "properties": {
    "gn:admin1_code":"7.0",
    "gn:asciiname":"Kandama",
    "gn:country_code":"NE",
    "gn:dem":371,
    "gn:feature_class":"P",
    "gn:feature_code":"PPL",
    "gn:name":"Kandama",
    "gn:population":0,
    "gn:timezone":"Africa/Niamey",
    "iso:country":"NE",
    "wof:name":"Kandama",
    "wof:placetype":"locality"
},
  "geometry": {"coordinates":[9.521,13.1207],"type":"Point"}
}