{
  "type": "Feature",
  "properties": {
    "gn:admin1_code":"7.0",
    "gn:asciiname":"Maderi",
    "gn:country_code":"NE",
    "gn:dem":491,
    "gn:feature_class":"P",
    "gn:feature_code":"PPL",
    "gn:name":"Mad\u00e9ri",
    "gn:population":0,
    "gn:timezone":"Africa/Niamey",
    "iso:country":"NE",
    "wof:name":"Maderi",
    "wof:placetype":"locality"
},
  "geometry": {"coordinates":[9.4402,14.516],"type":"Point"}
}