{
  "type": "Feature",
  "properties": {
    "gn:admin1_code":"6.0",
    "gn:asciiname":"Dan Touhdou",
    "gn:country_code":"NE",
    "gn:dem":272,
    "gn:feature_class":"P",
    "gn:feature_code":"PPL",
    "gn:name":"Dan Touhdou",
    "gn:population":0,
    "gn:timezone":"Africa/Niamey",
    "iso:country":"NE",
    "wof:name":"Dan Touhdou",
    "wof:placetype":"locality"
},
  "geometry": {"coordinates":[5.2471,14.0126],"type":"Point"}
}