{
  "type": "Feature",
  "properties": {
    "gn:admin1_code":"9.0",
    "gn:asciiname":"Kiarmey",
    "gn:country_code":"NE",
    "gn:dem":223,
    "gn:feature_class":"P",
    "gn:feature_code":"PPL",
    "gn:name":"Kiarmey",
    "gn:population":0,
    "gn:timezone":"Africa/Niamey",
    "iso:country":"NE",
    "name:und_x_variant":[
        "K\u00e9rim\u00e9"
    ],
    "wof:name":"Kiarmey",
    "wof:placetype":"locality"
},
  "geometry": {"coordinates":[1.56051,14.26988],"type":"Point"}
}