{
  "type": "Feature",
  "properties": {
    "gn:admin1_code":"6.0",
    "gn:asciiname":"Biris",
    "gn:country_code":"NE",
    "gn:dem":445,
    "gn:feature_class":"P",
    "gn:feature_code":"PPL",
    "gn:name":"Biris",
    "gn:population":0,
    "gn:timezone":"Africa/Niamey",
    "iso:country":"NE",
    "wof:name":"Biris",
    "wof:placetype":"locality"
},
  "geometry": {"coordinates":[6.10112,14.54018],"type":"Point"}
}