{
  "type": "Feature",
  "properties": {
    "iso:country":"NE",
    "name:ara_x_preferred":[
        "\u0623\u063a\u0648\u064a\u064a"
    ],
    "name:ben_x_preferred":[
        "\u0985\u09cd\u09af\u09be\u0997\u09c1\u09c1\u0987"
    ],
    "name:cat_x_preferred":[
        "Agui\u00e9"
    ],
    "name:ceb_x_preferred":[
        "Agui\u00e9"
    ],
    "name:dan_x_preferred":[
        "Agui\u00e9"
    ],
    "name:deu_x_preferred":[
        "Agui\u00e9"
    ],
    "name:ell_x_preferred":[
        "\u0386\u03b3\u03ba\u03bf\u03c5\u03b9\u03b5"
    ],
    "name:eng_x_preferred":[
        "Agui\u00e9"
    ],
    "name:fin_x_preferred":[
        "Agui\u00e9"
    ],
    "name:fra_x_preferred":[
        "Agui\u00e9"
    ],
    "name:guj_x_preferred":[
        "\u0a8f\u0a97\u0ac1\u0a88\u0a8f"
    ],
    "name:hau_x_preferred":[
        "Agui\u00e9"
    ],
    "name:hin_x_preferred":[
        "\u090f\u0917\u093f\u092f"
    ],
    "name:ind_x_preferred":[
        "Agui\u00e9"
    ],
    "name:ita_x_preferred":[
        "Aguie"
    ],
    "name:jpn_x_preferred":[
        "\u30a2\u30ae\u30a8"
    ],
    "name:kan_x_preferred":[
        "\u0c85\u0c97\u0cc1\u0caf\u0cbf"
    ],
    "name:kor_x_preferred":[
        "\uc544\uadc0"
    ],
    "name:lav_x_preferred":[
        "Agije"
    ],
    "name:lit_x_preferred":[
        "Ag\u0117"
    ],
    "name:mar_x_preferred":[
        "\u0905\u0917\u0941\u0907\u090f"
    ],
    "name:msa_x_preferred":[
        "Aguie"
    ],
    "name:nld_x_preferred":[
        "Aguie"
    ],
    "name:nob_x_preferred":[
        "Aguie"
    ],
    "name:pol_x_preferred":[
        "Agui\u00e9"
    ],
    "name:ron_x_preferred":[
        "Aguie"
    ],
    "name:rus_x_preferred":[
        "\u0410\u0433\u044c\u0435"
    ],
    "name:sin_x_preferred":[
        "\u0d85\u0d9c\u0dd4\u0dba\u0dd2"
    ],
    "name:spa_x_preferred":[
        "Agui\u00e9"
    ],
    "name:swe_x_preferred":[
        "Agui\u00e9"
    ],
    "name:tam_x_preferred":[
        "\u0b85\u0b95\u0bc1\u0baf\u0bbf"
    ],
    "name:tel_x_preferred":[
        "\u0c0e\u0c17\u0c3f\u0c2f"
    ],
    "name:tha_x_preferred":[
        "\u0e41\u0e2d\u0e01\u0e35\u0e40\u0e19"
    ],
    "name:tur_x_preferred":[
        "Aguie"
    ],
    "name:ukr_x_preferred":[
        "\u0410\u0433\u044c\u0435"
    ],
    "name:und_x_variant":[
        "Agy\u00e9"
    ],
    "name:urd_x_preferred":[
        "\u0627\u06af\u0648\u06cc"
    ],
    "name:vie_x_preferred":[
        "Aguie"
    ],
    "qs:gn_country":"NE",
    "qs:gn_fcode":"PPL",
    "qs:gn_pop":13152,
    "qs:name":"Aguie",
    "qs:name_adm0":"Niger",
    "qs:name_adm1":"Maradi",
    "qs:photos":0,
    "qs:photos_1k":0,
    "qs:photos_9k":1,
    "qs:photos_9r":1,
    "qs:photos_all":1,
    "qs:photos_sr":0,
    "qs:placetype":"Town",
    "qs:pop_sr":"6",
    "qs:woe_adm0":23424906,
    "wd:wordcount":452,
    "wof:name":"Aguie",
    "wof:placetype":"locality",
    "wof:population":13152
},
  "geometry": {"coordinates":[7.77863,13.50601],"type":"Point"}
}