{
  "type": "Feature",
  "properties": {
    "iso:country":"NE",
    "name:deu_x_preferred":[
        "Agui\u00e9"
    ],
    "name:fin_x_preferred":[
        "Agui\u00e9"
    ],
    "name:fra_x_preferred":[
        "Agui\u00e9"
    ],
    "name:ita_x_preferred":[
        "Aguie"
    ],
    "name:msa_x_preferred":[
        "Aguie"
    ],
    "name:pol_x_preferred":[
        "Agui\u00e9"
    ],
    "name:ron_x_preferred":[
        "Aguie"
    ],
    "name:unk_x_variant":[
        "Agy\u00e9"
    ],
    "name:urd_x_preferred":[
        "\u0627\u06af\u0648\u06cc"
    ],
    "qs:gn_country":"NE",
    "qs:gn_fcode":"PPL",
    "qs:gn_pop":13152,
    "qs:name":"Aguie",
    "qs:name_adm0":"Niger",
    "qs:name_adm1":"Maradi",
    "qs:photos":0,
    "qs:photos_1k":0,
    "qs:photos_9k":1,
    "qs:photos_9r":1,
    "qs:photos_all":1,
    "qs:photos_sr":0,
    "qs:placetype":"Town",
    "qs:pop_sr":"6",
    "qs:woe_adm0":23424906,
    "wd:wordcount":452,
    "wof:name":"Aguie",
    "wof:placetype":"locality",
    "wof:population":13152
},
  "geometry": {"coordinates":[7.77863,13.50601],"type":"Point"}
}