{
  "type": "Feature",
  "properties": {
    "gn:admin1_code":"6.0",
    "gn:asciiname":"Tachalawa Leymi",
    "gn:country_code":"NE",
    "gn:dem":337,
    "gn:feature_class":"P",
    "gn:feature_code":"PPL",
    "gn:name":"Tachalawa Leymi",
    "gn:population":0,
    "gn:timezone":"Africa/Niamey",
    "iso:country":"NE",
    "wof:name":"Tachalawa Leymi",
    "wof:placetype":"locality"
},
  "geometry": {"coordinates":[6.28063,13.90504],"type":"Point"}
}