{
  "type": "Feature",
  "properties": {
    "gn:admin1_code":"4.0",
    "gn:asciiname":"Gangara",
    "gn:country_code":"NE",
    "gn:dem":396,
    "gn:feature_class":"P",
    "gn:feature_code":"PPL",
    "gn:name":"Gangara",
    "gn:population":0,
    "gn:timezone":"Africa/Niamey",
    "iso:country":"NE",
    "name:ceb_x_preferred":[
        "Gangara"
    ],
    "name:nor_x_preferred":[
        "Gangara"
    ],
    "name:spa_x_preferred":[
        "Gangara"
    ],
    "name:swe_x_preferred":[
        "Gangara"
    ],
    "name:und_x_variant":[
        "Gidan Ngaya",
        "Guidan Gaya"
    ],
    "name:vie_x_preferred":[
        "Gangara"
    ],
    "name:war_x_preferred":[
        "Gangara"
    ],
    "wof:name":"Gangara",
    "wof:placetype":"locality"
},
  "geometry": {"coordinates":[7.31518,13.97412],"type":"Point"}
}