{
  "type": "Feature",
  "properties": {
    "gn:admin1_code":"6.0",
    "gn:asciiname":"Toulou",
    "gn:country_code":"NE",
    "gn:dem":304,
    "gn:feature_class":"P",
    "gn:feature_code":"PPL",
    "gn:name":"Toulou",
    "gn:population":0,
    "gn:timezone":"Africa/Niamey",
    "iso:country":"NE",
    "name:und_x_variant":[
        "Toullou",
        "Toulou"
    ],
    "wof:name":"Toulou",
    "wof:placetype":"locality"
},
  "geometry": {"coordinates":[5.1969,14.1675],"type":"Point"}
}