{
  "type": "Feature",
  "properties": {
    "gn:admin1_code":"9.0",
    "gn:asciiname":"Fartal",
    "gn:country_code":"NE",
    "gn:dem":271,
    "gn:feature_class":"P",
    "gn:feature_code":"PPL",
    "gn:name":"Fartal",
    "gn:population":0,
    "gn:timezone":"Africa/Niamey",
    "iso:country":"NE",
    "wof:name":"Fartal",
    "wof:placetype":"locality"
},
  "geometry": {"coordinates":[3.6469,14.9309],"type":"Point"}
}