{
  "type": "Feature",
  "properties": {
    "gn:admin1_code":"8.0",
    "gn:asciiname":"Libo Gaoucholon",
    "gn:country_code":"NE",
    "gn:dem":213,
    "gn:feature_class":"P",
    "gn:feature_code":"PPL",
    "gn:name":"Libo Gaoucholon",
    "gn:population":0,
    "gn:timezone":"Africa/Niamey",
    "iso:country":"NE",
    "wof:name":"Libo Gaoucholon",
    "wof:placetype":"locality"
},
  "geometry": {"coordinates":[2.23333,13.93333],"type":"Point"}
}