{
  "type": "Feature",
  "properties": {
    "gn:admin1_code":"9.0",
    "gn:asciiname":"Zonkon",
    "gn:country_code":"NE",
    "gn:dem":230,
    "gn:feature_class":"P",
    "gn:feature_code":"PPLL",
    "gn:name":"Zonkon",
    "gn:population":0,
    "gn:timezone":"Africa/Niamey",
    "iso:country":"NE",
    "wof:name":"Zonkon",
    "wof:placetype":"locality"
},
  "geometry": {"coordinates":[1.3217,13.9365],"type":"Point"}
}