{
  "type": "Feature",
  "properties": {
    "gn:admin1_code":"7.0",
    "gn:asciiname":"Tarka",
    "gn:country_code":"NE",
    "gn:dem":465,
    "gn:feature_class":"P",
    "gn:feature_code":"PPL",
    "gn:name":"Tarka",
    "gn:population":0,
    "gn:timezone":"Africa/Niamey",
    "iso:country":"NE",
    "wof:name":"Tarka",
    "wof:placetype":"locality"
},
  "geometry": {"coordinates":[8.83163,14.20415],"type":"Point"}
}