{
  "type": "Feature",
  "properties": {
    "gn:admin1_code":"7.0",
    "gn:asciiname":"Mad'atey Sultan",
    "gn:country_code":"NE",
    "gn:dem":448,
    "gn:feature_class":"P",
    "gn:feature_code":"PPL",
    "gn:name":"Mad'\u00e2tey Sultan",
    "gn:population":0,
    "gn:timezone":"Africa/Niamey",
    "iso:country":"NE",
    "wof:name":"Mad'atey Sultan",
    "wof:placetype":"locality"
},
  "geometry": {"coordinates":[8.97947,13.836],"type":"Point"}
}