{
  "type": "Feature",
  "properties": {
    "gn:admin1_code":"9.0",
    "gn:asciiname":"Bamey Kouarey",
    "gn:country_code":"NE",
    "gn:dem":225,
    "gn:feature_class":"P",
    "gn:feature_code":"PPL",
    "gn:name":"Bamey Kouarey",
    "gn:population":0,
    "gn:timezone":"Africa/Niamey",
    "iso:country":"NE",
    "name:und_x_variant":[
        "Bamey Koir\u00e9",
        "Bamey Koyr\u00e9",
        "Bamey Kouarey"
    ],
    "wof:name":"Bamey Kouarey",
    "wof:placetype":"locality"
},
  "geometry": {"coordinates":[1.73333,13.66503],"type":"Point"}
}