{
  "type": "Feature",
  "properties": {
    "gn:admin1_code":"7.0",
    "gn:asciiname":"Boussari",
    "gn:country_code":"NE",
    "gn:dem":434,
    "gn:feature_class":"P",
    "gn:feature_code":"PPL",
    "gn:name":"Boussari",
    "gn:population":0,
    "gn:timezone":"Africa/Niamey",
    "iso:country":"NE",
    "wof:name":"Boussari",
    "wof:placetype":"locality"
},
  "geometry": {"coordinates":[9.7673,14.284],"type":"Point"}
}