{
  "type": "Feature",
  "properties": {
    "gn:admin1_code":"4.0",
    "gn:asciiname":"Doundou",
    "gn:country_code":"NE",
    "gn:dem":429,
    "gn:feature_class":"P",
    "gn:feature_code":"PPL",
    "gn:name":"Doundou",
    "gn:population":0,
    "gn:timezone":"Africa/Niamey",
    "iso:country":"NE",
    "wof:name":"Doundou",
    "wof:placetype":"locality"
},
  "geometry": {"coordinates":[8.06577,13.3731],"type":"Point"}
}