{
  "type": "Feature",
  "properties": {
    "gn:admin1_code":"6.0",
    "gn:asciiname":"Zouba",
    "gn:country_code":"NE",
    "gn:dem":371,
    "gn:feature_class":"P",
    "gn:feature_code":"PPL",
    "gn:name":"Zouba",
    "gn:population":0,
    "gn:timezone":"Africa/Niamey",
    "iso:country":"NE",
    "wof:name":"Zouba",
    "wof:placetype":"locality"
},
  "geometry": {"coordinates":[6.36001,14.08856],"type":"Point"}
}