{
  "type": "Feature",
  "properties": {
    "gn:admin1_code":"6.0",
    "gn:asciiname":"Tunga Mosage",
    "gn:country_code":"NE",
    "gn:dem":287,
    "gn:feature_class":"P",
    "gn:feature_code":"PPL",
    "gn:name":"Tunga Mosage",
    "gn:population":0,
    "gn:timezone":"Africa/Niamey",
    "iso:country":"NE",
    "wof:name":"Tunga Mosage",
    "wof:placetype":"locality"
},
  "geometry": {"coordinates":[5.36878,13.88167],"type":"Point"}
}