{
  "type": "Feature",
  "properties": {
    "gn:admin1_code":"9.0",
    "gn:asciiname":"Louram",
    "gn:country_code":"NE",
    "gn:dem":247,
    "gn:feature_class":"P",
    "gn:feature_code":"PPL",
    "gn:name":"Louram",
    "gn:population":0,
    "gn:timezone":"Africa/Niamey",
    "iso:country":"NE",
    "wof:name":"Louram",
    "wof:placetype":"locality"
},
  "geometry": {"coordinates":[1.4289,13.2923],"type":"Point"}
}