{
  "type": "Feature",
  "properties": {
    "gn:admin1_code":"7.0",
    "gn:asciiname":"Garin Malamay",
    "gn:country_code":"NE",
    "gn:dem":474,
    "gn:feature_class":"P",
    "gn:feature_code":"PPL",
    "gn:name":"Garin Malamay",
    "gn:population":0,
    "gn:timezone":"Africa/Niamey",
    "iso:country":"NE",
    "wof:name":"Garin Malamay",
    "wof:placetype":"locality"
},
  "geometry": {"coordinates":[8.87405,14.23283],"type":"Point"}
}