{
  "type": "Feature",
  "properties": {
    "gn:admin1_code":"3.0",
    "gn:asciiname":"Yaloa",
    "gn:country_code":"NE",
    "gn:dem":261,
    "gn:feature_class":"P",
    "gn:feature_code":"PPL",
    "gn:name":"Yaloa",
    "gn:population":0,
    "gn:timezone":"Africa/Niamey",
    "iso:country":"NE",
    "wof:name":"Yaloa",
    "wof:placetype":"locality"
},
  "geometry": {"coordinates":[4.19184,14.14101],"type":"Point"}
}