{
  "type": "Feature",
  "properties": {
    "gn:admin1_code":"4.0",
    "gn:asciiname":"Assaou Tagabas",
    "gn:country_code":"NE",
    "gn:dem":373,
    "gn:feature_class":"P",
    "gn:feature_code":"PPL",
    "gn:name":"Assaou Tagabas",
    "gn:population":0,
    "gn:timezone":"Africa/Niamey",
    "iso:country":"NE",
    "name:und_x_variant":[
        "Assou",
        "Assow",
        "Asao",
        "Assoou",
        "Assao",
        "Assaou Tagabas"
    ],
    "wof:name":"Assaou Tagabas",
    "wof:placetype":"locality"
},
  "geometry": {"coordinates":[7.07289,13.25201],"type":"Point"}
}