{
  "type": "Feature",
  "properties": {
    "gn:admin1_code":"6.0",
    "gn:asciiname":"Elekaora",
    "gn:country_code":"NE",
    "gn:dem":388,
    "gn:feature_class":"P",
    "gn:feature_code":"PPL",
    "gn:name":"El\u00e9kaora",
    "gn:population":0,
    "gn:timezone":"Africa/Niamey",
    "iso:country":"NE",
    "wof:name":"Elekaora",
    "wof:placetype":"locality"
},
  "geometry": {"coordinates":[5.7199,14.4794],"type":"Point"}
}