{
  "type": "Feature",
  "properties": {
    "gn:admin1_code":"7.0",
    "gn:asciiname":"Kangaroua Falama",
    "gn:country_code":"NE",
    "gn:dem":408,
    "gn:feature_class":"P",
    "gn:feature_code":"PPL",
    "gn:name":"Kangaroua Falama",
    "gn:population":0,
    "gn:timezone":"Africa/Niamey",
    "iso:country":"NE",
    "wof:name":"Kangaroua Falama",
    "wof:placetype":"locality"
},
  "geometry": {"coordinates":[10.0075,14.2213],"type":"Point"}
}