{
  "type": "Feature",
  "properties": {
    "gn:admin1_code":"6.0",
    "gn:asciiname":"Mozage",
    "gn:country_code":"NE",
    "gn:dem":279,
    "gn:feature_class":"P",
    "gn:feature_code":"PPL",
    "gn:name":"Mozag\u00e9",
    "gn:population":0,
    "gn:timezone":"Africa/Niamey",
    "iso:country":"NE",
    "wof:name":"Mozage",
    "wof:placetype":"locality"
},
  "geometry": {"coordinates":[5.44791,13.892],"type":"Point"}
}