{
  "type": "Feature",
  "properties": {
    "gn:admin1_code":"7.0",
    "gn:asciiname":"Garin Mayna",
    "gn:country_code":"NE",
    "gn:dem":431,
    "gn:feature_class":"P",
    "gn:feature_code":"PPL",
    "gn:name":"Garin Mayna",
    "gn:population":0,
    "gn:timezone":"Africa/Niamey",
    "iso:country":"NE",
    "wof:name":"Garin Mayna",
    "wof:placetype":"locality"
},
  "geometry": {"coordinates":[8.9745,13.69395],"type":"Point"}
}