{
  "type": "Feature",
  "properties": {
    "gn:admin1_code":"3.0",
    "gn:asciiname":"Tunga-Majuka",
    "gn:country_code":"NE",
    "gn:dem":208,
    "gn:feature_class":"P",
    "gn:feature_code":"PPL",
    "gn:name":"Tunga-Majuka",
    "gn:population":0,
    "gn:timezone":"Africa/Niamey",
    "iso:country":"NE",
    "wof:name":"Tunga-Majuka",
    "wof:placetype":"locality"
},
  "geometry": {"coordinates":[3.93239,12.91441],"type":"Point"}
}