{
  "type": "Feature",
  "properties": {
    "gn:admin1_code":"7.0",
    "gn:asciiname":"Angoual Limam",
    "gn:country_code":"NE",
    "gn:dem":417,
    "gn:feature_class":"P",
    "gn:feature_code":"PPL",
    "gn:name":"Angoual L\u00eemam",
    "gn:population":0,
    "gn:timezone":"Africa/Niamey",
    "iso:country":"NE",
    "wof:name":"Angoual Limam",
    "wof:placetype":"locality"
},
  "geometry": {"coordinates":[8.78206,13.32363],"type":"Point"}
}