{
  "type": "Feature",
  "properties": {
    "gn:admin1_code":"2.0",
    "gn:asciiname":"Kojimiri",
    "gn:country_code":"NE",
    "gn:dem":342,
    "gn:feature_class":"P",
    "gn:feature_code":"PPL",
    "gn:name":"Kojimiri",
    "gn:population":0,
    "gn:timezone":"Africa/Niamey",
    "iso:country":"NE",
    "wof:name":"Kojimiri",
    "wof:placetype":"locality"
},
  "geometry": {"coordinates":[11.0977,13.4128],"type":"Point"}
}