{
  "type": "Feature",
  "properties": {
    "gn:admin1_code":"9.0",
    "gn:asciiname":"Gari Jeji",
    "gn:country_code":"NE",
    "gn:dem":252,
    "gn:feature_class":"P",
    "gn:feature_code":"PPL",
    "gn:name":"Gari J\u00e9ji",
    "gn:population":0,
    "gn:timezone":"Africa/Niamey",
    "iso:country":"NE",
    "wof:name":"Gari Jeji",
    "wof:placetype":"locality"
},
  "geometry": {"coordinates":[3.7416,14.4662],"type":"Point"}
}