{
  "type": "Feature",
  "properties": {
    "gn:admin1_code":"6.0",
    "gn:asciiname":"Guidan Issa",
    "gn:cc2":"NE",
    "gn:country_code":"NE",
    "gn:dem":244,
    "gn:feature_class":"P",
    "gn:feature_code":"PPL",
    "gn:name":"Guidan Issa",
    "gn:population":0,
    "gn:timezone":"Africa/Niamey",
    "iso:country":"NE",
    "name:und_x_variant":[
        "Gidan-Isa",
        "Guidan Issa"
    ],
    "wof:name":"Guidan Issa",
    "wof:placetype":"locality"
},
  "geometry": {"coordinates":[3.96667,13.83333],"type":"Point"}
}