{
  "type": "Feature",
  "properties": {
    "gn:admin1_code":"4.0",
    "gn:asciiname":"Ita Sofoua",
    "gn:country_code":"NE",
    "gn:dem":368,
    "gn:feature_class":"P",
    "gn:feature_code":"PPL",
    "gn:name":"Ita Sofoua",
    "gn:population":0,
    "gn:timezone":"Africa/Niamey",
    "iso:country":"NE",
    "name:und_x_variant":[
        "Ita",
        "Ita Sofoua"
    ],
    "wof:name":"Ita Sofoua",
    "wof:placetype":"locality"
},
  "geometry": {"coordinates":[7.25458,13.8777],"type":"Point"}
}