{
  "type": "Feature",
  "properties": {
    "gn:admin1_code":"6.0",
    "gn:asciiname":"Karkou",
    "gn:country_code":"NE",
    "gn:dem":278,
    "gn:feature_class":"P",
    "gn:feature_code":"PPL",
    "gn:name":"Karkou",
    "gn:population":0,
    "gn:timezone":"Africa/Niamey",
    "iso:country":"NE",
    "name:und_x_variant":[
        "Kakou",
        "Karkou"
    ],
    "wof:name":"Karkou",
    "wof:placetype":"locality"
},
  "geometry": {"coordinates":[5.32465,13.92599],"type":"Point"}
}