{
  "type": "Feature",
  "properties": {
    "gn:admin1_code":"4.0",
    "gn:asciiname":"Dan Fachima",
    "gn:country_code":"NE",
    "gn:dem":367,
    "gn:feature_class":"P",
    "gn:feature_code":"PPL",
    "gn:name":"Dan Fachima",
    "gn:population":0,
    "gn:timezone":"Africa/Niamey",
    "iso:country":"NE",
    "wof:name":"Dan Fachima",
    "wof:placetype":"locality"
},
  "geometry": {"coordinates":[6.96202,14.00606],"type":"Point"}
}