{
  "type": "Feature",
  "properties": {
    "gn:admin1_code":"4.0",
    "gn:asciiname":"Toudoun Kiria",
    "gn:country_code":"NE",
    "gn:dem":454,
    "gn:feature_class":"P",
    "gn:feature_code":"PPL",
    "gn:name":"Toudoun Kiria",
    "gn:population":0,
    "gn:timezone":"Africa/Niamey",
    "iso:country":"NE",
    "wof:name":"Toudoun Kiria",
    "wof:placetype":"locality"
},
  "geometry": {"coordinates":[8.26674,13.63034],"type":"Point"}
}