{
  "type": "Feature",
  "properties": {
    "gn:admin1_code":"6.0",
    "gn:asciiname":"Zangebe Tara",
    "gn:country_code":"NE",
    "gn:dem":518,
    "gn:feature_class":"P",
    "gn:feature_code":"PPL",
    "gn:name":"Zang\u00e9be Tara",
    "gn:population":0,
    "gn:timezone":"Africa/Niamey",
    "iso:country":"NE",
    "wof:name":"Zangebe Tara",
    "wof:placetype":"locality"
},
  "geometry": {"coordinates":[6.19726,14.80715],"type":"Point"}
}