{
  "type": "Feature",
  "properties": {
    "gn:admin1_code":"7.0",
    "gn:asciiname":"Malamawa",
    "gn:country_code":"NE",
    "gn:dem":448,
    "gn:feature_class":"P",
    "gn:feature_code":"PPL",
    "gn:name":"M\u00e2lamawa",
    "gn:population":0,
    "gn:timezone":"Africa/Niamey",
    "iso:country":"NE",
    "wof:name":"Malamawa",
    "wof:placetype":"locality"
},
  "geometry": {"coordinates":[8.36093,13.74885],"type":"Point"}
}