{
  "type": "Feature",
  "properties": {
    "gn:admin1_code":"6.0",
    "gn:asciiname":"Moulela",
    "gn:country_code":"NE",
    "gn:dem":424,
    "gn:feature_class":"P",
    "gn:feature_code":"PPL",
    "gn:name":"Moul\u00e9la",
    "gn:population":0,
    "gn:timezone":"Africa/Niamey",
    "iso:country":"NE",
    "wof:name":"Moulela",
    "wof:placetype":"locality"
},
  "geometry": {"coordinates":[6.05356,14.42122],"type":"Point"}
}