{
  "type": "Feature",
  "properties": {
    "gn:admin1_code":"7.0",
    "gn:asciiname":"Agouma",
    "gn:country_code":"NE",
    "gn:dem":428,
    "gn:feature_class":"P",
    "gn:feature_code":"PPL",
    "gn:name":"Agouma",
    "gn:population":0,
    "gn:timezone":"Africa/Niamey",
    "iso:country":"NE",
    "wof:name":"Agouma",
    "wof:placetype":"locality"
},
  "geometry": {"coordinates":[9.8821,14.2493],"type":"Point"}
}