{
  "type": "Feature",
  "properties": {
    "gn:admin1_code":"3.0",
    "gn:asciiname":"Barma",
    "gn:country_code":"NE",
    "gn:dem":247,
    "gn:feature_class":"P",
    "gn:feature_code":"PPL",
    "gn:name":"Barma",
    "gn:population":0,
    "gn:timezone":"Africa/Niamey",
    "iso:country":"NE",
    "name:ceb_x_preferred":[
        "Barma"
    ],
    "name:fra_x_preferred":[
        "Barma"
    ],
    "name:hye_x_preferred":[
        "\u0532\u0561\u0580\u0574\u0561"
    ],
    "name:ita_x_preferred":[
        "Barma"
    ],
    "name:rus_x_preferred":[
        "\u0411\u0430\u0440\u043c\u0430"
    ],
    "name:swe_x_preferred":[
        "Barma"
    ],
    "wof:name":"Barma",
    "wof:placetype":"locality"
},
  "geometry": {"coordinates":[3.1711,13.242],"type":"Point"}
}