{
  "type": "Feature",
  "properties": {
    "gn:admin1_code":"9.0",
    "gn:asciiname":"Hamdallay",
    "gn:country_code":"NE",
    "gn:dem":222,
    "gn:feature_class":"P",
    "gn:feature_code":"PPL",
    "gn:name":"Hamdallay",
    "gn:population":0,
    "gn:timezone":"Africa/Niamey",
    "iso:country":"NE",
    "name:deu_x_preferred":[
        "Hamdallaye"
    ],
    "name:fin_x_preferred":[
        "Hamdallaye"
    ],
    "name:ita_x_preferred":[
        "Hamdallaye"
    ],
    "name:msa_x_preferred":[
        "Hamdallaye"
    ],
    "name:ron_x_preferred":[
        "Hamdallaye"
    ],
    "name:spa_x_preferred":[
        "Hamdallaye"
    ],
    "name:und_x_variant":[
        "Amdallaye",
        "Djerma",
        "Hamdilaye",
        "Hamdallay"
    ],
    "wof:name":"Hamdallay",
    "wof:placetype":"locality"
},
  "geometry": {"coordinates":[2.4108,13.5583],"type":"Point"}
}