{
  "type": "Feature",
  "properties": {
    "gn:admin1_code":"7.0",
    "gn:asciiname":"Kredi",
    "gn:country_code":"NE",
    "gn:dem":436,
    "gn:feature_class":"P",
    "gn:feature_code":"PPL",
    "gn:name":"Kr\u00e9di",
    "gn:population":0,
    "gn:timezone":"Africa/Niamey",
    "iso:country":"NE",
    "wof:name":"Kredi",
    "wof:placetype":"locality"
},
  "geometry": {"coordinates":[10.1718,14.2663],"type":"Point"}
}