{
  "type": "Feature",
  "properties": {
    "gn:admin1_code":"3.0",
    "gn:asciiname":"Guiwa",
    "gn:country_code":"NE",
    "gn:dem":229,
    "gn:feature_class":"P",
    "gn:feature_code":"PPL",
    "gn:name":"Guiwa",
    "gn:population":0,
    "gn:timezone":"Africa/Niamey",
    "iso:country":"NE",
    "wof:name":"Guiwa",
    "wof:placetype":"locality"
},
  "geometry": {"coordinates":[4.15719,13.4927],"type":"Point"}
}