{
  "type": "Feature",
  "properties": {
    "gn:admin1_code":"7.0",
    "gn:asciiname":"Maza Malendi",
    "gn:country_code":"NE",
    "gn:dem":391,
    "gn:feature_class":"P",
    "gn:feature_code":"PPL",
    "gn:name":"Maza Malendi",
    "gn:population":0,
    "gn:timezone":"Africa/Niamey",
    "iso:country":"NE",
    "wof:name":"Maza Malendi",
    "wof:placetype":"locality"
},
  "geometry": {"coordinates":[9.82097,13.81158],"type":"Point"}
}