{
  "type": "Feature",
  "properties": {
    "gn:admin1_code":"4.0",
    "gn:asciiname":"Dan Ja Amoute",
    "gn:country_code":"NE",
    "gn:dem":379,
    "gn:feature_class":"P",
    "gn:feature_code":"PPL",
    "gn:name":"Dan Ja Amout\u00e9",
    "gn:population":0,
    "gn:timezone":"Africa/Niamey",
    "iso:country":"NE",
    "wof:name":"Dan Ja Amoute",
    "wof:placetype":"locality"
},
  "geometry": {"coordinates":[7.11046,14.15348],"type":"Point"}
}