{
  "type": "Feature",
  "properties": {
    "gn:admin1_code":"3.0",
    "gn:asciiname":"Garyangoul",
    "gn:country_code":"NE",
    "gn:dem":305,
    "gn:feature_class":"P",
    "gn:feature_code":"PPL",
    "gn:name":"Garyangoul",
    "gn:population":0,
    "gn:timezone":"Africa/Niamey",
    "iso:country":"NE",
    "wof:name":"Garyangoul",
    "wof:placetype":"locality"
},
  "geometry": {"coordinates":[4.41859,13.92359],"type":"Point"}
}