{
  "type": "Feature",
  "properties": {
    "gn:admin1_code":"9.0",
    "gn:asciiname":"Dey",
    "gn:country_code":"NE",
    "gn:dem":244,
    "gn:feature_class":"P",
    "gn:feature_code":"PPL",
    "gn:name":"D\u00e8y",
    "gn:population":0,
    "gn:timezone":"Africa/Niamey",
    "iso:country":"NE",
    "name:ara_x_preferred":[
        "\u062f\u0627\u064a \u0627\u0644\u062c\u0632\u0627\u0626\u0631"
    ],
    "name:cat_x_preferred":[
        "Dey"
    ],
    "name:deu_x_preferred":[
        "Dey"
    ],
    "name:ell_x_preferred":[
        "\u039d\u03c4\u03b1\u03ae\u03c2"
    ],
    "name:fra_x_preferred":[
        "Dey d'Alger"
    ],
    "name:heb_x_preferred":[
        "\u05d3\u05d9\u05d9"
    ],
    "name:ita_x_preferred":[
        "Dey"
    ],
    "name:jpn_x_preferred":[
        "\u30c7\u30a4"
    ],
    "name:rus_x_preferred":[
        "\u0414\u0435\u0438 \u0410\u043b\u0436\u0438\u0440\u0430"
    ],
    "name:swe_x_preferred":[
        "Dej"
    ],
    "name:tur_x_preferred":[
        "Day\u0131"
    ],
    "name:uzb_x_preferred":[
        "Dey"
    ],
    "wof:name":"Dey",
    "wof:placetype":"locality"
},
  "geometry": {"coordinates":[1.82635,14.33022],"type":"Point"}
}