{
  "type": "Feature",
  "properties": {
    "gn:admin1_code":"7.0",
    "gn:asciiname":"Dangoum",
    "gn:country_code":"NE",
    "gn:dem":484,
    "gn:feature_class":"P",
    "gn:feature_code":"PPL",
    "gn:name":"Dangoum",
    "gn:population":0,
    "gn:timezone":"Africa/Niamey",
    "iso:country":"NE",
    "wof:name":"Dangoum",
    "wof:placetype":"locality"
},
  "geometry": {"coordinates":[9.1603,14.5611],"type":"Point"}
}