{
  "type": "Feature",
  "properties": {
    "gn:admin1_code":"7.0",
    "gn:asciiname":"Ganoua",
    "gn:country_code":"NE",
    "gn:dem":462,
    "gn:feature_class":"P",
    "gn:feature_code":"PPL",
    "gn:name":"Ganou\u00e2",
    "gn:population":0,
    "gn:timezone":"Africa/Niamey",
    "iso:country":"NE",
    "wof:name":"Ganoua",
    "wof:placetype":"locality"
},
  "geometry": {"coordinates":[8.54864,13.57035],"type":"Point"}
}