{
  "type": "Feature",
  "properties": {
    "gn:admin1_code":"9.0",
    "gn:asciiname":"Bakin Toulou",
    "gn:country_code":"NE",
    "gn:dem":229,
    "gn:feature_class":"P",
    "gn:feature_code":"PPL",
    "gn:name":"Bakin Toulou",
    "gn:population":0,
    "gn:timezone":"Africa/Niamey",
    "iso:country":"NE",
    "wof:name":"Bakin Toulou",
    "wof:placetype":"locality"
},
  "geometry": {"coordinates":[3.4562,14.4116],"type":"Point"}
}