{
  "type": "Feature",
  "properties": {
    "gn:admin1_code":"7.0",
    "gn:asciiname":"Choki Elkardawa",
    "gn:country_code":"NE",
    "gn:dem":479,
    "gn:feature_class":"P",
    "gn:feature_code":"PPL",
    "gn:name":"Choki Elkardawa",
    "gn:population":0,
    "gn:timezone":"Africa/Niamey",
    "iso:country":"NE",
    "wof:name":"Choki Elkardawa",
    "wof:placetype":"locality"
},
  "geometry": {"coordinates":[8.41186,13.44729],"type":"Point"}
}