{
  "type": "Feature",
  "properties": {
    "gn:admin1_code":"9.0",
    "gn:asciiname":"Fambita",
    "gn:country_code":"NE",
    "gn:dem":266,
    "gn:feature_class":"P",
    "gn:feature_code":"PPL",
    "gn:name":"Fambita",
    "gn:population":0,
    "gn:timezone":"Africa/Niamey",
    "iso:country":"NE",
    "name:und_x_variant":[
        "Famb\u00e9ta",
        "Fambita"
    ],
    "wof:name":"Fambita",
    "wof:placetype":"locality"
},
  "geometry": {"coordinates":[0.89936,14.33393],"type":"Point"}
}