{
  "type": "Feature",
  "properties": {
    "gn:admin1_code":"6.0",
    "gn:asciiname":"Dan Kande",
    "gn:country_code":"NE",
    "gn:dem":293,
    "gn:feature_class":"P",
    "gn:feature_code":"PPL",
    "gn:name":"Dan Kand\u00e9",
    "gn:population":0,
    "gn:timezone":"Africa/Niamey",
    "iso:country":"NE",
    "wof:name":"Dan Kande",
    "wof:placetype":"locality"
},
  "geometry": {"coordinates":[6.02718,13.72284],"type":"Point"}
}