{
  "type": "Feature",
  "properties": {
    "gn:admin1_code":"3.0",
    "gn:asciiname":"Tombo Assane",
    "gn:country_code":"NE",
    "gn:dem":241,
    "gn:feature_class":"P",
    "gn:feature_code":"PPL",
    "gn:name":"Tombo Assane",
    "gn:population":0,
    "gn:timezone":"Africa/Niamey",
    "iso:country":"NE",
    "name:und_x_variant":[
        "Tomboasan",
        "Tomboassan",
        "Tombo Assane",
        "Assane Kouara"
    ],
    "wof:name":"Tombo Assane",
    "wof:placetype":"locality"
},
  "geometry": {"coordinates":[2.78677,12.92591],"type":"Point"}
}