{
  "type": "Feature",
  "properties": {
    "gn:admin1_code":"9.0",
    "gn:asciiname":"Tielolbaleol",
    "gn:country_code":"NE",
    "gn:dem":246,
    "gn:feature_class":"P",
    "gn:feature_code":"PPL",
    "gn:name":"Ti\u00e9lolbal\u00e9ol",
    "gn:population":0,
    "gn:timezone":"Africa/Niamey",
    "iso:country":"NE",
    "name:und_x_variant":[
        "Ti\u00e9lolbal\u00e9ol",
        "Ty\u00e9lolbal\u00e9ol"
    ],
    "wof:name":"Tielolbaleol",
    "wof:placetype":"locality"
},
  "geometry": {"coordinates":[1.79928,12.64815],"type":"Point"}
}