{
  "type": "Feature",
  "properties": {
    "gn:admin1_code":"3.0",
    "gn:asciiname":"Sadoura",
    "gn:country_code":"NE",
    "gn:dem":265,
    "gn:feature_class":"P",
    "gn:feature_code":"PPL",
    "gn:name":"Sadoura",
    "gn:population":0,
    "gn:timezone":"Africa/Niamey",
    "iso:country":"NE",
    "wof:name":"Sadoura",
    "wof:placetype":"locality"
},
  "geometry": {"coordinates":[4.3488,14.08661],"type":"Point"}
}