{
  "type": "Feature",
  "properties": {
    "gn:admin1_code":"7.0",
    "gn:asciiname":"Maygarke",
    "gn:country_code":"NE",
    "gn:dem":473,
    "gn:feature_class":"P",
    "gn:feature_code":"PPL",
    "gn:name":"Maygark\u00e9",
    "gn:population":0,
    "gn:timezone":"Africa/Niamey",
    "iso:country":"NE",
    "wof:name":"Maygarke",
    "wof:placetype":"locality"
},
  "geometry": {"coordinates":[8.96491,14.22121],"type":"Point"}
}