{
  "type": "Feature",
  "properties": {
    "gn:admin1_code":"3.0",
    "gn:asciiname":"Kotifafa",
    "gn:country_code":"NE",
    "gn:dem":248,
    "gn:feature_class":"P",
    "gn:feature_code":"PPL",
    "gn:name":"Kotifafa",
    "gn:population":0,
    "gn:timezone":"Africa/Niamey",
    "iso:country":"NE",
    "wof:name":"Kotifafa",
    "wof:placetype":"locality"
},
  "geometry": {"coordinates":[3.3373,13.25],"type":"Point"}
}