{
  "type": "Feature",
  "properties": {
    "gn:admin1_code":"7.0",
    "gn:asciiname":"Kafa",
    "gn:country_code":"NE",
    "gn:dem":530,
    "gn:feature_class":"P",
    "gn:feature_code":"PPL",
    "gn:name":"Kafa",
    "gn:population":0,
    "gn:timezone":"Africa/Niamey",
    "iso:country":"NE",
    "name:cat_x_preferred":[
        "Kafa"
    ],
    "name:ceb_x_preferred":[
        "Kafa"
    ],
    "name:swe_x_preferred":[
        "Kafa"
    ],
    "name:tur_x_preferred":[
        "Kafa"
    ],
    "wof:name":"Kafa",
    "wof:placetype":"locality"
},
  "geometry": {"coordinates":[9.2379,14.1322],"type":"Point"}
}