{
  "type": "Feature",
  "properties": {
    "gn:admin1_code":"7.0",
    "gn:asciiname":"May Serka",
    "gn:country_code":"NE",
    "gn:dem":442,
    "gn:feature_class":"P",
    "gn:feature_code":"PPL",
    "gn:name":"May S\u00e8rka",
    "gn:population":0,
    "gn:timezone":"Africa/Niamey",
    "iso:country":"NE",
    "wof:name":"May Serka",
    "wof:placetype":"locality"
},
  "geometry": {"coordinates":[8.38333,14.85],"type":"Point"}
}