{
  "type": "Feature",
  "properties": {
    "gn:admin1_code":"7.0",
    "gn:asciiname":"Kataka Bori",
    "gn:country_code":"NE",
    "gn:dem":358,
    "gn:feature_class":"P",
    "gn:feature_code":"PPL",
    "gn:name":"Kataka Bori",
    "gn:population":0,
    "gn:timezone":"Africa/Niamey",
    "iso:country":"NE",
    "wof:name":"Kataka Bori",
    "wof:placetype":"locality"
},
  "geometry": {"coordinates":[9.79081,12.98563],"type":"Point"}
}