{
  "type": "Feature",
  "properties": {
    "gn:admin1_code":"3.0",
    "gn:asciiname":"Louguedyan Bornou",
    "gn:country_code":"NE",
    "gn:dem":181,
    "gn:feature_class":"P",
    "gn:feature_code":"PPL",
    "gn:name":"Lougu\u00e9dyan Bornou",
    "gn:population":0,
    "gn:timezone":"Africa/Niamey",
    "iso:country":"NE",
    "name:und_x_variant":[
        "Loug\u00e9dyan Bornou",
        "Lougu\u00e9dyan Bornou"
    ],
    "wof:name":"Louguedyan Bornou",
    "wof:placetype":"locality"
},
  "geometry": {"coordinates":[2.92558,12.74008],"type":"Point"}
}