{
  "type": "Feature",
  "properties": {
    "gn:admin1_code":"6.0",
    "gn:asciiname":"Kadouba",
    "gn:country_code":"NE",
    "gn:dem":312,
    "gn:feature_class":"P",
    "gn:feature_code":"PPL",
    "gn:name":"Kadouba",
    "gn:population":0,
    "gn:timezone":"Africa/Niamey",
    "iso:country":"NE",
    "wof:name":"Kadouba",
    "wof:placetype":"locality"
},
  "geometry": {"coordinates":[5.2156,14.5783],"type":"Point"}
}