{
  "type": "Feature",
  "properties": {
    "gn:admin1_code":"9.0",
    "gn:asciiname":"Jakasa",
    "gn:country_code":"NE",
    "gn:dem":241,
    "gn:feature_class":"P",
    "gn:feature_code":"PPL",
    "gn:name":"Jakasa",
    "gn:population":0,
    "gn:timezone":"Africa/Niamey",
    "iso:country":"NE",
    "name:und_x_variant":[
        "Jakassa",
        "Jakasa"
    ],
    "wof:name":"Jakasa",
    "wof:placetype":"locality"
},
  "geometry": {"coordinates":[3.3927,15.0503],"type":"Point"}
}