{
  "type": "Feature",
  "properties": {
    "gn:admin1_code":"6.0",
    "gn:asciiname":"Wakou",
    "gn:country_code":"NE",
    "gn:dem":437,
    "gn:feature_class":"P",
    "gn:feature_code":"PPL",
    "gn:name":"Wakou",
    "gn:population":0,
    "gn:timezone":"Africa/Niamey",
    "iso:country":"NE",
    "name:und_x_variant":[
        "Ouakou",
        "Wakou"
    ],
    "wof:name":"Wakou",
    "wof:placetype":"locality"
},
  "geometry": {"coordinates":[5.2465,15.1193],"type":"Point"}
}