{
  "type": "Feature",
  "properties": {
    "gn:admin1_code":"3.0",
    "gn:asciiname":"Badifa",
    "gn:country_code":"NE",
    "gn:dem":250,
    "gn:feature_class":"P",
    "gn:feature_code":"PPL",
    "gn:name":"Badifa",
    "gn:population":0,
    "gn:timezone":"Africa/Niamey",
    "iso:country":"NE",
    "name:und_x_variant":[
        "Badefa",
        "Banifa",
        "Badifa"
    ],
    "wof:name":"Badifa",
    "wof:placetype":"locality"
},
  "geometry": {"coordinates":[3.78577,13.20826],"type":"Point"}
}