{
  "type": "Feature",
  "properties": {
    "gn:admin1_code":"7.0",
    "gn:asciiname":"Gourgam",
    "gn:country_code":"NE",
    "gn:dem":354,
    "gn:feature_class":"P",
    "gn:feature_code":"PPL",
    "gn:name":"Gourgam",
    "gn:population":0,
    "gn:timezone":"Africa/Niamey",
    "iso:country":"NE",
    "wof:name":"Gourgam",
    "wof:placetype":"locality"
},
  "geometry": {"coordinates":[10.48503,13.55238],"type":"Point"}
}