{
  "type": "Feature",
  "properties": {
    "gn:admin1_code":"4.0",
    "gn:asciiname":"Tabkin Guiwa",
    "gn:country_code":"NE",
    "gn:dem":457,
    "gn:feature_class":"P",
    "gn:feature_code":"PPL",
    "gn:name":"Tabkin Guiwa",
    "gn:population":0,
    "gn:timezone":"Africa/Niamey",
    "iso:country":"NE",
    "name:und_x_variant":[
        "Topkin Giwa",
        "Tapkin Giwa",
        "Tibiri",
        "Tabkin Guiwa"
    ],
    "wof:name":"Tabkin Guiwa",
    "wof:placetype":"locality"
},
  "geometry": {"coordinates":[7.55194,13.31747],"type":"Point"}
}