{
  "type": "Feature",
  "properties": {
    "gn:admin1_code":"6.0",
    "gn:asciiname":"Garadoume",
    "gn:country_code":"NE",
    "gn:dem":387,
    "gn:feature_class":"P",
    "gn:feature_code":"PPL",
    "gn:name":"Garadoum\u00e9",
    "gn:population":0,
    "gn:timezone":"Africa/Niamey",
    "iso:country":"NE",
    "name:und_x_variant":[
        "Garadoum",
        "Garadoum\u00e9"
    ],
    "wof:name":"Garadoume",
    "wof:placetype":"locality"
},
  "geometry": {"coordinates":[5.8888,14.3679],"type":"Point"}
}