{
  "type": "Feature",
  "properties": {
    "gn:admin1_code":"1.0",
    "gn:asciiname":"I-n-Gall",
    "gn:country_code":"NE",
    "gn:dem":488,
    "gn:feature_class":"P",
    "gn:feature_code":"PPL",
    "gn:name":"I-n-Gall",
    "gn:population":0,
    "gn:timezone":"Africa/Niamey",
    "iso:country":"NE",
    "name:cat_x_preferred":[
        "Ingall"
    ],
    "name:ceb_x_preferred":[
        "I-n-Gall"
    ],
    "name:deu_x_preferred":[
        "Ingall"
    ],
    "name:fin_x_preferred":[
        "Ingall"
    ],
    "name:fra_x_preferred":[
        "Ingall"
    ],
    "name:ita_x_preferred":[
        "Ingall"
    ],
    "name:msa_x_preferred":[
        "In-Gall"
    ],
    "name:ron_x_preferred":[
        "Ingall"
    ],
    "name:spa_x_preferred":[
        "In-Gall"
    ],
    "name:swe_x_preferred":[
        "In-Gall"
    ],
    "name:und_x_variant":[
        "In-Gal",
        "Ingal"
    ],
    "wof:name":"I-n-Gall",
    "wof:placetype":"locality"
},
  "geometry": {"coordinates":[6.93417,16.78778],"type":"Point"}
}