{
  "type": "Feature",
  "properties": {
    "gn:admin1_code":"7.0",
    "gn:asciiname":"Majyankari",
    "gn:country_code":"NE",
    "gn:dem":378,
    "gn:feature_class":"P",
    "gn:feature_code":"PPL",
    "gn:name":"Majyankari",
    "gn:population":0,
    "gn:timezone":"Africa/Niamey",
    "iso:country":"NE",
    "wof:name":"Majyankari",
    "wof:placetype":"locality"
},
  "geometry": {"coordinates":[9.222,13.0119],"type":"Point"}
}