{
  "type": "Feature",
  "properties": {
    "gn:admin1_code":"9.0",
    "gn:asciiname":"Deli Tondi Kouara Zeno",
    "gn:country_code":"NE",
    "gn:dem":242,
    "gn:feature_class":"P",
    "gn:feature_code":"PPL",
    "gn:name":"D\u00e9li Tondi Kouara Z\u00e9no",
    "gn:population":0,
    "gn:timezone":"Africa/Niamey",
    "iso:country":"NE",
    "wof:name":"Deli Tondi Kouara Zeno",
    "wof:placetype":"locality"
},
  "geometry": {"coordinates":[2.2037,13.9935],"type":"Point"}
}