{
  "type": "Feature",
  "properties": {
    "gn:admin1_code":"9.0",
    "gn:asciiname":"Dayberi",
    "gn:country_code":"NE",
    "gn:dem":204,
    "gn:feature_class":"P",
    "gn:feature_code":"PPL",
    "gn:name":"Dayb\u00e9ri",
    "gn:population":0,
    "gn:timezone":"Africa/Niamey",
    "iso:country":"NE",
    "name:und_x_variant":[
        "Dalb\u00e9ri",
        "Dey B\u00e9ri",
        "Daib\u00e9ri",
        "Dayb\u00e9ri"
    ],
    "wof:name":"Dayberi",
    "wof:placetype":"locality"
},
  "geometry": {"coordinates":[1.50572,14.159],"type":"Point"}
}