{
  "type": "Feature",
  "properties": {
    "gn:admin1_code":"4.0",
    "gn:asciiname":"Chabare",
    "gn:country_code":"NE",
    "gn:dem":427,
    "gn:feature_class":"P",
    "gn:feature_code":"PPL",
    "gn:name":"Chabar\u00e9",
    "gn:population":0,
    "gn:timezone":"Africa/Niamey",
    "iso:country":"NE",
    "name:und_x_variant":[
        "Ghabar\u00e9",
        "Chabar\u00e9"
    ],
    "wof:name":"Chabare",
    "wof:placetype":"locality"
},
  "geometry": {"coordinates":[8.17774,13.73417],"type":"Point"}
}