{
  "type": "Feature",
  "properties": {
    "gn:admin1_code":"3.0",
    "gn:asciiname":"Tinoma",
    "gn:country_code":"NE",
    "gn:dem":197,
    "gn:feature_class":"P",
    "gn:feature_code":"PPL",
    "gn:name":"Tinoma",
    "gn:population":0,
    "gn:timezone":"Africa/Niamey",
    "iso:country":"NE",
    "wof:name":"Tinoma",
    "wof:placetype":"locality"
},
  "geometry": {"coordinates":[2.8781,13.2153],"type":"Point"}
}