{
  "type": "Feature",
  "properties": {
    "gn:admin1_code":"4.0",
    "gn:asciiname":"Illias Saboua",
    "gn:country_code":"NE",
    "gn:dem":353,
    "gn:feature_class":"P",
    "gn:feature_code":"PPL",
    "gn:name":"Illias Saboua",
    "gn:population":0,
    "gn:timezone":"Africa/Niamey",
    "iso:country":"NE",
    "wof:name":"Illias Saboua",
    "wof:placetype":"locality"
},
  "geometry": {"coordinates":[6.71,13.93],"type":"Point"}
}