{
  "type": "Feature",
  "properties": {
    "gn:admin1_code":"9.0",
    "gn:asciiname":"I-n-Tousen",
    "gn:country_code":"NE",
    "gn:dem":268,
    "gn:feature_class":"P",
    "gn:feature_code":"PPL",
    "gn:name":"I-n-Tousen",
    "gn:population":0,
    "gn:timezone":"Africa/Niamey",
    "iso:country":"NE",
    "name:und_x_variant":[
        "In Tousen",
        "I-n-Tousen"
    ],
    "wof:name":"I-n-Tousen",
    "wof:placetype":"locality"
},
  "geometry": {"coordinates":[3.2341,15.1224],"type":"Point"}
}