{
  "type": "Feature",
  "properties": {
    "gn:admin1_code":"7.0",
    "gn:asciiname":"Kame",
    "gn:country_code":"NE",
    "gn:dem":459,
    "gn:feature_class":"P",
    "gn:feature_code":"PPL",
    "gn:name":"Kam\u00e9",
    "gn:population":0,
    "gn:timezone":"Africa/Niamey",
    "iso:country":"NE",
    "name:bar_x_preferred":[
        "Kame"
    ],
    "name:bel_x_preferred":[
        "\u041a\u0430\u043c\u044b"
    ],
    "name:bul_x_preferred":[
        "\u041a\u0430\u043c\u0438"
    ],
    "name:ces_x_preferred":[
        "Kamy"
    ],
    "name:csb_x_preferred":[
        "Kem"
    ],
    "name:deu_x_preferred":[
        "Kame"
    ],
    "name:est_x_preferred":[
        "M\u00f5hn"
    ],
    "name:fas_x_preferred":[
        "\u067e\u0634\u062a\u0647 \u06cc\u062e\u0686\u0627\u0644\u06cc"
    ],
    "name:fin_x_preferred":[
        "Kames-muodostumat"
    ],
    "name:fra_x_preferred":[
        "Kame"
    ],
    "name:glg_x_preferred":[
        "Kame"
    ],
    "name:hin_x_preferred":[
        "\u0915\u0947\u092e"
    ],
    "name:hun_x_preferred":[
        "Kame"
    ],
    "name:hye_x_preferred":[
        "\u053f\u0561\u0574"
    ],
    "name:ita_x_preferred":[
        "Kame"
    ],
    "name:lav_x_preferred":[
        "K\u0113ms"
    ],
    "name:lit_x_preferred":[
        "Keimas"
    ],
    "name:nld_x_preferred":[
        "Kame"
    ],
    "name:nno_x_preferred":[
        "Kame"
    ],
    "name:pol_x_preferred":[
        "Kem"
    ],
    "name:por_x_preferred":[
        "Kame"
    ],
    "name:rus_x_preferred":[
        "\u041a\u0430\u043c\u044b"
    ],
    "name:spa_x_preferred":[
        "Kame"
    ],
    "name:swe_x_preferred":[
        "Kame"
    ],
    "name:ukr_x_preferred":[
        "\u041a\u0430\u043c\u0438"
    ],
    "name:zho_x_preferred":[
        "\u51b0\u783e\u961c"
    ],
    "wof:name":"Kame",
    "wof:placetype":"locality"
},
  "geometry": {"coordinates":[8.57734,13.23088],"type":"Point"}
}