{
  "type": "Feature",
  "properties": {
    "gn:admin1_code":"4.0",
    "gn:asciiname":"Tambarawa",
    "gn:country_code":"NE",
    "gn:dem":334,
    "gn:feature_class":"P",
    "gn:feature_code":"PPL",
    "gn:name":"Tambarawa",
    "gn:population":0,
    "gn:timezone":"Africa/Niamey",
    "iso:country":"NE",
    "wof:name":"Tambarawa",
    "wof:placetype":"locality"
},
  "geometry": {"coordinates":[6.79541,13.72197],"type":"Point"}
}