{
  "type": "Feature",
  "properties": {
    "gn:admin1_code":"7.0",
    "gn:asciiname":"Targa",
    "gn:country_code":"NE",
    "gn:dem":510,
    "gn:feature_class":"P",
    "gn:feature_code":"PPL",
    "gn:name":"Targa",
    "gn:population":0,
    "gn:timezone":"Africa/Niamey",
    "iso:country":"NE",
    "wof:name":"Targa",
    "wof:placetype":"locality"
},
  "geometry": {"coordinates":[9.8204,14.368],"type":"Point"}
}