{
  "type": "Feature",
  "properties": {
    "gn:admin1_code":"7.0",
    "gn:asciiname":"Targa",
    "gn:country_code":"NE",
    "gn:dem":510,
    "gn:feature_class":"P",
    "gn:feature_code":"PPL",
    "gn:name":"Targa",
    "gn:population":0,
    "gn:timezone":"Africa/Niamey",
    "iso:country":"NE",
    "name:cat_x_preferred":[
        "Targa"
    ],
    "name:ceb_x_preferred":[
        "Targa"
    ],
    "name:ces_x_preferred":[
        "Targa"
    ],
    "name:deu_x_preferred":[
        "Targa"
    ],
    "name:fra_x_preferred":[
        "Targa"
    ],
    "name:ita_x_preferred":[
        "Targa"
    ],
    "name:nld_x_preferred":[
        "Targa"
    ],
    "name:swe_x_preferred":[
        "Targa"
    ],
    "wof:name":"Targa",
    "wof:placetype":"locality"
},
  "geometry": {"coordinates":[9.8204,14.368],"type":"Point"}
}