{
  "type": "Feature",
  "properties": {
    "gn:admin1_code":"7.0",
    "gn:asciiname":"Garin Ala",
    "gn:country_code":"NE",
    "gn:dem":468,
    "gn:feature_class":"P",
    "gn:feature_code":"PPL",
    "gn:name":"Garin Ala",
    "gn:population":0,
    "gn:timezone":"Africa/Niamey",
    "iso:country":"NE",
    "wof:name":"Garin Ala",
    "wof:placetype":"locality"
},
  "geometry": {"coordinates":[8.9198,14.224],"type":"Point"}
}