{
  "type": "Feature",
  "properties": {
    "gn:admin1_code":"9.0",
    "gn:asciiname":"Baleyara",
    "gn:country_code":"NE",
    "gn:dem":211,
    "gn:feature_class":"P",
    "gn:feature_code":"PPL",
    "gn:name":"Bal\u00e9yara",
    "gn:population":0,
    "gn:timezone":"Africa/Niamey",
    "iso:country":"NE",
    "wof:name":"Baleyara",
    "wof:placetype":"locality"
},
  "geometry": {"coordinates":[2.9523,13.7838],"type":"Point"}
}