{
  "type": "Feature",
  "properties": {
    "gn:admin1_code":"8.0",
    "gn:asciiname":"Banizoumbou",
    "gn:country_code":"NE",
    "gn:dem":223,
    "gn:feature_class":"P",
    "gn:feature_code":"PPL",
    "gn:name":"Banizoumbou",
    "gn:population":0,
    "gn:timezone":"Africa/Niamey",
    "iso:country":"NE",
    "wof:name":"Banizoumbou",
    "wof:placetype":"locality"
},
  "geometry": {"coordinates":[2.15,13.56667],"type":"Point"}
}