{
  "type": "Feature",
  "properties": {
    "gn:admin1_code":"3.0",
    "gn:asciiname":"Bouringa Keyna",
    "gn:country_code":"NE",
    "gn:dem":178,
    "gn:feature_class":"P",
    "gn:feature_code":"PPL",
    "gn:name":"Bouringa Keyna",
    "gn:population":0,
    "gn:timezone":"Africa/Niamey",
    "iso:country":"NE",
    "name:und_x_variant":[
        "Bouringakaina",
        "Bouringa Keyna"
    ],
    "wof:name":"Bouringa Keyna",
    "wof:placetype":"locality"
},
  "geometry": {"coordinates":[2.89615,12.6423],"type":"Point"}
}