{
  "type": "Feature",
  "properties": {
    "gn:admin1_code":"9.0",
    "gn:asciiname":"Dangare",
    "gn:country_code":"NE",
    "gn:dem":210,
    "gn:feature_class":"P",
    "gn:feature_code":"PPL",
    "gn:name":"Dangar\u00e9",
    "gn:population":0,
    "gn:timezone":"Africa/Niamey",
    "iso:country":"NE",
    "name:und_x_variant":[
        "Dongar\u00e9",
        "Dangar\u00e9"
    ],
    "wof:name":"Dangare",
    "wof:placetype":"locality"
},
  "geometry": {"coordinates":[2.3161,13.1866],"type":"Point"}
}