{
  "type": "Feature",
  "properties": {
    "gn:admin1_code":"4.0",
    "gn:asciiname":"Sankarne",
    "gn:country_code":"NE",
    "gn:dem":430,
    "gn:feature_class":"P",
    "gn:feature_code":"PPL",
    "gn:name":"Sankarn\u00e9",
    "gn:population":0,
    "gn:timezone":"Africa/Niamey",
    "iso:country":"NE",
    "wof:name":"Sankarne",
    "wof:placetype":"locality"
},
  "geometry": {"coordinates":[7.22164,14.42143],"type":"Point"}
}