{
  "type": "Feature",
  "properties": {
    "gn:admin1_code":"2.0",
    "gn:asciiname":"Tyouari",
    "gn:country_code":"NE",
    "gn:dem":340,
    "gn:feature_class":"P",
    "gn:feature_code":"PPL",
    "gn:name":"Tyouari",
    "gn:population":0,
    "gn:timezone":"Africa/Niamey",
    "iso:country":"NE",
    "wof:name":"Tyouari",
    "wof:placetype":"locality"
},
  "geometry": {"coordinates":[10.91543,13.55591],"type":"Point"}
}