{
  "type": "Feature",
  "properties": {
    "gn:admin1_code":"9.0",
    "gn:asciiname":"Sonsoni",
    "gn:country_code":"NE",
    "gn:dem":197,
    "gn:feature_class":"P",
    "gn:feature_code":"PPL",
    "gn:name":"Sonsoni",
    "gn:population":0,
    "gn:timezone":"Africa/Niamey",
    "iso:country":"NE",
    "wof:name":"Sonsoni",
    "wof:placetype":"locality"
},
  "geometry": {"coordinates":[1.59618,13.8354],"type":"Point"}
}