{
  "type": "Feature",
  "properties": {
    "gn:admin1_code":"4.0",
    "gn:asciiname":"Gazori",
    "gn:country_code":"NE",
    "gn:dem":407,
    "gn:feature_class":"P",
    "gn:feature_code":"PPL",
    "gn:name":"Gazori",
    "gn:population":0,
    "gn:timezone":"Africa/Niamey",
    "iso:country":"NE",
    "wof:name":"Gazori",
    "wof:placetype":"locality"
},
  "geometry": {"coordinates":[7.95574,13.48465],"type":"Point"}
}