{
  "type": "Feature",
  "properties": {
    "gn:admin1_code":"7.0",
    "gn:asciiname":"Zinngui",
    "gn:country_code":"NE",
    "gn:dem":470,
    "gn:feature_class":"P",
    "gn:feature_code":"PPL",
    "gn:name":"Zinngui",
    "gn:population":0,
    "gn:timezone":"Africa/Niamey",
    "iso:country":"NE",
    "wof:name":"Zinngui",
    "wof:placetype":"locality"
},
  "geometry": {"coordinates":[8.63162,15.10996],"type":"Point"}
}