{
  "type": "Feature",
  "properties": {
    "gn:admin1_code":"6.0",
    "gn:asciiname":"Gidan Kaiya",
    "gn:country_code":"NE",
    "gn:dem":283,
    "gn:feature_class":"P",
    "gn:feature_code":"PPL",
    "gn:name":"Gidan Kaiya",
    "gn:population":0,
    "gn:timezone":"Africa/Niamey",
    "iso:country":"NE",
    "wof:name":"Gidan Kaiya",
    "wof:placetype":"locality"
},
  "geometry": {"coordinates":[5.18609,13.74073],"type":"Point"}
}