{
  "type": "Feature",
  "properties": {
    "gn:admin1_code":"4.0",
    "gn:asciiname":"Doukana",
    "gn:country_code":"NE",
    "gn:dem":329,
    "gn:feature_class":"P",
    "gn:feature_code":"PPL",
    "gn:name":"Doukana",
    "gn:population":0,
    "gn:timezone":"Africa/Niamey",
    "iso:country":"NE",
    "wof:name":"Doukana",
    "wof:placetype":"locality"
},
  "geometry": {"coordinates":[6.53546,13.93786],"type":"Point"}
}