{
  "type": "Feature",
  "properties": {
    "gn:admin1_code":"4.0",
    "gn:asciiname":"Batakolia",
    "gn:country_code":"NE",
    "gn:dem":393,
    "gn:feature_class":"P",
    "gn:feature_code":"PPL",
    "gn:name":"Batakolia",
    "gn:population":0,
    "gn:timezone":"Africa/Niamey",
    "iso:country":"NE",
    "name:und_x_variant":[
        "Bat\u00e9koliawa",
        "Batakolia"
    ],
    "wof:name":"Batakolia",
    "wof:placetype":"locality"
},
  "geometry": {"coordinates":[7.23967,13.67859],"type":"Point"}
}