{
  "type": "Feature",
  "properties": {
    "gn:admin1_code":"9.0",
    "gn:asciiname":"Kossa",
    "gn:country_code":"NE",
    "gn:dem":258,
    "gn:feature_class":"P",
    "gn:feature_code":"PPL",
    "gn:name":"Kossa",
    "gn:population":0,
    "gn:timezone":"Africa/Niamey",
    "iso:country":"NE",
    "name:ceb_x_preferred":[
        "Kossa"
    ],
    "name:deu_x_preferred":[
        "Kossa"
    ],
    "name:swe_x_preferred":[
        "Kossa"
    ],
    "name:und_x_variant":[
        "Gossa",
        "Kossa"
    ],
    "wof:name":"Kossa",
    "wof:placetype":"locality"
},
  "geometry": {"coordinates":[0.26571,14.6238],"type":"Point"}
}