{
  "type": "Feature",
  "properties": {
    "gn:admin1_code":"3.0",
    "gn:asciiname":"Oude Seybou",
    "gn:country_code":"NE",
    "gn:dem":196,
    "gn:feature_class":"P",
    "gn:feature_code":"PPL",
    "gn:name":"Oud\u00e9 Seybou",
    "gn:population":0,
    "gn:timezone":"Africa/Niamey",
    "iso:country":"NE",
    "name:und_x_variant":[
        "Ound\u00e9 Sayoou",
        "Oud\u00e9 Seybou"
    ],
    "wof:name":"Oude Seybou",
    "wof:placetype":"locality"
},
  "geometry": {"coordinates":[2.9342,13.3051],"type":"Point"}
}