{
  "type": "Feature",
  "properties": {
    "gn:admin1_code":"7.0",
    "gn:asciiname":"Kerwoule",
    "gn:country_code":"NE",
    "gn:dem":482,
    "gn:feature_class":"P",
    "gn:feature_code":"PPL",
    "gn:name":"Kerwoul\u00e9",
    "gn:population":0,
    "gn:timezone":"Africa/Niamey",
    "iso:country":"NE",
    "wof:name":"Kerwoule",
    "wof:placetype":"locality"
},
  "geometry": {"coordinates":[8.92344,14.69188],"type":"Point"}
}