{
  "type": "Feature",
  "properties": {
    "gn:admin1_code":"7.0",
    "gn:asciiname":"Tchatchalo",
    "gn:country_code":"NE",
    "gn:dem":479,
    "gn:feature_class":"P",
    "gn:feature_code":"PPL",
    "gn:name":"Tchatchalo",
    "gn:population":0,
    "gn:timezone":"Africa/Niamey",
    "iso:country":"NE",
    "wof:name":"Tchatchalo",
    "wof:placetype":"locality"
},
  "geometry": {"coordinates":[9.6814,14.4312],"type":"Point"}
}