{
  "type": "Feature",
  "properties": {
    "gn:admin1_code":"7.0",
    "gn:asciiname":"Garin May Kare",
    "gn:country_code":"NE",
    "gn:dem":396,
    "gn:feature_class":"P",
    "gn:feature_code":"PPL",
    "gn:name":"Garin May Kar\u00e9",
    "gn:population":0,
    "gn:timezone":"Africa/Niamey",
    "iso:country":"NE",
    "wof:name":"Garin May Kare",
    "wof:placetype":"locality"
},
  "geometry": {"coordinates":[8.98121,13.0774],"type":"Point"}
}