{
  "type": "Feature",
  "properties": {
    "gn:admin1_code":"2.0",
    "gn:asciiname":"Niwa",
    "gn:country_code":"NE",
    "gn:dem":344,
    "gn:feature_class":"P",
    "gn:feature_code":"PPL",
    "gn:name":"Niwa",
    "gn:population":0,
    "gn:timezone":"Africa/Niamey",
    "iso:country":"NE",
    "name:bel_x_preferred":[
        "\u041d\u0456\u0432\u0430"
    ],
    "name:ceb_x_preferred":[
        "Niwa"
    ],
    "name:deu_x_preferred":[
        "Niwa"
    ],
    "name:fra_x_preferred":[
        "Niwa"
    ],
    "name:nld_x_preferred":[
        "Niwa"
    ],
    "name:pol_x_preferred":[
        "Niwa"
    ],
    "name:ukr_x_preferred":[
        "\u041d\u0456\u0432\u0430"
    ],
    "wof:name":"Niwa",
    "wof:placetype":"locality"
},
  "geometry": {"coordinates":[11.5554,13.7647],"type":"Point"}
}