{
  "type": "Feature",
  "properties": {
    "gn:admin1_code":"6.0",
    "gn:asciiname":"Zorare",
    "gn:country_code":"NE",
    "gn:dem":328,
    "gn:feature_class":"P",
    "gn:feature_code":"PPL",
    "gn:name":"Zorar\u00e9",
    "gn:population":0,
    "gn:timezone":"Africa/Niamey",
    "iso:country":"NE",
    "name:und_x_variant":[
        "Zaourar\u00e9",
        "Zouarare",
        "Zorar\u00e9"
    ],
    "wof:name":"Zorare",
    "wof:placetype":"locality"
},
  "geometry": {"coordinates":[5.4042,14.226],"type":"Point"}
}