{
  "type": "Feature",
  "properties": {
    "gn:admin1_code":"7.0",
    "gn:asciiname":"Bak'o Raouni",
    "gn:country_code":"NE",
    "gn:dem":477,
    "gn:feature_class":"P",
    "gn:feature_code":"PPL",
    "gn:name":"B\u00e2k'\u00f4 Raouni",
    "gn:population":0,
    "gn:timezone":"Africa/Niamey",
    "iso:country":"NE",
    "name:und_x_variant":[
        "Bakorowani",
        "Bakoraouni",
        "B\u00e2k'\u00f4 Raouni"
    ],
    "wof:name":"Bak'o Raouni",
    "wof:placetype":"locality"
},
  "geometry": {"coordinates":[8.37728,13.24176],"type":"Point"}
}