{
  "type": "Feature",
  "properties": {
    "gn:admin1_code":"4.0",
    "gn:asciiname":"Guidan Menou",
    "gn:country_code":"NE",
    "gn:dem":361,
    "gn:feature_class":"P",
    "gn:feature_code":"PPL",
    "gn:name":"Guidan M\u00e9nou",
    "gn:population":0,
    "gn:timezone":"Africa/Niamey",
    "iso:country":"NE",
    "wof:name":"Guidan Menou",
    "wof:placetype":"locality"
},
  "geometry": {"coordinates":[6.67194,14.6861],"type":"Point"}
}