{
  "type": "Feature",
  "properties": {
    "gn:admin1_code":"9.0",
    "gn:asciiname":"Fafa",
    "gn:country_code":"NE",
    "gn:dem":218,
    "gn:feature_class":"P",
    "gn:feature_code":"PPL",
    "gn:name":"Fafa",
    "gn:population":0,
    "gn:timezone":"Africa/Niamey",
    "iso:country":"NE",
    "wof:name":"Fafa",
    "wof:placetype":"locality"
},
  "geometry": {"coordinates":[2.9064,13.833],"type":"Point"}
}