{
  "type": "Feature",
  "properties": {
    "gn:admin1_code":"7.0",
    "gn:asciiname":"Dodori",
    "gn:country_code":"NE",
    "gn:dem":385,
    "gn:feature_class":"P",
    "gn:feature_code":"PPL",
    "gn:name":"Dodori",
    "gn:population":0,
    "gn:timezone":"Africa/Niamey",
    "iso:country":"NE",
    "wof:name":"Dodori",
    "wof:placetype":"locality"
},
  "geometry": {"coordinates":[10.6878,14.0873],"type":"Point"}
}