{
  "type": "Feature",
  "properties": {
    "gn:admin1_code":"7.0",
    "gn:asciiname":"Barawa Saboua",
    "gn:country_code":"NE",
    "gn:dem":426,
    "gn:feature_class":"P",
    "gn:feature_code":"PPL",
    "gn:name":"Barawa Saboua",
    "gn:population":0,
    "gn:timezone":"Africa/Niamey",
    "iso:country":"NE",
    "wof:name":"Barawa Saboua",
    "wof:placetype":"locality"
},
  "geometry": {"coordinates":[8.77988,13.47667],"type":"Point"}
}