{
  "type": "Feature",
  "properties": {
    "gn:admin1_code":"4.0",
    "gn:asciiname":"Farara Korao",
    "gn:country_code":"NE",
    "gn:dem":422,
    "gn:feature_class":"P",
    "gn:feature_code":"PPL",
    "gn:name":"Farara Korao",
    "gn:population":0,
    "gn:timezone":"Africa/Niamey",
    "iso:country":"NE",
    "name:und_x_variant":[
        "Farara",
        "Farara Korao"
    ],
    "wof:name":"Farara Korao",
    "wof:placetype":"locality"
},
  "geometry": {"coordinates":[6.79233,14.40407],"type":"Point"}
}