{
  "type": "Feature",
  "properties": {
    "gn:admin1_code":"7.0",
    "gn:asciiname":"Kanta",
    "gn:country_code":"NE",
    "gn:dem":425,
    "gn:feature_class":"P",
    "gn:feature_code":"PPL",
    "gn:name":"Kanta",
    "gn:population":0,
    "gn:timezone":"Africa/Niamey",
    "iso:country":"NE",
    "name:fin_x_preferred":[
        "Kanta"
    ],
    "name:lav_x_preferred":[
        "Kanta"
    ],
    "wof:name":"Kanta",
    "wof:placetype":"locality"
},
  "geometry": {"coordinates":[7.74138,14.78642],"type":"Point"}
}