{
  "type": "Feature",
  "properties": {
    "gn:admin1_code":"7.0",
    "gn:asciiname":"Maybobawa",
    "gn:country_code":"NE",
    "gn:dem":478,
    "gn:feature_class":"P",
    "gn:feature_code":"PPL",
    "gn:name":"Maybobawa",
    "gn:population":0,
    "gn:timezone":"Africa/Niamey",
    "iso:country":"NE",
    "wof:name":"Maybobawa",
    "wof:placetype":"locality"
},
  "geometry": {"coordinates":[8.9471,14.2362],"type":"Point"}
}