{
  "type": "Feature",
  "properties": {
    "gn:admin1_code":"9.0",
    "gn:asciiname":"Tera",
    "gn:country_code":"NE",
    "gn:dem":225,
    "gn:feature_class":"P",
    "gn:feature_code":"PPL",
    "gn:name":"T\u00e9ra",
    "gn:population":0,
    "gn:timezone":"Africa/Niamey",
    "iso:country":"NE",
    "name:bul_x_preferred":[
        "\u0422\u0435\u0440\u0430"
    ],
    "name:ceb_x_preferred":[
        "Tera"
    ],
    "name:deu_x_preferred":[
        "Tera"
    ],
    "name:eus_x_preferred":[
        "Tera"
    ],
    "name:fas_x_preferred":[
        "\u062a\u0631\u0627"
    ],
    "name:fin_x_preferred":[
        "Tera"
    ],
    "name:fra_x_preferred":[
        "Tera"
    ],
    "name:glg_x_preferred":[
        "Tera"
    ],
    "name:ita_x_preferred":[
        "Tera"
    ],
    "name:nds_x_preferred":[
        "Tera"
    ],
    "name:pap_x_preferred":[
        "Tera"
    ],
    "name:pol_x_preferred":[
        "Tera"
    ],
    "name:por_x_preferred":[
        "Tera"
    ],
    "name:rus_x_preferred":[
        "\u0422\u0435\u0440\u0430"
    ],
    "name:spa_x_preferred":[
        "Tera"
    ],
    "name:swe_x_preferred":[
        "Tera"
    ],
    "wof:name":"Tera",
    "wof:placetype":"locality"
},
  "geometry": {"coordinates":[2.0143,13.8572],"type":"Point"}
}