{
  "type": "Feature",
  "properties": {
    "gn:admin1_code":"7.0",
    "gn:asciiname":"Ansabera Enada",
    "gn:country_code":"NE",
    "gn:dem":378,
    "gn:feature_class":"P",
    "gn:feature_code":"PPL",
    "gn:name":"Ansab\u00e9ra Enada",
    "gn:population":0,
    "gn:timezone":"Africa/Niamey",
    "iso:country":"NE",
    "wof:name":"Ansabera Enada",
    "wof:placetype":"locality"
},
  "geometry": {"coordinates":[9.1613,12.93184],"type":"Point"}
}