{
  "type": "Feature",
  "properties": {
    "gn:admin1_code":"4.0",
    "gn:asciiname":"Maykaka",
    "gn:country_code":"NE",
    "gn:dem":402,
    "gn:feature_class":"P",
    "gn:feature_code":"PPL",
    "gn:name":"Maykaka",
    "gn:population":0,
    "gn:timezone":"Africa/Niamey",
    "iso:country":"NE",
    "wof:name":"Maykaka",
    "wof:placetype":"locality"
},
  "geometry": {"coordinates":[6.63785,14.25062],"type":"Point"}
}