{
  "type": "Feature",
  "properties": {
    "gn:admin1_code":"4.0",
    "gn:asciiname":"Dan Jaoudi",
    "gn:country_code":"NE",
    "gn:dem":390,
    "gn:feature_class":"P",
    "gn:feature_code":"PPL",
    "gn:name":"Dan Jaoudi",
    "gn:population":0,
    "gn:timezone":"Africa/Niamey",
    "iso:country":"NE",
    "wof:name":"Dan Jaoudi",
    "wof:placetype":"locality"
},
  "geometry": {"coordinates":[7.00975,14.73365],"type":"Point"}
}