{
  "type": "Feature",
  "properties": {
    "gn:admin1_code":"7.0",
    "gn:asciiname":"Guida Moussa",
    "gn:country_code":"NE",
    "gn:dem":481,
    "gn:feature_class":"P",
    "gn:feature_code":"PPL",
    "gn:name":"Guida Moussa",
    "gn:population":0,
    "gn:timezone":"Africa/Niamey",
    "iso:country":"NE",
    "wof:name":"Guida Moussa",
    "wof:placetype":"locality"
},
  "geometry": {"coordinates":[9.214,14.6712],"type":"Point"}
}