{
  "type": "Feature",
  "properties": {
    "gn:admin1_code":"2.0",
    "gn:asciiname":"Bouldoua",
    "gn:country_code":"NE",
    "gn:dem":279,
    "gn:feature_class":"P",
    "gn:feature_code":"PPL",
    "gn:name":"Bouldoua",
    "gn:population":0,
    "gn:timezone":"Africa/Niamey",
    "iso:country":"NE",
    "wof:name":"Bouldoua",
    "wof:placetype":"locality"
},
  "geometry": {"coordinates":[13.35187,14.02396],"type":"Point"}
}