{
  "type": "Feature",
  "properties": {
    "gn:admin1_code":"3.0",
    "gn:asciiname":"Koasseye",
    "gn:country_code":"NE",
    "gn:dem":231,
    "gn:feature_class":"P",
    "gn:feature_code":"PPL",
    "gn:name":"Koass\u00e8ye",
    "gn:population":0,
    "gn:timezone":"Africa/Niamey",
    "iso:country":"NE",
    "name:und_x_variant":[
        "Kwassey",
        "Koass\u00e8ye"
    ],
    "wof:name":"Koasseye",
    "wof:placetype":"locality"
},
  "geometry": {"coordinates":[3.19426,12.89879],"type":"Point"}
}