{
  "type": "Feature",
  "properties": {
    "gn:admin1_code":"7.0",
    "gn:asciiname":"Kitchi Yaskou",
    "gn:country_code":"NE",
    "gn:dem":463,
    "gn:feature_class":"P",
    "gn:feature_code":"PPL",
    "gn:name":"Kitchi Yaskou",
    "gn:population":0,
    "gn:timezone":"Africa/Niamey",
    "iso:country":"NE",
    "name:und_x_variant":[
        "T\u00e9chiasko",
        "Ketchiasko",
        "Techiasco",
        "Kechiasko",
        "Kitchi Yaskou"
    ],
    "wof:name":"Kitchi Yaskou",
    "wof:placetype":"locality"
},
  "geometry": {"coordinates":[8.34891,14.99637],"type":"Point"}
}