{
  "type": "Feature",
  "properties": {
    "gn:admin1_code":"6.0",
    "gn:asciiname":"Guidan Tanko",
    "gn:country_code":"NE",
    "gn:dem":414,
    "gn:feature_class":"P",
    "gn:feature_code":"PPL",
    "gn:name":"Guidan Tanko",
    "gn:population":0,
    "gn:timezone":"Africa/Niamey",
    "iso:country":"NE",
    "wof:name":"Guidan Tanko",
    "wof:placetype":"locality"
},
  "geometry": {"coordinates":[6.44143,14.33687],"type":"Point"}
}