{
  "type": "Feature",
  "properties": {
    "gn:admin1_code":"2.0",
    "gn:asciiname":"Adjilari",
    "gn:country_code":"NE",
    "gn:dem":308,
    "gn:feature_class":"P",
    "gn:feature_code":"PPL",
    "gn:name":"Adjilari",
    "gn:population":0,
    "gn:timezone":"Africa/Niamey",
    "iso:country":"NE",
    "wof:name":"Adjilari",
    "wof:placetype":"locality"
},
  "geometry": {"coordinates":[12.43215,13.26015],"type":"Point"}
}