{
  "type": "Feature",
  "properties": {
    "gn:admin1_code":"6.0",
    "gn:asciiname":"Nadabar",
    "gn:country_code":"NE",
    "gn:dem":285,
    "gn:feature_class":"P",
    "gn:feature_code":"PPL",
    "gn:name":"Nadabar",
    "gn:population":0,
    "gn:timezone":"Africa/Niamey",
    "iso:country":"NE",
    "wof:name":"Nadabar",
    "wof:placetype":"locality"
},
  "geometry": {"coordinates":[5.36668,13.88048],"type":"Point"}
}