{
  "type": "Feature",
  "properties": {
    "gn:admin1_code":"7.0",
    "gn:asciiname":"Chamoeli",
    "gn:country_code":"NE",
    "gn:dem":506,
    "gn:feature_class":"P",
    "gn:feature_code":"PPL",
    "gn:name":"Chamoeli",
    "gn:population":0,
    "gn:timezone":"Africa/Niamey",
    "iso:country":"NE",
    "wof:name":"Chamoeli",
    "wof:placetype":"locality"
},
  "geometry": {"coordinates":[9.4503,13.8642],"type":"Point"}
}