{
  "type": "Feature",
  "properties": {
    "gn:admin1_code":"4.0",
    "gn:asciiname":"Aitadane",
    "gn:country_code":"NE",
    "gn:dem":409,
    "gn:feature_class":"P",
    "gn:feature_code":"PPL",
    "gn:name":"A\u00eftadane",
    "gn:population":0,
    "gn:timezone":"Africa/Niamey",
    "iso:country":"NE",
    "name:und_x_variant":[
        "Aytaden",
        "A\u00eftadane"
    ],
    "wof:name":"Aitadane",
    "wof:placetype":"locality"
},
  "geometry": {"coordinates":[7.90597,13.9856],"type":"Point"}
}