{
  "type": "Feature",
  "properties": {
    "gn:admin1_code":"6.0",
    "gn:asciiname":"Karaji",
    "gn:country_code":"NE",
    "gn:dem":393,
    "gn:feature_class":"P",
    "gn:feature_code":"PPL",
    "gn:name":"Karaji",
    "gn:population":0,
    "gn:timezone":"Africa/Niamey",
    "iso:country":"NE",
    "wof:name":"Karaji",
    "wof:placetype":"locality"
},
  "geometry": {"coordinates":[5.3332,15.1399],"type":"Point"}
}