{
  "type": "Feature",
  "properties": {
    "gn:admin1_code":"4.0",
    "gn:asciiname":"Dan Gatamaou",
    "gn:country_code":"NE",
    "gn:dem":456,
    "gn:feature_class":"P",
    "gn:feature_code":"PPL",
    "gn:name":"Dan Gatamaou",
    "gn:population":0,
    "gn:timezone":"Africa/Niamey",
    "iso:country":"NE",
    "wof:name":"Dan Gatamaou",
    "wof:placetype":"locality"
},
  "geometry": {"coordinates":[7.74958,13.4284],"type":"Point"}
}