{
  "type": "Feature",
  "properties": {
    "gn:admin1_code":"2.0",
    "gn:asciiname":"Tourbanguida",
    "gn:country_code":"NE",
    "gn:dem":311,
    "gn:feature_class":"P",
    "gn:feature_code":"PPL",
    "gn:name":"Tourbanguida",
    "gn:population":0,
    "gn:timezone":"Africa/Niamey",
    "iso:country":"NE",
    "name:und_x_variant":[
        "Turbangida",
        "Tiurbangida",
        "Tourbanguida"
    ],
    "wof:name":"Tourbanguida",
    "wof:placetype":"locality"
},
  "geometry": {"coordinates":[12.57441,13.27379],"type":"Point"}
}