{
  "type": "Feature",
  "properties": {
    "gn:admin1_code":"3.0",
    "gn:asciiname":"Aeni Koy Kwara",
    "gn:country_code":"NE",
    "gn:dem":223,
    "gn:feature_class":"P",
    "gn:feature_code":"PPL",
    "gn:name":"A\u00e9ni Koy Kwara",
    "gn:population":0,
    "gn:timezone":"Africa/Niamey",
    "iso:country":"NE",
    "name:und_x_variant":[
        "A\u00e9ni-Koye-Koara",
        "A\u00e9ni Koy Kwara"
    ],
    "wof:name":"Aeni Koy Kwara",
    "wof:placetype":"locality"
},
  "geometry": {"coordinates":[3.25126,12.61052],"type":"Point"}
}