{
  "type": "Feature",
  "properties": {
    "gn:admin1_code":"7.0",
    "gn:asciiname":"Garaouaski",
    "gn:country_code":"NE",
    "gn:dem":482,
    "gn:feature_class":"P",
    "gn:feature_code":"PPL",
    "gn:name":"Garaouaski",
    "gn:population":0,
    "gn:timezone":"Africa/Niamey",
    "iso:country":"NE",
    "wof:name":"Garaouaski",
    "wof:placetype":"locality"
},
  "geometry": {"coordinates":[9.1399,14.4594],"type":"Point"}
}