{
  "type": "Feature",
  "properties": {
    "gn:admin1_code":"6.0",
    "gn:asciiname":"Lakot",
    "gn:country_code":"NE",
    "gn:dem":320,
    "gn:feature_class":"P",
    "gn:feature_code":"PPL",
    "gn:name":"Lakot",
    "gn:population":0,
    "gn:timezone":"Africa/Niamey",
    "iso:country":"NE",
    "wof:name":"Lakot",
    "wof:placetype":"locality"
},
  "geometry": {"coordinates":[6.07043,14.09763],"type":"Point"}
}