{
  "type": "Feature",
  "properties": {
    "gn:admin1_code":"4.0",
    "gn:asciiname":"May Katari",
    "gn:country_code":"NE",
    "gn:dem":439,
    "gn:feature_class":"P",
    "gn:feature_code":"PPL",
    "gn:name":"May Katari",
    "gn:population":0,
    "gn:timezone":"Africa/Niamey",
    "iso:country":"NE",
    "wof:name":"May Katari",
    "wof:placetype":"locality"
},
  "geometry": {"coordinates":[8.27245,13.24572],"type":"Point"}
}