{
  "type": "Feature",
  "properties": {
    "gn:admin1_code":"2.0",
    "gn:asciiname":"Tchekouri",
    "gn:country_code":"NE",
    "gn:dem":315,
    "gn:feature_class":"P",
    "gn:feature_code":"PPL",
    "gn:name":"Tch\u00e9kouri",
    "gn:population":0,
    "gn:timezone":"Africa/Niamey",
    "iso:country":"NE",
    "wof:name":"Tchekouri",
    "wof:placetype":"locality"
},
  "geometry": {"coordinates":[12.22787,13.12357],"type":"Point"}
}