{
  "type": "Feature",
  "properties": {
    "gn:admin1_code":"6.0",
    "gn:asciiname":"Kouroufa",
    "gn:country_code":"NE",
    "gn:dem":318,
    "gn:feature_class":"P",
    "gn:feature_code":"PPL",
    "gn:name":"Kouroufa",
    "gn:population":0,
    "gn:timezone":"Africa/Niamey",
    "iso:country":"NE",
    "wof:name":"Kouroufa",
    "wof:placetype":"locality"
},
  "geometry": {"coordinates":[5.94534,13.89181],"type":"Point"}
}