{
  "type": "Feature",
  "properties": {
    "gn:admin1_code":"3.0",
    "gn:asciiname":"Margou",
    "gn:country_code":"NE",
    "gn:dem":191,
    "gn:feature_class":"P",
    "gn:feature_code":"PPL",
    "gn:name":"Margou",
    "gn:population":0,
    "gn:timezone":"Africa/Niamey",
    "iso:country":"NE",
    "wof:name":"Margou",
    "wof:placetype":"locality"
},
  "geometry": {"coordinates":[2.855,13.1049],"type":"Point"}
}