{
  "type": "Feature",
  "properties": {
    "gn:admin1_code":"9.0",
    "gn:asciiname":"Koga",
    "gn:country_code":"NE",
    "gn:dem":214,
    "gn:feature_class":"P",
    "gn:feature_code":"PPL",
    "gn:name":"Koga",
    "gn:population":0,
    "gn:timezone":"Africa/Niamey",
    "iso:country":"NE",
    "name:cat_x_preferred":[
        "Koga"
    ],
    "name:ceb_x_preferred":[
        "Koga"
    ],
    "name:deu_x_preferred":[
        "Koga"
    ],
    "name:fin_x_preferred":[
        "Koga"
    ],
    "name:fra_x_preferred":[
        "Koga"
    ],
    "name:ita_x_preferred":[
        "Koga"
    ],
    "name:kor_x_preferred":[
        "\uace0\uac00\uc2dc"
    ],
    "name:nld_x_preferred":[
        "Koga"
    ],
    "name:pol_x_preferred":[
        "Koga"
    ],
    "name:por_x_preferred":[
        "Koga"
    ],
    "name:ron_x_preferred":[
        "Koga"
    ],
    "name:rus_x_preferred":[
        "\u041a\u043e\u0433\u0430"
    ],
    "name:sco_x_preferred":[
        "Koga"
    ],
    "name:slk_x_preferred":[
        "Koga"
    ],
    "name:spa_x_preferred":[
        "Koga"
    ],
    "name:swe_x_preferred":[
        "Koga"
    ],
    "name:ukr_x_preferred":[
        "\u041a\u043e\u0491\u0430"
    ],
    "wof:name":"Koga",
    "wof:placetype":"locality"
},
  "geometry": {"coordinates":[2.9942,13.8563],"type":"Point"}
}