{
  "type": "Feature",
  "properties": {
    "gn:admin1_code":"6.0",
    "gn:asciiname":"Wala Asan",
    "gn:country_code":"NE",
    "gn:dem":374,
    "gn:feature_class":"P",
    "gn:feature_code":"PPL",
    "gn:name":"Wala Asan",
    "gn:population":0,
    "gn:timezone":"Africa/Niamey",
    "iso:country":"NE",
    "wof:name":"Wala Asan",
    "wof:placetype":"locality"
},
  "geometry": {"coordinates":[6.48172,14.11241],"type":"Point"}
}