{
  "type": "Feature",
  "properties": {
    "gn:admin1_code":"3.0",
    "gn:asciiname":"Ruda",
    "gn:country_code":"NE",
    "gn:dem":227,
    "gn:feature_class":"P",
    "gn:feature_code":"PPL",
    "gn:name":"Ruda",
    "gn:population":0,
    "gn:timezone":"Africa/Niamey",
    "iso:country":"NE",
    "name:bos_x_preferred":[
        "Ruda"
    ],
    "name:ceb_x_preferred":[
        "Ruda"
    ],
    "name:ces_x_preferred":[
        "Ruda"
    ],
    "name:deu_x_preferred":[
        "Ruda"
    ],
    "name:epo_x_preferred":[
        "Ruda"
    ],
    "name:fra_x_preferred":[
        "Ruda"
    ],
    "name:glg_x_preferred":[
        "Ruda"
    ],
    "name:hrv_x_preferred":[
        "Ruda"
    ],
    "name:hun_x_preferred":[
        "Ruda"
    ],
    "name:ita_x_preferred":[
        "Ruda"
    ],
    "name:lit_x_preferred":[
        "Ruda"
    ],
    "name:nld_x_preferred":[
        "Ruda"
    ],
    "name:oci_x_preferred":[
        "Ruda"
    ],
    "name:pol_x_preferred":[
        "Ruda"
    ],
    "name:ron_x_preferred":[
        "Ruda"
    ],
    "name:slk_x_preferred":[
        "Ruda"
    ],
    "name:slv_x_preferred":[
        "Ruda"
    ],
    "name:spa_x_preferred":[
        "Ruda"
    ],
    "name:swe_x_preferred":[
        "Ruda"
    ],
    "name:uzb_x_preferred":[
        "Ruda"
    ],
    "wof:name":"Ruda",
    "wof:placetype":"locality"
},
  "geometry": {"coordinates":[4.18455,13.49802],"type":"Point"}
}