{
  "type": "Feature",
  "properties": {
    "gn:admin1_code":"2.0",
    "gn:asciiname":"Arisinedi",
    "gn:country_code":"NE",
    "gn:dem":337,
    "gn:feature_class":"P",
    "gn:feature_code":"PPL",
    "gn:name":"Arisin\u00e9di",
    "gn:population":0,
    "gn:timezone":"Africa/Niamey",
    "iso:country":"NE",
    "wof:name":"Arisinedi",
    "wof:placetype":"locality"
},
  "geometry": {"coordinates":[11.6778,13.5326],"type":"Point"}
}