{
  "type": "Feature",
  "properties": {
    "gn:admin1_code":"6.0",
    "gn:asciiname":"Ramoutan",
    "gn:country_code":"NE",
    "gn:dem":370,
    "gn:feature_class":"P",
    "gn:feature_code":"PPL",
    "gn:name":"Ramoutan",
    "gn:population":0,
    "gn:timezone":"Africa/Niamey",
    "iso:country":"NE",
    "wof:name":"Ramoutan",
    "wof:placetype":"locality"
},
  "geometry": {"coordinates":[6.059,14.27132],"type":"Point"}
}