{
  "type": "Feature",
  "properties": {
    "gn:admin1_code":"3.0",
    "gn:asciiname":"Damari",
    "gn:country_code":"NE",
    "gn:dem":207,
    "gn:feature_class":"P",
    "gn:feature_code":"PPL",
    "gn:name":"Damari",
    "gn:population":0,
    "gn:timezone":"Africa/Niamey",
    "iso:country":"NE",
    "name:heb_x_preferred":[
        "\u05d3\u05de\u05d0\u05e8\u05d9"
    ],
    "wof:name":"Damari",
    "wof:placetype":"locality"
},
  "geometry": {"coordinates":[2.98849,12.95556],"type":"Point"}
}