{
  "type": "Feature",
  "properties": {
    "gn:admin1_code":"3.0",
    "gn:asciiname":"Toulay",
    "gn:country_code":"NE",
    "gn:dem":260,
    "gn:feature_class":"P",
    "gn:feature_code":"PPL",
    "gn:name":"Toulay",
    "gn:population":0,
    "gn:timezone":"Africa/Niamey",
    "iso:country":"NE",
    "wof:name":"Toulay",
    "wof:placetype":"locality"
},
  "geometry": {"coordinates":[4.13306,13.88812],"type":"Point"}
}