{
  "type": "Feature",
  "properties": {
    "gn:admin1_code":"7.0",
    "gn:asciiname":"Tata Fawa",
    "gn:country_code":"NE",
    "gn:dem":456,
    "gn:feature_class":"P",
    "gn:feature_code":"PPL",
    "gn:name":"Tata Fawa",
    "gn:population":0,
    "gn:timezone":"Africa/Niamey",
    "iso:country":"NE",
    "wof:name":"Tata Fawa",
    "wof:placetype":"locality"
},
  "geometry": {"coordinates":[8.31259,13.16213],"type":"Point"}
}