{
  "type": "Feature",
  "properties": {
    "gn:admin1_code":"7.0",
    "gn:asciiname":"Maygoadahi",
    "gn:country_code":"NE",
    "gn:dem":483,
    "gn:feature_class":"P",
    "gn:feature_code":"PPL",
    "gn:name":"Maygoadahi",
    "gn:population":0,
    "gn:timezone":"Africa/Niamey",
    "iso:country":"NE",
    "wof:name":"Maygoadahi",
    "wof:placetype":"locality"
},
  "geometry": {"coordinates":[8.8824,14.0415],"type":"Point"}
}