{
  "type": "Feature",
  "properties": {
    "gn:admin1_code":"3.0",
    "gn:asciiname":"Are-Koara",
    "gn:country_code":"NE",
    "gn:dem":249,
    "gn:feature_class":"P",
    "gn:feature_code":"PPL",
    "gn:name":"Ar\u00e9-Koara",
    "gn:population":0,
    "gn:timezone":"Africa/Niamey",
    "iso:country":"NE",
    "name:und_x_variant":[
        "Ar\u00e9 Kwara",
        "Ar\u00e9-Koara"
    ],
    "wof:name":"Are-Koara",
    "wof:placetype":"locality"
},
  "geometry": {"coordinates":[3.6553,13.3091],"type":"Point"}
}