{
  "type": "Feature",
  "properties": {
    "gn:admin1_code":"2.0",
    "gn:asciiname":"Dougourwa",
    "gn:country_code":"NE",
    "gn:dem":356,
    "gn:feature_class":"P",
    "gn:feature_code":"PPL",
    "gn:name":"Dougourwa",
    "gn:population":0,
    "gn:timezone":"Africa/Niamey",
    "iso:country":"NE",
    "wof:name":"Dougourwa",
    "wof:placetype":"locality"
},
  "geometry": {"coordinates":[10.83745,13.81661],"type":"Point"}
}