{
  "type": "Feature",
  "properties": {
    "gn:admin1_code":"7.0",
    "gn:asciiname":"Katambaje",
    "gn:country_code":"NE",
    "gn:dem":412,
    "gn:feature_class":"P",
    "gn:feature_code":"PPL",
    "gn:name":"Katambaj\u00e9",
    "gn:population":0,
    "gn:timezone":"Africa/Niamey",
    "iso:country":"NE",
    "name:und_x_variant":[
        "Katanbaj\u00e9",
        "Katambaj\u00e9"
    ],
    "wof:name":"Katambaje",
    "wof:placetype":"locality"
},
  "geometry": {"coordinates":[8.84559,13.31961],"type":"Point"}
}