{
  "type": "Feature",
  "properties": {
    "gn:admin1_code":"4.0",
    "gn:asciiname":"Kowa Bouta",
    "gn:country_code":"NE",
    "gn:dem":403,
    "gn:feature_class":"P",
    "gn:feature_code":"PPL",
    "gn:name":"K\u00f4w\u00e2 Bo\u00fbta",
    "gn:population":0,
    "gn:timezone":"Africa/Niamey",
    "iso:country":"NE",
    "wof:name":"Kowa Bouta",
    "wof:placetype":"locality"
},
  "geometry": {"coordinates":[7.44946,13.6149],"type":"Point"}
}