{
  "type": "Feature",
  "properties": {
    "gn:admin1_code":"7.0",
    "gn:asciiname":"Baouda",
    "gn:country_code":"NE",
    "gn:dem":356,
    "gn:feature_class":"P",
    "gn:feature_code":"PPL",
    "gn:name":"Baouda",
    "gn:population":0,
    "gn:timezone":"Africa/Niamey",
    "iso:country":"NE",
    "wof:name":"Baouda",
    "wof:placetype":"locality"
},
  "geometry": {"coordinates":[10.40922,13.325],"type":"Point"}
}