{
  "type": "Feature",
  "properties": {
    "gn:admin1_code":"9.0",
    "gn:asciiname":"Dessa",
    "gn:country_code":"NE",
    "gn:dem":219,
    "gn:feature_class":"P",
    "gn:feature_code":"PPL",
    "gn:name":"D\u00e9ssa",
    "gn:population":0,
    "gn:timezone":"Africa/Niamey",
    "iso:country":"NE",
    "name:und_x_variant":[
        "Desa",
        "D\u00e9ssa"
    ],
    "wof:name":"Dessa",
    "wof:placetype":"locality"
},
  "geometry": {"coordinates":[1.10629,14.5259],"type":"Point"}
}