{
  "type": "Feature",
  "properties": {
    "gn:admin1_code":"6.0",
    "gn:asciiname":"Faska",
    "gn:country_code":"NE",
    "gn:dem":277,
    "gn:feature_class":"P",
    "gn:feature_code":"PPL",
    "gn:name":"Faska",
    "gn:population":0,
    "gn:timezone":"Africa/Niamey",
    "iso:country":"NE",
    "name:und_x_variant":[
        "Kaska",
        "Faska"
    ],
    "wof:name":"Faska",
    "wof:placetype":"locality"
},
  "geometry": {"coordinates":[5.2741,14.0969],"type":"Point"}
}