{
  "type": "Feature",
  "properties": {
    "gn:admin1_code":"9.0",
    "gn:asciiname":"Gao Zengi",
    "gn:country_code":"NE",
    "gn:dem":225,
    "gn:feature_class":"P",
    "gn:feature_code":"PPL",
    "gn:name":"Gao Zengi",
    "gn:population":0,
    "gn:timezone":"Africa/Niamey",
    "iso:country":"NE",
    "name:und_x_variant":[
        "Gao Zengui",
        "Gao Zengi"
    ],
    "wof:name":"Gao Zengi",
    "wof:placetype":"locality"
},
  "geometry": {"coordinates":[3.3596,14.3645],"type":"Point"}
}