{
  "type": "Feature",
  "properties": {
    "gn:admin1_code":"2.0",
    "gn:asciiname":"Mousari",
    "gn:country_code":"NE",
    "gn:dem":300,
    "gn:feature_class":"P",
    "gn:feature_code":"PPL",
    "gn:name":"Mousari",
    "gn:population":0,
    "gn:timezone":"Africa/Niamey",
    "iso:country":"NE",
    "wof:name":"Mousari",
    "wof:placetype":"locality"
},
  "geometry": {"coordinates":[12.95229,13.61658],"type":"Point"}
}