{
  "type": "Feature",
  "properties": {
    "gn:admin1_code":"3.0",
    "gn:asciiname":"Mayara Kwara",
    "gn:country_code":"NE",
    "gn:dem":218,
    "gn:feature_class":"P",
    "gn:feature_code":"PPL",
    "gn:name":"Mayara Kwara",
    "gn:population":0,
    "gn:timezone":"Africa/Niamey",
    "iso:country":"NE",
    "name:und_x_variant":[
        "Mayara-Koara",
        "Mayara Kwara"
    ],
    "wof:name":"Mayara Kwara",
    "wof:placetype":"locality"
},
  "geometry": {"coordinates":[3.20549,12.38122],"type":"Point"}
}