{
  "type": "Feature",
  "properties": {
    "gn:admin1_code":"4.0",
    "gn:asciiname":"Magaji",
    "gn:country_code":"NE",
    "gn:dem":360,
    "gn:feature_class":"P",
    "gn:feature_code":"PPL",
    "gn:name":"Magaji",
    "gn:population":0,
    "gn:timezone":"Africa/Niamey",
    "iso:country":"NE",
    "wof:name":"Magaji",
    "wof:placetype":"locality"
},
  "geometry": {"coordinates":[6.95304,13.52823],"type":"Point"}
}