{
  "type": "Feature",
  "properties": {
    "gn:admin1_code":"6.0",
    "gn:asciiname":"Chindigi",
    "gn:country_code":"NE",
    "gn:dem":389,
    "gn:feature_class":"P",
    "gn:feature_code":"PPL",
    "gn:name":"Chindigi",
    "gn:population":0,
    "gn:timezone":"Africa/Niamey",
    "iso:country":"NE",
    "wof:name":"Chindigi",
    "wof:placetype":"locality"
},
  "geometry": {"coordinates":[6.09763,14.36271],"type":"Point"}
}