{
  "type": "Feature",
  "properties": {
    "gn:admin1_code":"4.0",
    "gn:asciiname":"Maydoubou",
    "gn:country_code":"NE",
    "gn:dem":412,
    "gn:feature_class":"P",
    "gn:feature_code":"PPL",
    "gn:name":"Maydoubou",
    "gn:population":0,
    "gn:timezone":"Africa/Niamey",
    "iso:country":"NE",
    "name:und_x_variant":[
        "Maidoubou",
        "Maydoubou"
    ],
    "wof:name":"Maydoubou",
    "wof:placetype":"locality"
},
  "geometry": {"coordinates":[7.42369,14.63954],"type":"Point"}
}