{
  "type": "Feature",
  "properties": {
    "gn:admin1_code":"9.0",
    "gn:asciiname":"Ouro Timba",
    "gn:country_code":"NE",
    "gn:dem":211,
    "gn:feature_class":"P",
    "gn:feature_code":"PPL",
    "gn:name":"Ouro Timba",
    "gn:population":0,
    "gn:timezone":"Africa/Niamey",
    "iso:country":"NE",
    "name:und_x_variant":[
        "Ouro-Timbaso",
        "Ouro Timbasso",
        "Ouro Timba"
    ],
    "wof:name":"Ouro Timba",
    "wof:placetype":"locality"
},
  "geometry": {"coordinates":[1.96943,13.13632],"type":"Point"}
}