{
  "type": "Feature",
  "properties": {
    "gn:admin1_code":"7.0",
    "gn:asciiname":"Kouhouri",
    "gn:country_code":"NE",
    "gn:dem":397,
    "gn:feature_class":"P",
    "gn:feature_code":"PPL",
    "gn:name":"Kouhouri",
    "gn:population":0,
    "gn:timezone":"Africa/Niamey",
    "iso:country":"NE",
    "wof:name":"Kouhouri",
    "wof:placetype":"locality"
},
  "geometry": {"coordinates":[8.9666,13.08337],"type":"Point"}
}