{
  "type": "Feature",
  "properties": {
    "gn:admin1_code":"4.0",
    "gn:asciiname":"Dan Gara Saboa",
    "gn:country_code":"NE",
    "gn:dem":379,
    "gn:feature_class":"P",
    "gn:feature_code":"PPL",
    "gn:name":"Dan Gara Saboa",
    "gn:population":0,
    "gn:timezone":"Africa/Niamey",
    "iso:country":"NE",
    "wof:name":"Dan Gara Saboa",
    "wof:placetype":"locality"
},
  "geometry": {"coordinates":[7.12215,13.58502],"type":"Point"}
}