{
  "type": "Feature",
  "properties": {
    "gn:admin1_code":"2.0",
    "gn:asciiname":"Adjiri",
    "gn:country_code":"NE",
    "gn:dem":291,
    "gn:feature_class":"P",
    "gn:feature_code":"PPL",
    "gn:name":"Adjiri",
    "gn:population":0,
    "gn:timezone":"Africa/Niamey",
    "iso:country":"NE",
    "wof:name":"Adjiri",
    "wof:placetype":"locality"
},
  "geometry": {"coordinates":[12.99763,14.04939],"type":"Point"}
}