{
  "type": "Feature",
  "properties": {
    "gn:admin1_code":"3.0",
    "gn:asciiname":"Gazila",
    "gn:country_code":"NE",
    "gn:dem":169,
    "gn:feature_class":"P",
    "gn:feature_code":"PPL",
    "gn:name":"Gazila",
    "gn:population":0,
    "gn:timezone":"Africa/Niamey",
    "iso:country":"NE",
    "wof:name":"Gazila",
    "wof:placetype":"locality"
},
  "geometry": {"coordinates":[3.58575,11.94181],"type":"Point"}
}