{
  "type": "Feature",
  "properties": {
    "gn:admin1_code":"3.0",
    "gn:asciiname":"Kabeye",
    "gn:country_code":"NE",
    "gn:dem":250,
    "gn:feature_class":"P",
    "gn:feature_code":"PPL",
    "gn:name":"Kabeye",
    "gn:population":0,
    "gn:timezone":"Africa/Niamey",
    "iso:country":"NE",
    "wof:name":"Kabeye",
    "wof:placetype":"locality"
},
  "geometry": {"coordinates":[3.9952,13.9256],"type":"Point"}
}