{
  "type": "Feature",
  "properties": {
    "gn:admin1_code":"7.0",
    "gn:asciiname":"May Maje Bao",
    "gn:country_code":"NE",
    "gn:dem":472,
    "gn:feature_class":"P",
    "gn:feature_code":"PPL",
    "gn:name":"May Maj\u00e9 Bao",
    "gn:population":0,
    "gn:timezone":"Africa/Niamey",
    "iso:country":"NE",
    "wof:name":"May Maje Bao",
    "wof:placetype":"locality"
},
  "geometry": {"coordinates":[8.37129,13.12724],"type":"Point"}
}