{
  "type": "Feature",
  "properties": {
    "gn:admin1_code":"3.0",
    "gn:asciiname":"Bineguel",
    "gn:country_code":"NE",
    "gn:dem":244,
    "gn:feature_class":"P",
    "gn:feature_code":"PPL",
    "gn:name":"Bin\u00e9guel",
    "gn:population":0,
    "gn:timezone":"Africa/Niamey",
    "iso:country":"NE",
    "wof:name":"Bineguel",
    "wof:placetype":"locality"
},
  "geometry": {"coordinates":[3.9286,13.1374],"type":"Point"}
}