{
  "type": "Feature",
  "properties": {
    "gn:admin1_code":"9.0",
    "gn:asciiname":"Bogodji",
    "gn:country_code":"NE",
    "gn:dem":225,
    "gn:feature_class":"P",
    "gn:feature_code":"PPL",
    "gn:name":"Bogodji",
    "gn:population":0,
    "gn:timezone":"Africa/Niamey",
    "iso:country":"NE",
    "wof:name":"Bogodji",
    "wof:placetype":"locality"
},
  "geometry": {"coordinates":[2.0937,13.087],"type":"Point"}
}