{
  "type": "Feature",
  "properties": {
    "gn:admin1_code":"6.0",
    "gn:asciiname":"Laham",
    "gn:country_code":"NE",
    "gn:dem":296,
    "gn:feature_class":"P",
    "gn:feature_code":"PPL",
    "gn:name":"Laham",
    "gn:population":0,
    "gn:timezone":"Africa/Niamey",
    "iso:country":"NE",
    "wof:name":"Laham",
    "wof:placetype":"locality"
},
  "geometry": {"coordinates":[4.30779,14.86139],"type":"Point"}
}