{
  "type": "Feature",
  "properties": {
    "gn:admin1_code":"9.0",
    "gn:asciiname":"Baye Gozi Kouara",
    "gn:country_code":"NE",
    "gn:dem":234,
    "gn:feature_class":"P",
    "gn:feature_code":"PPL",
    "gn:name":"Bay\u00e9 Gozi Kouara",
    "gn:population":0,
    "gn:timezone":"Africa/Niamey",
    "iso:country":"NE",
    "wof:name":"Baye Gozi Kouara",
    "wof:placetype":"locality"
},
  "geometry": {"coordinates":[1.55684,14.39684],"type":"Point"}
}