{
  "type": "Feature",
  "properties": {
    "gn:admin1_code":"3.0",
    "gn:asciiname":"Bani Zoumbou",
    "gn:country_code":"NE",
    "gn:dem":163,
    "gn:feature_class":"P",
    "gn:feature_code":"PPL",
    "gn:name":"Bani Zoumbou",
    "gn:population":0,
    "gn:timezone":"Africa/Niamey",
    "iso:country":"NE",
    "name:und_x_variant":[
        "Birni-Zoumbou",
        "Bani Zoumbou"
    ],
    "wof:name":"Bani Zoumbou",
    "wof:placetype":"locality"
},
  "geometry": {"coordinates":[3.60474,11.76546],"type":"Point"}
}