{
  "type": "Feature",
  "properties": {
    "gn:admin1_code":"4.0",
    "gn:asciiname":"Baban Dawa",
    "gn:country_code":"NE",
    "gn:dem":437,
    "gn:feature_class":"P",
    "gn:feature_code":"PPL",
    "gn:name":"Baban Dawa",
    "gn:population":0,
    "gn:timezone":"Africa/Niamey",
    "iso:country":"NE",
    "wof:name":"Baban Dawa",
    "wof:placetype":"locality"
},
  "geometry": {"coordinates":[8.3267,13.56419],"type":"Point"}
}