{
  "type": "Feature",
  "properties": {
    "gn:admin1_code":"3.0",
    "gn:asciiname":"Saboudeye",
    "gn:country_code":"NE",
    "gn:dem":236,
    "gn:feature_class":"P",
    "gn:feature_code":"PPL",
    "gn:name":"Saboud\u00e8ye",
    "gn:population":0,
    "gn:timezone":"Africa/Niamey",
    "iso:country":"NE",
    "name:und_x_variant":[
        "Sabou Dey",
        "Saboud\u00e8ye"
    ],
    "wof:name":"Saboudeye",
    "wof:placetype":"locality"
},
  "geometry": {"coordinates":[3.3933,13.2463],"type":"Point"}
}