{
  "type": "Feature",
  "properties": {
    "gn:admin1_code":"3.0",
    "gn:asciiname":"Son Alla Kwara",
    "gn:country_code":"NE",
    "gn:dem":213,
    "gn:feature_class":"P",
    "gn:feature_code":"PPL",
    "gn:name":"Son Alla Kwara",
    "gn:population":0,
    "gn:timezone":"Africa/Niamey",
    "iso:country":"NE",
    "name:und_x_variant":[
        "Son-Alla-Koara",
        "Son Alla Kwara"
    ],
    "wof:name":"Son Alla Kwara",
    "wof:placetype":"locality"
},
  "geometry": {"coordinates":[3.5219,12.86818],"type":"Point"}
}