{
  "type": "Feature",
  "properties": {
    "gn:admin1_code":"7.0",
    "gn:asciiname":"Bouara",
    "gn:country_code":"NE",
    "gn:dem":448,
    "gn:feature_class":"P",
    "gn:feature_code":"PPL",
    "gn:name":"Bouara",
    "gn:population":0,
    "gn:timezone":"Africa/Niamey",
    "iso:country":"NE",
    "wof:name":"Bouara",
    "wof:placetype":"locality"
},
  "geometry": {"coordinates":[9.47961,13.73138],"type":"Point"}
}