{
  "type": "Feature",
  "properties": {
    "gn:admin1_code":"3.0",
    "gn:asciiname":"Bangarasa",
    "gn:country_code":"NE",
    "gn:dem":210,
    "gn:feature_class":"P",
    "gn:feature_code":"PPL",
    "gn:name":"Bangarasa",
    "gn:population":0,
    "gn:timezone":"Africa/Niamey",
    "iso:country":"NE",
    "name:und_x_variant":[
        "Bangarassa",
        "Bangarasa"
    ],
    "wof:name":"Bangarasa",
    "wof:placetype":"locality"
},
  "geometry": {"coordinates":[4.0654,13.18234],"type":"Point"}
}