{
  "type": "Feature",
  "properties": {
    "gn:admin1_code":"4.0",
    "gn:asciiname":"Guidan Dawey",
    "gn:country_code":"NE",
    "gn:dem":435,
    "gn:feature_class":"P",
    "gn:feature_code":"PPL",
    "gn:name":"Guidan Dawey",
    "gn:population":0,
    "gn:timezone":"Africa/Niamey",
    "iso:country":"NE",
    "name:und_x_variant":[
        "Gidan Dawey",
        "Guidan Dawey"
    ],
    "wof:name":"Guidan Dawey",
    "wof:placetype":"locality"
},
  "geometry": {"coordinates":[7.80022,13.66305],"type":"Point"}
}