{
  "type": "Feature",
  "properties": {
    "gn:admin1_code":"7.0",
    "gn:asciiname":"Katoukoume",
    "gn:country_code":"NE",
    "gn:dem":448,
    "gn:feature_class":"P",
    "gn:feature_code":"PPL",
    "gn:name":"Katoukoum\u00e9",
    "gn:population":0,
    "gn:timezone":"Africa/Niamey",
    "iso:country":"NE",
    "wof:name":"Katoukoume",
    "wof:placetype":"locality"
},
  "geometry": {"coordinates":[8.29555,14.63692],"type":"Point"}
}