{
  "type": "Feature",
  "properties": {
    "gn:admin1_code":"1.0",
    "gn:asciiname":"Akokan",
    "gn:country_code":"NE",
    "gn:dem":420,
    "gn:feature_class":"P",
    "gn:feature_code":"PPL",
    "gn:name":"Akokan",
    "gn:population":0,
    "gn:timezone":"Africa/Niamey",
    "iso:country":"NE",
    "wof:name":"Akokan",
    "wof:placetype":"locality"
},
  "geometry": {"coordinates":[7.34361,18.71083],"type":"Point"}
}