{
  "type": "Feature",
  "properties": {
    "gn:admin1_code":"2.0",
    "gn:asciiname":"Kaola-Djima",
    "gn:country_code":"NE",
    "gn:dem":295,
    "gn:feature_class":"P",
    "gn:feature_code":"PPL",
    "gn:name":"Kaola-Djima",
    "gn:population":0,
    "gn:timezone":"Africa/Niamey",
    "iso:country":"NE",
    "wof:name":"Kaola-Djima",
    "wof:placetype":"locality"
},
  "geometry": {"coordinates":[12.84801,13.81111],"type":"Point"}
}