{
  "type": "Feature",
  "properties": {
    "gn:admin1_code":"3.0",
    "gn:asciiname":"Kwase",
    "gn:country_code":"NE",
    "gn:dem":253,
    "gn:feature_class":"P",
    "gn:feature_code":"PPL",
    "gn:name":"Kwas\u00e9",
    "gn:population":0,
    "gn:timezone":"Africa/Niamey",
    "iso:country":"NE",
    "name:und_x_variant":[
        "Kwass\u00e9",
        "Kwas\u00e9"
    ],
    "wof:name":"Kwase",
    "wof:placetype":"locality"
},
  "geometry": {"coordinates":[3.8358,14.066],"type":"Point"}
}