{
  "type": "Feature",
  "properties": {
    "gn:admin1_code":"4.0",
    "gn:asciiname":"Kamakoro",
    "gn:country_code":"NE",
    "gn:dem":411,
    "gn:feature_class":"P",
    "gn:feature_code":"PPL",
    "gn:name":"Kamakoro",
    "gn:population":0,
    "gn:timezone":"Africa/Niamey",
    "iso:country":"NE",
    "wof:name":"Kamakoro",
    "wof:placetype":"locality"
},
  "geometry": {"coordinates":[6.7391,14.39627],"type":"Point"}
}