{
  "type": "Feature",
  "properties": {
    "gn:admin1_code":"3.0",
    "gn:asciiname":"Bare-Bari",
    "gn:country_code":"NE",
    "gn:dem":224,
    "gn:feature_class":"P",
    "gn:feature_code":"PPL",
    "gn:name":"Bar\u00e9-Bari",
    "gn:population":0,
    "gn:timezone":"Africa/Niamey",
    "iso:country":"NE",
    "wof:name":"Bare-Bari",
    "wof:placetype":"locality"
},
  "geometry": {"coordinates":[4.05066,13.78537],"type":"Point"}
}