{
  "type": "Feature",
  "properties": {
    "gn:admin1_code":"7.0",
    "gn:asciiname":"Roumji",
    "gn:country_code":"NE",
    "gn:dem":460,
    "gn:feature_class":"P",
    "gn:feature_code":"PPL",
    "gn:name":"Roumji",
    "gn:population":0,
    "gn:timezone":"Africa/Niamey",
    "iso:country":"NE",
    "name:und_x_variant":[
        "Roumdji",
        "Roumji"
    ],
    "wof:name":"Roumji",
    "wof:placetype":"locality"
},
  "geometry": {"coordinates":[8.42475,13.19748],"type":"Point"}
}