{
  "type": "Feature",
  "properties": {
    "gn:admin1_code":"9.0",
    "gn:asciiname":"Yelwani",
    "gn:country_code":"NE",
    "gn:dem":206,
    "gn:feature_class":"P",
    "gn:feature_code":"PPL",
    "gn:name":"Yelwani",
    "gn:population":0,
    "gn:timezone":"Africa/Niamey",
    "iso:country":"NE",
    "name:und_x_variant":[
        "Y\u00e9l\u00e9ouani",
        "Y\u00e9louan\u00e9",
        "Yelwani",
        "Y\u00e9l\u00e9wani"
    ],
    "wof:name":"Yelwani",
    "wof:placetype":"locality"
},
  "geometry": {"coordinates":[1.43617,14.1742],"type":"Point"}
}