{
  "type": "Feature",
  "properties": {
    "gn:admin1_code":"7.0",
    "gn:asciiname":"Rwan Denya",
    "gn:country_code":"NE",
    "gn:dem":447,
    "gn:feature_class":"P",
    "gn:feature_code":"PPL",
    "gn:name":"Rwan D\u00e9nya",
    "gn:population":0,
    "gn:timezone":"Africa/Niamey",
    "iso:country":"NE",
    "wof:name":"Rwan Denya",
    "wof:placetype":"locality"
},
  "geometry": {"coordinates":[8.02514,14.80797],"type":"Point"}
}