{
  "type": "Feature",
  "properties": {
    "gn:admin1_code":"2.0",
    "gn:asciiname":"Kirl Bitoa Kader",
    "gn:country_code":"NE",
    "gn:dem":348,
    "gn:feature_class":"P",
    "gn:feature_code":"PPL",
    "gn:name":"Kirl Bitoa Kad\u00e9r",
    "gn:population":0,
    "gn:timezone":"Africa/Niamey",
    "iso:country":"NE",
    "wof:name":"Kirl Bitoa Kader",
    "wof:placetype":"locality"
},
  "geometry": {"coordinates":[10.78004,13.37601],"type":"Point"}
}