{
  "type": "Feature",
  "properties": {
    "gn:admin1_code":"3.0",
    "gn:asciiname":"Goumande-Sene",
    "gn:country_code":"NE",
    "gn:dem":215,
    "gn:feature_class":"P",
    "gn:feature_code":"PPL",
    "gn:name":"Goumand\u00e9-S\u00e8n\u00e9",
    "gn:population":0,
    "gn:timezone":"Africa/Niamey",
    "iso:country":"NE",
    "wof:name":"Goumande-Sene",
    "wof:placetype":"locality"
},
  "geometry": {"coordinates":[3.5582,13.0685],"type":"Point"}
}