{
  "type": "Feature",
  "properties": {
    "gn:admin1_code":"7.0",
    "gn:asciiname":"Gogoro",
    "gn:country_code":"NE",
    "gn:dem":456,
    "gn:feature_class":"P",
    "gn:feature_code":"PPL",
    "gn:name":"Gogoro",
    "gn:population":0,
    "gn:timezone":"Africa/Niamey",
    "iso:country":"NE",
    "name:jpn_x_preferred":[
        "Gogoro"
    ],
    "name:zho_x_preferred":[
        "Gogoro"
    ],
    "wof:name":"Gogoro",
    "wof:placetype":"locality"
},
  "geometry": {"coordinates":[8.5419,14.4809],"type":"Point"}
}