{
  "type": "Feature",
  "properties": {
    "gn:admin1_code":"9.0",
    "gn:asciiname":"Gourmakindi",
    "gn:country_code":"NE",
    "gn:dem":242,
    "gn:feature_class":"P",
    "gn:feature_code":"PPL",
    "gn:name":"Gourmakindi",
    "gn:population":0,
    "gn:timezone":"Africa/Niamey",
    "iso:country":"NE",
    "wof:name":"Gourmakindi",
    "wof:placetype":"locality"
},
  "geometry": {"coordinates":[1.10473,13.82055],"type":"Point"}
}