{
  "type": "Feature",
  "properties": {
    "gn:admin1_code":"4.0",
    "gn:asciiname":"Talagawa",
    "gn:country_code":"NE",
    "gn:dem":391,
    "gn:feature_class":"P",
    "gn:feature_code":"PPL",
    "gn:name":"Talagawa",
    "gn:population":0,
    "gn:timezone":"Africa/Niamey",
    "iso:country":"NE",
    "name:und_x_variant":[
        "Tagaza",
        "Talagawa"
    ],
    "wof:name":"Talagawa",
    "wof:placetype":"locality"
},
  "geometry": {"coordinates":[7.18578,13.55694],"type":"Point"}
}