{
  "type": "Feature",
  "properties": {
    "gn:admin1_code":"4.0",
    "gn:asciiname":"Gafia",
    "gn:country_code":"NE",
    "gn:dem":412,
    "gn:feature_class":"P",
    "gn:feature_code":"PPL",
    "gn:name":"Gafia",
    "gn:population":0,
    "gn:timezone":"Africa/Niamey",
    "iso:country":"NE",
    "wof:name":"Gafia",
    "wof:placetype":"locality"
},
  "geometry": {"coordinates":[7.95339,13.45498],"type":"Point"}
}