{
  "type": "Feature",
  "properties": {
    "gn:admin1_code":"2.0",
    "gn:asciiname":"Yourdeseni",
    "gn:country_code":"NE",
    "gn:dem":349,
    "gn:feature_class":"P",
    "gn:feature_code":"PPL",
    "gn:name":"Yourd\u00e9s\u00e9ni",
    "gn:population":0,
    "gn:timezone":"Africa/Niamey",
    "iso:country":"NE",
    "wof:name":"Yourdeseni",
    "wof:placetype":"locality"
},
  "geometry": {"coordinates":[10.98977,13.66754],"type":"Point"}
}