{
  "type": "Feature",
  "properties": {
    "gn:admin1_code":"7.0",
    "gn:asciiname":"Roufao",
    "gn:country_code":"NE",
    "gn:dem":465,
    "gn:feature_class":"P",
    "gn:feature_code":"PPL",
    "gn:name":"Roufao",
    "gn:population":0,
    "gn:timezone":"Africa/Niamey",
    "iso:country":"NE",
    "wof:name":"Roufao",
    "wof:placetype":"locality"
},
  "geometry": {"coordinates":[8.352,13.19743],"type":"Point"}
}