{
  "type": "Feature",
  "properties": {
    "gn:admin1_code":"7.0",
    "gn:asciiname":"Yan Gandou",
    "gn:country_code":"NE",
    "gn:dem":422,
    "gn:feature_class":"P",
    "gn:feature_code":"PPL",
    "gn:name":"Yan Gandou",
    "gn:population":0,
    "gn:timezone":"Africa/Niamey",
    "iso:country":"NE",
    "wof:name":"Yan Gandou",
    "wof:placetype":"locality"
},
  "geometry": {"coordinates":[8.77869,13.24193],"type":"Point"}
}