{
  "type": "Feature",
  "properties": {
    "gn:admin1_code":"7.0",
    "gn:asciiname":"Birji",
    "gn:country_code":"NE",
    "gn:dem":486,
    "gn:feature_class":"P",
    "gn:feature_code":"PPL",
    "gn:name":"Birji",
    "gn:population":0,
    "gn:timezone":"Africa/Niamey",
    "iso:country":"NE",
    "wof:name":"Birji",
    "wof:placetype":"locality"
},
  "geometry": {"coordinates":[8.64729,14.59652],"type":"Point"}
}