{
  "type": "Feature",
  "properties": {
    "gn:admin1_code":"9.0",
    "gn:asciiname":"Tasya",
    "gn:country_code":"NE",
    "gn:dem":233,
    "gn:feature_class":"P",
    "gn:feature_code":"PPL",
    "gn:name":"Tasya",
    "gn:population":0,
    "gn:timezone":"Africa/Niamey",
    "iso:country":"NE",
    "name:und_x_variant":[
        "Tassya"
    ],
    "wof:name":"Tasya",
    "wof:placetype":"locality"
},
  "geometry": {"coordinates":[1.85634,12.69794],"type":"Point"}
}