{
  "type": "Feature",
  "properties": {
    "gn:admin1_code":"9.0",
    "gn:asciiname":"Kabanda",
    "gn:country_code":"NE",
    "gn:dem":265,
    "gn:feature_class":"P",
    "gn:feature_code":"PPL",
    "gn:name":"Kabanda",
    "gn:population":0,
    "gn:timezone":"Africa/Niamey",
    "iso:country":"NE",
    "wof:name":"Kabanda",
    "wof:placetype":"locality"
},
  "geometry": {"coordinates":[1.99954,14.12354],"type":"Point"}
}