{
  "type": "Feature",
  "properties": {
    "gn:admin1_code":"3.0",
    "gn:asciiname":"Angoa Maba",
    "gn:country_code":"NE",
    "gn:dem":211,
    "gn:feature_class":"P",
    "gn:feature_code":"PPL",
    "gn:name":"Angoa Maba",
    "gn:population":0,
    "gn:timezone":"Africa/Niamey",
    "iso:country":"NE",
    "wof:name":"Angoa Maba",
    "wof:placetype":"locality"
},
  "geometry": {"coordinates":[3.82483,12.86943],"type":"Point"}
}