{
  "type": "Feature",
  "properties": {
    "gn:admin1_code":"7.0",
    "gn:asciiname":"Kaki Barama",
    "gn:country_code":"NE",
    "gn:dem":513,
    "gn:feature_class":"P",
    "gn:feature_code":"PPL",
    "gn:name":"Kaki Barama",
    "gn:population":0,
    "gn:timezone":"Africa/Niamey",
    "iso:country":"NE",
    "wof:name":"Kaki Barama",
    "wof:placetype":"locality"
},
  "geometry": {"coordinates":[9.1685,14.3258],"type":"Point"}
}