{
  "type": "Feature",
  "properties": {
    "gn:admin1_code":"3.0",
    "gn:asciiname":"Larey",
    "gn:country_code":"NE",
    "gn:dem":169,
    "gn:feature_class":"P",
    "gn:feature_code":"PPL",
    "gn:name":"Larey",
    "gn:population":0,
    "gn:timezone":"Africa/Niamey",
    "iso:country":"NE",
    "name:und_x_variant":[
        "Lar\u00e8ye",
        "Larey"
    ],
    "wof:name":"Larey",
    "wof:placetype":"locality"
},
  "geometry": {"coordinates":[3.02019,12.28842],"type":"Point"}
}