{
  "type": "Feature",
  "properties": {
    "gn:admin1_code":"3.0",
    "gn:asciiname":"Zalokoto",
    "gn:country_code":"NE",
    "gn:dem":220,
    "gn:feature_class":"P",
    "gn:feature_code":"PPL",
    "gn:name":"Zalokoto",
    "gn:population":0,
    "gn:timezone":"Africa/Niamey",
    "iso:country":"NE",
    "wof:name":"Zalokoto",
    "wof:placetype":"locality"
},
  "geometry": {"coordinates":[3.41642,12.43051],"type":"Point"}
}