{
  "type": "Feature",
  "properties": {
    "gn:admin1_code":"9.0",
    "gn:asciiname":"Fegana Kabe",
    "gn:country_code":"NE",
    "gn:dem":236,
    "gn:feature_class":"P",
    "gn:feature_code":"PPL",
    "gn:name":"F\u00e9gana Kab\u00e9",
    "gn:population":0,
    "gn:timezone":"Africa/Niamey",
    "iso:country":"NE",
    "wof:name":"Fegana Kabe",
    "wof:placetype":"locality"
},
  "geometry": {"coordinates":[2.69123,14.67147],"type":"Point"}
}