{
  "type": "Feature",
  "properties": {
    "gn:admin1_code":"7.0",
    "gn:asciiname":"Kalachinbiri",
    "gn:country_code":"NE",
    "gn:dem":451,
    "gn:feature_class":"P",
    "gn:feature_code":"PPL",
    "gn:name":"Kalachinbiri",
    "gn:population":0,
    "gn:timezone":"Africa/Niamey",
    "iso:country":"NE",
    "wof:name":"Kalachinbiri",
    "wof:placetype":"locality"
},
  "geometry": {"coordinates":[8.7886,14.1671],"type":"Point"}
}