{
  "type": "Feature",
  "properties": {
    "gn:admin1_code":"6.0",
    "gn:asciiname":"Moutela",
    "gn:country_code":"NE",
    "gn:dem":259,
    "gn:feature_class":"P",
    "gn:feature_code":"PPL",
    "gn:name":"Mout\u00e9la",
    "gn:population":0,
    "gn:timezone":"Africa/Niamey",
    "iso:country":"NE",
    "wof:name":"Moutela",
    "wof:placetype":"locality"
},
  "geometry": {"coordinates":[4.53161,14.13839],"type":"Point"}
}