{
  "type": "Feature",
  "properties": {
    "gn:admin1_code":"7.0",
    "gn:asciiname":"Bakoum",
    "gn:country_code":"NE",
    "gn:dem":395,
    "gn:feature_class":"P",
    "gn:feature_code":"PPL",
    "gn:name":"Bakoum",
    "gn:population":0,
    "gn:timezone":"Africa/Niamey",
    "iso:country":"NE",
    "wof:name":"Bakoum",
    "wof:placetype":"locality"
},
  "geometry": {"coordinates":[8.9606,13.36288],"type":"Point"}
}