{
  "type": "Feature",
  "properties": {
    "gn:admin1_code":"6.0",
    "gn:asciiname":"Guidan Kaso",
    "gn:country_code":"NE",
    "gn:dem":319,
    "gn:feature_class":"P",
    "gn:feature_code":"PPL",
    "gn:name":"Guidan Kaso",
    "gn:population":0,
    "gn:timezone":"Africa/Niamey",
    "iso:country":"NE",
    "name:und_x_variant":[
        "Guidan Kasso",
        "Guidan Kaso"
    ],
    "wof:name":"Guidan Kaso",
    "wof:placetype":"locality"
},
  "geometry": {"coordinates":[6.16121,13.84381],"type":"Point"}
}