{
  "type": "Feature",
  "properties": {
    "gn:admin1_code":"4.0",
    "gn:asciiname":"Tamidao",
    "gn:country_code":"NE",
    "gn:dem":364,
    "gn:feature_class":"P",
    "gn:feature_code":"PPL",
    "gn:name":"Tamidao",
    "gn:population":0,
    "gn:timezone":"Africa/Niamey",
    "iso:country":"NE",
    "wof:name":"Tamidao",
    "wof:placetype":"locality"
},
  "geometry": {"coordinates":[6.89553,13.92129],"type":"Point"}
}