{
  "type": "Feature",
  "properties": {
    "gn:admin1_code":"6.0",
    "gn:asciiname":"Guidan Gardawa",
    "gn:country_code":"NE",
    "gn:dem":392,
    "gn:feature_class":"P",
    "gn:feature_code":"PPL",
    "gn:name":"Guidan Gardawa",
    "gn:population":0,
    "gn:timezone":"Africa/Niamey",
    "iso:country":"NE",
    "name:und_x_variant":[
        "Gardaoua",
        "Guidan Gardawa"
    ],
    "wof:name":"Guidan Gardawa",
    "wof:placetype":"locality"
},
  "geometry": {"coordinates":[6.21908,14.53314],"type":"Point"}
}