{
  "type": "Feature",
  "properties": {
    "gn:admin1_code":"7.0",
    "gn:asciiname":"Zangatourari",
    "gn:country_code":"NE",
    "gn:dem":442,
    "gn:feature_class":"P",
    "gn:feature_code":"PPL",
    "gn:name":"Zangatourari",
    "gn:population":0,
    "gn:timezone":"Africa/Niamey",
    "iso:country":"NE",
    "wof:name":"Zangatourari",
    "wof:placetype":"locality"
},
  "geometry": {"coordinates":[9.1442,13.7455],"type":"Point"}
}