{
  "type": "Feature",
  "properties": {
    "gn:admin1_code":"4.0",
    "gn:asciiname":"Garin Amadou",
    "gn:country_code":"NE",
    "gn:dem":355,
    "gn:feature_class":"P",
    "gn:feature_code":"PPL",
    "gn:name":"Garin Amadou",
    "gn:population":0,
    "gn:timezone":"Africa/Niamey",
    "iso:country":"NE",
    "wof:name":"Garin Amadou",
    "wof:placetype":"locality"
},
  "geometry": {"coordinates":[6.81781,13.95452],"type":"Point"}
}