{
  "type": "Feature",
  "properties": {
    "gn:admin1_code":"4.0",
    "gn:asciiname":"Barmo",
    "gn:country_code":"NE",
    "gn:dem":371,
    "gn:feature_class":"P",
    "gn:feature_code":"PPL",
    "gn:name":"Barmo",
    "gn:population":0,
    "gn:timezone":"Africa/Niamey",
    "iso:country":"NE",
    "name:und_x_variant":[
        "Guidan Barmou",
        "Barmo"
    ],
    "wof:name":"Barmo",
    "wof:placetype":"locality"
},
  "geometry": {"coordinates":[6.90017,14.20393],"type":"Point"}
}