{
  "type": "Feature",
  "properties": {
    "gn:admin1_code":"7.0",
    "gn:asciiname":"Gabagaoua",
    "gn:country_code":"NE",
    "gn:dem":463,
    "gn:feature_class":"P",
    "gn:feature_code":"PPL",
    "gn:name":"Gabagaoua",
    "gn:population":0,
    "gn:timezone":"Africa/Niamey",
    "iso:country":"NE",
    "wof:name":"Gabagaoua",
    "wof:placetype":"locality"
},
  "geometry": {"coordinates":[9.4586,14.1713],"type":"Point"}
}