{
  "type": "Feature",
  "properties": {
    "gn:admin1_code":"3.0",
    "gn:asciiname":"Kwalen Dawa",
    "gn:country_code":"NE",
    "gn:dem":278,
    "gn:feature_class":"P",
    "gn:feature_code":"PPL",
    "gn:name":"Kwal\u00e8n Dawa",
    "gn:population":0,
    "gn:timezone":"Africa/Niamey",
    "iso:country":"NE",
    "wof:name":"Kwalen Dawa",
    "wof:placetype":"locality"
},
  "geometry": {"coordinates":[3.8192,14.1668],"type":"Point"}
}