{
  "type": "Feature",
  "properties": {
    "gn:admin1_code":"7.0",
    "gn:asciiname":"Soli",
    "gn:country_code":"NE",
    "gn:dem":373,
    "gn:feature_class":"P",
    "gn:feature_code":"PPL",
    "gn:name":"Soli",
    "gn:population":0,
    "gn:timezone":"Africa/Niamey",
    "iso:country":"NE",
    "wof:name":"Soli",
    "wof:placetype":"locality"
},
  "geometry": {"coordinates":[9.25711,12.83672],"type":"Point"}
}