{
  "type": "Feature",
  "properties": {
    "gn:admin1_code":"7.0",
    "gn:asciiname":"Soli",
    "gn:country_code":"NE",
    "gn:dem":373,
    "gn:feature_class":"P",
    "gn:feature_code":"PPL",
    "gn:name":"Soli",
    "gn:population":0,
    "gn:timezone":"Africa/Niamey",
    "iso:country":"NE",
    "name:bel_x_preferred":[
        "\u0421\u043e\u043b\u044b"
    ],
    "name:bos_x_preferred":[
        "Soli"
    ],
    "name:bul_x_preferred":[
        "\u0421\u043e\u043b\u0438"
    ],
    "name:cat_x_preferred":[
        "Soli"
    ],
    "name:ceb_x_preferred":[
        "Soli"
    ],
    "name:deu_x_preferred":[
        "Soli"
    ],
    "name:ell_x_preferred":[
        "\u03a3\u03cc\u03bb\u03bf\u03b9"
    ],
    "name:eus_x_preferred":[
        "Soli"
    ],
    "name:fra_x_preferred":[
        "Soli"
    ],
    "name:heb_x_preferred":[
        "\u05e1\u05d5\u05dc\u05d9"
    ],
    "name:hrv_x_preferred":[
        "Soli"
    ],
    "name:ita_x_preferred":[
        "Soli"
    ],
    "name:lat_x_preferred":[
        "Soli"
    ],
    "name:nld_x_preferred":[
        "Soli"
    ],
    "name:rus_x_preferred":[
        "\u0421\u043e\u043b\u044b"
    ],
    "name:srp_x_preferred":[
        "\u0421\u043e\u043b\u0438"
    ],
    "name:swe_x_preferred":[
        "Soli"
    ],
    "name:tur_x_preferred":[
        "Soli"
    ],
    "name:ukr_x_preferred":[
        "Soli"
    ],
    "wof:name":"Soli",
    "wof:placetype":"locality"
},
  "geometry": {"coordinates":[9.25711,12.83672],"type":"Point"}
}