{
  "type": "Feature",
  "properties": {
    "gn:admin1_code":"7.0",
    "gn:asciiname":"Komizabewa",
    "gn:country_code":"NE",
    "gn:dem":365,
    "gn:feature_class":"P",
    "gn:feature_code":"PPL",
    "gn:name":"Komizab\u00e9wa",
    "gn:population":0,
    "gn:timezone":"Africa/Niamey",
    "iso:country":"NE",
    "wof:name":"Komizabewa",
    "wof:placetype":"locality"
},
  "geometry": {"coordinates":[10.09542,13.37657],"type":"Point"}
}