{
  "type": "Feature",
  "properties": {
    "gn:admin1_code":"8.0",
    "gn:asciiname":"Loley Tondi",
    "gn:cc2":"NE",
    "gn:country_code":"NE",
    "gn:dem":223,
    "gn:feature_class":"P",
    "gn:feature_code":"PPL",
    "gn:name":"Loley Tondi",
    "gn:population":0,
    "gn:timezone":"Africa/Niamey",
    "iso:country":"NE",
    "name:und_x_variant":[
        "Lolleitondi",
        "Loleye-Tondi",
        "Loley Tondi"
    ],
    "wof:name":"Loley Tondi",
    "wof:placetype":"locality"
},
  "geometry": {"coordinates":[2.01667,13.93333],"type":"Point"}
}