{
  "type": "Feature",
  "properties": {
    "gn:admin1_code":"6.0",
    "gn:asciiname":"Abongoulou",
    "gn:country_code":"NE",
    "gn:dem":285,
    "gn:feature_class":"P",
    "gn:feature_code":"PPL",
    "gn:name":"Abongoulou",
    "gn:population":0,
    "gn:timezone":"Africa/Niamey",
    "iso:country":"NE",
    "wof:name":"Abongoulou",
    "wof:placetype":"locality"
},
  "geometry": {"coordinates":[4.91655,14.44466],"type":"Point"}
}