{
  "type": "Feature",
  "properties": {
    "gn:admin1_code":"7.0",
    "gn:asciiname":"Bashiri",
    "gn:country_code":"NE",
    "gn:dem":358,
    "gn:feature_class":"P",
    "gn:feature_code":"PPL",
    "gn:name":"Bashiri",
    "gn:population":0,
    "gn:timezone":"Africa/Niamey",
    "iso:country":"NE",
    "wof:name":"Bashiri",
    "wof:placetype":"locality"
},
  "geometry": {"coordinates":[9.993,13.1986],"type":"Point"}
}