{
  "type": "Feature",
  "properties": {
    "gn:admin1_code":"7.0",
    "gn:asciiname":"Dohinguel",
    "gn:country_code":"NE",
    "gn:dem":387,
    "gn:feature_class":"P",
    "gn:feature_code":"PPL",
    "gn:name":"Dohingu\u00e8l",
    "gn:population":0,
    "gn:timezone":"Africa/Niamey",
    "iso:country":"NE",
    "wof:name":"Dohinguel",
    "wof:placetype":"locality"
},
  "geometry": {"coordinates":[10.8357,14.1848],"type":"Point"}
}