{
  "type": "Feature",
  "properties": {
    "gn:admin1_code":"7.0",
    "gn:asciiname":"Koreoua",
    "gn:country_code":"NE",
    "gn:dem":482,
    "gn:feature_class":"P",
    "gn:feature_code":"PPL",
    "gn:name":"Kor\u00e9oua",
    "gn:population":0,
    "gn:timezone":"Africa/Niamey",
    "iso:country":"NE",
    "wof:name":"Koreoua",
    "wof:placetype":"locality"
},
  "geometry": {"coordinates":[9.1883,14.6278],"type":"Point"}
}