{
  "type": "Feature",
  "properties": {
    "gn:admin1_code":"9.0",
    "gn:asciiname":"Gerin Djinba",
    "gn:country_code":"NE",
    "gn:dem":266,
    "gn:feature_class":"P",
    "gn:feature_code":"PPL",
    "gn:name":"G\u00e9rin Djinba",
    "gn:population":0,
    "gn:timezone":"Africa/Niamey",
    "iso:country":"NE",
    "name:und_x_variant":[
        "Gu\u00e9rin Djinba",
        "G\u00e9rin Djinba"
    ],
    "wof:name":"Gerin Djinba",
    "wof:placetype":"locality"
},
  "geometry": {"coordinates":[3.3187,15.0353],"type":"Point"}
}