{
  "type": "Feature",
  "properties": {
    "gn:admin1_code":"2.0",
    "gn:asciiname":"Garana",
    "gn:country_code":"NE",
    "gn:dem":348,
    "gn:feature_class":"P",
    "gn:feature_code":"PPL",
    "gn:name":"Garana",
    "gn:population":0,
    "gn:timezone":"Africa/Niamey",
    "iso:country":"NE",
    "wof:name":"Garana",
    "wof:placetype":"locality"
},
  "geometry": {"coordinates":[10.94387,13.66878],"type":"Point"}
}