{
  "type": "Feature",
  "properties": {
    "gn:admin1_code":"4.0",
    "gn:asciiname":"Goulou Koulsao",
    "gn:country_code":"NE",
    "gn:dem":380,
    "gn:feature_class":"P",
    "gn:feature_code":"PPL",
    "gn:name":"Goulou Koulsao",
    "gn:population":0,
    "gn:timezone":"Africa/Niamey",
    "iso:country":"NE",
    "wof:name":"Goulou Koulsao",
    "wof:placetype":"locality"
},
  "geometry": {"coordinates":[6.80088,13.19297],"type":"Point"}
}