{
  "type": "Feature",
  "properties": {
    "gn:admin1_code":"7.0",
    "gn:asciiname":"Koulala",
    "gn:country_code":"NE",
    "gn:dem":430,
    "gn:feature_class":"P",
    "gn:feature_code":"PPL",
    "gn:name":"Koulala",
    "gn:population":0,
    "gn:timezone":"Africa/Niamey",
    "iso:country":"NE",
    "wof:name":"Koulala",
    "wof:placetype":"locality"
},
  "geometry": {"coordinates":[9.2914,13.9037],"type":"Point"}
}