{
  "type": "Feature",
  "properties": {
    "gn:admin1_code":"4.0",
    "gn:asciiname":"Ardo Aleke",
    "gn:country_code":"NE",
    "gn:dem":426,
    "gn:feature_class":"P",
    "gn:feature_code":"PPL",
    "gn:name":"Ardo Al\u00e9k\u00e9",
    "gn:population":0,
    "gn:timezone":"Africa/Niamey",
    "iso:country":"NE",
    "wof:name":"Ardo Aleke",
    "wof:placetype":"locality"
},
  "geometry": {"coordinates":[7.49183,14.17029],"type":"Point"}
}