{
  "type": "Feature",
  "properties": {
    "gn:admin1_code":"6.0",
    "gn:asciiname":"Komosou",
    "gn:country_code":"NE",
    "gn:dem":441,
    "gn:feature_class":"P",
    "gn:feature_code":"PPL",
    "gn:name":"Komosou",
    "gn:population":0,
    "gn:timezone":"Africa/Niamey",
    "iso:country":"NE",
    "wof:name":"Komosou",
    "wof:placetype":"locality"
},
  "geometry": {"coordinates":[5.8811,14.4411],"type":"Point"}
}