{
  "type": "Feature",
  "properties": {
    "gn:admin1_code":"7.0",
    "gn:asciiname":"Kondiri",
    "gn:country_code":"NE",
    "gn:dem":380,
    "gn:feature_class":"P",
    "gn:feature_code":"PPL",
    "gn:name":"Kondiri",
    "gn:population":0,
    "gn:timezone":"Africa/Niamey",
    "iso:country":"NE",
    "wof:name":"Kondiri",
    "wof:placetype":"locality"
},
  "geometry": {"coordinates":[9.12624,12.97381],"type":"Point"}
}