{
  "type": "Feature",
  "properties": {
    "gn:admin1_code":"4.0",
    "gn:asciiname":"Koren Saboa",
    "gn:country_code":"NE",
    "gn:dem":374,
    "gn:feature_class":"P",
    "gn:feature_code":"PPL",
    "gn:name":"Kor\u00e9n Saboa",
    "gn:population":0,
    "gn:timezone":"Africa/Niamey",
    "iso:country":"NE",
    "wof:name":"Koren Saboa",
    "wof:placetype":"locality"
},
  "geometry": {"coordinates":[7.10903,14.00773],"type":"Point"}
}