{
  "type": "Feature",
  "properties": {
    "gn:admin1_code":"6.0",
    "gn:asciiname":"Toudoun Kara",
    "gn:country_code":"NE",
    "gn:dem":360,
    "gn:feature_class":"P",
    "gn:feature_code":"PPL",
    "gn:name":"Toudoun Kara",
    "gn:population":0,
    "gn:timezone":"Africa/Niamey",
    "iso:country":"NE",
    "wof:name":"Toudoun Kara",
    "wof:placetype":"locality"
},
  "geometry": {"coordinates":[5.2321,14.8172],"type":"Point"}
}