{
  "type": "Feature",
  "properties": {
    "gn:admin1_code":"4.0",
    "gn:asciiname":"Guidan Kognao",
    "gn:country_code":"NE",
    "gn:dem":323,
    "gn:feature_class":"P",
    "gn:feature_code":"PPL",
    "gn:name":"Guidan Kognao",
    "gn:population":0,
    "gn:timezone":"Africa/Niamey",
    "iso:country":"NE",
    "name:und_x_variant":[
        "Gidan Kognao",
        "Guidan Konyao",
        "Guidan Kognao"
    ],
    "wof:name":"Guidan Kognao",
    "wof:placetype":"locality"
},
  "geometry": {"coordinates":[6.34263,13.77267],"type":"Point"}
}