{
  "type": "Feature",
  "properties": {
    "gn:admin1_code":"3.0",
    "gn:asciiname":"Faredeye",
    "gn:country_code":"NE",
    "gn:dem":246,
    "gn:feature_class":"P",
    "gn:feature_code":"PPL",
    "gn:name":"Far\u00e9d\u00e8ye",
    "gn:population":0,
    "gn:timezone":"Africa/Niamey",
    "iso:country":"NE",
    "wof:name":"Faredeye",
    "wof:placetype":"locality"
},
  "geometry": {"coordinates":[3.3691,13.1159],"type":"Point"}
}