{
  "type": "Feature",
  "properties": {
    "gn:admin1_code":"4.0",
    "gn:asciiname":"Bakire",
    "gn:country_code":"NE",
    "gn:dem":381,
    "gn:feature_class":"P",
    "gn:feature_code":"PPL",
    "gn:name":"Bakir\u00e9",
    "gn:population":0,
    "gn:timezone":"Africa/Niamey",
    "iso:country":"NE",
    "wof:name":"Bakire",
    "wof:placetype":"locality"
},
  "geometry": {"coordinates":[6.94198,14.21725],"type":"Point"}
}