{
  "type": "Feature",
  "properties": {
    "gn:admin1_code":"7.0",
    "gn:asciiname":"Faragona",
    "gn:country_code":"NE",
    "gn:dem":476,
    "gn:feature_class":"P",
    "gn:feature_code":"PPL",
    "gn:name":"Faragona",
    "gn:population":0,
    "gn:timezone":"Africa/Niamey",
    "iso:country":"NE",
    "wof:name":"Faragona",
    "wof:placetype":"locality"
},
  "geometry": {"coordinates":[8.56941,14.94682],"type":"Point"}
}