{
  "type": "Feature",
  "properties": {
    "gn:admin1_code":"9.0",
    "gn:asciiname":"Arikiley",
    "gn:country_code":"NE",
    "gn:dem":240,
    "gn:feature_class":"P",
    "gn:feature_code":"PPL",
    "gn:name":"Arikil\u00e8y",
    "gn:population":0,
    "gn:timezone":"Africa/Niamey",
    "iso:country":"NE",
    "name:und_x_variant":[
        "Arikir\u00e9",
        "Arikil\u00e8y"
    ],
    "wof:name":"Arikiley",
    "wof:placetype":"locality"
},
  "geometry": {"coordinates":[2.21776,14.62195],"type":"Point"}
}