{
  "type": "Feature",
  "properties": {
    "gn:admin1_code":"7.0",
    "gn:asciiname":"Koudouddoufi",
    "gn:country_code":"NE",
    "gn:dem":448,
    "gn:feature_class":"P",
    "gn:feature_code":"PPL",
    "gn:name":"Koudouddoufi",
    "gn:population":0,
    "gn:timezone":"Africa/Niamey",
    "iso:country":"NE",
    "name:und_x_variant":[
        "Koudidifi",
        "Koudouddoufi"
    ],
    "wof:name":"Koudouddoufi",
    "wof:placetype":"locality"
},
  "geometry": {"coordinates":[8.40838,13.79292],"type":"Point"}
}