{
  "type": "Feature",
  "properties": {
    "gn:admin1_code":"4.0",
    "gn:asciiname":"Malali",
    "gn:country_code":"NE",
    "gn:dem":446,
    "gn:feature_class":"P",
    "gn:feature_code":"PPL",
    "gn:name":"Malali",
    "gn:population":0,
    "gn:timezone":"Africa/Niamey",
    "iso:country":"NE",
    "wof:name":"Malali",
    "wof:placetype":"locality"
},
  "geometry": {"coordinates":[7.69578,14.27838],"type":"Point"}
}