{
  "type": "Feature",
  "properties": {
    "gn:admin1_code":"9.0",
    "gn:asciiname":"Niame",
    "gn:country_code":"NE",
    "gn:dem":196,
    "gn:feature_class":"P",
    "gn:feature_code":"PPL",
    "gn:name":"Niam\u00e9",
    "gn:population":0,
    "gn:timezone":"Africa/Niamey",
    "iso:country":"NE",
    "name:und_x_variant":[
        "Niamey",
        "Niam\u00e9"
    ],
    "wof:name":"Niame",
    "wof:placetype":"locality"
},
  "geometry": {"coordinates":[1.79068,13.6708],"type":"Point"}
}