{
  "type": "Feature",
  "properties": {
    "gn:admin1_code":"3.0",
    "gn:asciiname":"Guindogoloma",
    "gn:country_code":"NE",
    "gn:dem":163,
    "gn:feature_class":"P",
    "gn:feature_code":"PPL",
    "gn:name":"Guindogoloma",
    "gn:population":0,
    "gn:timezone":"Africa/Niamey",
    "iso:country":"NE",
    "wof:name":"Guindogoloma",
    "wof:placetype":"locality"
},
  "geometry": {"coordinates":[3.61404,11.73464],"type":"Point"}
}