{
  "type": "Feature",
  "properties": {
    "gn:admin1_code":"4.0",
    "gn:asciiname":"Guidan Barmou",
    "gn:country_code":"NE",
    "gn:dem":325,
    "gn:feature_class":"P",
    "gn:feature_code":"PPL",
    "gn:name":"Guidan Barmou",
    "gn:population":0,
    "gn:timezone":"Africa/Niamey",
    "iso:country":"NE",
    "wof:name":"Guidan Barmou",
    "wof:placetype":"locality"
},
  "geometry": {"coordinates":[6.36767,13.75266],"type":"Point"}
}