{
  "type": "Feature",
  "properties": {
    "gn:admin1_code":"3.0",
    "gn:asciiname":"Gardi Zarma",
    "gn:country_code":"NE",
    "gn:dem":204,
    "gn:feature_class":"P",
    "gn:feature_code":"PPL",
    "gn:name":"Gardi Zarma",
    "gn:population":0,
    "gn:timezone":"Africa/Niamey",
    "iso:country":"NE",
    "name:und_x_variant":[
        "Gardi",
        "Gardi Zarma"
    ],
    "wof:name":"Gardi Zarma",
    "wof:placetype":"locality"
},
  "geometry": {"coordinates":[2.9482,13.4925],"type":"Point"}
}