{
  "type": "Feature",
  "properties": {
    "gn:admin1_code":"9.0",
    "gn:asciiname":"Gassa",
    "gn:country_code":"NE",
    "gn:dem":269,
    "gn:feature_class":"P",
    "gn:feature_code":"PPL",
    "gn:name":"Gassa",
    "gn:population":0,
    "gn:timezone":"Africa/Niamey",
    "iso:country":"NE",
    "name:und_x_variant":[
        "Gassa Ziban"
    ],
    "wof:name":"Gassa",
    "wof:placetype":"locality"
},
  "geometry": {"coordinates":[1.54048,14.47698],"type":"Point"}
}