{
  "type": "Feature",
  "properties": {
    "gn:admin1_code":"7.0",
    "gn:asciiname":"Gariadi",
    "gn:country_code":"NE",
    "gn:dem":490,
    "gn:feature_class":"P",
    "gn:feature_code":"PPL",
    "gn:name":"Gariadi",
    "gn:population":0,
    "gn:timezone":"Africa/Niamey",
    "iso:country":"NE",
    "wof:name":"Gariadi",
    "wof:placetype":"locality"
},
  "geometry": {"coordinates":[9.1059,14.9218],"type":"Point"}
}