{
  "type": "Feature",
  "properties": {
    "gn:admin1_code":"4.0",
    "gn:asciiname":"Karo",
    "gn:country_code":"NE",
    "gn:dem":403,
    "gn:feature_class":"P",
    "gn:feature_code":"PPL",
    "gn:name":"Karo",
    "gn:population":0,
    "gn:timezone":"Africa/Niamey",
    "iso:country":"NE",
    "name:cat_x_preferred":[
        "Karo"
    ],
    "name:ceb_x_preferred":[
        "Karo"
    ],
    "name:deu_x_preferred":[
        "Karo"
    ],
    "name:fas_x_preferred":[
        "\u06a9\u0627\u0631\u0648"
    ],
    "name:fra_x_preferred":[
        "Karo"
    ],
    "name:hye_x_preferred":[
        "\u053f\u0561\u0580\u0578"
    ],
    "name:ind_x_preferred":[
        "Karo"
    ],
    "name:pol_x_preferred":[
        "Karo"
    ],
    "name:rus_x_preferred":[
        "\u041a\u0430\u0440\u043e"
    ],
    "name:slv_x_preferred":[
        "Karo"
    ],
    "name:swe_x_preferred":[
        "Karo"
    ],
    "name:ukr_x_preferred":[
        "\u041a\u0430\u0440\u043e"
    ],
    "wof:name":"Karo",
    "wof:placetype":"locality"
},
  "geometry": {"coordinates":[7.5427,14.07936],"type":"Point"}
}