{
  "type": "Feature",
  "properties": {
    "gn:admin1_code":"6.0",
    "gn:asciiname":"Gadou Sabon Guida",
    "gn:country_code":"NE",
    "gn:dem":568,
    "gn:feature_class":"P",
    "gn:feature_code":"PPL",
    "gn:name":"Gadou Sabon Guida",
    "gn:population":0,
    "gn:timezone":"Africa/Niamey",
    "iso:country":"NE",
    "name:und_x_variant":[
        "Gadou Sabon Gida",
        "Gadou Sabon Guida"
    ],
    "wof:name":"Gadou Sabon Guida",
    "wof:placetype":"locality"
},
  "geometry": {"coordinates":[5.898,14.586],"type":"Point"}
}