{
  "type": "Feature",
  "properties": {
    "gn:admin1_code":"4.0",
    "gn:asciiname":"Madatey",
    "gn:country_code":"NE",
    "gn:dem":468,
    "gn:feature_class":"P",
    "gn:feature_code":"PPL",
    "gn:name":"Madatey",
    "gn:population":0,
    "gn:timezone":"Africa/Niamey",
    "iso:country":"NE",
    "wof:name":"Madatey",
    "wof:placetype":"locality"
},
  "geometry": {"coordinates":[8.49985,13.87123],"type":"Point"}
}