{
  "type": "Feature",
  "properties": {
    "gn:admin1_code":"7.0",
    "gn:asciiname":"Sounsia Garin Makad'a",
    "gn:country_code":"NE",
    "gn:dem":474,
    "gn:feature_class":"P",
    "gn:feature_code":"PPL",
    "gn:name":"Sounsia Garin Makad'\u00e2",
    "gn:population":0,
    "gn:timezone":"Africa/Niamey",
    "iso:country":"NE",
    "wof:name":"Sounsia Garin Makad'a",
    "wof:placetype":"locality"
},
  "geometry": {"coordinates":[8.61996,13.91707],"type":"Point"}
}