{
  "type": "Feature",
  "properties": {
    "gn:admin1_code":"7.0",
    "gn:asciiname":"Adoumchi Bouzou",
    "gn:country_code":"NE",
    "gn:dem":390,
    "gn:feature_class":"P",
    "gn:feature_code":"PPL",
    "gn:name":"Adoumchi Bouzou",
    "gn:population":0,
    "gn:timezone":"Africa/Niamey",
    "iso:country":"NE",
    "wof:name":"Adoumchi Bouzou",
    "wof:placetype":"locality"
},
  "geometry": {"coordinates":[10.26719,13.73918],"type":"Point"}
}