{
  "type": "Feature",
  "properties": {
    "gn:admin1_code":"7.0",
    "gn:asciiname":"Baranga Leko",
    "gn:country_code":"NE",
    "gn:dem":415,
    "gn:feature_class":"P",
    "gn:feature_code":"PPL",
    "gn:name":"Baranga L\u00e9ko",
    "gn:population":0,
    "gn:timezone":"Africa/Niamey",
    "iso:country":"NE",
    "wof:name":"Baranga Leko",
    "wof:placetype":"locality"
},
  "geometry": {"coordinates":[8.80668,13.32068],"type":"Point"}
}