{
  "type": "Feature",
  "properties": {
    "gn:admin1_code":"3.0",
    "gn:asciiname":"Gari-Nbiga",
    "gn:country_code":"NE",
    "gn:dem":252,
    "gn:feature_class":"P",
    "gn:feature_code":"PPL",
    "gn:name":"Gari-Nbiga",
    "gn:population":0,
    "gn:timezone":"Africa/Niamey",
    "iso:country":"NE",
    "name:und_x_variant":[
        "Garin Biga",
        "Gari-Nbiga"
    ],
    "wof:name":"Gari-Nbiga",
    "wof:placetype":"locality"
},
  "geometry": {"coordinates":[3.9659,13.5909],"type":"Point"}
}