{
  "type": "Feature",
  "properties": {
    "gn:admin1_code":"7.0",
    "gn:asciiname":"Saouni Haoussa",
    "gn:country_code":"NE",
    "gn:dem":482,
    "gn:feature_class":"P",
    "gn:feature_code":"PPL",
    "gn:name":"Saouni Haoussa",
    "gn:population":0,
    "gn:timezone":"Africa/Niamey",
    "iso:country":"NE",
    "wof:name":"Saouni Haoussa",
    "wof:placetype":"locality"
},
  "geometry": {"coordinates":[8.45616,13.34119],"type":"Point"}
}