{
  "type": "Feature",
  "properties": {
    "gn:admin1_code":"8.0",
    "gn:asciiname":"Sidare",
    "gn:cc2":"NE",
    "gn:country_code":"NE",
    "gn:dem":205,
    "gn:feature_class":"P",
    "gn:feature_code":"PPL",
    "gn:name":"Sidar\u00e9",
    "gn:population":0,
    "gn:timezone":"Africa/Niamey",
    "iso:country":"NE",
    "name:und_x_variant":[
        "Sid\u00e9r\u00e9",
        "Sidar\u00e9"
    ],
    "wof:name":"Sidare",
    "wof:placetype":"locality"
},
  "geometry": {"coordinates":[2.93333,13.63333],"type":"Point"}
}