{
  "type": "Feature",
  "properties": {
    "gn:admin1_code":"9.0",
    "gn:asciiname":"Nikoy",
    "gn:country_code":"NE",
    "gn:dem":217,
    "gn:feature_class":"P",
    "gn:feature_code":"PPL",
    "gn:name":"Nikoy",
    "gn:population":0,
    "gn:timezone":"Africa/Niamey",
    "iso:country":"NE",
    "name:und_x_variant":[
        "Nikoy\u00e9",
        "Nikoy"
    ],
    "wof:name":"Nikoy",
    "wof:placetype":"locality"
},
  "geometry": {"coordinates":[1.75491,13.05443],"type":"Point"}
}