{
  "type": "Feature",
  "properties": {
    "gn:admin1_code":"7.0",
    "gn:asciiname":"Chakalounka",
    "gn:country_code":"NE",
    "gn:dem":472,
    "gn:feature_class":"P",
    "gn:feature_code":"PPL",
    "gn:name":"Chakalounka",
    "gn:population":0,
    "gn:timezone":"Africa/Niamey",
    "iso:country":"NE",
    "wof:name":"Chakalounka",
    "wof:placetype":"locality"
},
  "geometry": {"coordinates":[8.6474,14.6269],"type":"Point"}
}