{
  "type": "Feature",
  "properties": {
    "gn:admin1_code":"9.0",
    "gn:asciiname":"Fouliande",
    "gn:country_code":"NE",
    "gn:dem":214,
    "gn:feature_class":"P",
    "gn:feature_code":"PPL",
    "gn:name":"Fouliand\u00e9",
    "gn:population":0,
    "gn:timezone":"Africa/Niamey",
    "iso:country":"NE",
    "wof:name":"Fouliande",
    "wof:placetype":"locality"
},
  "geometry": {"coordinates":[1.13177,14.41788],"type":"Point"}
}