{
  "type": "Feature",
  "properties": {
    "gn:admin1_code":"7.0",
    "gn:asciiname":"Maygadanbo",
    "gn:country_code":"NE",
    "gn:dem":456,
    "gn:feature_class":"P",
    "gn:feature_code":"PPL",
    "gn:name":"Maygadanbo",
    "gn:population":0,
    "gn:timezone":"Africa/Niamey",
    "iso:country":"NE",
    "wof:name":"Maygadanbo",
    "wof:placetype":"locality"
},
  "geometry": {"coordinates":[8.2245,14.4101],"type":"Point"}
}