{
  "type": "Feature",
  "properties": {
    "gn:admin1_code":"6.0",
    "gn:asciiname":"Alibou",
    "gn:country_code":"NE",
    "gn:dem":415,
    "gn:feature_class":"P",
    "gn:feature_code":"PPL",
    "gn:name":"Alibou",
    "gn:population":0,
    "gn:timezone":"Africa/Niamey",
    "iso:country":"NE",
    "wof:name":"Alibou",
    "wof:placetype":"locality"
},
  "geometry": {"coordinates":[5.5189,14.8098],"type":"Point"}
}