{
  "type": "Feature",
  "properties": {
    "gn:admin1_code":"7.0",
    "gn:asciiname":"Asounkou",
    "gn:country_code":"NE",
    "gn:dem":444,
    "gn:feature_class":"P",
    "gn:feature_code":"PPL",
    "gn:name":"Asounkou",
    "gn:population":0,
    "gn:timezone":"Africa/Niamey",
    "iso:country":"NE",
    "wof:name":"Asounkou",
    "wof:placetype":"locality"
},
  "geometry": {"coordinates":[9.0887,13.891],"type":"Point"}
}