{
  "type": "Feature",
  "properties": {
    "gn:admin1_code":"6.0",
    "gn:asciiname":"Oubouroubak",
    "gn:country_code":"NE",
    "gn:dem":358,
    "gn:feature_class":"P",
    "gn:feature_code":"PPL",
    "gn:name":"Oubouroubak",
    "gn:population":0,
    "gn:timezone":"Africa/Niamey",
    "iso:country":"NE",
    "wof:name":"Oubouroubak",
    "wof:placetype":"locality"
},
  "geometry": {"coordinates":[6.27311,14.46319],"type":"Point"}
}