{
  "type": "Feature",
  "properties": {
    "gn:admin1_code":"4.0",
    "gn:asciiname":"Guidan Lehida",
    "gn:country_code":"NE",
    "gn:dem":391,
    "gn:feature_class":"P",
    "gn:feature_code":"PPL",
    "gn:name":"Guidan L\u00e9hida",
    "gn:population":0,
    "gn:timezone":"Africa/Niamey",
    "iso:country":"NE",
    "wof:name":"Guidan Lehida",
    "wof:placetype":"locality"
},
  "geometry": {"coordinates":[7.44548,13.88184],"type":"Point"}
}