{
  "type": "Feature",
  "properties": {
    "gn:admin1_code":"7.0",
    "gn:asciiname":"Ouaouiram",
    "gn:country_code":"NE",
    "gn:dem":488,
    "gn:feature_class":"P",
    "gn:feature_code":"PPL",
    "gn:name":"Ouaouiram",
    "gn:population":0,
    "gn:timezone":"Africa/Niamey",
    "iso:country":"NE",
    "wof:name":"Ouaouiram",
    "wof:placetype":"locality"
},
  "geometry": {"coordinates":[9.3568,14.4686],"type":"Point"}
}