{
  "type": "Feature",
  "properties": {
    "gn:admin1_code":"7.0",
    "gn:asciiname":"Bourourou",
    "gn:country_code":"NE",
    "gn:dem":565,
    "gn:feature_class":"P",
    "gn:feature_code":"PPL",
    "gn:name":"Bourourou",
    "gn:population":0,
    "gn:timezone":"Africa/Niamey",
    "iso:country":"NE",
    "wof:name":"Bourourou",
    "wof:placetype":"locality"
},
  "geometry": {"coordinates":[10.041,14.5047],"type":"Point"}
}