{
  "type": "Feature",
  "properties": {
    "gn:admin1_code":"3.0",
    "gn:asciiname":"Mamadou-Koara",
    "gn:country_code":"NE",
    "gn:dem":242,
    "gn:feature_class":"P",
    "gn:feature_code":"PPL",
    "gn:name":"Mamadou-Koara",
    "gn:population":0,
    "gn:timezone":"Africa/Niamey",
    "iso:country":"NE",
    "name:und_x_variant":[
        "Mamadou Kwara",
        "Mamadou-Koara"
    ],
    "wof:name":"Mamadou-Koara",
    "wof:placetype":"locality"
},
  "geometry": {"coordinates":[3.5235,13.0988],"type":"Point"}
}