{
  "type": "Feature",
  "properties": {
    "gn:admin1_code":"4.0",
    "gn:asciiname":"Guidan Dao",
    "gn:country_code":"NE",
    "gn:dem":384,
    "gn:feature_class":"P",
    "gn:feature_code":"PPL",
    "gn:name":"Guidan Dao",
    "gn:population":0,
    "gn:timezone":"Africa/Niamey",
    "iso:country":"NE",
    "name:und_x_variant":[
        "Gidan Dao",
        "Guidan Dao"
    ],
    "wof:name":"Guidan Dao",
    "wof:placetype":"locality"
},
  "geometry": {"coordinates":[7.33982,13.85202],"type":"Point"}
}