{
  "type": "Feature",
  "properties": {
    "gn:admin1_code":"9.0",
    "gn:asciiname":"Tiloa",
    "gn:country_code":"NE",
    "gn:dem":254,
    "gn:feature_class":"P",
    "gn:feature_code":"PPL",
    "gn:name":"Tiloa",
    "gn:population":0,
    "gn:timezone":"Africa/Niamey",
    "iso:country":"NE",
    "wof:name":"Tiloa",
    "wof:placetype":"locality"
},
  "geometry": {"coordinates":[2.12366,14.4918],"type":"Point"}
}