{
  "type": "Feature",
  "properties": {
    "gn:admin1_code":"3.0",
    "gn:asciiname":"Tondigame-Issa",
    "gn:country_code":"NE",
    "gn:dem":220,
    "gn:feature_class":"P",
    "gn:feature_code":"PPL",
    "gn:name":"Tondigame-Issa",
    "gn:population":0,
    "gn:timezone":"Africa/Niamey",
    "iso:country":"NE",
    "name:und_x_variant":[
        "Tondigam",
        "Tondigam Issa Koara",
        "Tondigame-Issa"
    ],
    "wof:name":"Tondigame-Issa",
    "wof:placetype":"locality"
},
  "geometry": {"coordinates":[3.618,13.1433],"type":"Point"}
}