{
  "type": "Feature",
  "properties": {
    "gn:admin1_code":"7.0",
    "gn:asciiname":"Barmari",
    "gn:country_code":"NE",
    "gn:dem":406,
    "gn:feature_class":"P",
    "gn:feature_code":"PPL",
    "gn:name":"Barmari",
    "gn:population":0,
    "gn:timezone":"Africa/Niamey",
    "iso:country":"NE",
    "wof:name":"Barmari",
    "wof:placetype":"locality"
},
  "geometry": {"coordinates":[9.6573,13.6569],"type":"Point"}
}