{
  "type": "Feature",
  "properties": {
    "gn:admin1_code":"6.0",
    "gn:asciiname":"Yegalalan",
    "gn:country_code":"NE",
    "gn:dem":445,
    "gn:feature_class":"P",
    "gn:feature_code":"PPL",
    "gn:name":"Y\u00e9galalan",
    "gn:population":0,
    "gn:timezone":"Africa/Niamey",
    "iso:country":"NE",
    "name:und_x_variant":[
        "Y\u00e9galalane",
        "Y\u00e9galalan"
    ],
    "wof:name":"Yegalalan",
    "wof:placetype":"locality"
},
  "geometry": {"coordinates":[6.09328,14.53954],"type":"Point"}
}