{
  "type": "Feature",
  "properties": {
    "gn:admin1_code":"4.0",
    "gn:asciiname":"Yerima Wa",
    "gn:country_code":"NE",
    "gn:dem":418,
    "gn:feature_class":"P",
    "gn:feature_code":"PPL",
    "gn:name":"Y\u00e9rima Wa",
    "gn:population":0,
    "gn:timezone":"Africa/Niamey",
    "iso:country":"NE",
    "wof:name":"Yerima Wa",
    "wof:placetype":"locality"
},
  "geometry": {"coordinates":[8.03578,14.07037],"type":"Point"}
}