{
  "type": "Feature",
  "properties": {
    "gn:admin1_code":"4.0",
    "gn:asciiname":"Zangon Alasan",
    "gn:country_code":"NE",
    "gn:dem":361,
    "gn:feature_class":"P",
    "gn:feature_code":"PPL",
    "gn:name":"Zangon Alasan",
    "gn:population":0,
    "gn:timezone":"Africa/Niamey",
    "iso:country":"NE",
    "wof:name":"Zangon Alasan",
    "wof:placetype":"locality"
},
  "geometry": {"coordinates":[6.73371,14.60866],"type":"Point"}
}