{
  "type": "Feature",
  "properties": {
    "gn:admin1_code":"7.0",
    "gn:asciiname":"Mak'era",
    "gn:country_code":"NE",
    "gn:dem":453,
    "gn:feature_class":"P",
    "gn:feature_code":"PPL",
    "gn:name":"Mak'\u00e9ra",
    "gn:population":0,
    "gn:timezone":"Africa/Niamey",
    "iso:country":"NE",
    "wof:name":"Mak'era",
    "wof:placetype":"locality"
},
  "geometry": {"coordinates":[8.69975,13.65741],"type":"Point"}
}