{
  "type": "Feature",
  "properties": {
    "gn:admin1_code":"7.0",
    "gn:asciiname":"May Hantchi",
    "gn:country_code":"NE",
    "gn:dem":498,
    "gn:feature_class":"P",
    "gn:feature_code":"PPL",
    "gn:name":"May Hantchi",
    "gn:population":0,
    "gn:timezone":"Africa/Niamey",
    "iso:country":"NE",
    "name:und_x_variant":[
        "Bani",
        "May Hantchi"
    ],
    "wof:name":"May Hantchi",
    "wof:placetype":"locality"
},
  "geometry": {"coordinates":[8.89828,13.93921],"type":"Point"}
}