{
  "type": "Feature",
  "properties": {
    "gn:admin1_code":"9.0",
    "gn:asciiname":"Singill",
    "gn:country_code":"NE",
    "gn:dem":278,
    "gn:feature_class":"P",
    "gn:feature_code":"PPL",
    "gn:name":"Singill",
    "gn:population":0,
    "gn:timezone":"Africa/Niamey",
    "iso:country":"NE",
    "wof:name":"Singill",
    "wof:placetype":"locality"
},
  "geometry": {"coordinates":[2.18177,14.71293],"type":"Point"}
}