{
  "type": "Feature",
  "properties": {
    "gn:admin1_code":"9.0",
    "gn:asciiname":"Gari Agi",
    "gn:country_code":"NE",
    "gn:dem":227,
    "gn:feature_class":"P",
    "gn:feature_code":"PPL",
    "gn:name":"Gari Agi",
    "gn:population":0,
    "gn:timezone":"Africa/Niamey",
    "iso:country":"NE",
    "name:und_x_variant":[
        "Gari Agui",
        "Gari Agi"
    ],
    "wof:name":"Gari Agi",
    "wof:placetype":"locality"
},
  "geometry": {"coordinates":[3.3992,14.2439],"type":"Point"}
}