{
  "type": "Feature",
  "properties": {
    "gn:admin1_code":"2.0",
    "gn:asciiname":"Koudougou",
    "gn:country_code":"NE",
    "gn:dem":296,
    "gn:feature_class":"P",
    "gn:feature_code":"PPL",
    "gn:name":"Koudougou",
    "gn:population":0,
    "gn:timezone":"Africa/Niamey",
    "iso:country":"NE",
    "wof:name":"Koudougou",
    "wof:placetype":"locality"
},
  "geometry": {"coordinates":[12.99502,13.53378],"type":"Point"}
}