{
  "type": "Feature",
  "properties": {
    "gn:admin1_code":"7.0",
    "gn:asciiname":"Ajiram",
    "gn:country_code":"NE",
    "gn:dem":511,
    "gn:feature_class":"P",
    "gn:feature_code":"PPL",
    "gn:name":"Ajiram",
    "gn:population":0,
    "gn:timezone":"Africa/Niamey",
    "iso:country":"NE",
    "wof:name":"Ajiram",
    "wof:placetype":"locality"
},
  "geometry": {"coordinates":[10.0686,14.4668],"type":"Point"}
}