{
  "type": "Feature",
  "properties": {
    "gn:admin1_code":"2.0",
    "gn:asciiname":"Isari",
    "gn:country_code":"NE",
    "gn:dem":323,
    "gn:feature_class":"P",
    "gn:feature_code":"PPL",
    "gn:name":"Isari",
    "gn:population":0,
    "gn:timezone":"Africa/Niamey",
    "iso:country":"NE",
    "wof:name":"Isari",
    "wof:placetype":"locality"
},
  "geometry": {"coordinates":[12.2297,13.18149],"type":"Point"}
}