{
  "type": "Feature",
  "properties": {
    "gn:admin1_code":"7.0",
    "gn:asciiname":"Sakari",
    "gn:country_code":"NE",
    "gn:dem":433,
    "gn:feature_class":"P",
    "gn:feature_code":"PPL",
    "gn:name":"Sakari",
    "gn:population":0,
    "gn:timezone":"Africa/Niamey",
    "iso:country":"NE",
    "name:fin_x_preferred":[
        "Sakari"
    ],
    "name:fra_x_preferred":[
        "Sakari"
    ],
    "wof:name":"Sakari",
    "wof:placetype":"locality"
},
  "geometry": {"coordinates":[9.1076,13.8099],"type":"Point"}
}