{
  "type": "Feature",
  "properties": {
    "gn:admin1_code":"3.0",
    "gn:asciiname":"Gomande-Koara",
    "gn:country_code":"NE",
    "gn:dem":224,
    "gn:feature_class":"P",
    "gn:feature_code":"PPL",
    "gn:name":"Gomande-Koara",
    "gn:population":0,
    "gn:timezone":"Africa/Niamey",
    "iso:country":"NE",
    "name:und_x_variant":[
        "Gomande Kwara",
        "Gomande-Koara"
    ],
    "wof:name":"Gomande-Koara",
    "wof:placetype":"locality"
},
  "geometry": {"coordinates":[3.674,13.1261],"type":"Point"}
}