{
  "type": "Feature",
  "properties": {
    "gn:admin1_code":"3.0",
    "gn:asciiname":"Sabon Birni",
    "gn:country_code":"NE",
    "gn:dem":180,
    "gn:feature_class":"P",
    "gn:feature_code":"PPL",
    "gn:name":"Sabon Birni",
    "gn:population":0,
    "gn:timezone":"Africa/Niamey",
    "iso:country":"NE",
    "name:und_x_variant":[
        "Sabunbirni",
        "Sabon Birni"
    ],
    "wof:name":"Sabon Birni",
    "wof:placetype":"locality"
},
  "geometry": {"coordinates":[3.59187,11.88785],"type":"Point"}
}