{
  "type": "Feature",
  "properties": {
    "gn:admin1_code":"3.0",
    "gn:asciiname":"Sabon Birni",
    "gn:country_code":"NE",
    "gn:dem":180,
    "gn:feature_class":"P",
    "gn:feature_code":"PPL",
    "gn:name":"Sabon Birni",
    "gn:population":0,
    "gn:timezone":"Africa/Niamey",
    "iso:country":"NE",
    "name:fra_x_preferred":[
        "Sabon Birni"
    ],
    "name:hau_x_preferred":[
        "Sabon Birni"
    ],
    "name:ita_x_preferred":[
        "Sabon Birni"
    ],
    "name:spa_x_preferred":[
        "Sabon Birni"
    ],
    "name:und_x_variant":[
        "Sabunbirni"
    ],
    "name:urd_x_preferred":[
        "\u0633\u0628\u0648\u06ba \u0628\u0631\u0646\u06cc"
    ],
    "name:yor_x_preferred":[
        "Agb\u00e8gb\u00e8 \u00ccj\u1ecdba \u00ccb\u00edl\u1eb9\u0300 Sabon-Birni"
    ],
    "wof:name":"Sabon Birni",
    "wof:placetype":"locality"
},
  "geometry": {"coordinates":[3.59187,11.88785],"type":"Point"}
}