{
  "type": "Feature",
  "properties": {
    "gn:admin1_code":"3.0",
    "gn:asciiname":"Doumega",
    "gn:country_code":"NE",
    "gn:dem":218,
    "gn:feature_class":"P",
    "gn:feature_code":"PPL",
    "gn:name":"Doum\u00e9ga",
    "gn:population":0,
    "gn:timezone":"Africa/Niamey",
    "iso:country":"NE",
    "name:ceb_x_preferred":[
        "Doum\u00e9ga"
    ],
    "name:deu_x_preferred":[
        "Doum\u00e9ga"
    ],
    "name:ita_x_preferred":[
        "Doumega"
    ],
    "name:msa_x_preferred":[
        "Doumega"
    ],
    "name:ron_x_preferred":[
        "Doumega"
    ],
    "name:und_x_variant":[
        "Dumega"
    ],
    "wof:name":"Doumega",
    "wof:placetype":"locality"
},
  "geometry": {"coordinates":[3.97894,12.96976],"type":"Point"}
}