{
  "type": "Feature",
  "properties": {
    "gn:admin1_code":"7.0",
    "gn:asciiname":"Madousa",
    "gn:country_code":"NE",
    "gn:dem":477,
    "gn:feature_class":"P",
    "gn:feature_code":"PPL",
    "gn:name":"Madousa",
    "gn:population":0,
    "gn:timezone":"Africa/Niamey",
    "iso:country":"NE",
    "name:und_x_variant":[
        "Madoussa",
        "Madousa"
    ],
    "wof:name":"Madousa",
    "wof:placetype":"locality"
},
  "geometry": {"coordinates":[8.9649,14.3831],"type":"Point"}
}