{
  "type": "Feature",
  "properties": {
    "gn:admin1_code":"2.0",
    "gn:asciiname":"Bedouaram",
    "gn:country_code":"NE",
    "gn:dem":323,
    "gn:feature_class":"P",
    "gn:feature_code":"PPL",
    "gn:name":"Bedouaram",
    "gn:population":0,
    "gn:timezone":"Africa/Niamey",
    "iso:country":"NE",
    "name:und_x_variant":[
        "Sedouaram",
        "B\u00e9duaram",
        "Bedouaram"
    ],
    "wof:name":"Bedouaram",
    "wof:placetype":"locality"
},
  "geometry": {"coordinates":[13.14843,15.74326],"type":"Point"}
}