{
  "type": "Feature",
  "properties": {
    "gn:admin1_code":"8.0",
    "gn:asciiname":"Bitinkodji",
    "gn:country_code":"NE",
    "gn:dem":193,
    "gn:feature_class":"P",
    "gn:feature_code":"PPL",
    "gn:name":"Bitinkodji",
    "gn:population":0,
    "gn:timezone":"Africa/Niamey",
    "iso:country":"NE",
    "name:deu_x_preferred":[
        "Bitinkodji"
    ],
    "name:ita_x_preferred":[
        "Bitinkodji"
    ],
    "name:msa_x_preferred":[
        "Bitinkodji"
    ],
    "name:ron_x_preferred":[
        "Bitinkodji"
    ],
    "name:spa_x_preferred":[
        "Bitinkodji"
    ],
    "wof:name":"Bitinkodji",
    "wof:placetype":"locality"
},
  "geometry": {"coordinates":[1.95944,13.58389],"type":"Point"}
}