{
  "type": "Feature",
  "properties": {
    "gn:admin1_code":"7.0",
    "gn:asciiname":"Dara",
    "gn:country_code":"NE",
    "gn:dem":457,
    "gn:feature_class":"P",
    "gn:feature_code":"PPL",
    "gn:name":"Dara",
    "gn:population":0,
    "gn:timezone":"Africa/Niamey",
    "iso:country":"NE",
    "name:ces_x_preferred":[
        "Dara"
    ],
    "name:isl_x_preferred":[
        "Dara"
    ],
    "name:slv_x_preferred":[
        "Dara"
    ],
    "name:srp_x_preferred":[
        "\u0414\u0430\u0440\u0430"
    ],
    "wof:name":"Dara",
    "wof:placetype":"locality"
},
  "geometry": {"coordinates":[8.7261,14.2453],"type":"Point"}
}