{
  "type": "Feature",
  "properties": {
    "gn:admin1_code":"1.0",
    "gn:asciiname":"Arrigui",
    "gn:country_code":"NE",
    "gn:dem":385,
    "gn:feature_class":"P",
    "gn:feature_code":"PPL",
    "gn:name":"Arrigui",
    "gn:population":0,
    "gn:timezone":"Africa/Niamey",
    "iso:country":"NE",
    "name:fra_x_preferred":[
        "Arrigui"
    ],
    "wof:name":"Arrigui",
    "wof:placetype":"locality"
},
  "geometry": {"coordinates":[12.91787,19.0763],"type":"Point"}
}