{
  "type": "Feature",
  "properties": {
    "gn:admin1_code":"3.0",
    "gn:asciiname":"Landari",
    "gn:country_code":"NE",
    "gn:dem":214,
    "gn:feature_class":"P",
    "gn:feature_code":"PPL",
    "gn:name":"Landari",
    "gn:population":0,
    "gn:timezone":"Africa/Niamey",
    "iso:country":"NE",
    "wof:name":"Landari",
    "wof:placetype":"locality"
},
  "geometry": {"coordinates":[3.79752,12.85236],"type":"Point"}
}