{
  "type": "Feature",
  "properties": {
    "gn:admin1_code":"7.0",
    "gn:asciiname":"Boulama",
    "gn:country_code":"NE",
    "gn:dem":522,
    "gn:feature_class":"P",
    "gn:feature_code":"PPL",
    "gn:name":"Boulama",
    "gn:population":0,
    "gn:timezone":"Africa/Niamey",
    "iso:country":"NE",
    "wof:name":"Boulama",
    "wof:placetype":"locality"
},
  "geometry": {"coordinates":[10.3102,14.4066],"type":"Point"}
}