{
  "type": "Feature",
  "properties": {
    "gn:admin1_code":"3.0",
    "gn:asciiname":"Bana",
    "gn:country_code":"NE",
    "gn:dem":181,
    "gn:feature_class":"P",
    "gn:feature_code":"PPL",
    "gn:name":"Bana",
    "gn:population":0,
    "gn:timezone":"Africa/Niamey",
    "iso:country":"NE",
    "name:ceb_x_preferred":[
        "Bana"
    ],
    "name:deu_x_preferred":[
        "Bana"
    ],
    "name:ita_x_preferred":[
        "Bana"
    ],
    "name:msa_x_preferred":[
        "Bana"
    ],
    "name:ron_x_preferred":[
        "Bana"
    ],
    "name:spa_x_preferred":[
        "Bana"
    ],
    "name:und_x_variant":[
        "Baha",
        "Bana"
    ],
    "wof:name":"Bana",
    "wof:placetype":"locality"
},
  "geometry": {"coordinates":[3.55235,12.05187],"type":"Point"}
}