{
  "type": "Feature",
  "properties": {
    "gn:admin1_code":"7.0",
    "gn:asciiname":"Kafouhou",
    "gn:country_code":"NE",
    "gn:dem":382,
    "gn:feature_class":"P",
    "gn:feature_code":"PPL",
    "gn:name":"Kafouhou",
    "gn:population":0,
    "gn:timezone":"Africa/Niamey",
    "iso:country":"NE",
    "wof:name":"Kafouhou",
    "wof:placetype":"locality"
},
  "geometry": {"coordinates":[9.3642,13.1847],"type":"Point"}
}