{
  "type": "Feature",
  "properties": {
    "gn:admin1_code":"2.0",
    "gn:asciiname":"Karagou",
    "gn:country_code":"NE",
    "gn:dem":350,
    "gn:feature_class":"P",
    "gn:feature_code":"PPL",
    "gn:name":"Karagou",
    "gn:population":0,
    "gn:timezone":"Africa/Niamey",
    "iso:country":"NE",
    "name:und_x_variant":[
        "Karagu",
        "Karagoua",
        "Karamgaoua",
        "Karagou"
    ],
    "wof:name":"Karagou",
    "wof:placetype":"locality"
},
  "geometry": {"coordinates":[10.97992,13.51237],"type":"Point"}
}