{
  "type": "Feature",
  "properties": {
    "gn:admin1_code":"7.0",
    "gn:asciiname":"Bangaya",
    "gn:country_code":"NE",
    "gn:dem":383,
    "gn:feature_class":"P",
    "gn:feature_code":"PPL",
    "gn:name":"Bangaya",
    "gn:population":0,
    "gn:timezone":"Africa/Niamey",
    "iso:country":"NE",
    "name:und_x_variant":[
        "Bangaia",
        "Bangaya"
    ],
    "wof:name":"Bangaya",
    "wof:placetype":"locality"
},
  "geometry": {"coordinates":[9.06442,12.96198],"type":"Point"}
}