{
  "type": "Feature",
  "properties": {
    "gn:admin1_code":"3.0",
    "gn:asciiname":"Koussa-Koara",
    "gn:country_code":"NE",
    "gn:dem":225,
    "gn:feature_class":"P",
    "gn:feature_code":"PPL",
    "gn:name":"Koussa-Koara",
    "gn:population":0,
    "gn:timezone":"Africa/Niamey",
    "iso:country":"NE",
    "name:und_x_variant":[
        "Koussa Kwara",
        "Koussa-Koara"
    ],
    "wof:name":"Koussa-Koara",
    "wof:placetype":"locality"
},
  "geometry": {"coordinates":[3.5577,13.3615],"type":"Point"}
}