{
  "type": "Feature",
  "properties": {
    "gn:admin1_code":"4.0",
    "gn:asciiname":"Garin Malam",
    "gn:country_code":"NE",
    "gn:dem":366,
    "gn:feature_class":"P",
    "gn:feature_code":"PPL",
    "gn:name":"Garin M\u00e2lam",
    "gn:population":0,
    "gn:timezone":"Africa/Niamey",
    "iso:country":"NE",
    "wof:name":"Garin Malam",
    "wof:placetype":"locality"
},
  "geometry": {"coordinates":[7.11632,13.35073],"type":"Point"}
}