{
  "type": "Feature",
  "properties": {
    "gn:admin1_code":"9.0",
    "gn:asciiname":"Gountiena",
    "gn:country_code":"NE",
    "gn:dem":250,
    "gn:feature_class":"P",
    "gn:feature_code":"PPL",
    "gn:name":"Gounti\u00e9na",
    "gn:population":0,
    "gn:timezone":"Africa/Niamey",
    "iso:country":"NE",
    "wof:name":"Gountiena",
    "wof:placetype":"locality"
},
  "geometry": {"coordinates":[0.29704,14.69576],"type":"Point"}
}