{
  "type": "Feature",
  "properties": {
    "gn:admin1_code":"6.0",
    "gn:asciiname":"Gidan Hami",
    "gn:country_code":"NE",
    "gn:dem":399,
    "gn:feature_class":"P",
    "gn:feature_code":"PPL",
    "gn:name":"Gidan Hami",
    "gn:population":0,
    "gn:timezone":"Africa/Niamey",
    "iso:country":"NE",
    "wof:name":"Gidan Hami",
    "wof:placetype":"locality"
},
  "geometry": {"coordinates":[5.8574,14.1622],"type":"Point"}
}