{
  "type": "Feature",
  "properties": {
    "gn:admin1_code":"6.0",
    "gn:asciiname":"Tesak",
    "gn:country_code":"NE",
    "gn:dem":440,
    "gn:feature_class":"P",
    "gn:feature_code":"PPL",
    "gn:name":"T\u00e9sak",
    "gn:population":0,
    "gn:timezone":"Africa/Niamey",
    "iso:country":"NE",
    "name:und_x_variant":[
        "Tessak",
        "T\u00e9sak"
    ],
    "wof:name":"Tesak",
    "wof:placetype":"locality"
},
  "geometry": {"coordinates":[6.25092,14.76313],"type":"Point"}
}