{
  "type": "Feature",
  "properties": {
    "gn:admin1_code":"7.0",
    "gn:asciiname":"Garin el Hadji",
    "gn:country_code":"NE",
    "gn:dem":354,
    "gn:feature_class":"P",
    "gn:feature_code":"PPL",
    "gn:name":"Garin el Hadji",
    "gn:population":0,
    "gn:timezone":"Africa/Niamey",
    "iso:country":"NE",
    "wof:name":"Garin el Hadji",
    "wof:placetype":"locality"
},
  "geometry": {"coordinates":[10.70291,13.63519],"type":"Point"}
}