{
  "type": "Feature",
  "properties": {
    "gn:admin1_code":"4.0",
    "gn:asciiname":"Batcha",
    "gn:country_code":"NE",
    "gn:dem":459,
    "gn:feature_class":"P",
    "gn:feature_code":"PPL",
    "gn:name":"Batcha",
    "gn:population":0,
    "gn:timezone":"Africa/Niamey",
    "iso:country":"NE",
    "wof:name":"Batcha",
    "wof:placetype":"locality"
},
  "geometry": {"coordinates":[8.32708,13.28682],"type":"Point"}
}