{
  "type": "Feature",
  "properties": {
    "gn:admin1_code":"7.0",
    "gn:asciiname":"Maysararaka",
    "gn:country_code":"NE",
    "gn:dem":452,
    "gn:feature_class":"P",
    "gn:feature_code":"PPL",
    "gn:name":"Maysararaka",
    "gn:population":0,
    "gn:timezone":"Africa/Niamey",
    "iso:country":"NE",
    "wof:name":"Maysararaka",
    "wof:placetype":"locality"
},
  "geometry": {"coordinates":[8.316,14.627],"type":"Point"}
}