{
  "type": "Feature",
  "properties": {
    "gn:admin1_code":"2.0",
    "gn:asciiname":"Birinia",
    "gn:country_code":"NE",
    "gn:dem":350,
    "gn:feature_class":"P",
    "gn:feature_code":"PPL",
    "gn:name":"Birinia",
    "gn:population":0,
    "gn:timezone":"Africa/Niamey",
    "iso:country":"NE",
    "wof:name":"Birinia",
    "wof:placetype":"locality"
},
  "geometry": {"coordinates":[11.2806,13.8736],"type":"Point"}
}