{
  "type": "Feature",
  "properties": {
    "gn:admin1_code":"4.0",
    "gn:asciiname":"Nahala",
    "gn:country_code":"NE",
    "gn:dem":392,
    "gn:feature_class":"P",
    "gn:feature_code":"PPL",
    "gn:name":"Nahala",
    "gn:population":0,
    "gn:timezone":"Africa/Niamey",
    "iso:country":"NE",
    "name:und_x_variant":[
        "Nahalla",
        "Nahala"
    ],
    "wof:name":"Nahala",
    "wof:placetype":"locality"
},
  "geometry": {"coordinates":[6.91735,14.66404],"type":"Point"}
}