{
  "type": "Feature",
  "properties": {
    "gn:admin1_code":"3.0",
    "gn:asciiname":"Kobo Dey",
    "gn:country_code":"NE",
    "gn:dem":230,
    "gn:feature_class":"P",
    "gn:feature_code":"PPL",
    "gn:name":"Kobo Dey",
    "gn:population":0,
    "gn:timezone":"Africa/Niamey",
    "iso:country":"NE",
    "name:und_x_variant":[
        "Kobeday",
        "Kobedey",
        "Kobod\u00e9",
        "Kobo Dey"
    ],
    "wof:name":"Kobo Dey",
    "wof:placetype":"locality"
},
  "geometry": {"coordinates":[2.5253,13.1638],"type":"Point"}
}