{
  "type": "Feature",
  "properties": {
    "gn:admin1_code":"7.0",
    "gn:asciiname":"Kalgotirani",
    "gn:country_code":"NE",
    "gn:dem":397,
    "gn:feature_class":"P",
    "gn:feature_code":"PPL",
    "gn:name":"Kalgotirani",
    "gn:population":0,
    "gn:timezone":"Africa/Niamey",
    "iso:country":"NE",
    "wof:name":"Kalgotirani",
    "wof:placetype":"locality"
},
  "geometry": {"coordinates":[9.0597,13.3963],"type":"Point"}
}