{
  "type": "Feature",
  "properties": {
    "gn:admin1_code":"1.0",
    "gn:asciiname":"Sogha",
    "gn:country_code":"NE",
    "gn:dem":845,
    "gn:feature_class":"P",
    "gn:feature_code":"PPL",
    "gn:name":"Sogha",
    "gn:population":0,
    "gn:timezone":"Africa/Niamey",
    "iso:country":"NE",
    "wof:name":"Sogha",
    "wof:placetype":"locality"
},
  "geometry": {"coordinates":[8.9353,17.5748],"type":"Point"}
}