{
  "type": "Feature",
  "properties": {
    "gn:admin1_code":"7.0",
    "gn:asciiname":"Dango",
    "gn:country_code":"NE",
    "gn:dem":410,
    "gn:feature_class":"P",
    "gn:feature_code":"PPL",
    "gn:name":"Dango",
    "gn:population":0,
    "gn:timezone":"Africa/Niamey",
    "iso:country":"NE",
    "name:und_x_variant":[
        "Dan Mayaki",
        "Dango"
    ],
    "wof:name":"Dango",
    "wof:placetype":"locality"
},
  "geometry": {"coordinates":[8.9601,13.18496],"type":"Point"}
}