{
  "type": "Feature",
  "properties": {
    "gn:admin1_code":"7.0",
    "gn:asciiname":"Dango",
    "gn:country_code":"NE",
    "gn:dem":410,
    "gn:feature_class":"P",
    "gn:feature_code":"PPL",
    "gn:name":"Dango",
    "gn:population":0,
    "gn:timezone":"Africa/Niamey",
    "iso:country":"NE",
    "name:ara_x_preferred":[
        "\u062f\u0627\u0646\u063a\u0648"
    ],
    "name:cat_x_preferred":[
        "Dango"
    ],
    "name:dan_x_preferred":[
        "Dango"
    ],
    "name:deu_x_preferred":[
        "Dango"
    ],
    "name:epo_x_preferred":[
        "Dango"
    ],
    "name:fas_x_preferred":[
        "\u062f\u0627\u0646\u06af\u0648"
    ],
    "name:fin_x_preferred":[
        "Dango"
    ],
    "name:fra_x_preferred":[
        "Dango"
    ],
    "name:gla_x_preferred":[
        "Dango"
    ],
    "name:heb_x_preferred":[
        "\u05d3\u05e0\u05d2\u05d5"
    ],
    "name:ind_x_preferred":[
        "Dango"
    ],
    "name:ita_x_preferred":[
        "Dango"
    ],
    "name:jav_x_preferred":[
        "Dango"
    ],
    "name:msa_x_preferred":[
        "Dango"
    ],
    "name:nld_x_preferred":[
        "Dango"
    ],
    "name:pol_x_preferred":[
        "Dango"
    ],
    "name:por_x_preferred":[
        "Dango"
    ],
    "name:rus_x_preferred":[
        "\u0414\u0430\u043d\u0433\u043e"
    ],
    "name:spa_x_preferred":[
        "Dango"
    ],
    "name:swe_x_preferred":[
        "Dango"
    ],
    "name:tur_x_preferred":[
        "Dango"
    ],
    "name:ukr_x_preferred":[
        "\u0414\u0430\u043d\u0491\u043e"
    ],
    "name:und_x_variant":[
        "Dan Mayaki",
        "Dango"
    ],
    "name:vie_x_preferred":[
        "Dango"
    ],
    "name:zho_x_preferred":[
        "\u7cf0\u5b50"
    ],
    "wof:name":"Dango",
    "wof:placetype":"locality"
},
  "geometry": {"coordinates":[8.9601,13.18496],"type":"Point"}
}