{
  "type": "Feature",
  "properties": {
    "gn:admin1_code":"3.0",
    "gn:asciiname":"Gari-Ndombokaka",
    "gn:country_code":"NE",
    "gn:dem":256,
    "gn:feature_class":"P",
    "gn:feature_code":"PPL",
    "gn:name":"Gari-Ndombokaka",
    "gn:population":0,
    "gn:timezone":"Africa/Niamey",
    "iso:country":"NE",
    "wof:name":"Gari-Ndombokaka",
    "wof:placetype":"locality"
},
  "geometry": {"coordinates":[3.9609,13.4897],"type":"Point"}
}