{
  "type": "Feature",
  "properties": {
    "gn:admin1_code":"2.0",
    "gn:asciiname":"Mandawa",
    "gn:country_code":"NE",
    "gn:dem":339,
    "gn:feature_class":"P",
    "gn:feature_code":"PPL",
    "gn:name":"Mandawa",
    "gn:population":0,
    "gn:timezone":"Africa/Niamey",
    "iso:country":"NE",
    "name:ben_x_preferred":[
        "\u09ae\u09be\u09a8\u09cd\u09a6\u09be\u0993\u09af\u09bc\u09be"
    ],
    "name:bpy_x_preferred":[
        "\u09ae\u09be\u09a8\u09cd\u09a6\u09be\u09f1\u09be"
    ],
    "name:cat_x_preferred":[
        "Mandawa"
    ],
    "name:ceb_x_preferred":[
        "Mand\u0101wa"
    ],
    "name:deu_x_preferred":[
        "Mandawa"
    ],
    "name:fra_x_preferred":[
        "Mandawa"
    ],
    "name:hif_x_preferred":[
        "Mandawa"
    ],
    "name:hin_x_preferred":[
        "\u092e\u0902\u0921\u093e\u0935\u093e"
    ],
    "name:ita_x_preferred":[
        "Mandawa"
    ],
    "name:mlg_x_preferred":[
        "Mandawa"
    ],
    "name:msa_x_preferred":[
        "Mandawa"
    ],
    "name:new_x_preferred":[
        "\u092e\u0928\u094d\u0926\u0935\u093e"
    ],
    "name:ori_x_preferred":[
        "\u0b2e\u0b3e\u0b28\u0b4d\u0b26\u0b3e\u0b71\u0b3e"
    ],
    "name:rus_x_preferred":[
        "\u041c\u0430\u043d\u0434\u0430\u0432\u0430"
    ],
    "name:swe_x_preferred":[
        "Mand\u0101wa"
    ],
    "name:urd_x_preferred":[
        "\u0645\u0646\u0688\u0627\u0648\u0627"
    ],
    "name:vie_x_preferred":[
        "Mandawa"
    ],
    "name:xmf_x_preferred":[
        "\u10db\u10d0\u10dc\u10d3\u10d0\u10d5\u10d0"
    ],
    "name:zho_x_preferred":[
        "\u66fc\u8fbe\u74e6"
    ],
    "wof:name":"Mandawa",
    "wof:placetype":"locality"
},
  "geometry": {"coordinates":[11.6906,13.7153],"type":"Point"}
}