{
  "type": "Feature",
  "properties": {
    "gn:admin1_code":"2.0",
    "gn:asciiname":"Mandawa",
    "gn:country_code":"NE",
    "gn:dem":339,
    "gn:feature_class":"P",
    "gn:feature_code":"PPL",
    "gn:name":"Mandawa",
    "gn:population":0,
    "gn:timezone":"Africa/Niamey",
    "iso:country":"NE",
    "wof:name":"Mandawa",
    "wof:placetype":"locality"
},
  "geometry": {"coordinates":[11.6906,13.7153],"type":"Point"}
}