{
  "type": "Feature",
  "properties": {
    "gn:admin1_code":"4.0",
    "gn:asciiname":"Konkorey",
    "gn:country_code":"NE",
    "gn:dem":411,
    "gn:feature_class":"P",
    "gn:feature_code":"PPL",
    "gn:name":"Konkorey",
    "gn:population":0,
    "gn:timezone":"Africa/Niamey",
    "iso:country":"NE",
    "name:und_x_variant":[
        "Konkoza",
        "Konkorey"
    ],
    "wof:name":"Konkorey",
    "wof:placetype":"locality"
},
  "geometry": {"coordinates":[7.29181,13.63097],"type":"Point"}
}