{
  "type": "Feature",
  "properties": {
    "gn:admin1_code":"7.0",
    "gn:asciiname":"Dan Kwantaro",
    "gn:country_code":"NE",
    "gn:dem":443,
    "gn:feature_class":"P",
    "gn:feature_code":"PPL",
    "gn:name":"Dan Kwantaro",
    "gn:population":0,
    "gn:timezone":"Africa/Niamey",
    "iso:country":"NE",
    "wof:name":"Dan Kwantaro",
    "wof:placetype":"locality"
},
  "geometry": {"coordinates":[7.83934,14.42871],"type":"Point"}
}