{
  "type": "Feature",
  "properties": {
    "gn:admin1_code":"6.0",
    "gn:asciiname":"Fararat Karama",
    "gn:country_code":"NE",
    "gn:dem":429,
    "gn:feature_class":"P",
    "gn:feature_code":"PPL",
    "gn:name":"Fararat Karama",
    "gn:population":0,
    "gn:timezone":"Africa/Niamey",
    "iso:country":"NE",
    "wof:name":"Fararat Karama",
    "wof:placetype":"locality"
},
  "geometry": {"coordinates":[6.00774,14.68323],"type":"Point"}
}