{
  "type": "Feature",
  "properties": {
    "gn:admin1_code":"6.0",
    "gn:asciiname":"Chadeke",
    "gn:country_code":"NE",
    "gn:dem":273,
    "gn:feature_class":"P",
    "gn:feature_code":"PPL",
    "gn:name":"Chad\u00e9k\u00e9",
    "gn:population":0,
    "gn:timezone":"Africa/Niamey",
    "iso:country":"NE",
    "wof:name":"Chadeke",
    "wof:placetype":"locality"
},
  "geometry": {"coordinates":[4.48009,14.05154],"type":"Point"}
}