{
  "type": "Feature",
  "properties": {
    "gn:admin1_code":"4.0",
    "gn:asciiname":"Kalgo",
    "gn:country_code":"NE",
    "gn:dem":416,
    "gn:feature_class":"P",
    "gn:feature_code":"PPL",
    "gn:name":"Kalg\u00f4",
    "gn:population":0,
    "gn:timezone":"Africa/Niamey",
    "iso:country":"NE",
    "wof:name":"Kalgo",
    "wof:placetype":"locality"
},
  "geometry": {"coordinates":[8.0088,13.64015],"type":"Point"}
}