{
  "type": "Feature",
  "properties": {
    "gn:admin1_code":"3.0",
    "gn:asciiname":"Kambadeye",
    "gn:country_code":"NE",
    "gn:dem":243,
    "gn:feature_class":"P",
    "gn:feature_code":"PPL",
    "gn:name":"Kambadeye",
    "gn:population":0,
    "gn:timezone":"Africa/Niamey",
    "iso:country":"NE",
    "name:und_x_variant":[
        "Kambadey",
        "Kambadeye"
    ],
    "wof:name":"Kambadeye",
    "wof:placetype":"locality"
},
  "geometry": {"coordinates":[3.3182,13.5676],"type":"Point"}
}