{
  "type": "Feature",
  "properties": {
    "gn:admin1_code":"4.0",
    "gn:asciiname":"Tagaza Dan Keraou",
    "gn:country_code":"NE",
    "gn:dem":398,
    "gn:feature_class":"P",
    "gn:feature_code":"PPL",
    "gn:name":"Tagaza Dan K\u00e9raou",
    "gn:population":0,
    "gn:timezone":"Africa/Niamey",
    "iso:country":"NE",
    "name:und_x_variant":[
        "Tagaza Dan Kl\u00e9ro",
        "Dan K\u00e9lo",
        "Tagaza Dan K\u00e9raou"
    ],
    "wof:name":"Tagaza Dan Keraou",
    "wof:placetype":"locality"
},
  "geometry": {"coordinates":[7.29425,13.82553],"type":"Point"}
}