{
  "type": "Feature",
  "properties": {
    "gn:admin1_code":"9.0",
    "gn:asciiname":"Tamalaoulaout",
    "gn:country_code":"NE",
    "gn:dem":261,
    "gn:feature_class":"P",
    "gn:feature_code":"PPL",
    "gn:name":"Tamalaoulaout",
    "gn:population":0,
    "gn:timezone":"Africa/Niamey",
    "iso:country":"NE",
    "wof:name":"Tamalaoulaout",
    "wof:placetype":"locality"
},
  "geometry": {"coordinates":[3.6974,15.1805],"type":"Point"}
}