{
  "type": "Feature",
  "properties": {
    "gn:admin1_code":"6.0",
    "gn:asciiname":"Kosama",
    "gn:country_code":"NE",
    "gn:dem":325,
    "gn:feature_class":"P",
    "gn:feature_code":"PPL",
    "gn:name":"Kosama",
    "gn:population":0,
    "gn:timezone":"Africa/Niamey",
    "iso:country":"NE",
    "wof:name":"Kosama",
    "wof:placetype":"locality"
},
  "geometry": {"coordinates":[5.2027,14.6536],"type":"Point"}
}