{
  "type": "Feature",
  "properties": {
    "gn:admin1_code":"4.0",
    "gn:asciiname":"Dan Garki",
    "gn:country_code":"NE",
    "gn:dem":346,
    "gn:feature_class":"P",
    "gn:feature_code":"PPL",
    "gn:name":"Dan Garki",
    "gn:population":0,
    "gn:timezone":"Africa/Niamey",
    "iso:country":"NE",
    "wof:name":"Dan Garki",
    "wof:placetype":"locality"
},
  "geometry": {"coordinates":[6.85647,13.95052],"type":"Point"}
}