{
  "type": "Feature",
  "properties": {
    "gn:admin1_code":"7.0",
    "gn:asciiname":"Garin Karo",
    "gn:country_code":"NE",
    "gn:dem":490,
    "gn:feature_class":"P",
    "gn:feature_code":"PPL",
    "gn:name":"Garin Karo",
    "gn:population":0,
    "gn:timezone":"Africa/Niamey",
    "iso:country":"NE",
    "wof:name":"Garin Karo",
    "wof:placetype":"locality"
},
  "geometry": {"coordinates":[9.2393,14.3716],"type":"Point"}
}