{
  "type": "Feature",
  "properties": {
    "gn:admin1_code":"9.0",
    "gn:asciiname":"Karma",
    "gn:country_code":"NE",
    "gn:dem":196,
    "gn:feature_class":"P",
    "gn:feature_code":"PPL",
    "gn:name":"Karma",
    "gn:population":0,
    "gn:timezone":"Africa/Niamey",
    "iso:country":"NE",
    "wof:name":"Karma",
    "wof:placetype":"locality"
},
  "geometry": {"coordinates":[1.81247,13.67242],"type":"Point"}
}