{
  "type": "Feature",
  "properties": {
    "gn:admin1_code":"2.0",
    "gn:asciiname":"Moul",
    "gn:country_code":"NE",
    "gn:dem":324,
    "gn:feature_class":"P",
    "gn:feature_code":"PPL",
    "gn:name":"Moul",
    "gn:population":0,
    "gn:timezone":"Africa/Niamey",
    "iso:country":"NE",
    "name:und_x_variant":[
        "Maul",
        "Moull",
        "Maut",
        "Moul"
    ],
    "wof:name":"Moul",
    "wof:placetype":"locality"
},
  "geometry": {"coordinates":[13.29652,15.05528],"type":"Point"}
}