{
  "type": "Feature",
  "properties": {
    "gn:admin1_code":"4.0",
    "gn:asciiname":"Nage Nage",
    "gn:country_code":"NE",
    "gn:dem":395,
    "gn:feature_class":"P",
    "gn:feature_code":"PPL",
    "gn:name":"Nag\u00e9 Nag\u00e9",
    "gn:population":0,
    "gn:timezone":"Africa/Niamey",
    "iso:country":"NE",
    "wof:name":"Nage Nage",
    "wof:placetype":"locality"
},
  "geometry": {"coordinates":[6.56369,14.09596],"type":"Point"}
}