{
  "type": "Feature",
  "properties": {
    "gn:admin1_code":"3.0",
    "gn:asciiname":"Doli",
    "gn:country_code":"NE",
    "gn:dem":203,
    "gn:feature_class":"P",
    "gn:feature_code":"PPL",
    "gn:name":"Doli",
    "gn:population":0,
    "gn:timezone":"Africa/Niamey",
    "iso:country":"NE",
    "name:bos_x_preferred":[
        "Doli"
    ],
    "name:ceb_x_preferred":[
        "Doli"
    ],
    "name:deu_x_preferred":[
        "Doli"
    ],
    "name:fra_x_preferred":[
        "Doli"
    ],
    "name:swe_x_preferred":[
        "Doli"
    ],
    "wof:name":"Doli",
    "wof:placetype":"locality"
},
  "geometry": {"coordinates":[3.64139,12.43173],"type":"Point"}
}