{
  "type": "Feature",
  "properties": {
    "gn:admin1_code":"6.0",
    "gn:asciiname":"Maysabi",
    "gn:country_code":"NE",
    "gn:dem":306,
    "gn:feature_class":"P",
    "gn:feature_code":"PPL",
    "gn:name":"Maysabi",
    "gn:population":0,
    "gn:timezone":"Africa/Niamey",
    "iso:country":"NE",
    "wof:name":"Maysabi",
    "wof:placetype":"locality"
},
  "geometry": {"coordinates":[6.27337,13.80356],"type":"Point"}
}