{
  "type": "Feature",
  "properties": {
    "gn:admin1_code":"7.0",
    "gn:asciiname":"Guidan Illo",
    "gn:country_code":"NE",
    "gn:dem":436,
    "gn:feature_class":"P",
    "gn:feature_code":"PPL",
    "gn:name":"Guidan Illo",
    "gn:population":0,
    "gn:timezone":"Africa/Niamey",
    "iso:country":"NE",
    "wof:name":"Guidan Illo",
    "wof:placetype":"locality"
},
  "geometry": {"coordinates":[7.74262,14.52132],"type":"Point"}
}