{
  "type": "Feature",
  "properties": {
    "gn:admin1_code":"4.0",
    "gn:asciiname":"Guidan Gobje",
    "gn:country_code":"NE",
    "gn:dem":439,
    "gn:feature_class":"P",
    "gn:feature_code":"PPL",
    "gn:name":"Guidan Gobj\u00e9",
    "gn:population":0,
    "gn:timezone":"Africa/Niamey",
    "iso:country":"NE",
    "name:und_x_variant":[
        "Guidan Gabje",
        "Guidan Gobj\u00e9"
    ],
    "wof:name":"Guidan Gobje",
    "wof:placetype":"locality"
},
  "geometry": {"coordinates":[8.13523,14.28836],"type":"Point"}
}