{
  "type": "Feature",
  "properties": {
    "gn:admin1_code":"3.0",
    "gn:asciiname":"Merizan",
    "gn:country_code":"NE",
    "gn:dem":251,
    "gn:feature_class":"P",
    "gn:feature_code":"PPL",
    "gn:name":"M\u00e9rizan",
    "gn:population":0,
    "gn:timezone":"Africa/Niamey",
    "iso:country":"NE",
    "wof:name":"Merizan",
    "wof:placetype":"locality"
},
  "geometry": {"coordinates":[3.6338,13.3597],"type":"Point"}
}