{
  "type": "Feature",
  "properties": {
    "gn:admin1_code":"7.0",
    "gn:asciiname":"Yar Yarni",
    "gn:country_code":"NE",
    "gn:dem":372,
    "gn:feature_class":"P",
    "gn:feature_code":"PPL",
    "gn:name":"Yar Yarni",
    "gn:population":0,
    "gn:timezone":"Africa/Niamey",
    "iso:country":"NE",
    "wof:name":"Yar Yarni",
    "wof:placetype":"locality"
},
  "geometry": {"coordinates":[10.41915,13.76836],"type":"Point"}
}