{
  "type": "Feature",
  "properties": {
    "gn:admin1_code":"9.0",
    "gn:asciiname":"Ghaliletane",
    "gn:country_code":"NE",
    "gn:dem":207,
    "gn:feature_class":"P",
    "gn:feature_code":"PPL",
    "gn:name":"Ghalil\u00e9tane",
    "gn:population":0,
    "gn:timezone":"Africa/Niamey",
    "iso:country":"NE",
    "wof:name":"Ghaliletane",
    "wof:placetype":"locality"
},
  "geometry": {"coordinates":[2.9356,13.7503],"type":"Point"}
}