{
  "type": "Feature",
  "properties": {
    "gn:admin1_code":"9.0",
    "gn:asciiname":"Ti-m-Berkaouane",
    "gn:country_code":"NE",
    "gn:dem":209,
    "gn:feature_class":"P",
    "gn:feature_code":"PPL",
    "gn:name":"Ti-m-Berkaouane",
    "gn:population":0,
    "gn:timezone":"Africa/Niamey",
    "iso:country":"NE",
    "wof:name":"Ti-m-Berkaouane",
    "wof:placetype":"locality"
},
  "geometry": {"coordinates":[2.9348,13.7574],"type":"Point"}
}