{
  "type": "Feature",
  "properties": {
    "gn:admin1_code":"9.0",
    "gn:asciiname":"Danyan",
    "gn:country_code":"NE",
    "gn:dem":269,
    "gn:feature_class":"P",
    "gn:feature_code":"PPL",
    "gn:name":"Danyan",
    "gn:population":0,
    "gn:timezone":"Africa/Niamey",
    "iso:country":"NE",
    "wof:name":"Danyan",
    "wof:placetype":"locality"
},
  "geometry": {"coordinates":[3.0517,14.3795],"type":"Point"}
}