{
  "type": "Feature",
  "properties": {
    "gn:admin1_code":"9.0",
    "gn:asciiname":"Famale",
    "gn:country_code":"NE",
    "gn:dem":217,
    "gn:feature_class":"P",
    "gn:feature_code":"PPL",
    "gn:name":"Famal\u00e9",
    "gn:population":0,
    "gn:timezone":"Africa/Niamey",
    "iso:country":"NE",
    "name:und_x_variant":[
        "Fam\u00e9l\u00e9",
        "Famal\u00e9"
    ],
    "wof:name":"Famale",
    "wof:placetype":"locality"
},
  "geometry": {"coordinates":[1.08239,14.55213],"type":"Point"}
}