{
  "type": "Feature",
  "properties": {
    "gn:admin1_code":"2.0",
    "gn:asciiname":"Maloum-Meleri",
    "gn:country_code":"NE",
    "gn:dem":305,
    "gn:feature_class":"P",
    "gn:feature_code":"PPL",
    "gn:name":"Maloum-M\u00e9leri",
    "gn:population":0,
    "gn:timezone":"Africa/Niamey",
    "iso:country":"NE",
    "wof:name":"Maloum-Meleri",
    "wof:placetype":"locality"
},
  "geometry": {"coordinates":[12.77,13.41245],"type":"Point"}
}