{
  "type": "Feature",
  "properties": {
    "gn:admin1_code":"7.0",
    "gn:asciiname":"Garagoumza",
    "gn:country_code":"NE",
    "gn:dem":449,
    "gn:feature_class":"P",
    "gn:feature_code":"PPL",
    "gn:name":"Garagoumza",
    "gn:population":0,
    "gn:timezone":"Africa/Niamey",
    "iso:country":"NE",
    "wof:name":"Garagoumza",
    "wof:placetype":"locality"
},
  "geometry": {"coordinates":[7.9861,14.91129],"type":"Point"}
}