{
  "type": "Feature",
  "properties": {
    "gn:admin1_code":"2.0",
    "gn:asciiname":"Fongorimaram",
    "gn:country_code":"NE",
    "gn:dem":345,
    "gn:feature_class":"P",
    "gn:feature_code":"PPL",
    "gn:name":"Fongorimaram",
    "gn:population":0,
    "gn:timezone":"Africa/Niamey",
    "iso:country":"NE",
    "wof:name":"Fongorimaram",
    "wof:placetype":"locality"
},
  "geometry": {"coordinates":[11.4237,13.5393],"type":"Point"}
}