{
  "type": "Feature",
  "properties": {
    "gn:admin1_code":"7.0",
    "gn:asciiname":"Halbawa Bougaje",
    "gn:country_code":"NE",
    "gn:dem":451,
    "gn:feature_class":"P",
    "gn:feature_code":"PPL",
    "gn:name":"Halbawa Bougaj\u00e9",
    "gn:population":0,
    "gn:timezone":"Africa/Niamey",
    "iso:country":"NE",
    "wof:name":"Halbawa Bougaje",
    "wof:placetype":"locality"
},
  "geometry": {"coordinates":[8.54894,13.34057],"type":"Point"}
}