{
  "type": "Feature",
  "properties": {
    "gn:admin1_code":"3.0",
    "gn:asciiname":"Maouredeye",
    "gn:country_code":"NE",
    "gn:dem":237,
    "gn:feature_class":"P",
    "gn:feature_code":"PPL",
    "gn:name":"Maour\u00e9d\u00e8ye",
    "gn:population":0,
    "gn:timezone":"Africa/Niamey",
    "iso:country":"NE",
    "name:und_x_variant":[
        "Mauridei",
        "Maouridey",
        "Maour\u00e9dey",
        "Maour\u00e9d\u00e8ye"
    ],
    "wof:name":"Maouredeye",
    "wof:placetype":"locality"
},
  "geometry": {"coordinates":[3.6848,13.2396],"type":"Point"}
}