{
  "type": "Feature",
  "properties": {
    "gn:admin1_code":"3.0",
    "gn:asciiname":"Nakifada",
    "gn:country_code":"NE",
    "gn:dem":227,
    "gn:feature_class":"P",
    "gn:feature_code":"PPL",
    "gn:name":"Nakifada",
    "gn:population":0,
    "gn:timezone":"Africa/Niamey",
    "iso:country":"NE",
    "wof:name":"Nakifada",
    "wof:placetype":"locality"
},
  "geometry": {"coordinates":[3.22331,12.82271],"type":"Point"}
}