{
  "type": "Feature",
  "properties": {
    "gn:admin1_code":"4.0",
    "gn:asciiname":"Garin Chefou",
    "gn:country_code":"NE",
    "gn:dem":376,
    "gn:feature_class":"P",
    "gn:feature_code":"PPL",
    "gn:name":"Garin Ch\u00e9fou",
    "gn:population":0,
    "gn:timezone":"Africa/Niamey",
    "iso:country":"NE",
    "wof:name":"Garin Chefou",
    "wof:placetype":"locality"
},
  "geometry": {"coordinates":[6.76888,13.88338],"type":"Point"}
}