{
  "type": "Feature",
  "properties": {
    "gn:admin1_code":"3.0",
    "gn:asciiname":"Fetalare",
    "gn:country_code":"NE",
    "gn:dem":189,
    "gn:feature_class":"P",
    "gn:feature_code":"PPL",
    "gn:name":"F\u00e9talar\u00e9",
    "gn:population":0,
    "gn:timezone":"Africa/Niamey",
    "iso:country":"NE",
    "wof:name":"Fetalare",
    "wof:placetype":"locality"
},
  "geometry": {"coordinates":[2.89168,12.94998],"type":"Point"}
}