{
  "type": "Feature",
  "properties": {
    "gn:admin1_code":"4.0",
    "gn:asciiname":"Soumarana",
    "gn:country_code":"NE",
    "gn:dem":350,
    "gn:feature_class":"P",
    "gn:feature_code":"PPL",
    "gn:name":"Soumarana",
    "gn:population":0,
    "gn:timezone":"Africa/Niamey",
    "iso:country":"NE",
    "wof:name":"Soumarana",
    "wof:placetype":"locality"
},
  "geometry": {"coordinates":[7.07372,13.45329],"type":"Point"}
}