{
  "type": "Feature",
  "properties": {
    "gn:admin1_code":"7.0",
    "gn:asciiname":"Djoubatoua",
    "gn:country_code":"NE",
    "gn:dem":464,
    "gn:feature_class":"P",
    "gn:feature_code":"PPL",
    "gn:name":"Djoubatoua",
    "gn:population":0,
    "gn:timezone":"Africa/Niamey",
    "iso:country":"NE",
    "wof:name":"Djoubatoua",
    "wof:placetype":"locality"
},
  "geometry": {"coordinates":[10.466,14.2957],"type":"Point"}
}