{
  "type": "Feature",
  "properties": {
    "gn:admin1_code":"9.0",
    "gn:asciiname":"Maori Koira",
    "gn:country_code":"NE",
    "gn:dem":261,
    "gn:feature_class":"P",
    "gn:feature_code":"PPL",
    "gn:name":"Maori Koira",
    "gn:population":0,
    "gn:timezone":"Africa/Niamey",
    "iso:country":"NE",
    "name:und_x_variant":[
        "Maori Koyra",
        "Maori Koira"
    ],
    "wof:name":"Maori Koira",
    "wof:placetype":"locality"
},
  "geometry": {"coordinates":[1.93902,14.91758],"type":"Point"}
}