{
  "type": "Feature",
  "properties": {
    "gn:admin1_code":"6.0",
    "gn:asciiname":"Kouzoubou",
    "gn:country_code":"NE",
    "gn:dem":479,
    "gn:feature_class":"P",
    "gn:feature_code":"PPL",
    "gn:name":"Kouzoubou",
    "gn:population":0,
    "gn:timezone":"Africa/Niamey",
    "iso:country":"NE",
    "wof:name":"Kouzoubou",
    "wof:placetype":"locality"
},
  "geometry": {"coordinates":[6.12136,14.74297],"type":"Point"}
}