{
  "type": "Feature",
  "properties": {
    "gn:admin1_code":"7.0",
    "gn:asciiname":"Dali",
    "gn:country_code":"NE",
    "gn:dem":480,
    "gn:feature_class":"P",
    "gn:feature_code":"PPL",
    "gn:name":"Dali",
    "gn:population":0,
    "gn:timezone":"Africa/Niamey",
    "iso:country":"NE",
    "wof:name":"Dali",
    "wof:placetype":"locality"
},
  "geometry": {"coordinates":[8.36926,14.53306],"type":"Point"}
}