{
  "type": "Feature",
  "properties": {
    "gn:admin1_code":"3.0",
    "gn:asciiname":"Krya",
    "gn:country_code":"NE",
    "gn:dem":248,
    "gn:feature_class":"P",
    "gn:feature_code":"PPL",
    "gn:name":"Krya",
    "gn:population":0,
    "gn:timezone":"Africa/Niamey",
    "iso:country":"NE",
    "name:und_x_variant":[
        "Kria",
        "Krya"
    ],
    "wof:name":"Krya",
    "wof:placetype":"locality"
},
  "geometry": {"coordinates":[3.8514,14.0524],"type":"Point"}
}