{
  "type": "Feature",
  "properties": {
    "gn:admin1_code":"3.0",
    "gn:asciiname":"Tanaguey",
    "gn:country_code":"NE",
    "gn:dem":204,
    "gn:feature_class":"P",
    "gn:feature_code":"PPL",
    "gn:name":"Tanaguey",
    "gn:population":0,
    "gn:timezone":"Africa/Niamey",
    "iso:country":"NE",
    "name:und_x_variant":[
        "Tanagu\u00e8ye",
        "Tanag\u00e8y",
        "Tanaguey"
    ],
    "wof:name":"Tanaguey",
    "wof:placetype":"locality"
},
  "geometry": {"coordinates":[3.43752,12.08354],"type":"Point"}
}