{
  "type": "Feature",
  "properties": {
    "gn:admin1_code":"3.0",
    "gn:asciiname":"Gorou-Yeno",
    "gn:country_code":"NE",
    "gn:dem":206,
    "gn:feature_class":"P",
    "gn:feature_code":"PPL",
    "gn:name":"Gorou-Y\u00e9no",
    "gn:population":0,
    "gn:timezone":"Africa/Niamey",
    "iso:country":"NE",
    "wof:name":"Gorou-Yeno",
    "wof:placetype":"locality"
},
  "geometry": {"coordinates":[3.01903,12.8218],"type":"Point"}
}