{
  "type": "Feature",
  "properties": {
    "gn:admin1_code":"2.0",
    "gn:asciiname":"Zaramiri",
    "gn:country_code":"NE",
    "gn:dem":317,
    "gn:feature_class":"P",
    "gn:feature_code":"PPL",
    "gn:name":"Zaramiri",
    "gn:population":0,
    "gn:timezone":"Africa/Niamey",
    "iso:country":"NE",
    "wof:name":"Zaramiri",
    "wof:placetype":"locality"
},
  "geometry": {"coordinates":[12.24245,13.18108],"type":"Point"}
}