{
  "type": "Feature",
  "properties": {
    "gn:admin1_code":"3.0",
    "gn:asciiname":"Kouka Hadi",
    "gn:country_code":"NE",
    "gn:dem":195,
    "gn:feature_class":"P",
    "gn:feature_code":"PPL",
    "gn:name":"Kouka Hadi",
    "gn:population":0,
    "gn:timezone":"Africa/Niamey",
    "iso:country":"NE",
    "wof:name":"Kouka Hadi",
    "wof:placetype":"locality"
},
  "geometry": {"coordinates":[3.59456,12.60322],"type":"Point"}
}