{
  "type": "Feature",
  "properties": {
    "gn:admin1_code":"9.0",
    "gn:asciiname":"Goudourio",
    "gn:country_code":"NE",
    "gn:dem":234,
    "gn:feature_class":"P",
    "gn:feature_code":"PPL",
    "gn:name":"Goudourio",
    "gn:population":0,
    "gn:timezone":"Africa/Niamey",
    "iso:country":"NE",
    "name:und_x_variant":[
        "Boudourio",
        "Goudourio"
    ],
    "wof:name":"Goudourio",
    "wof:placetype":"locality"
},
  "geometry": {"coordinates":[2.2875,13.1621],"type":"Point"}
}