{
  "type": "Feature",
  "properties": {
    "gn:admin1_code":"6.0",
    "gn:asciiname":"Sabon Guida",
    "gn:country_code":"NE",
    "gn:dem":374,
    "gn:feature_class":"P",
    "gn:feature_code":"PPL",
    "gn:name":"Sabon Guida",
    "gn:population":0,
    "gn:timezone":"Africa/Niamey",
    "iso:country":"NE",
    "name:und_x_variant":[
        "Sabon Gida",
        "Sabon Guida"
    ],
    "wof:name":"Sabon Guida",
    "wof:placetype":"locality"
},
  "geometry": {"coordinates":[5.5764,14.7895],"type":"Point"}
}