{
  "type": "Feature",
  "properties": {
    "gn:admin1_code":"3.0",
    "gn:asciiname":"Boula Gandatie",
    "gn:country_code":"NE",
    "gn:dem":198,
    "gn:feature_class":"P",
    "gn:feature_code":"PPL",
    "gn:name":"Boula Gandati\u00e9",
    "gn:population":0,
    "gn:timezone":"Africa/Niamey",
    "iso:country":"NE",
    "wof:name":"Boula Gandatie",
    "wof:placetype":"locality"
},
  "geometry": {"coordinates":[2.8095,13.3375],"type":"Point"}
}