{
  "type": "Feature",
  "properties": {
    "gn:admin1_code":"6.0",
    "gn:asciiname":"I-n-Karkada",
    "gn:country_code":"NE",
    "gn:dem":353,
    "gn:feature_class":"P",
    "gn:feature_code":"PPL",
    "gn:name":"I-n-Karkada",
    "gn:population":0,
    "gn:timezone":"Africa/Niamey",
    "iso:country":"NE",
    "name:und_x_variant":[
        "In Korkada",
        "Karkada",
        "Kardaga",
        "I-n-Karkada"
    ],
    "wof:name":"I-n-Karkada",
    "wof:placetype":"locality"
},
  "geometry": {"coordinates":[4.97553,14.82863],"type":"Point"}
}