{
  "type": "Feature",
  "properties": {
    "gn:admin1_code":"2.0",
    "gn:asciiname":"Kaoya",
    "gn:country_code":"NE",
    "gn:dem":310,
    "gn:feature_class":"P",
    "gn:feature_code":"PPL",
    "gn:name":"Kaoya",
    "gn:population":0,
    "gn:timezone":"Africa/Niamey",
    "iso:country":"NE",
    "wof:name":"Kaoya",
    "wof:placetype":"locality"
},
  "geometry": {"coordinates":[12.37685,13.13746],"type":"Point"}
}