{
  "type": "Feature",
  "properties": {
    "gn:admin1_code":"2.0",
    "gn:asciiname":"Abdoukakouri",
    "gn:country_code":"NE",
    "gn:dem":336,
    "gn:feature_class":"P",
    "gn:feature_code":"PPL",
    "gn:name":"Abdoukakouri",
    "gn:population":0,
    "gn:timezone":"Africa/Niamey",
    "iso:country":"NE",
    "wof:name":"Abdoukakouri",
    "wof:placetype":"locality"
},
  "geometry": {"coordinates":[11.63244,13.65809],"type":"Point"}
}