{
  "type": "Feature",
  "properties": {
    "gn:admin1_code":"4.0",
    "gn:asciiname":"Guidan Ara",
    "gn:country_code":"NE",
    "gn:dem":385,
    "gn:feature_class":"P",
    "gn:feature_code":"PPL",
    "gn:name":"Guidan Ara",
    "gn:population":0,
    "gn:timezone":"Africa/Niamey",
    "iso:country":"NE",
    "name:und_x_variant":[
        "Gidan Ara Gigal\u00e9",
        "Guidan Ara Guigal\u00e9",
        "Guidan Ara"
    ],
    "wof:name":"Guidan Ara",
    "wof:placetype":"locality"
},
  "geometry": {"coordinates":[7.09485,13.67969],"type":"Point"}
}