{
  "type": "Feature",
  "properties": {
    "gn:admin1_code":"6.0",
    "gn:asciiname":"Akala",
    "gn:country_code":"NE",
    "gn:dem":441,
    "gn:feature_class":"P",
    "gn:feature_code":"PPL",
    "gn:name":"Akala",
    "gn:population":0,
    "gn:timezone":"Africa/Niamey",
    "iso:country":"NE",
    "name:srp_x_preferred":[
        "\u0410\u043a\u0430\u043b\u0430"
    ],
    "wof:name":"Akala",
    "wof:placetype":"locality"
},
  "geometry": {"coordinates":[5.8436,14.8194],"type":"Point"}
}