{
  "type": "Feature",
  "properties": {
    "gn:admin1_code":"9.0",
    "gn:asciiname":"Tyala",
    "gn:country_code":"NE",
    "gn:dem":223,
    "gn:feature_class":"P",
    "gn:feature_code":"PPL",
    "gn:name":"Tyala",
    "gn:population":0,
    "gn:timezone":"Africa/Niamey",
    "iso:country":"NE",
    "wof:name":"Tyala",
    "wof:placetype":"locality"
},
  "geometry": {"coordinates":[2.25427,12.87948],"type":"Point"}
}