{
  "type": "Feature",
  "properties": {
    "gn:admin1_code":"9.0",
    "gn:asciiname":"Foumbia",
    "gn:country_code":"NE",
    "gn:dem":238,
    "gn:feature_class":"P",
    "gn:feature_code":"PPL",
    "gn:name":"Foumbia",
    "gn:population":0,
    "gn:timezone":"Africa/Niamey",
    "iso:country":"NE",
    "wof:name":"Foumbia",
    "wof:placetype":"locality"
},
  "geometry": {"coordinates":[2.1823,13.1864],"type":"Point"}
}