{
  "type": "Feature",
  "properties": {
    "gn:admin1_code":"3.0",
    "gn:asciiname":"Sandi Dey",
    "gn:country_code":"NE",
    "gn:dem":222,
    "gn:feature_class":"P",
    "gn:feature_code":"PPL",
    "gn:name":"Sandi Dey",
    "gn:population":0,
    "gn:timezone":"Africa/Niamey",
    "iso:country":"NE",
    "name:und_x_variant":[
        "Sandi-D\u00e8ye",
        "Sandi Dey"
    ],
    "wof:name":"Sandi Dey",
    "wof:placetype":"locality"
},
  "geometry": {"coordinates":[3.43736,12.71728],"type":"Point"}
}