{
  "type": "Feature",
  "properties": {
    "gn:admin1_code":"7.0",
    "gn:asciiname":"Zangon Koumbia",
    "gn:country_code":"NE",
    "gn:dem":548,
    "gn:feature_class":"P",
    "gn:feature_code":"PPL",
    "gn:name":"Zangon Koumbia",
    "gn:population":0,
    "gn:timezone":"Africa/Niamey",
    "iso:country":"NE",
    "wof:name":"Zangon Koumbia",
    "wof:placetype":"locality"
},
  "geometry": {"coordinates":[10.0768,14.3557],"type":"Point"}
}