{
  "type": "Feature",
  "properties": {
    "gn:admin1_code":"4.0",
    "gn:asciiname":"Koton Kohi",
    "gn:country_code":"NE",
    "gn:dem":477,
    "gn:feature_class":"P",
    "gn:feature_code":"PPL",
    "gn:name":"Koton Kohi",
    "gn:population":0,
    "gn:timezone":"Africa/Niamey",
    "iso:country":"NE",
    "wof:name":"Koton Kohi",
    "wof:placetype":"locality"
},
  "geometry": {"coordinates":[8.30042,13.50023],"type":"Point"}
}