{
  "type": "Feature",
  "properties": {
    "gn:admin1_code":"7.0",
    "gn:asciiname":"Guerou",
    "gn:country_code":"NE",
    "gn:dem":421,
    "gn:feature_class":"P",
    "gn:feature_code":"PPL",
    "gn:name":"Gu\u00e9rou",
    "gn:population":0,
    "gn:timezone":"Africa/Niamey",
    "iso:country":"NE",
    "name:ara_x_preferred":[
        "\u0643\u0631\u0648"
    ],
    "name:fra_x_preferred":[
        "Guerou"
    ],
    "name:ita_x_preferred":[
        "Guerou"
    ],
    "name:msa_x_preferred":[
        "Guerou"
    ],
    "name:pol_x_preferred":[
        "Karu"
    ],
    "name:ron_x_preferred":[
        "Gu\u00e9rou"
    ],
    "name:rus_x_preferred":[
        "\u0413\u0435\u0440\u0443"
    ],
    "name:spa_x_preferred":[
        "Guerou"
    ],
    "name:swe_x_preferred":[
        "Guerou"
    ],
    "name:urd_x_preferred":[
        "\u06a9\u0631\u0648"
    ],
    "wof:name":"Guerou",
    "wof:placetype":"locality"
},
  "geometry": {"coordinates":[9.5858,14.048],"type":"Point"}
}