{
  "type": "Feature",
  "properties": {
    "gn:admin1_code":"6.0",
    "gn:asciiname":"Manbawa",
    "gn:country_code":"NE",
    "gn:dem":384,
    "gn:feature_class":"P",
    "gn:feature_code":"PPL",
    "gn:name":"Manbawa",
    "gn:population":0,
    "gn:timezone":"Africa/Niamey",
    "iso:country":"NE",
    "wof:name":"Manbawa",
    "wof:placetype":"locality"
},
  "geometry": {"coordinates":[6.24229,14.5388],"type":"Point"}
}