{
  "type": "Feature",
  "properties": {
    "gn:admin1_code":"7.0",
    "gn:asciiname":"Ouhoule",
    "gn:country_code":"NE",
    "gn:dem":356,
    "gn:feature_class":"P",
    "gn:feature_code":"PPL",
    "gn:name":"Ouhoul\u00e9",
    "gn:population":0,
    "gn:timezone":"Africa/Niamey",
    "iso:country":"NE",
    "wof:name":"Ouhoule",
    "wof:placetype":"locality"
},
  "geometry": {"coordinates":[10.9515,14.1858],"type":"Point"}
}