{
  "type": "Feature",
  "properties": {
    "gn:admin1_code":"9.0",
    "gn:asciiname":"Boundou Warou",
    "gn:country_code":"NE",
    "gn:dem":238,
    "gn:feature_class":"P",
    "gn:feature_code":"PPL",
    "gn:name":"Boundou Warou",
    "gn:population":0,
    "gn:timezone":"Africa/Niamey",
    "iso:country":"NE",
    "name:und_x_variant":[
        "Boundouarou",
        "Boundou Warou"
    ],
    "wof:name":"Boundou Warou",
    "wof:placetype":"locality"
},
  "geometry": {"coordinates":[2.7981,13.5644],"type":"Point"}
}