{
  "type": "Feature",
  "properties": {
    "gn:admin1_code":"9.0",
    "gn:asciiname":"Chikal Ilela",
    "gn:country_code":"NE",
    "gn:dem":236,
    "gn:feature_class":"P",
    "gn:feature_code":"PPL",
    "gn:name":"Chikal Il\u00e9la",
    "gn:population":0,
    "gn:timezone":"Africa/Niamey",
    "iso:country":"NE",
    "wof:name":"Chikal Ilela",
    "wof:placetype":"locality"
},
  "geometry": {"coordinates":[3.4611,14.2445],"type":"Point"}
}