{
  "type": "Feature",
  "properties": {
    "gn:admin1_code":"6.0",
    "gn:asciiname":"Tebaram",
    "gn:country_code":"NE",
    "gn:dem":300,
    "gn:feature_class":"P",
    "gn:feature_code":"PPL",
    "gn:name":"T\u00e9baram",
    "gn:population":0,
    "gn:timezone":"Africa/Niamey",
    "iso:country":"NE",
    "name:ceb_x_preferred":[
        "T\u00e9baram"
    ],
    "name:deu_x_preferred":[
        "T\u00e9baram"
    ],
    "name:ita_x_preferred":[
        "Tebaram"
    ],
    "name:msa_x_preferred":[
        "Tebaram"
    ],
    "name:ron_x_preferred":[
        "Tebaram"
    ],
    "name:spa_x_preferred":[
        "T\u00e9baram"
    ],
    "name:und_x_variant":[
        "T\u00e9barat",
        "T\u00e9baram"
    ],
    "wof:name":"Tebaram",
    "wof:placetype":"locality"
},
  "geometry": {"coordinates":[4.4582,14.83407],"type":"Point"}
}