{
  "type": "Feature",
  "properties": {
    "gn:admin1_code":"9.0",
    "gn:asciiname":"Djiga",
    "gn:country_code":"NE",
    "gn:dem":260,
    "gn:feature_class":"P",
    "gn:feature_code":"PPL",
    "gn:name":"Djiga",
    "gn:population":0,
    "gn:timezone":"Africa/Niamey",
    "iso:country":"NE",
    "wof:name":"Djiga",
    "wof:placetype":"locality"
},
  "geometry": {"coordinates":[3.9112,14.4263],"type":"Point"}
}