{
  "type": "Feature",
  "properties": {
    "gn:admin1_code":"3.0",
    "gn:asciiname":"Hilikoy Kouara",
    "gn:country_code":"NE",
    "gn:dem":191,
    "gn:feature_class":"P",
    "gn:feature_code":"PPL",
    "gn:name":"Hilikoy Kouara",
    "gn:population":0,
    "gn:timezone":"Africa/Niamey",
    "iso:country":"NE",
    "wof:name":"Hilikoy Kouara",
    "wof:placetype":"locality"
},
  "geometry": {"coordinates":[2.973,12.83585],"type":"Point"}
}