{
  "type": "Feature",
  "properties": {
    "gn:admin1_code":"4.0",
    "gn:asciiname":"Mouri Dan Dounia",
    "gn:country_code":"NE",
    "gn:dem":419,
    "gn:feature_class":"P",
    "gn:feature_code":"PPL",
    "gn:name":"Mouri Dan Dounia",
    "gn:population":0,
    "gn:timezone":"Africa/Niamey",
    "iso:country":"NE",
    "name:und_x_variant":[
        "Dan Dounia",
        "Mouri Dan Dounia"
    ],
    "wof:name":"Mouri Dan Dounia",
    "wof:placetype":"locality"
},
  "geometry": {"coordinates":[7.57119,13.6055],"type":"Point"}
}