{
  "type": "Feature",
  "properties": {
    "gn:admin1_code":"7.0",
    "gn:asciiname":"Tajae",
    "gn:country_code":"NE",
    "gn:dem":467,
    "gn:feature_class":"P",
    "gn:feature_code":"PPL",
    "gn:name":"Taja\u00e9",
    "gn:population":0,
    "gn:timezone":"Africa/Niamey",
    "iso:country":"NE",
    "name:deu_x_preferred":[
        "Taja\u00e9"
    ],
    "name:fin_x_preferred":[
        "Taja\u00e9"
    ],
    "name:fra_x_preferred":[
        "Taja\u00e9"
    ],
    "name:ita_x_preferred":[
        "Tajae"
    ],
    "name:msa_x_preferred":[
        "Tajae"
    ],
    "name:ron_x_preferred":[
        "Tajae"
    ],
    "name:spa_x_preferred":[
        "Taja\u00e9"
    ],
    "wof:name":"Tajae",
    "wof:placetype":"locality"
},
  "geometry": {"coordinates":[9.0899,14.1053],"type":"Point"}
}