{
  "type": "Feature",
  "properties": {
    "gn:admin1_code":"4.0",
    "gn:asciiname":"Ta-jae",
    "gn:country_code":"NE",
    "gn:dem":412,
    "gn:feature_class":"P",
    "gn:feature_code":"PPL",
    "gn:name":"T\u00e2-ja\u00e9",
    "gn:population":0,
    "gn:timezone":"Africa/Niamey",
    "iso:country":"NE",
    "wof:name":"Ta-jae",
    "wof:placetype":"locality"
},
  "geometry": {"coordinates":[7.85351,13.40656],"type":"Point"}
}