{
  "type": "Feature",
  "properties": {
    "gn:admin1_code":"9.0",
    "gn:asciiname":"Sadyo",
    "gn:country_code":"NE",
    "gn:dem":262,
    "gn:feature_class":"P",
    "gn:feature_code":"PPL",
    "gn:name":"Sadyo",
    "gn:population":0,
    "gn:timezone":"Africa/Niamey",
    "iso:country":"NE",
    "name:und_x_variant":[
        "Sadio",
        "Sadyo"
    ],
    "wof:name":"Sadyo",
    "wof:placetype":"locality"
},
  "geometry": {"coordinates":[2.32782,14.36086],"type":"Point"}
}