{
  "type": "Feature",
  "properties": {
    "gn:admin1_code":"7.0",
    "gn:asciiname":"Baja Baja",
    "gn:country_code":"NE",
    "gn:dem":443,
    "gn:feature_class":"P",
    "gn:feature_code":"PPL",
    "gn:name":"Baja Baja",
    "gn:population":0,
    "gn:timezone":"Africa/Niamey",
    "iso:country":"NE",
    "wof:name":"Baja Baja",
    "wof:placetype":"locality"
},
  "geometry": {"coordinates":[8.89012,13.7209],"type":"Point"}
}