{
  "type": "Feature",
  "properties": {
    "gn:admin1_code":"7.0",
    "gn:asciiname":"Goguine",
    "gn:country_code":"NE",
    "gn:dem":525,
    "gn:feature_class":"P",
    "gn:feature_code":"PPL",
    "gn:name":"Goguin\u00e9",
    "gn:population":0,
    "gn:timezone":"Africa/Niamey",
    "iso:country":"NE",
    "name:und_x_variant":[
        "Gogin\u00e9",
        "Goguin\u00e9"
    ],
    "wof:name":"Goguine",
    "wof:placetype":"locality"
},
  "geometry": {"coordinates":[8.89652,14.91187],"type":"Point"}
}