{
  "type": "Feature",
  "properties": {
    "gn:admin1_code":"4.0",
    "gn:asciiname":"Tabkin Kiria",
    "gn:country_code":"NE",
    "gn:dem":352,
    "gn:feature_class":"P",
    "gn:feature_code":"PPL",
    "gn:name":"Tabkin Kiria",
    "gn:population":0,
    "gn:timezone":"Africa/Niamey",
    "iso:country":"NE",
    "name:und_x_variant":[
        "Tapkin Kiria",
        "Tabkin Kiria"
    ],
    "wof:name":"Tabkin Kiria",
    "wof:placetype":"locality"
},
  "geometry": {"coordinates":[6.705,13.31676],"type":"Point"}
}