{
  "type": "Feature",
  "properties": {
    "gn:admin1_code":"3.0",
    "gn:asciiname":"Made Kwara",
    "gn:country_code":"NE",
    "gn:dem":203,
    "gn:feature_class":"P",
    "gn:feature_code":"PPL",
    "gn:name":"Mad\u00e9 Kwara",
    "gn:population":0,
    "gn:timezone":"Africa/Niamey",
    "iso:country":"NE",
    "name:und_x_variant":[
        "Mad\u00e9-Koara",
        "Mad\u00e9 Kwara"
    ],
    "wof:name":"Made Kwara",
    "wof:placetype":"locality"
},
  "geometry": {"coordinates":[3.24038,12.74345],"type":"Point"}
}