{
  "type": "Feature",
  "properties": {
    "gn:admin1_code":"3.0",
    "gn:asciiname":"Marjak",
    "gn:country_code":"NE",
    "gn:dem":287,
    "gn:feature_class":"P",
    "gn:feature_code":"PPL",
    "gn:name":"Marjak",
    "gn:population":0,
    "gn:timezone":"Africa/Niamey",
    "iso:country":"NE",
    "wof:name":"Marjak",
    "wof:placetype":"locality"
},
  "geometry": {"coordinates":[4.43371,14.42607],"type":"Point"}
}