{
  "type": "Feature",
  "properties": {
    "gn:admin1_code":"3.0",
    "gn:asciiname":"Gari-Nkoana",
    "gn:country_code":"NE",
    "gn:dem":234,
    "gn:feature_class":"P",
    "gn:feature_code":"PPL",
    "gn:name":"Gari-Nkoana",
    "gn:population":0,
    "gn:timezone":"Africa/Niamey",
    "iso:country":"NE",
    "name:und_x_variant":[
        "Garin Koana",
        "Gari-Nkoana"
    ],
    "wof:name":"Gari-Nkoana",
    "wof:placetype":"locality"
},
  "geometry": {"coordinates":[3.878,13.3569],"type":"Point"}
}