{
  "type": "Feature",
  "properties": {
    "gn:admin1_code":"7.0",
    "gn:asciiname":"Dan Zabia",
    "gn:country_code":"NE",
    "gn:dem":507,
    "gn:feature_class":"P",
    "gn:feature_code":"PPL",
    "gn:name":"Dan Zabia",
    "gn:population":0,
    "gn:timezone":"Africa/Niamey",
    "iso:country":"NE",
    "wof:name":"Dan Zabia",
    "wof:placetype":"locality"
},
  "geometry": {"coordinates":[8.79055,14.86987],"type":"Point"}
}