{
  "type": "Feature",
  "properties": {
    "gn:admin1_code":"4.0",
    "gn:asciiname":"Mato",
    "gn:country_code":"NE",
    "gn:dem":381,
    "gn:feature_class":"P",
    "gn:feature_code":"PPL",
    "gn:name":"Mato",
    "gn:population":0,
    "gn:timezone":"Africa/Niamey",
    "iso:country":"NE",
    "wof:name":"Mato",
    "wof:placetype":"locality"
},
  "geometry": {"coordinates":[7.10592,14.31119],"type":"Point"}
}