{
  "type": "Feature",
  "properties": {
    "gn:admin1_code":"3.0",
    "gn:asciiname":"Ilela",
    "gn:country_code":"NE",
    "gn:dem":217,
    "gn:feature_class":"P",
    "gn:feature_code":"PPL",
    "gn:name":"Il\u00e9la",
    "gn:population":0,
    "gn:timezone":"Africa/Niamey",
    "iso:country":"NE",
    "name:und_x_variant":[
        "Ill\u00e9la",
        "Il\u00e9la"
    ],
    "wof:name":"Ilela",
    "wof:placetype":"locality"
},
  "geometry": {"coordinates":[3.68609,12.87891],"type":"Point"}
}