{
  "type": "Feature",
  "properties": {
    "gn:admin1_code":"7.0",
    "gn:asciiname":"Bouboute",
    "gn:country_code":"NE",
    "gn:dem":422,
    "gn:feature_class":"P",
    "gn:feature_code":"PPL",
    "gn:name":"Boubout\u00e9",
    "gn:population":0,
    "gn:timezone":"Africa/Niamey",
    "iso:country":"NE",
    "wof:name":"Bouboute",
    "wof:placetype":"locality"
},
  "geometry": {"coordinates":[9.8186,14.1293],"type":"Point"}
}