{
  "type": "Feature",
  "properties": {
    "gn:admin1_code":"4.0",
    "gn:asciiname":"Tachako",
    "gn:country_code":"NE",
    "gn:dem":337,
    "gn:feature_class":"P",
    "gn:feature_code":"PPL",
    "gn:name":"Tachako",
    "gn:population":0,
    "gn:timezone":"Africa/Niamey",
    "iso:country":"NE",
    "wof:name":"Tachako",
    "wof:placetype":"locality"
},
  "geometry": {"coordinates":[6.80993,13.97602],"type":"Point"}
}