{
  "type": "Feature",
  "properties": {
    "gn:admin1_code":"7.0",
    "gn:asciiname":"Mournazabo",
    "gn:country_code":"NE",
    "gn:dem":455,
    "gn:feature_class":"P",
    "gn:feature_code":"PPL",
    "gn:name":"Mournazabo",
    "gn:population":0,
    "gn:timezone":"Africa/Niamey",
    "iso:country":"NE",
    "wof:name":"Mournazabo",
    "wof:placetype":"locality"
},
  "geometry": {"coordinates":[7.8005,14.7301],"type":"Point"}
}