{
  "type": "Feature",
  "properties": {
    "gn:admin1_code":"9.0",
    "gn:asciiname":"Louma",
    "gn:country_code":"NE",
    "gn:dem":221,
    "gn:feature_class":"P",
    "gn:feature_code":"PPL",
    "gn:name":"Louma",
    "gn:population":0,
    "gn:timezone":"Africa/Niamey",
    "iso:country":"NE",
    "name:und_x_variant":[
        "Luma",
        "Louma"
    ],
    "wof:name":"Louma",
    "wof:placetype":"locality"
},
  "geometry": {"coordinates":[3.2538,14.1581],"type":"Point"}
}