{
  "type": "Feature",
  "properties": {
    "gn:admin1_code":"3.0",
    "gn:asciiname":"Adeki",
    "gn:country_code":"NE",
    "gn:dem":228,
    "gn:feature_class":"P",
    "gn:feature_code":"PPL",
    "gn:name":"Ad\u00e9ki",
    "gn:population":0,
    "gn:timezone":"Africa/Niamey",
    "iso:country":"NE",
    "wof:name":"Adeki",
    "wof:placetype":"locality"
},
  "geometry": {"coordinates":[4.04268,13.90691],"type":"Point"}
}