{
  "type": "Feature",
  "properties": {
    "gn:admin1_code":"4.0",
    "gn:asciiname":"Dan Goulbi",
    "gn:country_code":"NE",
    "gn:dem":400,
    "gn:feature_class":"P",
    "gn:feature_code":"PPL",
    "gn:name":"Dan Goulbi",
    "gn:population":0,
    "gn:timezone":"Africa/Niamey",
    "iso:country":"NE",
    "wof:name":"Dan Goulbi",
    "wof:placetype":"locality"
},
  "geometry": {"coordinates":[7.6944,13.86917],"type":"Point"}
}