{
  "type": "Feature",
  "properties": {
    "gn:admin1_code":"3.0",
    "gn:asciiname":"Lalanedji Djerma",
    "gn:country_code":"NE",
    "gn:dem":180,
    "gn:feature_class":"P",
    "gn:feature_code":"PPL",
    "gn:name":"Lalan\u00e9dji Djerma",
    "gn:population":0,
    "gn:timezone":"Africa/Niamey",
    "iso:country":"NE",
    "name:und_x_variant":[
        "Lalan\u00e9dji Dyerma",
        "Lalan\u00e9dji Djerma"
    ],
    "wof:name":"Lalanedji Djerma",
    "wof:placetype":"locality"
},
  "geometry": {"coordinates":[2.88521,12.67705],"type":"Point"}
}