{
  "type": "Feature",
  "properties": {
    "gn:admin1_code":"3.0",
    "gn:asciiname":"Aoudou Tounga",
    "gn:country_code":"NE",
    "gn:dem":183,
    "gn:feature_class":"P",
    "gn:feature_code":"PPL",
    "gn:name":"Aoudou Tounga",
    "gn:population":0,
    "gn:timezone":"Africa/Niamey",
    "iso:country":"NE",
    "name:und_x_variant":[
        "Tungan Aoudou",
        "Aoudou Tounga"
    ],
    "wof:name":"Aoudou Tounga",
    "wof:placetype":"locality"
},
  "geometry": {"coordinates":[3.55656,11.86969],"type":"Point"}
}