{
  "type": "Feature",
  "properties": {
    "gn:admin1_code":"4.0",
    "gn:asciiname":"Guidan Mato",
    "gn:country_code":"NE",
    "gn:dem":473,
    "gn:feature_class":"P",
    "gn:feature_code":"PPL",
    "gn:name":"Guidan Mato",
    "gn:population":0,
    "gn:timezone":"Africa/Niamey",
    "iso:country":"NE",
    "wof:name":"Guidan Mato",
    "wof:placetype":"locality"
},
  "geometry": {"coordinates":[8.49922,14.14828],"type":"Point"}
}