{
  "type": "Feature",
  "properties": {
    "gn:admin1_code":"6.0",
    "gn:asciiname":"Arewa",
    "gn:country_code":"NE",
    "gn:dem":341,
    "gn:feature_class":"P",
    "gn:feature_code":"PPL",
    "gn:name":"Ar\u00e9wa",
    "gn:population":0,
    "gn:timezone":"Africa/Niamey",
    "iso:country":"NE",
    "wof:name":"Arewa",
    "wof:placetype":"locality"
},
  "geometry": {"coordinates":[5.8838,14.0506],"type":"Point"}
}