{
  "type": "Feature",
  "properties": {
    "gn:admin1_code":"4.0",
    "gn:asciiname":"Taka",
    "gn:country_code":"NE",
    "gn:dem":449,
    "gn:feature_class":"P",
    "gn:feature_code":"PPL",
    "gn:name":"Taka",
    "gn:population":0,
    "gn:timezone":"Africa/Niamey",
    "iso:country":"NE",
    "wof:name":"Taka",
    "wof:placetype":"locality"
},
  "geometry": {"coordinates":[8.05137,14.29916],"type":"Point"}
}