{
  "type": "Feature",
  "properties": {
    "gn:admin1_code":"2.0",
    "gn:asciiname":"Kingoua",
    "gn:country_code":"NE",
    "gn:dem":297,
    "gn:feature_class":"P",
    "gn:feature_code":"PPL",
    "gn:name":"Kingoua",
    "gn:population":0,
    "gn:timezone":"Africa/Niamey",
    "iso:country":"NE",
    "wof:name":"Kingoua",
    "wof:placetype":"locality"
},
  "geometry": {"coordinates":[13.02941,13.62891],"type":"Point"}
}