{
  "type": "Feature",
  "properties": {
    "gn:admin1_code":"7.0",
    "gn:asciiname":"Zourzawa",
    "gn:country_code":"NE",
    "gn:dem":466,
    "gn:feature_class":"P",
    "gn:feature_code":"PPL",
    "gn:name":"Zourzawa",
    "gn:population":0,
    "gn:timezone":"Africa/Niamey",
    "iso:country":"NE",
    "wof:name":"Zourzawa",
    "wof:placetype":"locality"
},
  "geometry": {"coordinates":[8.72626,14.29989],"type":"Point"}
}