{
  "type": "Feature",
  "properties": {
    "gn:admin1_code":"9.0",
    "gn:asciiname":"Atou Baba Kouara",
    "gn:country_code":"NE",
    "gn:dem":230,
    "gn:feature_class":"P",
    "gn:feature_code":"PPL",
    "gn:name":"Atou Baba Kouara",
    "gn:population":0,
    "gn:timezone":"Africa/Niamey",
    "iso:country":"NE",
    "name:und_x_variant":[
        "Atoubabo-Koara",
        "Atou Babo Kwara",
        "Atou Baba Kouara"
    ],
    "wof:name":"Atou Baba Kouara",
    "wof:placetype":"locality"
},
  "geometry": {"coordinates":[2.4028,13.5447],"type":"Point"}
}