{
  "type": "Feature",
  "properties": {
    "gn:admin1_code":"7.0",
    "gn:asciiname":"Marmane",
    "gn:country_code":"NE",
    "gn:dem":491,
    "gn:feature_class":"P",
    "gn:feature_code":"PPL",
    "gn:name":"Marmane",
    "gn:population":0,
    "gn:timezone":"Africa/Niamey",
    "iso:country":"NE",
    "wof:name":"Marmane",
    "wof:placetype":"locality"
},
  "geometry": {"coordinates":[9.19444,15.00694],"type":"Point"}
}