{
  "type": "Feature",
  "properties": {
    "gn:admin1_code":"9.0",
    "gn:asciiname":"Tiambanga",
    "gn:country_code":"NE",
    "gn:dem":224,
    "gn:feature_class":"P",
    "gn:feature_code":"PPL",
    "gn:name":"Tiambanga",
    "gn:population":0,
    "gn:timezone":"Africa/Niamey",
    "iso:country":"NE",
    "wof:name":"Tiambanga",
    "wof:placetype":"locality"
},
  "geometry": {"coordinates":[1.86619,13.12723],"type":"Point"}
}