{
  "type": "Feature",
  "properties": {
    "gn:admin1_code":"3.0",
    "gn:asciiname":"Tade-Koara",
    "gn:country_code":"NE",
    "gn:dem":221,
    "gn:feature_class":"P",
    "gn:feature_code":"PPL",
    "gn:name":"Tad\u00e9-Koara",
    "gn:population":0,
    "gn:timezone":"Africa/Niamey",
    "iso:country":"NE",
    "name:und_x_variant":[
        "Tad\u00e9 Kwara",
        "Tad\u00e9-Koara"
    ],
    "wof:name":"Tade-Koara",
    "wof:placetype":"locality"
},
  "geometry": {"coordinates":[3.0142,13.0022],"type":"Point"}
}