{
  "type": "Feature",
  "properties": {
    "gn:admin1_code":"3.0",
    "gn:asciiname":"Bargoumawa",
    "gn:country_code":"NE",
    "gn:dem":223,
    "gn:feature_class":"P",
    "gn:feature_code":"PPL",
    "gn:name":"Bargoumawa",
    "gn:population":0,
    "gn:timezone":"Africa/Niamey",
    "iso:country":"NE",
    "wof:name":"Bargoumawa",
    "wof:placetype":"locality"
},
  "geometry": {"coordinates":[4.0197,13.23912],"type":"Point"}
}