{
  "type": "Feature",
  "properties": {
    "gn:admin1_code":"9.0",
    "gn:asciiname":"Hayni Fada",
    "gn:country_code":"NE",
    "gn:dem":241,
    "gn:feature_class":"P",
    "gn:feature_code":"PPL",
    "gn:name":"Hayni Fada",
    "gn:population":0,
    "gn:timezone":"Africa/Niamey",
    "iso:country":"NE",
    "wof:name":"Hayni Fada",
    "wof:placetype":"locality"
},
  "geometry": {"coordinates":[2.7076,13.7464],"type":"Point"}
}