{
  "type": "Feature",
  "properties": {
    "gn:admin1_code":"4.0",
    "gn:asciiname":"Gaoude",
    "gn:country_code":"NE",
    "gn:dem":344,
    "gn:feature_class":"P",
    "gn:feature_code":"PPL",
    "gn:name":"Gaoud\u00e9",
    "gn:population":0,
    "gn:timezone":"Africa/Niamey",
    "iso:country":"NE",
    "wof:name":"Gaoude",
    "wof:placetype":"locality"
},
  "geometry": {"coordinates":[6.56627,13.7296],"type":"Point"}
}