{
  "type": "Feature",
  "properties": {
    "gn:admin1_code":"6.0",
    "gn:asciiname":"Dan Toudou I",
    "gn:country_code":"NE",
    "gn:dem":352,
    "gn:feature_class":"P",
    "gn:feature_code":"PPL",
    "gn:name":"Dan Toudou I",
    "gn:population":0,
    "gn:timezone":"Africa/Niamey",
    "iso:country":"NE",
    "wof:name":"Dan Toudou I",
    "wof:placetype":"locality"
},
  "geometry": {"coordinates":[6.30929,14.05262],"type":"Point"}
}