{
  "type": "Feature",
  "properties": {
    "gn:admin1_code":"4.0",
    "gn:asciiname":"Mousa",
    "gn:country_code":"NE",
    "gn:dem":355,
    "gn:feature_class":"P",
    "gn:feature_code":"PPL",
    "gn:name":"Mousa",
    "gn:population":0,
    "gn:timezone":"Africa/Niamey",
    "iso:country":"NE",
    "name:cat_x_preferred":[
        "Mousa"
    ],
    "name:ceb_x_preferred":[
        "Mousa"
    ],
    "name:cym_x_preferred":[
        "Mousa"
    ],
    "name:deu_x_preferred":[
        "Mousa"
    ],
    "name:eus_x_preferred":[
        "Mousa"
    ],
    "name:fra_x_preferred":[
        "Mousa"
    ],
    "name:gla_x_preferred":[
        "Mousa"
    ],
    "name:nno_x_preferred":[
        "Mousa"
    ],
    "name:nor_x_preferred":[
        "Mousa"
    ],
    "name:rus_x_preferred":[
        "\u041c\u0430\u0443\u0441\u0430"
    ],
    "name:sco_x_preferred":[
        "Mousa"
    ],
    "name:spa_x_preferred":[
        "Mousa"
    ],
    "name:swe_x_preferred":[
        "Mousa"
    ],
    "name:und_x_variant":[
        "Moussa"
    ],
    "name:zho_x_preferred":[
        "\u7a46\u85a9\u5cf6"
    ],
    "wof:name":"Mousa",
    "wof:placetype":"locality"
},
  "geometry": {"coordinates":[6.74726,13.45309],"type":"Point"}
}