{
  "type": "Feature",
  "properties": {
    "gn:admin1_code":"4.0",
    "gn:asciiname":"Mousa",
    "gn:country_code":"NE",
    "gn:dem":355,
    "gn:feature_class":"P",
    "gn:feature_code":"PPL",
    "gn:name":"Mousa",
    "gn:population":0,
    "gn:timezone":"Africa/Niamey",
    "iso:country":"NE",
    "name:und_x_variant":[
        "Moussa",
        "Mousa"
    ],
    "wof:name":"Mousa",
    "wof:placetype":"locality"
},
  "geometry": {"coordinates":[6.74726,13.45309],"type":"Point"}
}