{
  "type": "Feature",
  "properties": {
    "gn:admin1_code":"9.0",
    "gn:asciiname":"Tessa",
    "gn:country_code":"NE",
    "gn:dem":217,
    "gn:feature_class":"P",
    "gn:feature_code":"PPL",
    "gn:name":"Tessa",
    "gn:population":0,
    "gn:timezone":"Africa/Niamey",
    "iso:country":"NE",
    "name:deu_x_preferred":[
        "Tessa"
    ],
    "name:fin_x_preferred":[
        "Tessa"
    ],
    "name:ita_x_preferred":[
        "Tessa"
    ],
    "name:nld_x_preferred":[
        "Tessa"
    ],
    "wof:name":"Tessa",
    "wof:placetype":"locality"
},
  "geometry": {"coordinates":[1.2999,14.25826],"type":"Point"}
}