{
  "type": "Feature",
  "properties": {
    "gn:admin1_code":"6.0",
    "gn:asciiname":"Antchi",
    "gn:country_code":"NE",
    "gn:dem":349,
    "gn:feature_class":"P",
    "gn:feature_code":"PPL",
    "gn:name":"Antchi",
    "gn:population":0,
    "gn:timezone":"Africa/Niamey",
    "iso:country":"NE",
    "wof:name":"Antchi",
    "wof:placetype":"locality"
},
  "geometry": {"coordinates":[5.0807,14.8901],"type":"Point"}
}