{
  "type": "Feature",
  "properties": {
    "gn:admin1_code":"7.0",
    "gn:asciiname":"Pada",
    "gn:country_code":"NE",
    "gn:dem":376,
    "gn:feature_class":"P",
    "gn:feature_code":"PPL",
    "gn:name":"Pada",
    "gn:population":0,
    "gn:timezone":"Africa/Niamey",
    "iso:country":"NE",
    "name:cat_x_preferred":[
        "Pada"
    ],
    "name:ceb_x_preferred":[
        "Pada"
    ],
    "name:nor_x_preferred":[
        "Pada"
    ],
    "name:swe_x_preferred":[
        "Pada"
    ],
    "wof:name":"Pada",
    "wof:placetype":"locality"
},
  "geometry": {"coordinates":[9.18198,12.94023],"type":"Point"}
}