{
  "type": "Feature",
  "properties": {
    "gn:admin1_code":"6.0",
    "gn:asciiname":"Mayleghi",
    "gn:country_code":"NE",
    "gn:dem":260,
    "gn:feature_class":"P",
    "gn:feature_code":"PPL",
    "gn:name":"Mayleghi",
    "gn:population":0,
    "gn:timezone":"Africa/Niamey",
    "iso:country":"NE",
    "name:und_x_variant":[
        "Maylerhi",
        "Mayleghi"
    ],
    "wof:name":"Mayleghi",
    "wof:placetype":"locality"
},
  "geometry": {"coordinates":[4.46233,14.11081],"type":"Point"}
}