{
  "type": "Feature",
  "properties": {
    "gn:admin1_code":"1.0",
    "gn:asciiname":"Aderbissinat",
    "gn:country_code":"NE",
    "gn:dem":470,
    "gn:feature_class":"P",
    "gn:feature_code":"PPL",
    "gn:name":"Ad\u00e9rbissinat",
    "gn:population":0,
    "gn:timezone":"Africa/Niamey",
    "iso:country":"NE",
    "name:und_x_variant":[
        "Ad\u00e9rbissinat"
    ],
    "wof:name":"Aderbissinat",
    "wof:placetype":"locality"
},
  "geometry": {"coordinates":[7.8945,15.6275],"type":"Point"}
}