{
  "type": "Feature",
  "properties": {
    "gn:admin1_code":"1.0",
    "gn:asciiname":"Aderbissinat",
    "gn:country_code":"NE",
    "gn:dem":470,
    "gn:feature_class":"P",
    "gn:feature_code":"PPL",
    "gn:name":"Ad\u00e9rbissinat",
    "gn:population":0,
    "gn:timezone":"Africa/Niamey",
    "iso:country":"NE",
    "name:azb_x_preferred":[
        "\u0627\u062f\u0631\u0628\u06cc\u0633\u06cc\u0646\u0627\u062a"
    ],
    "name:ceb_x_preferred":[
        "Ad\u00e9rbissinat"
    ],
    "name:deu_x_preferred":[
        "Aderbissinat"
    ],
    "name:fas_x_preferred":[
        "\u0627\u062f\u0631\u0628\u06cc\u0633\u06cc\u0646\u0627\u062a"
    ],
    "name:fin_x_preferred":[
        "Aderbissinat"
    ],
    "name:ita_x_preferred":[
        "Aderbissinat"
    ],
    "name:msa_x_preferred":[
        "Aderbissinat"
    ],
    "name:ron_x_preferred":[
        "Aderbissinat"
    ],
    "name:spa_x_preferred":[
        "Aderbissinat"
    ],
    "wof:name":"Aderbissinat",
    "wof:placetype":"locality"
},
  "geometry": {"coordinates":[7.8945,15.6275],"type":"Point"}
}