{
  "type": "Feature",
  "properties": {
    "gn:admin1_code":"7.0",
    "gn:asciiname":"Massabka",
    "gn:country_code":"NE",
    "gn:dem":411,
    "gn:feature_class":"P",
    "gn:feature_code":"PPL",
    "gn:name":"Massabka",
    "gn:population":0,
    "gn:timezone":"Africa/Niamey",
    "iso:country":"NE",
    "wof:name":"Massabka",
    "wof:placetype":"locality"
},
  "geometry": {"coordinates":[8.80803,13.41302],"type":"Point"}
}