{
  "type": "Feature",
  "properties": {
    "gn:admin1_code":"6.0",
    "gn:asciiname":"Loudou i-n-Bagaten",
    "gn:country_code":"NE",
    "gn:dem":481,
    "gn:feature_class":"P",
    "gn:feature_code":"PPL",
    "gn:name":"Loudou i-n-Bagat\u00e8n",
    "gn:population":0,
    "gn:timezone":"Africa/Niamey",
    "iso:country":"NE",
    "name:und_x_variant":[
        "Loudou",
        "Loudou i-n-Bagat\u00e8n",
        "Loudou i-n-Bagat\u00e8ne",
        "Loudou In Bagat\u00e8n"
    ],
    "wof:name":"Loudou i-n-Bagaten",
    "wof:placetype":"locality"
},
  "geometry": {"coordinates":[5.9047,14.9382],"type":"Point"}
}