{
  "type": "Feature",
  "properties": {
    "gn:admin1_code":"2.0",
    "gn:asciiname":"Kadia",
    "gn:country_code":"NE",
    "gn:dem":341,
    "gn:feature_class":"P",
    "gn:feature_code":"PPL",
    "gn:name":"Kadia",
    "gn:population":0,
    "gn:timezone":"Africa/Niamey",
    "iso:country":"NE",
    "name:ceb_x_preferred":[
        "Kadia"
    ],
    "name:swe_x_preferred":[
        "Kadia"
    ],
    "wof:name":"Kadia",
    "wof:placetype":"locality"
},
  "geometry": {"coordinates":[11.2645,13.7544],"type":"Point"}
}