{
  "type": "Feature",
  "properties": {
    "gn:admin1_code":"7.0",
    "gn:asciiname":"Ka tirje",
    "gn:country_code":"NE",
    "gn:dem":450,
    "gn:feature_class":"P",
    "gn:feature_code":"PPL",
    "gn:name":"K\u00e2 tirj\u00e9",
    "gn:population":0,
    "gn:timezone":"Africa/Niamey",
    "iso:country":"NE",
    "wof:name":"Ka tirje",
    "wof:placetype":"locality"
},
  "geometry": {"coordinates":[8.81639,13.70779],"type":"Point"}
}