{
  "type": "Feature",
  "properties": {
    "iso:country":"NE",
    "name:bul_x_preferred":[
        "\u041c\u0430\u0442\u0430\u043c\u0435\u0439"
    ],
    "name:ceb_x_preferred":[
        "Matamey"
    ],
    "name:deu_x_preferred":[
        "Matam\u00e8ye"
    ],
    "name:eng_x_preferred":[
        "Matam\u00e8ye"
    ],
    "name:fra_x_preferred":[
        "Matam\u00e8ye"
    ],
    "name:ita_x_preferred":[
        "Matamey"
    ],
    "name:msa_x_preferred":[
        "Matamey"
    ],
    "name:nld_x_preferred":[
        "Matamey"
    ],
    "name:pol_x_preferred":[
        "Matameye"
    ],
    "name:ron_x_preferred":[
        "Matam\u00e8ye"
    ],
    "name:spa_x_preferred":[
        "Matam\u00e8ye"
    ],
    "qs:gn_country":"NE",
    "qs:gn_fcode":"PPL",
    "qs:gn_pop":16844,
    "qs:name":"Matamey",
    "qs:name_adm0":"Niger",
    "qs:name_adm1":"Zinder",
    "qs:photos":0,
    "qs:photos_1k":0,
    "qs:photos_9k":0,
    "qs:photos_9r":0,
    "qs:photos_all":0,
    "qs:photos_sr":0,
    "qs:placetype":"Town",
    "qs:pop_sr":"6",
    "qs:woe_adm0":23424906,
    "wd:wordcount":117,
    "wof:name":"Matamey",
    "wof:placetype":"locality",
    "wof:population":16844
},
  "geometry": {"coordinates":[8.47485,13.42309],"type":"Point"}
}