{
  "type": "Feature",
  "properties": {
    "gn:admin1_code":"2.0",
    "gn:asciiname":"Kalerom",
    "gn:country_code":"NE",
    "gn:dem":348,
    "gn:feature_class":"P",
    "gn:feature_code":"PPL",
    "gn:name":"Kal\u00e9rom",
    "gn:population":0,
    "gn:timezone":"Africa/Niamey",
    "iso:country":"NE",
    "wof:name":"Kalerom",
    "wof:placetype":"locality"
},
  "geometry": {"coordinates":[11.0569,13.8097],"type":"Point"}
}