{
  "type": "Feature",
  "properties": {
    "gn:admin1_code":"3.0",
    "gn:asciiname":"Boubawa",
    "gn:country_code":"NE",
    "gn:dem":238,
    "gn:feature_class":"P",
    "gn:feature_code":"PPL",
    "gn:name":"Boubawa",
    "gn:population":0,
    "gn:timezone":"Africa/Niamey",
    "iso:country":"NE",
    "wof:name":"Boubawa",
    "wof:placetype":"locality"
},
  "geometry": {"coordinates":[4.01554,13.26144],"type":"Point"}
}