{
  "type": "Feature",
  "properties": {
    "gn:admin1_code":"3.0",
    "gn:asciiname":"Tombo",
    "gn:country_code":"NE",
    "gn:dem":244,
    "gn:feature_class":"P",
    "gn:feature_code":"PPL",
    "gn:name":"Tombo",
    "gn:population":0,
    "gn:timezone":"Africa/Niamey",
    "iso:country":"NE",
    "name:ceb_x_preferred":[
        "Tombo"
    ],
    "name:deu_x_preferred":[
        "Tombo"
    ],
    "name:glg_x_preferred":[
        "Tombo"
    ],
    "name:rus_x_preferred":[
        "\u0422\u043e\u043c\u0431\u043e"
    ],
    "name:spa_x_preferred":[
        "Tombo"
    ],
    "name:swe_x_preferred":[
        "Tombo"
    ],
    "name:ukr_x_preferred":[
        "\u0422\u043e\u043c\u0431\u043e"
    ],
    "wof:name":"Tombo",
    "wof:placetype":"locality"
},
  "geometry": {"coordinates":[3.60015,12.84149],"type":"Point"}
}