{
  "type": "Feature",
  "properties": {
    "gn:admin1_code":"3.0",
    "gn:asciiname":"Tombo",
    "gn:country_code":"NE",
    "gn:dem":244,
    "gn:feature_class":"P",
    "gn:feature_code":"PPL",
    "gn:name":"Tombo",
    "gn:population":0,
    "gn:timezone":"Africa/Niamey",
    "iso:country":"NE",
    "wof:name":"Tombo",
    "wof:placetype":"locality"
},
  "geometry": {"coordinates":[3.60015,12.84149],"type":"Point"}
}