{
  "type": "Feature",
  "properties": {
    "gn:admin1_code":"9.0",
    "gn:asciiname":"Dionane",
    "gn:country_code":"NE",
    "gn:dem":260,
    "gn:feature_class":"P",
    "gn:feature_code":"PPL",
    "gn:name":"Dionan\u00e9",
    "gn:population":0,
    "gn:timezone":"Africa/Niamey",
    "iso:country":"NE",
    "wof:name":"Dionane",
    "wof:placetype":"locality"
},
  "geometry": {"coordinates":[2.1265,13.3247],"type":"Point"}
}