{
  "type": "Feature",
  "properties": {
    "gn:admin1_code":"4.0",
    "gn:asciiname":"Dachel Barmo",
    "gn:country_code":"NE",
    "gn:dem":391,
    "gn:feature_class":"P",
    "gn:feature_code":"PPL",
    "gn:name":"Dachel Barmo",
    "gn:population":0,
    "gn:timezone":"Africa/Niamey",
    "iso:country":"NE",
    "name:und_x_variant":[
        "Dachal",
        "Dachel Barmo"
    ],
    "wof:name":"Dachel Barmo",
    "wof:placetype":"locality"
},
  "geometry": {"coordinates":[6.73317,14.22891],"type":"Point"}
}