{
  "type": "Feature",
  "properties": {
    "gn:admin1_code":"9.0",
    "gn:asciiname":"Duna",
    "gn:country_code":"NE",
    "gn:dem":283,
    "gn:feature_class":"P",
    "gn:feature_code":"PPL",
    "gn:name":"Duna",
    "gn:population":0,
    "gn:timezone":"Africa/Niamey",
    "iso:country":"NE",
    "name:ceb_x_preferred":[
        "Duna"
    ],
    "name:ces_x_preferred":[
        "Duna"
    ],
    "name:deu_x_preferred":[
        "Duna"
    ],
    "name:ita_x_preferred":[
        "Duna"
    ],
    "name:por_x_preferred":[
        "Duna"
    ],
    "name:spa_x_preferred":[
        "Duna"
    ],
    "name:swe_x_preferred":[
        "Duna"
    ],
    "wof:name":"Duna",
    "wof:placetype":"locality"
},
  "geometry": {"coordinates":[4.04349,14.76619],"type":"Point"}
}