{
  "type": "Feature",
  "properties": {
    "gn:admin1_code":"7.0",
    "gn:asciiname":"Warme",
    "gn:country_code":"NE",
    "gn:dem":372,
    "gn:feature_class":"P",
    "gn:feature_code":"PPL",
    "gn:name":"Warm\u00e9",
    "gn:population":0,
    "gn:timezone":"Africa/Niamey",
    "iso:country":"NE",
    "name:chv_x_preferred":[
        "\u0412\u0430\u0440\u043c\u0435"
    ],
    "name:deu_x_preferred":[
        "Warme"
    ],
    "name:und_x_variant":[
        "Ouarm\u00e9",
        "Warm\u00e9"
    ],
    "wof:name":"Warme",
    "wof:placetype":"locality"
},
  "geometry": {"coordinates":[10.23189,13.57297],"type":"Point"}
}