{
  "type": "Feature",
  "properties": {
    "gn:admin1_code":"3.0",
    "gn:asciiname":"Silfaye",
    "gn:country_code":"NE",
    "gn:dem":249,
    "gn:feature_class":"P",
    "gn:feature_code":"PPL",
    "gn:name":"Silfaye",
    "gn:population":0,
    "gn:timezone":"Africa/Niamey",
    "iso:country":"NE",
    "wof:name":"Silfaye",
    "wof:placetype":"locality"
},
  "geometry": {"coordinates":[3.7018,13.0705],"type":"Point"}
}