{
  "type": "Feature",
  "properties": {
    "gn:admin1_code":"4.0",
    "gn:asciiname":"Aledawa",
    "gn:country_code":"NE",
    "gn:dem":471,
    "gn:feature_class":"P",
    "gn:feature_code":"PPL",
    "gn:name":"Al\u00e9dawa",
    "gn:population":0,
    "gn:timezone":"Africa/Niamey",
    "iso:country":"NE",
    "wof:name":"Aledawa",
    "wof:placetype":"locality"
},
  "geometry": {"coordinates":[8.27006,13.53841],"type":"Point"}
}