{
  "type": "Feature",
  "properties": {
    "gn:admin1_code":"4.0",
    "gn:asciiname":"Karawa",
    "gn:country_code":"NE",
    "gn:dem":441,
    "gn:feature_class":"P",
    "gn:feature_code":"PPL",
    "gn:name":"Karawa",
    "gn:population":0,
    "gn:timezone":"Africa/Niamey",
    "iso:country":"NE",
    "wof:name":"Karawa",
    "wof:placetype":"locality"
},
  "geometry": {"coordinates":[7.43992,14.47699],"type":"Point"}
}