{
  "type": "Feature",
  "properties": {
    "gn:admin1_code":"7.0",
    "gn:asciiname":"Marke",
    "gn:country_code":"NE",
    "gn:dem":468,
    "gn:feature_class":"P",
    "gn:feature_code":"PPL",
    "gn:name":"Mark\u00e9",
    "gn:population":0,
    "gn:timezone":"Africa/Niamey",
    "iso:country":"NE",
    "name:als_x_preferred":[
        "Marke"
    ],
    "name:ceb_x_preferred":[
        "Marke"
    ],
    "name:deu_x_preferred":[
        "Marke"
    ],
    "name:fry_x_preferred":[
        "Marke"
    ],
    "name:lit_x_preferred":[
        "Mark\u0117"
    ],
    "name:nld_x_preferred":[
        "Marke"
    ],
    "name:pol_x_preferred":[
        "Marke"
    ],
    "name:rus_x_preferred":[
        "\u041c\u0430\u0440\u043a\u0435"
    ],
    "name:swe_x_preferred":[
        "Marke"
    ],
    "wof:name":"Marke",
    "wof:placetype":"locality"
},
  "geometry": {"coordinates":[8.56022,13.11679],"type":"Point"}
}