{
  "type": "Feature",
  "properties": {
    "gn:admin1_code":"9.0",
    "gn:asciiname":"Diginasa Kaina",
    "gn:country_code":"NE",
    "gn:dem":235,
    "gn:feature_class":"P",
    "gn:feature_code":"PPL",
    "gn:name":"Diginasa Kaina",
    "gn:population":0,
    "gn:timezone":"Africa/Niamey",
    "iso:country":"NE",
    "wof:name":"Diginasa Kaina",
    "wof:placetype":"locality"
},
  "geometry": {"coordinates":[2.24766,14.32189],"type":"Point"}
}