{
  "type": "Feature",
  "properties": {
    "gn:admin1_code":"7.0",
    "gn:asciiname":"Sandi",
    "gn:country_code":"NE",
    "gn:dem":506,
    "gn:feature_class":"P",
    "gn:feature_code":"PPL",
    "gn:name":"Sandi",
    "gn:population":0,
    "gn:timezone":"Africa/Niamey",
    "iso:country":"NE",
    "wof:name":"Sandi",
    "wof:placetype":"locality"
},
  "geometry": {"coordinates":[10.0776,14.4125],"type":"Point"}
}