{
  "type": "Feature",
  "properties": {
    "gn:admin1_code":"7.0",
    "gn:asciiname":"Koulou",
    "gn:country_code":"NE",
    "gn:dem":393,
    "gn:feature_class":"P",
    "gn:feature_code":"PPL",
    "gn:name":"Koulou",
    "gn:population":0,
    "gn:timezone":"Africa/Niamey",
    "iso:country":"NE",
    "name:fin_x_preferred":[
        "Koulou"
    ],
    "name:fra_x_preferred":[
        "Koulou"
    ],
    "name:ita_x_preferred":[
        "Koulou"
    ],
    "name:nld_x_preferred":[
        "Koulou"
    ],
    "name:spa_x_preferred":[
        "Koulou"
    ],
    "wof:name":"Koulou",
    "wof:placetype":"locality"
},
  "geometry": {"coordinates":[8.93821,12.98787],"type":"Point"}
}