{
  "type": "Feature",
  "properties": {
    "gn:admin1_code":"6.0",
    "gn:asciiname":"Lougou",
    "gn:country_code":"NE",
    "gn:dem":360,
    "gn:feature_class":"P",
    "gn:feature_code":"PPL",
    "gn:name":"Lougou",
    "gn:population":0,
    "gn:timezone":"Africa/Niamey",
    "iso:country":"NE",
    "name:ceb_x_preferred":[
        "Lougou"
    ],
    "name:ita_x_preferred":[
        "Lougou"
    ],
    "name:msa_x_preferred":[
        "Lougou"
    ],
    "name:swe_x_preferred":[
        "Lougou"
    ],
    "wof:name":"Lougou",
    "wof:placetype":"locality"
},
  "geometry": {"coordinates":[5.4958,14.6605],"type":"Point"}
}