{
  "type": "Feature",
  "properties": {
    "gn:admin1_code":"6.0",
    "gn:asciiname":"Gernaza",
    "gn:country_code":"NE",
    "gn:dem":313,
    "gn:feature_class":"P",
    "gn:feature_code":"PPL",
    "gn:name":"G\u00e9rnaza",
    "gn:population":0,
    "gn:timezone":"Africa/Niamey",
    "iso:country":"NE",
    "wof:name":"Gernaza",
    "wof:placetype":"locality"
},
  "geometry": {"coordinates":[4.7648,14.57303],"type":"Point"}
}