{
  "type": "Feature",
  "properties": {
    "gn:admin1_code":"2.0",
    "gn:asciiname":"Bariram",
    "gn:country_code":"NE",
    "gn:dem":344,
    "gn:feature_class":"P",
    "gn:feature_code":"PPL",
    "gn:name":"Bariram",
    "gn:population":0,
    "gn:timezone":"Africa/Niamey",
    "iso:country":"NE",
    "wof:name":"Bariram",
    "wof:placetype":"locality"
},
  "geometry": {"coordinates":[11.1484,13.4118],"type":"Point"}
}