{
  "type": "Feature",
  "properties": {
    "gn:admin1_code":"7.0",
    "gn:asciiname":"Kadiou Bari",
    "gn:country_code":"NE",
    "gn:dem":380,
    "gn:feature_class":"P",
    "gn:feature_code":"PPL",
    "gn:name":"Kadiou Bari",
    "gn:population":0,
    "gn:timezone":"Africa/Niamey",
    "iso:country":"NE",
    "wof:name":"Kadiou Bari",
    "wof:placetype":"locality"
},
  "geometry": {"coordinates":[9.3914,13.3489],"type":"Point"}
}