{
  "type": "Feature",
  "properties": {
    "gn:admin1_code":"9.0",
    "gn:asciiname":"Gabikane",
    "gn:country_code":"NE",
    "gn:dem":254,
    "gn:feature_class":"P",
    "gn:feature_code":"PPL",
    "gn:name":"Gabikan\u00e9",
    "gn:population":0,
    "gn:timezone":"Africa/Niamey",
    "iso:country":"NE",
    "wof:name":"Gabikane",
    "wof:placetype":"locality"
},
  "geometry": {"coordinates":[1.15957,13.74716],"type":"Point"}
}