{
  "type": "Feature",
  "properties": {
    "gn:admin1_code":"2.0",
    "gn:asciiname":"Kadaouram",
    "gn:country_code":"NE",
    "gn:dem":354,
    "gn:feature_class":"P",
    "gn:feature_code":"PPL",
    "gn:name":"Kadaouram",
    "gn:population":0,
    "gn:timezone":"Africa/Niamey",
    "iso:country":"NE",
    "wof:name":"Kadaouram",
    "wof:placetype":"locality"
},
  "geometry": {"coordinates":[11.05203,13.79384],"type":"Point"}
}