{
  "type": "Feature",
  "properties": {
    "gn:admin1_code":"7.0",
    "gn:asciiname":"Gafari",
    "gn:country_code":"NE",
    "gn:dem":422,
    "gn:feature_class":"P",
    "gn:feature_code":"PPL",
    "gn:name":"Gafari",
    "gn:population":0,
    "gn:timezone":"Africa/Niamey",
    "iso:country":"NE",
    "name:und_x_variant":[
        "Gaffati",
        "Gafati",
        "Gafari"
    ],
    "wof:name":"Gafari",
    "wof:placetype":"locality"
},
  "geometry": {"coordinates":[9.10813,13.83373],"type":"Point"}
}