{
  "type": "Feature",
  "properties": {
    "gn:admin1_code":"4.0",
    "gn:asciiname":"Dimoa",
    "gn:country_code":"NE",
    "gn:dem":332,
    "gn:feature_class":"P",
    "gn:feature_code":"PPL",
    "gn:name":"Dimoa",
    "gn:population":0,
    "gn:timezone":"Africa/Niamey",
    "iso:country":"NE",
    "wof:name":"Dimoa",
    "wof:placetype":"locality"
},
  "geometry": {"coordinates":[6.50525,13.56294],"type":"Point"}
}