{
  "type": "Feature",
  "properties": {
    "gn:admin1_code":"9.0",
    "gn:asciiname":"Diokoti Lamorde",
    "gn:country_code":"NE",
    "gn:dem":220,
    "gn:feature_class":"P",
    "gn:feature_code":"PPL",
    "gn:name":"Diokoti Lamord\u00e9",
    "gn:population":0,
    "gn:timezone":"Africa/Niamey",
    "iso:country":"NE",
    "name:und_x_variant":[
        "Zokoti",
        "Diokoti Lamord\u00e9"
    ],
    "wof:name":"Diokoti Lamorde",
    "wof:placetype":"locality"
},
  "geometry": {"coordinates":[2.2999,13.2981],"type":"Point"}
}