{
  "type": "Feature",
  "properties": {
    "gn:admin1_code":"6.0",
    "gn:asciiname":"Arzerori",
    "gn:country_code":"NE",
    "gn:dem":343,
    "gn:feature_class":"P",
    "gn:feature_code":"PPL",
    "gn:name":"Arz\u00e9rori",
    "gn:population":0,
    "gn:timezone":"Africa/Niamey",
    "iso:country":"NE",
    "name:und_x_variant":[
        "Arzorori",
        "Arzakori",
        "Arzarori",
        "Arz\u00e9rori"
    ],
    "wof:name":"Arzerori",
    "wof:placetype":"locality"
},
  "geometry": {"coordinates":[5.9139,14.1406],"type":"Point"}
}