{
  "type": "Feature",
  "properties": {
    "gn:admin1_code":"7.0",
    "gn:asciiname":"Dogonsouri",
    "gn:country_code":"NE",
    "gn:dem":460,
    "gn:feature_class":"P",
    "gn:feature_code":"PPL",
    "gn:name":"Dogonsouri",
    "gn:population":0,
    "gn:timezone":"Africa/Niamey",
    "iso:country":"NE",
    "wof:name":"Dogonsouri",
    "wof:placetype":"locality"
},
  "geometry": {"coordinates":[9.05267,13.91976],"type":"Point"}
}