{
  "type": "Feature",
  "properties": {
    "gn:admin1_code":"3.0",
    "gn:asciiname":"Gari-Guerou",
    "gn:country_code":"NE",
    "gn:dem":284,
    "gn:feature_class":"P",
    "gn:feature_code":"PPL",
    "gn:name":"Gari-Gu\u00e9rou",
    "gn:population":0,
    "gn:timezone":"Africa/Niamey",
    "iso:country":"NE",
    "wof:name":"Gari-Guerou",
    "wof:placetype":"locality"
},
  "geometry": {"coordinates":[3.9148,13.7521],"type":"Point"}
}