{
  "type": "Feature",
  "properties": {
    "gn:admin1_code":"4.0",
    "gn:asciiname":"Guidan Masko",
    "gn:country_code":"NE",
    "gn:dem":477,
    "gn:feature_class":"P",
    "gn:feature_code":"PPL",
    "gn:name":"Guidan Masko",
    "gn:population":0,
    "gn:timezone":"Africa/Niamey",
    "iso:country":"NE",
    "wof:name":"Guidan Masko",
    "wof:placetype":"locality"
},
  "geometry": {"coordinates":[8.5057,14.0297],"type":"Point"}
}