{
  "type": "Feature",
  "properties": {
    "gn:admin1_code":"4.0",
    "gn:asciiname":"Guidan Malam Hassane",
    "gn:country_code":"NE",
    "gn:dem":416,
    "gn:feature_class":"P",
    "gn:feature_code":"PPL",
    "gn:name":"Guidan M\u00e2lam Hassane",
    "gn:population":0,
    "gn:timezone":"Africa/Niamey",
    "iso:country":"NE",
    "wof:name":"Guidan Malam Hassane",
    "wof:placetype":"locality"
},
  "geometry": {"coordinates":[7.97544,13.79571],"type":"Point"}
}