{
  "type": "Feature",
  "properties": {
    "gn:admin1_code":"6.0",
    "gn:asciiname":"Akanzafa",
    "gn:country_code":"NE",
    "gn:dem":385,
    "gn:feature_class":"P",
    "gn:feature_code":"PPL",
    "gn:name":"Akanzafa",
    "gn:population":0,
    "gn:timezone":"Africa/Niamey",
    "iso:country":"NE",
    "wof:name":"Akanzafa",
    "wof:placetype":"locality"
},
  "geometry": {"coordinates":[5.1628,15.0184],"type":"Point"}
}