{
  "type": "Feature",
  "properties": {
    "gn:admin1_code":"4.0",
    "gn:asciiname":"Guidan Chinaou",
    "gn:country_code":"NE",
    "gn:dem":441,
    "gn:feature_class":"P",
    "gn:feature_code":"PPL",
    "gn:name":"Guidan Chinaou",
    "gn:population":0,
    "gn:timezone":"Africa/Niamey",
    "iso:country":"NE",
    "name:und_x_variant":[
        "Guidan Chinao",
        "Guidan Chinaou"
    ],
    "wof:name":"Guidan Chinaou",
    "wof:placetype":"locality"
},
  "geometry": {"coordinates":[7.77328,13.32785],"type":"Point"}
}