{
  "type": "Feature",
  "properties": {
    "gn:admin1_code":"4.0",
    "gn:asciiname":"Dawaki",
    "gn:country_code":"NE",
    "gn:dem":412,
    "gn:feature_class":"P",
    "gn:feature_code":"PPL",
    "gn:name":"Dawaki",
    "gn:population":0,
    "gn:timezone":"Africa/Niamey",
    "iso:country":"NE",
    "wof:name":"Dawaki",
    "wof:placetype":"locality"
},
  "geometry": {"coordinates":[6.51743,14.31448],"type":"Point"}
}