{
  "type": "Feature",
  "properties": {
    "gn:admin1_code":"9.0",
    "gn:asciiname":"Sinsan Kouara",
    "gn:country_code":"NE",
    "gn:dem":213,
    "gn:feature_class":"P",
    "gn:feature_code":"PPL",
    "gn:name":"Sinsan Kouara",
    "gn:population":0,
    "gn:timezone":"Africa/Niamey",
    "iso:country":"NE",
    "name:und_x_variant":[
        "Sinnsan Kaoura",
        "Sinsan Kouara"
    ],
    "wof:name":"Sinsan Kouara",
    "wof:placetype":"locality"
},
  "geometry": {"coordinates":[2.2622,13.9064],"type":"Point"}
}