{
  "type": "Feature",
  "properties": {
    "iso:country":"NE",
    "name:ara_x_preferred":[
        "\u0628\u064a\u0644\u0645\u0627"
    ],
    "name:bul_x_preferred":[
        "\u0411\u0438\u043b\u043c\u0430"
    ],
    "name:cat_x_preferred":[
        "Bilma"
    ],
    "name:ceb_x_preferred":[
        "Bilma"
    ],
    "name:ces_x_preferred":[
        "Bilma"
    ],
    "name:deu_x_preferred":[
        "Bilma"
    ],
    "name:ell_x_preferred":[
        "\u039c\u03c0\u03af\u03bb\u03bc\u03b1"
    ],
    "name:eng_x_preferred":[
        "Bilma"
    ],
    "name:epo_x_preferred":[
        "Bilma"
    ],
    "name:fin_x_preferred":[
        "Bilma"
    ],
    "name:fra_x_preferred":[
        "Bilma"
    ],
    "name:hrv_x_preferred":[
        "Bilma"
    ],
    "name:ita_x_preferred":[
        "Bilma"
    ],
    "name:jpn_x_preferred":[
        "\u30d3\u30eb\u30de"
    ],
    "name:kor_x_preferred":[
        "\ube4c\ub9c8"
    ],
    "name:lit_x_preferred":[
        "Bilma"
    ],
    "name:ltz_x_preferred":[
        "Bilma"
    ],
    "name:msa_x_preferred":[
        "Bilma"
    ],
    "name:nld_x_preferred":[
        "Bilma"
    ],
    "name:pol_x_preferred":[
        "Bilma"
    ],
    "name:por_x_preferred":[
        "Bilma"
    ],
    "name:ron_x_preferred":[
        "Bilma"
    ],
    "name:rus_x_preferred":[
        "\u0411\u0438\u043b\u044c\u043c\u0430"
    ],
    "name:spa_x_preferred":[
        "Bilma"
    ],
    "name:swe_x_preferred":[
        "Bilma"
    ],
    "name:unk_x_variant":[
        "Fort Dromard"
    ],
    "name:urd_x_preferred":[
        "\u0628\u06cc\u0644\u0645\u0627"
    ],
    "name:zho_x_preferred":[
        "\u6bd4\u723e\u99ac"
    ],
    "qs:gn_country":"NE",
    "qs:gn_fcode":"PPL",
    "qs:gn_pop":2291,
    "qs:name":"Bilma",
    "qs:name_adm0":"Niger",
    "qs:name_adm1":"Agadez",
    "qs:photos":0,
    "qs:photos_1k":0,
    "qs:photos_9k":1,
    "qs:photos_9r":1,
    "qs:photos_all":2,
    "qs:photos_sr":0,
    "qs:placetype":"Town",
    "qs:pop_sr":"4",
    "qs:woe_adm0":23424906,
    "wd:elevation":358.0,
    "wd:wordcount":519,
    "wof:name":"Bilma",
    "wof:placetype":"locality",
    "wof:population":2291
},
  "geometry": {"coordinates":[12.91643,18.68532],"type":"Point"}
}