{
  "type": "Feature",
  "properties": {
    "gn:admin1_code":"4.0",
    "gn:asciiname":"Dad'in Serki",
    "gn:country_code":"NE",
    "gn:dem":444,
    "gn:feature_class":"P",
    "gn:feature_code":"PPL",
    "gn:name":"D\u00e2d'in Serki",
    "gn:population":0,
    "gn:timezone":"Africa/Niamey",
    "iso:country":"NE",
    "wof:name":"Dad'in Serki",
    "wof:placetype":"locality"
},
  "geometry": {"coordinates":[7.39985,13.3303],"type":"Point"}
}