{
  "type": "Feature",
  "properties": {
    "gn:admin1_code":"3.0",
    "gn:asciiname":"Guillare Zarma",
    "gn:country_code":"NE",
    "gn:dem":207,
    "gn:feature_class":"P",
    "gn:feature_code":"PPL",
    "gn:name":"Guillar\u00e9 Zarma",
    "gn:population":0,
    "gn:timezone":"Africa/Niamey",
    "iso:country":"NE",
    "name:und_x_variant":[
        "Guilar\u00e9",
        "Guillar\u00e9 Zarma"
    ],
    "wof:name":"Guillare Zarma",
    "wof:placetype":"locality"
},
  "geometry": {"coordinates":[2.8375,13.1253],"type":"Point"}
}