{
  "type": "Feature",
  "properties": {
    "gn:admin1_code":"4.0",
    "gn:asciiname":"InKouregao",
    "gn:country_code":"NE",
    "gn:dem":405,
    "gn:feature_class":"P",
    "gn:feature_code":"PPL",
    "gn:name":"InKour\u00e9gao",
    "gn:population":0,
    "gn:timezone":"Africa/Niamey",
    "iso:country":"NE",
    "name:und_x_variant":[
        "Dan Kour\u00e9gao",
        "InKour\u00e9gao"
    ],
    "wof:name":"InKouregao",
    "wof:placetype":"locality"
},
  "geometry": {"coordinates":[7.04115,13.10339],"type":"Point"}
}