{
  "type": "Feature",
  "properties": {
    "gn:admin1_code":"7.0",
    "gn:asciiname":"Kamoukajatari",
    "gn:country_code":"NE",
    "gn:dem":465,
    "gn:feature_class":"P",
    "gn:feature_code":"PPL",
    "gn:name":"Kamoukajatari",
    "gn:population":0,
    "gn:timezone":"Africa/Niamey",
    "iso:country":"NE",
    "wof:name":"Kamoukajatari",
    "wof:placetype":"locality"
},
  "geometry": {"coordinates":[10.3779,14.5399],"type":"Point"}
}