{
  "type": "Feature",
  "properties": {
    "gn:admin1_code":"7.0",
    "gn:asciiname":"K'arfin Kayaou",
    "gn:country_code":"NE",
    "gn:dem":506,
    "gn:feature_class":"P",
    "gn:feature_code":"PPL",
    "gn:name":"K'arf\u00een Kayaou",
    "gn:population":0,
    "gn:timezone":"Africa/Niamey",
    "iso:country":"NE",
    "wof:name":"K'arfin Kayaou",
    "wof:placetype":"locality"
},
  "geometry": {"coordinates":[8.8366,13.93605],"type":"Point"}
}