{
  "type": "Feature",
  "properties": {
    "gn:admin1_code":"9.0",
    "gn:asciiname":"Bali Bali",
    "gn:country_code":"NE",
    "gn:dem":222,
    "gn:feature_class":"P",
    "gn:feature_code":"PPL",
    "gn:name":"Bali Bali",
    "gn:population":0,
    "gn:timezone":"Africa/Niamey",
    "iso:country":"NE",
    "wof:name":"Bali Bali",
    "wof:placetype":"locality"
},
  "geometry": {"coordinates":[1.35057,13.88847],"type":"Point"}
}