{
  "type": "Feature",
  "properties": {
    "gn:admin1_code":"4.0",
    "gn:asciiname":"Tchakye",
    "gn:country_code":"NE",
    "gn:dem":408,
    "gn:feature_class":"P",
    "gn:feature_code":"PPL",
    "gn:name":"Tchaky\u00e9",
    "gn:population":0,
    "gn:timezone":"Africa/Niamey",
    "iso:country":"NE",
    "wof:name":"Tchakye",
    "wof:placetype":"locality"
},
  "geometry": {"coordinates":[7.61147,14.15888],"type":"Point"}
}