{
  "type": "Feature",
  "properties": {
    "gn:admin1_code":"6.0",
    "gn:asciiname":"Sagoumou",
    "gn:country_code":"NE",
    "gn:dem":336,
    "gn:feature_class":"P",
    "gn:feature_code":"PPL",
    "gn:name":"Sagoumou",
    "gn:population":0,
    "gn:timezone":"Africa/Niamey",
    "iso:country":"NE",
    "name:und_x_variant":[
        "Sagoum",
        "Sagoumou"
    ],
    "wof:name":"Sagoumou",
    "wof:placetype":"locality"
},
  "geometry": {"coordinates":[5.3395,14.4466],"type":"Point"}
}