{
  "type": "Feature",
  "properties": {
    "gn:admin1_code":"9.0",
    "gn:asciiname":"Banganieri",
    "gn:country_code":"NE",
    "gn:dem":217,
    "gn:feature_class":"P",
    "gn:feature_code":"PPL",
    "gn:name":"Bangani\u00e9ri",
    "gn:population":0,
    "gn:timezone":"Africa/Niamey",
    "iso:country":"NE",
    "name:und_x_variant":[
        "Bamgu\u00e9l Nyiri",
        "Bangani\u00e9ri"
    ],
    "wof:name":"Banganieri",
    "wof:placetype":"locality"
},
  "geometry": {"coordinates":[1.81728,13.27966],"type":"Point"}
}