{
  "type": "Feature",
  "properties": {
    "gn:admin1_code":"6.0",
    "gn:asciiname":"Dogon Daji",
    "gn:country_code":"NE",
    "gn:dem":394,
    "gn:feature_class":"P",
    "gn:feature_code":"PPL",
    "gn:name":"Dogon Daji",
    "gn:population":0,
    "gn:timezone":"Africa/Niamey",
    "iso:country":"NE",
    "wof:name":"Dogon Daji",
    "wof:placetype":"locality"
},
  "geometry": {"coordinates":[5.0808,15.1654],"type":"Point"}
}