{
  "type": "Feature",
  "properties": {
    "gn:admin1_code":"3.0",
    "gn:asciiname":"Habiri",
    "gn:country_code":"NE",
    "gn:dem":180,
    "gn:feature_class":"P",
    "gn:feature_code":"PPL",
    "gn:name":"Habiri",
    "gn:population":0,
    "gn:timezone":"Africa/Niamey",
    "iso:country":"NE",
    "wof:name":"Habiri",
    "wof:placetype":"locality"
},
  "geometry": {"coordinates":[2.88773,12.82684],"type":"Point"}
}