{
  "type": "Feature",
  "properties": {
    "gn:admin1_code":"4.0",
    "gn:asciiname":"Dan Bagou",
    "gn:country_code":"NE",
    "gn:dem":406,
    "gn:feature_class":"P",
    "gn:feature_code":"PPL",
    "gn:name":"Dan Bagou",
    "gn:population":0,
    "gn:timezone":"Africa/Niamey",
    "iso:country":"NE",
    "wof:name":"Dan Bagou",
    "wof:placetype":"locality"
},
  "geometry": {"coordinates":[7.90248,13.51397],"type":"Point"}
}