{
  "type": "Feature",
  "properties": {
    "gn:admin1_code":"7.0",
    "gn:asciiname":"Kouyomari",
    "gn:country_code":"NE",
    "gn:dem":380,
    "gn:feature_class":"P",
    "gn:feature_code":"PPL",
    "gn:name":"Kouyomari",
    "gn:population":0,
    "gn:timezone":"Africa/Niamey",
    "iso:country":"NE",
    "wof:name":"Kouyomari",
    "wof:placetype":"locality"
},
  "geometry": {"coordinates":[10.7109,14.0571],"type":"Point"}
}