{
  "type": "Feature",
  "properties": {
    "gn:admin1_code":"2.0",
    "gn:asciiname":"Kasatchia",
    "gn:country_code":"NE",
    "gn:dem":322,
    "gn:feature_class":"P",
    "gn:feature_code":"PPL",
    "gn:name":"Kasatchia",
    "gn:population":0,
    "gn:timezone":"Africa/Niamey",
    "iso:country":"NE",
    "wof:name":"Kasatchia",
    "wof:placetype":"locality"
},
  "geometry": {"coordinates":[12.18251,13.46151],"type":"Point"}
}