{
  "type": "Feature",
  "properties": {
    "gn:admin1_code":"9.0",
    "gn:asciiname":"Keyan-Zarma",
    "gn:country_code":"NE",
    "gn:dem":228,
    "gn:feature_class":"P",
    "gn:feature_code":"PPL",
    "gn:name":"K\u00e9yan-Zarma",
    "gn:population":0,
    "gn:timezone":"Africa/Niamey",
    "iso:country":"NE",
    "name:und_x_variant":[
        "Kayan",
        "K\u00e9yan-Zarma"
    ],
    "wof:name":"Keyan-Zarma",
    "wof:placetype":"locality"
},
  "geometry": {"coordinates":[2.4203,13.5914],"type":"Point"}
}