{
  "type": "Feature",
  "properties": {
    "gn:admin1_code":"4.0",
    "gn:asciiname":"Madeyni Elhadji",
    "gn:country_code":"NE",
    "gn:dem":408,
    "gn:feature_class":"P",
    "gn:feature_code":"PPL",
    "gn:name":"Madeyni Elhadji",
    "gn:population":0,
    "gn:timezone":"Africa/Niamey",
    "iso:country":"NE",
    "wof:name":"Madeyni Elhadji",
    "wof:placetype":"locality"
},
  "geometry": {"coordinates":[7.16377,13.14703],"type":"Point"}
}