{
  "type": "Feature",
  "properties": {
    "gn:admin1_code":"9.0",
    "gn:asciiname":"Kossey",
    "gn:country_code":"NE",
    "gn:dem":202,
    "gn:feature_class":"P",
    "gn:feature_code":"PPL",
    "gn:name":"Kossey",
    "gn:population":0,
    "gn:timezone":"Africa/Niamey",
    "iso:country":"NE",
    "name:und_x_variant":[
        "Kosseye",
        "Kossey"
    ],
    "wof:name":"Kossey",
    "wof:placetype":"locality"
},
  "geometry": {"coordinates":[2.9156,13.5278],"type":"Point"}
}