{
  "type": "Feature",
  "properties": {
    "gn:admin1_code":"4.0",
    "gn:asciiname":"Boulama Moussa",
    "gn:country_code":"NE",
    "gn:dem":408,
    "gn:feature_class":"P",
    "gn:feature_code":"PPL",
    "gn:name":"Boul\u00e2ma Moussa",
    "gn:population":0,
    "gn:timezone":"Africa/Niamey",
    "iso:country":"NE",
    "name:und_x_variant":[
        "Bilama Mousa",
        "Bilama Moussa",
        "Boul\u00e2ma Moussa"
    ],
    "wof:name":"Boulama Moussa",
    "wof:placetype":"locality"
},
  "geometry": {"coordinates":[7.8292,13.99155],"type":"Point"}
}