{
  "type": "Feature",
  "properties": {
    "gn:admin1_code":"6.0",
    "gn:asciiname":"Guidan Ango",
    "gn:country_code":"NE",
    "gn:dem":382,
    "gn:feature_class":"P",
    "gn:feature_code":"PPL",
    "gn:name":"Guidan Ango",
    "gn:population":0,
    "gn:timezone":"Africa/Niamey",
    "iso:country":"NE",
    "name:und_x_variant":[
        "Gidan Ango",
        "Guidan Ango"
    ],
    "wof:name":"Guidan Ango",
    "wof:placetype":"locality"
},
  "geometry": {"coordinates":[5.67755,13.93551],"type":"Point"}
}