{
  "type": "Feature",
  "properties": {
    "gn:admin1_code":"3.0",
    "gn:asciiname":"Aranguie",
    "gn:country_code":"NE",
    "gn:dem":232,
    "gn:feature_class":"P",
    "gn:feature_code":"PPL",
    "gn:name":"Arangui\u00e9",
    "gn:population":0,
    "gn:timezone":"Africa/Niamey",
    "iso:country":"NE",
    "name:und_x_variant":[
        "Arangie",
        "Arangui\u00e9"
    ],
    "wof:name":"Aranguie",
    "wof:placetype":"locality"
},
  "geometry": {"coordinates":[4.06532,13.45749],"type":"Point"}
}