{
  "type": "Feature",
  "properties": {
    "gn:admin1_code":"4.0",
    "gn:asciiname":"Dan Dola",
    "gn:country_code":"NE",
    "gn:dem":423,
    "gn:feature_class":"P",
    "gn:feature_code":"PPL",
    "gn:name":"Dan Dola",
    "gn:population":0,
    "gn:timezone":"Africa/Niamey",
    "iso:country":"NE",
    "wof:name":"Dan Dola",
    "wof:placetype":"locality"
},
  "geometry": {"coordinates":[7.34052,14.64797],"type":"Point"}
}