{
  "type": "Feature",
  "properties": {
    "gn:admin1_code":"9.0",
    "gn:asciiname":"Tiela Foulbe",
    "gn:country_code":"NE",
    "gn:dem":230,
    "gn:feature_class":"P",
    "gn:feature_code":"PPL",
    "gn:name":"Ti\u00e9la Foulb\u00e9",
    "gn:population":0,
    "gn:timezone":"Africa/Niamey",
    "iso:country":"NE",
    "name:und_x_variant":[
        "Ti\u00e9la Foulb\u00e9",
        "Ty\u00e9la Foulb\u00e9"
    ],
    "wof:name":"Tiela Foulbe",
    "wof:placetype":"locality"
},
  "geometry": {"coordinates":[1.95627,12.85941],"type":"Point"}
}