{
  "type": "Feature",
  "properties": {
    "gn:admin1_code":"2.0",
    "gn:asciiname":"Ngourgouram",
    "gn:country_code":"NE",
    "gn:dem":288,
    "gn:feature_class":"P",
    "gn:feature_code":"PPL",
    "gn:name":"Ngourgouram",
    "gn:population":0,
    "gn:timezone":"Africa/Niamey",
    "iso:country":"NE",
    "wof:name":"Ngourgouram",
    "wof:placetype":"locality"
},
  "geometry": {"coordinates":[13.27425,13.65104],"type":"Point"}
}