{
  "type": "Feature",
  "properties": {
    "gn:admin1_code":"4.0",
    "gn:asciiname":"Dan Jiko",
    "gn:country_code":"NE",
    "gn:dem":406,
    "gn:feature_class":"P",
    "gn:feature_code":"PPL",
    "gn:name":"Dan Jiko",
    "gn:population":0,
    "gn:timezone":"Africa/Niamey",
    "iso:country":"NE",
    "wof:name":"Dan Jiko",
    "wof:placetype":"locality"
},
  "geometry": {"coordinates":[7.96432,13.50014],"type":"Point"}
}