{
  "type": "Feature",
  "properties": {
    "gn:admin1_code":"7.0",
    "gn:asciiname":"Bossossoua",
    "gn:country_code":"NE",
    "gn:dem":394,
    "gn:feature_class":"P",
    "gn:feature_code":"PPL",
    "gn:name":"Bossossoua",
    "gn:population":0,
    "gn:timezone":"Africa/Niamey",
    "iso:country":"NE",
    "wof:name":"Bossossoua",
    "wof:placetype":"locality"
},
  "geometry": {"coordinates":[8.92787,12.91189],"type":"Point"}
}