{
  "type": "Feature",
  "properties": {
    "gn:admin1_code":"3.0",
    "gn:asciiname":"Doundaye",
    "gn:country_code":"NE",
    "gn:dem":262,
    "gn:feature_class":"P",
    "gn:feature_code":"PPL",
    "gn:name":"Doundaye",
    "gn:population":0,
    "gn:timezone":"Africa/Niamey",
    "iso:country":"NE",
    "wof:name":"Doundaye",
    "wof:placetype":"locality"
},
  "geometry": {"coordinates":[3.8948,13.8162],"type":"Point"}
}