{
  "type": "Feature",
  "properties": {
    "gn:admin1_code":"9.0",
    "gn:asciiname":"Takousa",
    "gn:country_code":"NE",
    "gn:dem":228,
    "gn:feature_class":"P",
    "gn:feature_code":"PPL",
    "gn:name":"Takousa",
    "gn:population":0,
    "gn:timezone":"Africa/Niamey",
    "iso:country":"NE",
    "name:und_x_variant":[
        "Takoussa",
        "Takousa"
    ],
    "wof:name":"Takousa",
    "wof:placetype":"locality"
},
  "geometry": {"coordinates":[3.27,14.6391],"type":"Point"}
}