{
  "type": "Feature",
  "properties": {
    "gn:admin1_code":"7.0",
    "gn:asciiname":"Ba-dawa",
    "gn:country_code":"NE",
    "gn:dem":431,
    "gn:feature_class":"P",
    "gn:feature_code":"PPL",
    "gn:name":"B\u00e2-dawa",
    "gn:population":0,
    "gn:timezone":"Africa/Niamey",
    "iso:country":"NE",
    "wof:name":"Ba-dawa",
    "wof:placetype":"locality"
},
  "geometry": {"coordinates":[8.36228,13.58049],"type":"Point"}
}