{
  "type": "Feature",
  "properties": {
    "gn:admin1_code":"4.0",
    "gn:asciiname":"Madi",
    "gn:country_code":"NE",
    "gn:dem":360,
    "gn:feature_class":"P",
    "gn:feature_code":"PPL",
    "gn:name":"Madi",
    "gn:population":0,
    "gn:timezone":"Africa/Niamey",
    "iso:country":"NE",
    "name:cat_x_preferred":[
        "Madi"
    ],
    "name:ceb_x_preferred":[
        "Madi"
    ],
    "name:deu_x_preferred":[
        "Madi"
    ],
    "name:fra_x_preferred":[
        "Madi"
    ],
    "name:swe_x_preferred":[
        "Madi"
    ],
    "wof:name":"Madi",
    "wof:placetype":"locality"
},
  "geometry": {"coordinates":[7.01323,13.91709],"type":"Point"}
}