{
  "type": "Feature",
  "properties": {
    "gn:admin1_code":"3.0",
    "gn:asciiname":"Rizia-Zaoui",
    "gn:country_code":"NE",
    "gn:dem":239,
    "gn:feature_class":"P",
    "gn:feature_code":"PPL",
    "gn:name":"Rizia-Zaoui",
    "gn:population":0,
    "gn:timezone":"Africa/Niamey",
    "iso:country":"NE",
    "wof:name":"Rizia-Zaoui",
    "wof:placetype":"locality"
},
  "geometry": {"coordinates":[3.9603,13.905],"type":"Point"}
}