{
  "type": "Feature",
  "properties": {
    "gn:admin1_code":"9.0",
    "gn:asciiname":"Darey",
    "gn:country_code":"NE",
    "gn:dem":249,
    "gn:feature_class":"P",
    "gn:feature_code":"PPL",
    "gn:name":"Darey",
    "gn:population":0,
    "gn:timezone":"Africa/Niamey",
    "iso:country":"NE",
    "name:und_x_variant":[
        "Dar\u00e9"
    ],
    "name:yor_x_preferred":[
        "Darey"
    ],
    "wof:name":"Darey",
    "wof:placetype":"locality"
},
  "geometry": {"coordinates":[2.7488,13.6151],"type":"Point"}
}