{
  "type": "Feature",
  "properties": {
    "gn:admin1_code":"7.0",
    "gn:asciiname":"Magajeri",
    "gn:country_code":"NE",
    "gn:dem":379,
    "gn:feature_class":"P",
    "gn:feature_code":"PPL",
    "gn:name":"Magaj\u00e9ri",
    "gn:population":0,
    "gn:timezone":"Africa/Niamey",
    "iso:country":"NE",
    "wof:name":"Magajeri",
    "wof:placetype":"locality"
},
  "geometry": {"coordinates":[9.97307,13.66751],"type":"Point"}
}