{
  "type": "Feature",
  "properties": {
    "gn:admin1_code":"7.0",
    "gn:asciiname":"Kirgui Haoussa",
    "gn:country_code":"NE",
    "gn:dem":468,
    "gn:feature_class":"P",
    "gn:feature_code":"PPL",
    "gn:name":"Kirgui Haoussa",
    "gn:population":0,
    "gn:timezone":"Africa/Niamey",
    "iso:country":"NE",
    "wof:name":"Kirgui Haoussa",
    "wof:placetype":"locality"
},
  "geometry": {"coordinates":[8.51099,13.38189],"type":"Point"}
}