{
  "type": "Feature",
  "properties": {
    "gn:admin1_code":"4.0",
    "gn:asciiname":"Gaba Abarchi",
    "gn:country_code":"NE",
    "gn:dem":370,
    "gn:feature_class":"P",
    "gn:feature_code":"PPL",
    "gn:name":"Gaba Abarchi",
    "gn:population":0,
    "gn:timezone":"Africa/Niamey",
    "iso:country":"NE",
    "wof:name":"Gaba Abarchi",
    "wof:placetype":"locality"
},
  "geometry": {"coordinates":[7.17382,13.93674],"type":"Point"}
}