{
  "type": "Feature",
  "properties": {
    "gn:admin1_code":"1.0",
    "gn:asciiname":"Bezza",
    "gn:country_code":"NE",
    "gn:dem":375,
    "gn:feature_class":"P",
    "gn:feature_code":"PPL",
    "gn:name":"Bezza",
    "gn:population":0,
    "gn:timezone":"Africa/Niamey",
    "iso:country":"NE",
    "wof:name":"Bezza",
    "wof:placetype":"locality"
},
  "geometry": {"coordinates":[12.88683,18.91527],"type":"Point"}
}