{
  "type": "Feature",
  "properties": {
    "gn:admin1_code":"9.0",
    "gn:asciiname":"Ibankan",
    "gn:country_code":"NE",
    "gn:dem":242,
    "gn:feature_class":"P",
    "gn:feature_code":"PPL",
    "gn:name":"Ibankan",
    "gn:population":0,
    "gn:timezone":"Africa/Niamey",
    "iso:country":"NE",
    "name:und_x_variant":[
        "Ibankane",
        "Ibankan"
    ],
    "wof:name":"Ibankan",
    "wof:placetype":"locality"
},
  "geometry": {"coordinates":[3.6043,14.4574],"type":"Point"}
}