{
  "type": "Feature",
  "properties": {
    "gn:admin1_code":"4.0",
    "gn:asciiname":"Dan Madi",
    "gn:country_code":"NE",
    "gn:dem":393,
    "gn:feature_class":"P",
    "gn:feature_code":"PPL",
    "gn:name":"Dan Madi",
    "gn:population":0,
    "gn:timezone":"Africa/Niamey",
    "iso:country":"NE",
    "wof:name":"Dan Madi",
    "wof:placetype":"locality"
},
  "geometry": {"coordinates":[7.10747,14.06034],"type":"Point"}
}