{
  "type": "Feature",
  "properties": {
    "gn:admin1_code":"7.0",
    "gn:asciiname":"Yaguiri",
    "gn:country_code":"NE",
    "gn:dem":506,
    "gn:feature_class":"P",
    "gn:feature_code":"PPL",
    "gn:name":"Yaguiri",
    "gn:population":0,
    "gn:timezone":"Africa/Niamey",
    "iso:country":"NE",
    "wof:name":"Yaguiri",
    "wof:placetype":"locality"
},
  "geometry": {"coordinates":[9.5009,14.4318],"type":"Point"}
}