{
  "type": "Feature",
  "properties": {
    "gn:admin1_code":"9.0",
    "gn:asciiname":"Kware",
    "gn:country_code":"NE",
    "gn:dem":229,
    "gn:feature_class":"P",
    "gn:feature_code":"PPL",
    "gn:name":"Kwar\u00e9",
    "gn:population":0,
    "gn:timezone":"Africa/Niamey",
    "iso:country":"NE",
    "name:fra_x_preferred":[
        "Kware"
    ],
    "name:hau_x_preferred":[
        "Kware"
    ],
    "name:ita_x_preferred":[
        "Kware"
    ],
    "name:por_x_preferred":[
        "Kware"
    ],
    "name:spa_x_preferred":[
        "Kware"
    ],
    "wof:name":"Kware",
    "wof:placetype":"locality"
},
  "geometry": {"coordinates":[3.3545,14.4869],"type":"Point"}
}