{
  "type": "Feature",
  "properties": {
    "gn:admin1_code":"4.0",
    "gn:asciiname":"Dan Sounsou",
    "gn:country_code":"NE",
    "gn:dem":409,
    "gn:feature_class":"P",
    "gn:feature_code":"PPL",
    "gn:name":"Dan Sounsou",
    "gn:population":0,
    "gn:timezone":"Africa/Niamey",
    "iso:country":"NE",
    "wof:name":"Dan Sounsou",
    "wof:placetype":"locality"
},
  "geometry": {"coordinates":[7.5057,13.83488],"type":"Point"}
}