{
  "type": "Feature",
  "properties": {
    "gn:admin1_code":"9.0",
    "gn:asciiname":"Tonkosom",
    "gn:country_code":"NE",
    "gn:dem":282,
    "gn:feature_class":"P",
    "gn:feature_code":"PPL",
    "gn:name":"Tonkosom",
    "gn:population":0,
    "gn:timezone":"Africa/Niamey",
    "iso:country":"NE",
    "wof:name":"Tonkosom",
    "wof:placetype":"locality"
},
  "geometry": {"coordinates":[1.67786,14.80351],"type":"Point"}
}