{
  "type": "Feature",
  "properties": {
    "gn:admin1_code":"9.0",
    "gn:asciiname":"Abou Bangou",
    "gn:country_code":"NE",
    "gn:dem":241,
    "gn:feature_class":"P",
    "gn:feature_code":"PPL",
    "gn:name":"Abou Bangou",
    "gn:population":0,
    "gn:timezone":"Africa/Niamey",
    "iso:country":"NE",
    "name:und_x_variant":[
        "Bou Bangou",
        "Abou Bangou"
    ],
    "wof:name":"Abou Bangou",
    "wof:placetype":"locality"
},
  "geometry": {"coordinates":[1.309,13.9642],"type":"Point"}
}