{
  "type": "Feature",
  "properties": {
    "gn:admin1_code":"7.0",
    "gn:asciiname":"Maymagaria",
    "gn:country_code":"NE",
    "gn:dem":468,
    "gn:feature_class":"P",
    "gn:feature_code":"PPL",
    "gn:name":"Maymagaria",
    "gn:population":0,
    "gn:timezone":"Africa/Niamey",
    "iso:country":"NE",
    "wof:name":"Maymagaria",
    "wof:placetype":"locality"
},
  "geometry": {"coordinates":[8.39924,14.68132],"type":"Point"}
}