{
  "type": "Feature",
  "properties": {
    "gn:admin1_code":"4.0",
    "gn:asciiname":"Zabon Moussou",
    "gn:country_code":"NE",
    "gn:dem":411,
    "gn:feature_class":"P",
    "gn:feature_code":"PPL",
    "gn:name":"Z\u00e2bon Moussou",
    "gn:population":0,
    "gn:timezone":"Africa/Niamey",
    "iso:country":"NE",
    "name:und_x_variant":[
        "Zabon Mousou",
        "Z\u00e2bon Moussou"
    ],
    "wof:name":"Zabon Moussou",
    "wof:placetype":"locality"
},
  "geometry": {"coordinates":[7.551,13.55819],"type":"Point"}
}