{
  "type": "Feature",
  "properties": {
    "gn:admin1_code":"4.0",
    "gn:asciiname":"El Kouka",
    "gn:country_code":"NE",
    "gn:dem":453,
    "gn:feature_class":"P",
    "gn:feature_code":"PPL",
    "gn:name":"El Kouka",
    "gn:population":0,
    "gn:timezone":"Africa/Niamey",
    "iso:country":"NE",
    "wof:name":"El Kouka",
    "wof:placetype":"locality"
},
  "geometry": {"coordinates":[8.03622,14.29633],"type":"Point"}
}