{
  "type": "Feature",
  "properties": {
    "gn:admin1_code":"3.0",
    "gn:asciiname":"Fandoubon-Tombo",
    "gn:country_code":"NE",
    "gn:dem":252,
    "gn:feature_class":"P",
    "gn:feature_code":"PPL",
    "gn:name":"Fandoubon-Tombo",
    "gn:population":0,
    "gn:timezone":"Africa/Niamey",
    "iso:country":"NE",
    "wof:name":"Fandoubon-Tombo",
    "wof:placetype":"locality"
},
  "geometry": {"coordinates":[3.6049,13.4263],"type":"Point"}
}