{
  "type": "Feature",
  "properties": {
    "gn:admin1_code":"6.0",
    "gn:asciiname":"Gao Mousou",
    "gn:country_code":"NE",
    "gn:dem":318,
    "gn:feature_class":"P",
    "gn:feature_code":"PPL",
    "gn:name":"Gao Mousou",
    "gn:population":0,
    "gn:timezone":"Africa/Niamey",
    "iso:country":"NE",
    "wof:name":"Gao Mousou",
    "wof:placetype":"locality"
},
  "geometry": {"coordinates":[5.2242,14.6078],"type":"Point"}
}