{
  "type": "Feature",
  "properties": {
    "gn:admin1_code":"7.0",
    "gn:asciiname":"Dagouji",
    "gn:country_code":"NE",
    "gn:dem":410,
    "gn:feature_class":"P",
    "gn:feature_code":"PPL",
    "gn:name":"Dagouji",
    "gn:population":0,
    "gn:timezone":"Africa/Niamey",
    "iso:country":"NE",
    "wof:name":"Dagouji",
    "wof:placetype":"locality"
},
  "geometry": {"coordinates":[8.8811,13.43846],"type":"Point"}
}