{
  "type": "Feature",
  "properties": {
    "gn:admin1_code":"3.0",
    "gn:asciiname":"Malam Kwara",
    "gn:country_code":"NE",
    "gn:dem":184,
    "gn:feature_class":"P",
    "gn:feature_code":"PPL",
    "gn:name":"Malam Kwara",
    "gn:population":0,
    "gn:timezone":"Africa/Niamey",
    "iso:country":"NE",
    "name:und_x_variant":[
        "Malamkoara",
        "Malam Kwara"
    ],
    "wof:name":"Malam Kwara",
    "wof:placetype":"locality"
},
  "geometry": {"coordinates":[2.84352,12.69032],"type":"Point"}
}