{
  "type": "Feature",
  "properties": {
    "gn:admin1_code":"2.0",
    "gn:asciiname":"Kayna",
    "gn:country_code":"NE",
    "gn:dem":303,
    "gn:feature_class":"P",
    "gn:feature_code":"PPL",
    "gn:name":"Kayna",
    "gn:population":0,
    "gn:timezone":"Africa/Niamey",
    "iso:country":"NE",
    "name:bak_x_preferred":[
        "\u041a\u0430\u0439\u043d\u0430"
    ],
    "name:ceb_x_preferred":[
        "Kayna"
    ],
    "name:deu_x_preferred":[
        "Kayna"
    ],
    "name:epo_x_preferred":[
        "Kayna"
    ],
    "name:fas_x_preferred":[
        "\u06a9\u0627\u0648\u0646\u0627"
    ],
    "name:kaz_x_preferred":[
        "\u041a\u0430\u0439\u043d\u0430"
    ],
    "name:kir_x_preferred":[
        "\u041a\u0430\u0439\u043d\u0430"
    ],
    "name:nld_x_preferred":[
        "Kayna"
    ],
    "name:pol_x_preferred":[
        "Kayna"
    ],
    "name:ron_x_preferred":[
        "Kayna"
    ],
    "name:rus_x_preferred":[
        "\u041a\u0430\u0439\u043d\u0430"
    ],
    "name:uzb_x_preferred":[
        "Kayna"
    ],
    "name:vol_x_preferred":[
        "Kayna"
    ],
    "wof:name":"Kayna",
    "wof:placetype":"locality"
},
  "geometry": {"coordinates":[12.69043,13.40083],"type":"Point"}
}