{
  "type": "Feature",
  "properties": {
    "gn:admin1_code":"2.0",
    "gn:asciiname":"Kayna",
    "gn:country_code":"NE",
    "gn:dem":303,
    "gn:feature_class":"P",
    "gn:feature_code":"PPL",
    "gn:name":"Kayna",
    "gn:population":0,
    "gn:timezone":"Africa/Niamey",
    "iso:country":"NE",
    "wof:name":"Kayna",
    "wof:placetype":"locality"
},
  "geometry": {"coordinates":[12.69043,13.40083],"type":"Point"}
}