{
  "type": "Feature",
  "properties": {
    "gn:admin1_code":"2.0",
    "gn:asciiname":"Djaboulam I",
    "gn:country_code":"NE",
    "gn:dem":301,
    "gn:feature_class":"P",
    "gn:feature_code":"PPL",
    "gn:name":"Djaboulam I",
    "gn:population":0,
    "gn:timezone":"Africa/Niamey",
    "iso:country":"NE",
    "name:und_x_variant":[
        "Tidaoua"
    ],
    "wof:name":"Djaboulam I",
    "wof:placetype":"locality"
},
  "geometry": {"coordinates":[13.01424,13.55708],"type":"Point"}
}