{
  "type": "Feature",
  "properties": {
    "gn:admin1_code":"6.0",
    "gn:asciiname":"Dan Tari",
    "gn:country_code":"NE",
    "gn:dem":364,
    "gn:feature_class":"P",
    "gn:feature_code":"PPL",
    "gn:name":"Dan Tari",
    "gn:population":0,
    "gn:timezone":"Africa/Niamey",
    "iso:country":"NE",
    "wof:name":"Dan Tari",
    "wof:placetype":"locality"
},
  "geometry": {"coordinates":[4.7311,15.2375],"type":"Point"}
}