{
  "type": "Feature",
  "properties": {
    "gn:admin1_code":"6.0",
    "gn:asciiname":"Zangon Kelata",
    "gn:country_code":"NE",
    "gn:dem":388,
    "gn:feature_class":"P",
    "gn:feature_code":"PPL",
    "gn:name":"Zangon K\u00e9lata",
    "gn:population":0,
    "gn:timezone":"Africa/Niamey",
    "iso:country":"NE",
    "wof:name":"Zangon Kelata",
    "wof:placetype":"locality"
},
  "geometry": {"coordinates":[6.48831,14.15297],"type":"Point"}
}