{
  "type": "Feature",
  "properties": {
    "gn:admin1_code":"6.0",
    "gn:asciiname":"Guidan Naynou",
    "gn:country_code":"NE",
    "gn:dem":342,
    "gn:feature_class":"P",
    "gn:feature_code":"PPL",
    "gn:name":"Guidan Naynou",
    "gn:population":0,
    "gn:timezone":"Africa/Niamey",
    "iso:country":"NE",
    "wof:name":"Guidan Naynou",
    "wof:placetype":"locality"
},
  "geometry": {"coordinates":[6.05045,14.02489],"type":"Point"}
}