{
  "type": "Feature",
  "properties": {
    "gn:admin1_code":"7.0",
    "gn:asciiname":"Kilaloum",
    "gn:country_code":"NE",
    "gn:dem":447,
    "gn:feature_class":"P",
    "gn:feature_code":"PPL",
    "gn:name":"Kilaloum",
    "gn:population":0,
    "gn:timezone":"Africa/Niamey",
    "iso:country":"NE",
    "wof:name":"Kilaloum",
    "wof:placetype":"locality"
},
  "geometry": {"coordinates":[9.461,14.0053],"type":"Point"}
}