{
  "type": "Feature",
  "properties": {
    "gn:admin1_code":"4.0",
    "gn:asciiname":"Finande",
    "gn:country_code":"NE",
    "gn:dem":442,
    "gn:feature_class":"P",
    "gn:feature_code":"PPL",
    "gn:name":"Finand\u00e9",
    "gn:population":0,
    "gn:timezone":"Africa/Niamey",
    "iso:country":"NE",
    "name:und_x_variant":[
        "Tinadi\u00e9",
        "Finand\u00e9"
    ],
    "wof:name":"Finande",
    "wof:placetype":"locality"
},
  "geometry": {"coordinates":[7.34562,13.16664],"type":"Point"}
}