{
  "type": "Feature",
  "properties": {
    "gn:admin1_code":"2.0",
    "gn:asciiname":"Neleri",
    "gn:country_code":"NE",
    "gn:dem":295,
    "gn:feature_class":"P",
    "gn:feature_code":"PPL",
    "gn:name":"N\u00e9l\u00e9ri",
    "gn:population":0,
    "gn:timezone":"Africa/Niamey",
    "iso:country":"NE",
    "wof:name":"Neleri",
    "wof:placetype":"locality"
},
  "geometry": {"coordinates":[13.18928,13.53235],"type":"Point"}
}