{
  "type": "Feature",
  "properties": {
    "gn:admin1_code":"4.0",
    "gn:asciiname":"Baraya",
    "gn:country_code":"NE",
    "gn:dem":430,
    "gn:feature_class":"P",
    "gn:feature_code":"PPL",
    "gn:name":"Baraya",
    "gn:population":0,
    "gn:timezone":"Africa/Niamey",
    "iso:country":"NE",
    "wof:name":"Baraya",
    "wof:placetype":"locality"
},
  "geometry": {"coordinates":[7.91127,14.14847],"type":"Point"}
}