{
  "type": "Feature",
  "properties": {
    "gn:admin1_code":"7.0",
    "gn:asciiname":"Ouadja",
    "gn:country_code":"NE",
    "gn:dem":392,
    "gn:feature_class":"P",
    "gn:feature_code":"PPL",
    "gn:name":"Ouadja",
    "gn:population":0,
    "gn:timezone":"Africa/Niamey",
    "iso:country":"NE",
    "wof:name":"Ouadja",
    "wof:placetype":"locality"
},
  "geometry": {"coordinates":[10.0581,14.0319],"type":"Point"}
}