{
  "type": "Feature",
  "properties": {
    "gn:admin1_code":"9.0",
    "gn:asciiname":"Soley Gano Tondi",
    "gn:country_code":"NE",
    "gn:dem":220,
    "gn:feature_class":"P",
    "gn:feature_code":"PPL",
    "gn:name":"Sol\u00e8y Gano Tondi",
    "gn:population":0,
    "gn:timezone":"Africa/Niamey",
    "iso:country":"NE",
    "wof:name":"Soley Gano Tondi",
    "wof:placetype":"locality"
},
  "geometry": {"coordinates":[2.85724,14.17112],"type":"Point"}
}