{
  "type": "Feature",
  "properties": {
    "gn:admin1_code":"9.0",
    "gn:asciiname":"Yanga",
    "gn:country_code":"NE",
    "gn:dem":262,
    "gn:feature_class":"P",
    "gn:feature_code":"PPL",
    "gn:name":"Yanga",
    "gn:population":0,
    "gn:timezone":"Africa/Niamey",
    "iso:country":"NE",
    "wof:name":"Yanga",
    "wof:placetype":"locality"
},
  "geometry": {"coordinates":[0.79788,13.93411],"type":"Point"}
}