{
  "type": "Feature",
  "properties": {
    "gn:admin1_code":"6.0",
    "gn:asciiname":"Mougou",
    "gn:country_code":"NE",
    "gn:dem":297,
    "gn:feature_class":"P",
    "gn:feature_code":"PPL",
    "gn:name":"Mougou",
    "gn:population":0,
    "gn:timezone":"Africa/Niamey",
    "iso:country":"NE",
    "wof:name":"Mougou",
    "wof:placetype":"locality"
},
  "geometry": {"coordinates":[5.05332,13.97761],"type":"Point"}
}