{
  "type": "Feature",
  "properties": {
    "gn:admin1_code":"6.0",
    "gn:asciiname":"Ediri Mohamam",
    "gn:country_code":"NE",
    "gn:dem":387,
    "gn:feature_class":"P",
    "gn:feature_code":"PPL",
    "gn:name":"Ediri Mohamam",
    "gn:population":0,
    "gn:timezone":"Africa/Niamey",
    "iso:country":"NE",
    "wof:name":"Ediri Mohamam",
    "wof:placetype":"locality"
},
  "geometry": {"coordinates":[6.39844,14.30257],"type":"Point"}
}