{
  "type": "Feature",
  "properties": {
    "gn:admin1_code":"3.0",
    "gn:asciiname":"Angoa Gao",
    "gn:country_code":"NE",
    "gn:dem":197,
    "gn:feature_class":"P",
    "gn:feature_code":"PPL",
    "gn:name":"Angoa Gao",
    "gn:population":0,
    "gn:timezone":"Africa/Niamey",
    "iso:country":"NE",
    "wof:name":"Angoa Gao",
    "wof:placetype":"locality"
},
  "geometry": {"coordinates":[3.74124,12.71349],"type":"Point"}
}