{
  "type": "Feature",
  "properties": {
    "gn:admin1_code":"2.0",
    "gn:asciiname":"Dyangiri",
    "gn:country_code":"NE",
    "gn:dem":314,
    "gn:feature_class":"P",
    "gn:feature_code":"PPL",
    "gn:name":"Dyangiri",
    "gn:population":0,
    "gn:timezone":"Africa/Niamey",
    "iso:country":"NE",
    "wof:name":"Dyangiri",
    "wof:placetype":"locality"
},
  "geometry": {"coordinates":[12.27282,13.12273],"type":"Point"}
}