{
  "type": "Feature",
  "properties": {
    "gn:admin1_code":"7.0",
    "gn:asciiname":"Angoal Nanpapa",
    "gn:country_code":"NE",
    "gn:dem":390,
    "gn:feature_class":"P",
    "gn:feature_code":"PPL",
    "gn:name":"Angoal Nanpapa",
    "gn:population":0,
    "gn:timezone":"Africa/Niamey",
    "iso:country":"NE",
    "wof:name":"Angoal Nanpapa",
    "wof:placetype":"locality"
},
  "geometry": {"coordinates":[9.1307,13.4262],"type":"Point"}
}