{
  "type": "Feature",
  "properties": {
    "gn:admin1_code":"9.0",
    "gn:asciiname":"Zoroney",
    "gn:country_code":"NE",
    "gn:dem":203,
    "gn:feature_class":"P",
    "gn:feature_code":"PPL",
    "gn:name":"Zoroney",
    "gn:population":0,
    "gn:timezone":"Africa/Niamey",
    "iso:country":"NE",
    "wof:name":"Zoroney",
    "wof:placetype":"locality"
},
  "geometry": {"coordinates":[2.7328,13.4275],"type":"Point"}
}