{
  "type": "Feature",
  "properties": {
    "gn:admin1_code":"4.0",
    "gn:asciiname":"Chayin Banza",
    "gn:country_code":"NE",
    "gn:dem":439,
    "gn:feature_class":"P",
    "gn:feature_code":"PPL",
    "gn:name":"Chay\u00efn Banza",
    "gn:population":0,
    "gn:timezone":"Africa/Niamey",
    "iso:country":"NE",
    "name:und_x_variant":[
        "Chayn Banza",
        "Chay\u00efn Banza"
    ],
    "wof:name":"Chayin Banza",
    "wof:placetype":"locality"
},
  "geometry": {"coordinates":[7.5536,13.34571],"type":"Point"}
}