{
  "type": "Feature",
  "properties": {
    "gn:admin1_code":"2.0",
    "gn:asciiname":"Leguem",
    "gn:country_code":"NE",
    "gn:dem":312,
    "gn:feature_class":"P",
    "gn:feature_code":"PPL",
    "gn:name":"L\u00e9guem",
    "gn:population":0,
    "gn:timezone":"Africa/Niamey",
    "iso:country":"NE",
    "wof:name":"Leguem",
    "wof:placetype":"locality"
},
  "geometry": {"coordinates":[13.07945,14.31626],"type":"Point"}
}