{
  "type": "Feature",
  "properties": {
    "gn:admin1_code":"7.0",
    "gn:asciiname":"Mabam",
    "gn:country_code":"NE",
    "gn:dem":388,
    "gn:feature_class":"P",
    "gn:feature_code":"PPL",
    "gn:name":"Mabam",
    "gn:population":0,
    "gn:timezone":"Africa/Niamey",
    "iso:country":"NE",
    "wof:name":"Mabam",
    "wof:placetype":"locality"
},
  "geometry": {"coordinates":[8.98488,12.85921],"type":"Point"}
}