{
  "type": "Feature",
  "properties": {
    "gn:admin1_code":"6.0",
    "gn:asciiname":"Tegar",
    "gn:country_code":"NE",
    "gn:dem":369,
    "gn:feature_class":"P",
    "gn:feature_code":"PPL",
    "gn:name":"T\u00e9gar",
    "gn:population":0,
    "gn:timezone":"Africa/Niamey",
    "iso:country":"NE",
    "wof:name":"Tegar",
    "wof:placetype":"locality"
},
  "geometry": {"coordinates":[5.3387,15.0143],"type":"Point"}
}