{
  "type": "Feature",
  "properties": {
    "gn:admin1_code":"1.0",
    "gn:asciiname":"Dao Timmi",
    "gn:country_code":"NE",
    "gn:dem":431,
    "gn:feature_class":"P",
    "gn:feature_code":"PPL",
    "gn:name":"Dao Timmi",
    "gn:population":0,
    "gn:timezone":"Africa/Niamey",
    "iso:country":"NE",
    "name:und_x_variant":[
        "Dao Timni",
        "Dao Timmi"
    ],
    "wof:name":"Dao Timmi",
    "wof:placetype":"locality"
},
  "geometry": {"coordinates":[13.55099,20.5281],"type":"Point"}
}