{
  "type": "Feature",
  "properties": {
    "gn:admin1_code":"3.0",
    "gn:asciiname":"Banizoumbou Guesse",
    "gn:country_code":"NE",
    "gn:dem":207,
    "gn:feature_class":"P",
    "gn:feature_code":"PPL",
    "gn:name":"Banizoumbou Guess\u00e9",
    "gn:population":0,
    "gn:timezone":"Africa/Niamey",
    "iso:country":"NE",
    "wof:name":"Banizoumbou Guesse",
    "wof:placetype":"locality"
},
  "geometry": {"coordinates":[3.18037,12.46298],"type":"Point"}
}