{
  "type": "Feature",
  "properties": {
    "gn:admin1_code":"7.0",
    "gn:asciiname":"May Douroumi",
    "gn:country_code":"NE",
    "gn:dem":399,
    "gn:feature_class":"P",
    "gn:feature_code":"PPL",
    "gn:name":"May Douroumi",
    "gn:population":0,
    "gn:timezone":"Africa/Niamey",
    "iso:country":"NE",
    "wof:name":"May Douroumi",
    "wof:placetype":"locality"
},
  "geometry": {"coordinates":[9.03959,13.4223],"type":"Point"}
}