{
  "type": "Feature",
  "properties": {
    "gn:admin1_code":"6.0",
    "gn:asciiname":"Atakonio",
    "gn:country_code":"NE",
    "gn:dem":307,
    "gn:feature_class":"P",
    "gn:feature_code":"PPL",
    "gn:name":"Atakonio",
    "gn:population":0,
    "gn:timezone":"Africa/Niamey",
    "iso:country":"NE",
    "wof:name":"Atakonio",
    "wof:placetype":"locality"
},
  "geometry": {"coordinates":[6.15109,13.78072],"type":"Point"}
}