{
  "type": "Feature",
  "properties": {
    "gn:admin1_code":"3.0",
    "gn:asciiname":"Dolle",
    "gn:country_code":"NE",
    "gn:dem":198,
    "gn:feature_class":"P",
    "gn:feature_code":"PPL",
    "gn:name":"Doll\u00e9",
    "gn:population":0,
    "gn:timezone":"Africa/Niamey",
    "iso:country":"NE",
    "name:bak_x_preferred":[
        "\u0414\u043e\u043b\u043b\u0435"
    ],
    "name:ceb_x_preferred":[
        "Dolle"
    ],
    "name:deu_x_preferred":[
        "Dolle"
    ],
    "name:epo_x_preferred":[
        "Dolle"
    ],
    "name:fas_x_preferred":[
        "\u062f\u0648\u0644\u0647"
    ],
    "name:ita_x_preferred":[
        "Dolle"
    ],
    "name:kaz_x_preferred":[
        "\u0414\u043e\u043b\u043b\u0435"
    ],
    "name:kir_x_preferred":[
        "\u0414\u043e\u043b\u043b\u0435"
    ],
    "name:nld_x_preferred":[
        "Dolle"
    ],
    "name:pol_x_preferred":[
        "Dolle"
    ],
    "name:ron_x_preferred":[
        "Dolle"
    ],
    "name:rus_x_preferred":[
        "\u0414\u043e\u043b\u043b\u0435"
    ],
    "name:uzb_x_preferred":[
        "Dolle"
    ],
    "name:vie_x_preferred":[
        "Dolle"
    ],
    "name:vol_x_preferred":[
        "Dolle"
    ],
    "wof:name":"Dolle",
    "wof:placetype":"locality"
},
  "geometry": {"coordinates":[2.84991,12.98483],"type":"Point"}
}