{
  "type": "Feature",
  "properties": {
    "gn:admin1_code":"9.0",
    "gn:asciiname":"Dinara",
    "gn:country_code":"NE",
    "gn:dem":259,
    "gn:feature_class":"P",
    "gn:feature_code":"PPL",
    "gn:name":"Dinara",
    "gn:population":0,
    "gn:timezone":"Africa/Niamey",
    "iso:country":"NE",
    "name:ara_x_preferred":[
        "\u062c\u0628\u0644 \u062f\u064a\u0646\u0627\u0631\u0627"
    ],
    "name:bel_x_preferred":[
        "\u0414\u0437\u0456\u043d\u0430\u0440\u0430"
    ],
    "name:ben_x_preferred":[
        "\u09a6\u09bf\u09a8\u09be\u09b0\u09be"
    ],
    "name:bos_x_preferred":[
        "Dinara"
    ],
    "name:bre_x_preferred":[
        "Dinara"
    ],
    "name:bul_x_preferred":[
        "\u0414\u0438\u043d\u0430\u0440\u0430"
    ],
    "name:ceb_x_preferred":[
        "Dinara"
    ],
    "name:ces_x_preferred":[
        "Dinara"
    ],
    "name:deu_x_preferred":[
        "Dinara"
    ],
    "name:ell_x_preferred":[
        "\u039d\u03c4\u03af\u03bd\u03b1\u03c1\u03b1"
    ],
    "name:est_x_preferred":[
        "Dinara"
    ],
    "name:eus_x_preferred":[
        "Dinara"
    ],
    "name:fas_x_preferred":[
        "\u062f\u06cc\u0646\u0627\u0631\u0627"
    ],
    "name:fra_x_preferred":[
        "Dinara"
    ],
    "name:glg_x_preferred":[
        "Dinara"
    ],
    "name:heb_x_preferred":[
        "\u05d3\u05d9\u05e0\u05d0\u05e8\u05d4"
    ],
    "name:hin_x_preferred":[
        "\u0926\u093f\u0928\u093e\u0930\u093e"
    ],
    "name:hrv_x_preferred":[
        "Dinara"
    ],
    "name:hye_x_preferred":[
        "\u0534\u056b\u0576\u0561\u0580\u0561"
    ],
    "name:ind_x_preferred":[
        "Dinara"
    ],
    "name:ita_x_preferred":[
        "Dinara"
    ],
    "name:kat_x_preferred":[
        "\u10d3\u10d8\u10dc\u10d0\u10e0\u10d0"
    ],
    "name:kor_x_preferred":[
        "\ub514\ub098\ub77c\uc0b0"
    ],
    "name:lit_x_preferred":[
        "Dinara"
    ],
    "name:lmo_x_preferred":[
        "Dinara"
    ],
    "name:mkd_x_preferred":[
        "\u0414\u0438\u043d\u0430\u0440\u0430"
    ],
    "name:nld_x_preferred":[
        "Dinara"
    ],
    "name:nno_x_preferred":[
        "Dinara"
    ],
    "name:nor_x_preferred":[
        "Dinara"
    ],
    "name:pnb_x_preferred":[
        "\u062f\u06cc\u0646\u0627\u0631\u0627"
    ],
    "name:pol_x_preferred":[
        "Dinara"
    ],
    "name:por_x_preferred":[
        "Dinara"
    ],
    "name:ron_x_preferred":[
        "Dinara"
    ],
    "name:rus_x_preferred":[
        "\u0414\u0438\u043d\u0430\u0440\u0430"
    ],
    "name:slk_x_preferred":[
        "Dinara"
    ],
    "name:slv_x_preferred":[
        "Dinara"
    ],
    "name:spa_x_preferred":[
        "Dinara"
    ],
    "name:sqi_x_preferred":[
        "Malet Dinarike"
    ],
    "name:srp_x_preferred":[
        "\u0414\u0438\u043d\u0430\u0440\u0430"
    ],
    "name:swa_x_preferred":[
        "Dinara"
    ],
    "name:swe_x_preferred":[
        "Dinara"
    ],
    "name:tur_x_preferred":[
        "Dinara"
    ],
    "name:ukr_x_preferred":[
        "\u0414\u0438\u043d\u0430\u0440\u0430"
    ],
    "name:urd_x_preferred":[
        "\u0688\u0627\u0626\u06d2\u0646\u0627\u0631\u0627"
    ],
    "name:vie_x_preferred":[
        "N\u00fai Dinara"
    ],
    "name:zho_x_preferred":[
        "\u8fea\u7d0d\u62c9\u5c71"
    ],
    "wof:name":"Dinara",
    "wof:placetype":"locality"
},
  "geometry": {"coordinates":[2.6302,15.037],"type":"Point"}
}