{
  "type": "Feature",
  "properties": {
    "gn:admin1_code":"9.0",
    "gn:asciiname":"Dinara",
    "gn:country_code":"NE",
    "gn:dem":259,
    "gn:feature_class":"P",
    "gn:feature_code":"PPL",
    "gn:name":"Dinara",
    "gn:population":0,
    "gn:timezone":"Africa/Niamey",
    "iso:country":"NE",
    "wof:name":"Dinara",
    "wof:placetype":"locality"
},
  "geometry": {"coordinates":[2.6302,15.037],"type":"Point"}
}