{
  "type": "Feature",
  "properties": {
    "gn:admin1_code":"3.0",
    "gn:asciiname":"Were Guietamey Peul",
    "gn:country_code":"NE",
    "gn:dem":190,
    "gn:feature_class":"P",
    "gn:feature_code":"PPL",
    "gn:name":"W\u00e9r\u00e9 Gui\u00e9tamey Peul",
    "gn:population":0,
    "gn:timezone":"Africa/Niamey",
    "iso:country":"NE",
    "wof:name":"Were Guietamey Peul",
    "wof:placetype":"locality"
},
  "geometry": {"coordinates":[2.94243,12.90884],"type":"Point"}
}