{
  "type": "Feature",
  "properties": {
    "gn:admin1_code":"3.0",
    "gn:asciiname":"Haousawa",
    "gn:country_code":"NE",
    "gn:dem":212,
    "gn:feature_class":"P",
    "gn:feature_code":"PPL",
    "gn:name":"Haousawa",
    "gn:population":0,
    "gn:timezone":"Africa/Niamey",
    "iso:country":"NE",
    "name:und_x_variant":[
        "Naousawa",
        "Haousawa"
    ],
    "wof:name":"Haousawa",
    "wof:placetype":"locality"
},
  "geometry": {"coordinates":[4.01437,13.14415],"type":"Point"}
}