{
  "type": "Feature",
  "properties": {
    "gn:admin1_code":"9.0",
    "gn:asciiname":"Soumboulikongo",
    "gn:country_code":"NE",
    "gn:dem":253,
    "gn:feature_class":"P",
    "gn:feature_code":"PPL",
    "gn:name":"Soumboulikongo",
    "gn:population":0,
    "gn:timezone":"Africa/Niamey",
    "iso:country":"NE",
    "name:und_x_variant":[
        "Soumboullikongo",
        "Soumboulikongo"
    ],
    "wof:name":"Soumboulikongo",
    "wof:placetype":"locality"
},
  "geometry": {"coordinates":[0.93353,14.06324],"type":"Point"}
}