{
  "type": "Feature",
  "properties": {
    "gn:admin1_code":"3.0",
    "gn:asciiname":"Deytigui-Niondou",
    "gn:country_code":"NE",
    "gn:dem":228,
    "gn:feature_class":"P",
    "gn:feature_code":"PPL",
    "gn:name":"Deytigui-Niondou",
    "gn:population":0,
    "gn:timezone":"Africa/Niamey",
    "iso:country":"NE",
    "name:und_x_variant":[
        "De\u00eftagui",
        "Dey T\u00e9gui Niondou",
        "Deytigui-Niondou"
    ],
    "wof:name":"Deytigui-Niondou",
    "wof:placetype":"locality"
},
  "geometry": {"coordinates":[3.1066,13.0574],"type":"Point"}
}