{
  "type": "Feature",
  "properties": {
    "gn:admin1_code":"7.0",
    "gn:asciiname":"Gandane",
    "gn:country_code":"NE",
    "gn:dem":450,
    "gn:feature_class":"P",
    "gn:feature_code":"PPL",
    "gn:name":"Gandane",
    "gn:population":0,
    "gn:timezone":"Africa/Niamey",
    "iso:country":"NE",
    "name:und_x_variant":[
        "Tchali",
        "Gandane"
    ],
    "wof:name":"Gandane",
    "wof:placetype":"locality"
},
  "geometry": {"coordinates":[8.36358,13.51561],"type":"Point"}
}