{
  "type": "Feature",
  "properties": {
    "gn:admin1_code":"6.0",
    "gn:asciiname":"Tabro",
    "gn:country_code":"NE",
    "gn:dem":420,
    "gn:feature_class":"P",
    "gn:feature_code":"PPL",
    "gn:name":"Tabro",
    "gn:population":0,
    "gn:timezone":"Africa/Niamey",
    "iso:country":"NE",
    "wof:name":"Tabro",
    "wof:placetype":"locality"
},
  "geometry": {"coordinates":[6.13756,14.58786],"type":"Point"}
}