{
  "type": "Feature",
  "properties": {
    "gn:admin1_code":"3.0",
    "gn:asciiname":"Gueremchi",
    "gn:country_code":"NE",
    "gn:dem":204,
    "gn:feature_class":"P",
    "gn:feature_code":"PPL",
    "gn:name":"Gu\u00e9remchi",
    "gn:population":0,
    "gn:timezone":"Africa/Niamey",
    "iso:country":"NE",
    "wof:name":"Gueremchi",
    "wof:placetype":"locality"
},
  "geometry": {"coordinates":[3.91854,13.06292],"type":"Point"}
}