{
  "type": "Feature",
  "properties": {
    "gn:admin1_code":"9.0",
    "gn:asciiname":"Bafale",
    "gn:country_code":"NE",
    "gn:dem":239,
    "gn:feature_class":"P",
    "gn:feature_code":"PPL",
    "gn:name":"Bafal\u00e9",
    "gn:population":0,
    "gn:timezone":"Africa/Niamey",
    "iso:country":"NE",
    "wof:name":"Bafale",
    "wof:placetype":"locality"
},
  "geometry": {"coordinates":[1.9035,14.6456],"type":"Point"}
}