{
  "type": "Feature",
  "properties": {
    "gn:admin1_code":"3.0",
    "gn:asciiname":"Marake Rogo",
    "gn:country_code":"NE",
    "gn:dem":241,
    "gn:feature_class":"P",
    "gn:feature_code":"PPL",
    "gn:name":"Marak\u00e9 Rogo",
    "gn:population":0,
    "gn:timezone":"Africa/Niamey",
    "iso:country":"NE",
    "name:und_x_variant":[
        "Kuarangami",
        "Marak\u00e9 Rogo"
    ],
    "wof:name":"Marake Rogo",
    "wof:placetype":"locality"
},
  "geometry": {"coordinates":[4.37289,13.65908],"type":"Point"}
}