{
  "type": "Feature",
  "properties": {
    "gn:admin1_code":"6.0",
    "gn:asciiname":"Manzou",
    "gn:country_code":"NE",
    "gn:dem":343,
    "gn:feature_class":"P",
    "gn:feature_code":"PPL",
    "gn:name":"Manzou",
    "gn:population":0,
    "gn:timezone":"Africa/Niamey",
    "iso:country":"NE",
    "wof:name":"Manzou",
    "wof:placetype":"locality"
},
  "geometry": {"coordinates":[6.32122,14.04232],"type":"Point"}
}