{
  "type": "Feature",
  "properties": {
    "gn:admin1_code":"4.0",
    "gn:asciiname":"Agar",
    "gn:country_code":"NE",
    "gn:dem":417,
    "gn:feature_class":"P",
    "gn:feature_code":"PPL",
    "gn:name":"Agar",
    "gn:population":0,
    "gn:timezone":"Africa/Niamey",
    "iso:country":"NE",
    "wof:name":"Agar",
    "wof:placetype":"locality"
},
  "geometry": {"coordinates":[7.24059,14.22936],"type":"Point"}
}