{
  "type": "Feature",
  "properties": {
    "gn:admin1_code":"4.0",
    "gn:asciiname":"Tchi-kaji",
    "gn:country_code":"NE",
    "gn:dem":367,
    "gn:feature_class":"P",
    "gn:feature_code":"PPL",
    "gn:name":"Tchi-kaji",
    "gn:population":0,
    "gn:timezone":"Africa/Niamey",
    "iso:country":"NE",
    "name:und_x_variant":[
        "Tchikadji",
        "Tchigaji",
        "Tchi-kaji"
    ],
    "wof:name":"Tchi-kaji",
    "wof:placetype":"locality"
},
  "geometry": {"coordinates":[7.12422,13.40224],"type":"Point"}
}