{
  "type": "Feature",
  "properties": {
    "gn:admin1_code":"7.0",
    "gn:asciiname":"Kalakamba",
    "gn:country_code":"NE",
    "gn:dem":470,
    "gn:feature_class":"P",
    "gn:feature_code":"PPL",
    "gn:name":"Kalakamba",
    "gn:population":0,
    "gn:timezone":"Africa/Niamey",
    "iso:country":"NE",
    "wof:name":"Kalakamba",
    "wof:placetype":"locality"
},
  "geometry": {"coordinates":[10.2932,14.2055],"type":"Point"}
}