{
  "type": "Feature",
  "properties": {
    "gn:admin1_code":"6.0",
    "gn:asciiname":"Fararat Toudou",
    "gn:country_code":"NE",
    "gn:dem":454,
    "gn:feature_class":"P",
    "gn:feature_code":"PPL",
    "gn:name":"Fararat Toudou",
    "gn:population":0,
    "gn:timezone":"Africa/Niamey",
    "iso:country":"NE",
    "wof:name":"Fararat Toudou",
    "wof:placetype":"locality"
},
  "geometry": {"coordinates":[6.05465,14.67157],"type":"Point"}
}