{
  "type": "Feature",
  "properties": {
    "gn:admin1_code":"4.0",
    "gn:asciiname":"Riguinguine",
    "gn:country_code":"NE",
    "gn:dem":436,
    "gn:feature_class":"P",
    "gn:feature_code":"PPL",
    "gn:name":"Riguinguine",
    "gn:population":0,
    "gn:timezone":"Africa/Niamey",
    "iso:country":"NE",
    "wof:name":"Riguinguine",
    "wof:placetype":"locality"
},
  "geometry": {"coordinates":[8.18442,13.45163],"type":"Point"}
}