{
  "type": "Feature",
  "properties": {
    "gn:admin1_code":"9.0",
    "gn:asciiname":"Kiki",
    "gn:country_code":"NE",
    "gn:dem":229,
    "gn:feature_class":"P",
    "gn:feature_code":"PPL",
    "gn:name":"Kiki",
    "gn:population":0,
    "gn:timezone":"Africa/Niamey",
    "iso:country":"NE",
    "name:ceb_x_preferred":[
        "Kiki"
    ],
    "name:deu_x_preferred":[
        "Kiki"
    ],
    "name:fas_x_preferred":[
        "\u06a9\u06cc\u06a9\u06cc"
    ],
    "name:fin_x_preferred":[
        "Kiki"
    ],
    "name:fra_x_preferred":[
        "Kiki"
    ],
    "name:ita_x_preferred":[
        "Kiki"
    ],
    "name:nld_x_preferred":[
        "Kiki"
    ],
    "name:pol_x_preferred":[
        "Kiki"
    ],
    "name:swe_x_preferred":[
        "Kiki"
    ],
    "name:tur_x_preferred":[
        "Kiki"
    ],
    "name:ukr_x_preferred":[
        "\u041a\u0438\u043a\u0438"
    ],
    "name:zho_x_preferred":[
        "Kiki"
    ],
    "wof:name":"Kiki",
    "wof:placetype":"locality"
},
  "geometry": {"coordinates":[1.56755,12.9851],"type":"Point"}
}