{
  "type": "Feature",
  "properties": {
    "gn:admin1_code":"4.0",
    "gn:asciiname":"Maychiara",
    "gn:country_code":"NE",
    "gn:dem":414,
    "gn:feature_class":"P",
    "gn:feature_code":"PPL",
    "gn:name":"Maychiara",
    "gn:population":0,
    "gn:timezone":"Africa/Niamey",
    "iso:country":"NE",
    "wof:name":"Maychiara",
    "wof:placetype":"locality"
},
  "geometry": {"coordinates":[6.62385,14.52207],"type":"Point"}
}