{
  "type": "Feature",
  "properties": {
    "gn:admin1_code":"1.0",
    "gn:asciiname":"Ilialene",
    "gn:country_code":"NE",
    "gn:dem":761,
    "gn:feature_class":"P",
    "gn:feature_code":"PPL",
    "gn:name":"Ilialene",
    "gn:population":0,
    "gn:timezone":"Africa/Niamey",
    "iso:country":"NE",
    "wof:name":"Ilialene",
    "wof:placetype":"locality"
},
  "geometry": {"coordinates":[9.0143,17.4672],"type":"Point"}
}