{
  "type": "Feature",
  "properties": {
    "gn:admin1_code":"4.0",
    "gn:asciiname":"Kagoum",
    "gn:country_code":"NE",
    "gn:dem":422,
    "gn:feature_class":"P",
    "gn:feature_code":"PPL",
    "gn:name":"Kagoum",
    "gn:population":0,
    "gn:timezone":"Africa/Niamey",
    "iso:country":"NE",
    "wof:name":"Kagoum",
    "wof:placetype":"locality"
},
  "geometry": {"coordinates":[7.95817,14.13258],"type":"Point"}
}