{
  "type": "Feature",
  "properties": {
    "gn:admin1_code":"9.0",
    "gn:asciiname":"Petel Ouomore",
    "gn:country_code":"NE",
    "gn:dem":296,
    "gn:feature_class":"P",
    "gn:feature_code":"PPL",
    "gn:name":"P\u00e9t\u00e9l Ouomor\u00e9",
    "gn:population":0,
    "gn:timezone":"Africa/Niamey",
    "iso:country":"NE",
    "wof:name":"Petel Ouomore",
    "wof:placetype":"locality"
},
  "geometry": {"coordinates":[0.8399,13.63595],"type":"Point"}
}