{
  "type": "Feature",
  "properties": {
    "gn:admin1_code":"3.0",
    "gn:asciiname":"Tounga Wondarou",
    "gn:country_code":"NE",
    "gn:dem":164,
    "gn:feature_class":"P",
    "gn:feature_code":"PPL",
    "gn:name":"Tounga Wondarou",
    "gn:population":0,
    "gn:timezone":"Africa/Niamey",
    "iso:country":"NE",
    "name:und_x_variant":[
        "Gwandura",
        "Wondarou",
        "Tounga Wondarou"
    ],
    "wof:name":"Tounga Wondarou",
    "wof:placetype":"locality"
},
  "geometry": {"coordinates":[3.64798,11.74435],"type":"Point"}
}