{
  "type": "Feature",
  "properties": {
    "gn:admin1_code":"3.0",
    "gn:asciiname":"Oude Ali Zarma",
    "gn:country_code":"NE",
    "gn:dem":194,
    "gn:feature_class":"P",
    "gn:feature_code":"PPL",
    "gn:name":"Oud\u00e9 Ali Zarma",
    "gn:population":0,
    "gn:timezone":"Africa/Niamey",
    "iso:country":"NE",
    "name:und_x_variant":[
        "Ound\u00e9",
        "Oud\u00e9 Ali Zarma"
    ],
    "wof:name":"Oude Ali Zarma",
    "wof:placetype":"locality"
},
  "geometry": {"coordinates":[2.9424,13.3119],"type":"Point"}
}