{
  "type": "Feature",
  "properties": {
    "gn:admin1_code":"7.0",
    "gn:asciiname":"Jan Roua",
    "gn:country_code":"NE",
    "gn:dem":460,
    "gn:feature_class":"P",
    "gn:feature_code":"PPL",
    "gn:name":"Jan Roua",
    "gn:population":0,
    "gn:timezone":"Africa/Niamey",
    "iso:country":"NE",
    "wof:name":"Jan Roua",
    "wof:placetype":"locality"
},
  "geometry": {"coordinates":[8.97978,13.89038],"type":"Point"}
}