{
  "type": "Feature",
  "properties": {
    "gn:admin1_code":"7.0",
    "gn:asciiname":"Kilakina",
    "gn:country_code":"NE",
    "gn:dem":359,
    "gn:feature_class":"P",
    "gn:feature_code":"PPL",
    "gn:name":"Kilakina",
    "gn:population":0,
    "gn:timezone":"Africa/Niamey",
    "iso:country":"NE",
    "wof:name":"Kilakina",
    "wof:placetype":"locality"
},
  "geometry": {"coordinates":[10.75103,13.7216],"type":"Point"}
}