{
  "type": "Feature",
  "properties": {
    "gn:admin1_code":"7.0",
    "gn:asciiname":"Almari",
    "gn:country_code":"NE",
    "gn:dem":453,
    "gn:feature_class":"P",
    "gn:feature_code":"PPL",
    "gn:name":"Almari",
    "gn:population":0,
    "gn:timezone":"Africa/Niamey",
    "iso:country":"NE",
    "wof:name":"Almari",
    "wof:placetype":"locality"
},
  "geometry": {"coordinates":[9.3074,13.9246],"type":"Point"}
}