{
  "type": "Feature",
  "properties": {
    "gn:admin1_code":"3.0",
    "gn:asciiname":"Ingaski",
    "gn:country_code":"NE",
    "gn:dem":179,
    "gn:feature_class":"P",
    "gn:feature_code":"PPL",
    "gn:name":"Ingaski",
    "gn:population":0,
    "gn:timezone":"Africa/Niamey",
    "iso:country":"NE",
    "name:und_x_variant":[
        "Inngaski",
        "Ingaski"
    ],
    "wof:name":"Ingaski",
    "wof:placetype":"locality"
},
  "geometry": {"coordinates":[3.48525,12.1575],"type":"Point"}
}