{
  "type": "Feature",
  "properties": {
    "gn:admin1_code":"4.0",
    "gn:asciiname":"Aladou",
    "gn:country_code":"NE",
    "gn:dem":429,
    "gn:feature_class":"P",
    "gn:feature_code":"PPL",
    "gn:name":"Aladou",
    "gn:population":0,
    "gn:timezone":"Africa/Niamey",
    "iso:country":"NE",
    "wof:name":"Aladou",
    "wof:placetype":"locality"
},
  "geometry": {"coordinates":[7.70968,13.53549],"type":"Point"}
}