{
  "type": "Feature",
  "properties": {
    "gn:admin1_code":"4.0",
    "gn:asciiname":"Kaha Samou",
    "gn:country_code":"NE",
    "gn:dem":328,
    "gn:feature_class":"P",
    "gn:feature_code":"PPL",
    "gn:name":"Kaha Samou",
    "gn:population":0,
    "gn:timezone":"Africa/Niamey",
    "iso:country":"NE",
    "wof:name":"Kaha Samou",
    "wof:placetype":"locality"
},
  "geometry": {"coordinates":[6.75961,13.60982],"type":"Point"}
}