{
  "type": "Feature",
  "properties": {
    "gn:admin1_code":"4.0",
    "gn:asciiname":"Barmo Saje",
    "gn:country_code":"NE",
    "gn:dem":404,
    "gn:feature_class":"P",
    "gn:feature_code":"PPL",
    "gn:name":"Barmo Saj\u00e9",
    "gn:population":0,
    "gn:timezone":"Africa/Niamey",
    "iso:country":"NE",
    "wof:name":"Barmo Saje",
    "wof:placetype":"locality"
},
  "geometry": {"coordinates":[7.04633,14.77267],"type":"Point"}
}