{
  "type": "Feature",
  "properties": {
    "gn:admin1_code":"4.0",
    "gn:asciiname":"Garin Kane",
    "gn:country_code":"NE",
    "gn:dem":322,
    "gn:feature_class":"P",
    "gn:feature_code":"PPL",
    "gn:name":"Garin Kan\u00e9",
    "gn:population":0,
    "gn:timezone":"Africa/Niamey",
    "iso:country":"NE",
    "wof:name":"Garin Kane",
    "wof:placetype":"locality"
},
  "geometry": {"coordinates":[6.46868,13.58135],"type":"Point"}
}