{
  "type": "Feature",
  "properties": {
    "gn:admin1_code":"6.0",
    "gn:asciiname":"Kaoura Dan Kadou",
    "gn:country_code":"NE",
    "gn:dem":338,
    "gn:feature_class":"P",
    "gn:feature_code":"PPL",
    "gn:name":"Kaoura Dan Kadou",
    "gn:population":0,
    "gn:timezone":"Africa/Niamey",
    "iso:country":"NE",
    "wof:name":"Kaoura Dan Kadou",
    "wof:placetype":"locality"
},
  "geometry": {"coordinates":[6.05,14.01667],"type":"Point"}
}