{
  "type": "Feature",
  "properties": {
    "gn:admin1_code":"4.0",
    "gn:asciiname":"Bangaja",
    "gn:country_code":"NE",
    "gn:dem":321,
    "gn:feature_class":"P",
    "gn:feature_code":"PPL",
    "gn:name":"Bangaja",
    "gn:population":0,
    "gn:timezone":"Africa/Niamey",
    "iso:country":"NE",
    "wof:name":"Bangaja",
    "wof:placetype":"locality"
},
  "geometry": {"coordinates":[6.52545,13.9278],"type":"Point"}
}