{
  "type": "Feature",
  "properties": {
    "gn:admin1_code":"4.0",
    "gn:asciiname":"Ibo Dan Jari",
    "gn:country_code":"NE",
    "gn:dem":413,
    "gn:feature_class":"P",
    "gn:feature_code":"PPL",
    "gn:name":"Ibo Dan Jari",
    "gn:population":0,
    "gn:timezone":"Africa/Niamey",
    "iso:country":"NE",
    "wof:name":"Ibo Dan Jari",
    "wof:placetype":"locality"
},
  "geometry": {"coordinates":[7.20536,14.60604],"type":"Point"}
}