{
  "type": "Feature",
  "properties": {
    "gn:admin1_code":"6.0",
    "gn:asciiname":"Soungali",
    "gn:country_code":"NE",
    "gn:dem":328,
    "gn:feature_class":"P",
    "gn:feature_code":"PPL",
    "gn:name":"Soungali",
    "gn:population":0,
    "gn:timezone":"Africa/Niamey",
    "iso:country":"NE",
    "wof:name":"Soungali",
    "wof:placetype":"locality"
},
  "geometry": {"coordinates":[6.32111,13.91688],"type":"Point"}
}