{
  "type": "Feature",
  "properties": {
    "gn:admin1_code":"2.0",
    "gn:asciiname":"Deloum",
    "gn:country_code":"NE",
    "gn:dem":302,
    "gn:feature_class":"P",
    "gn:feature_code":"PPL",
    "gn:name":"D\u00e9loum",
    "gn:population":0,
    "gn:timezone":"Africa/Niamey",
    "iso:country":"NE",
    "wof:name":"Deloum",
    "wof:placetype":"locality"
},
  "geometry": {"coordinates":[12.7903,13.38052],"type":"Point"}
}