{
  "type": "Feature",
  "properties": {
    "gn:admin1_code":"3.0",
    "gn:asciiname":"Samia",
    "gn:country_code":"NE",
    "gn:dem":452,
    "gn:feature_class":"P",
    "gn:feature_code":"PPL",
    "gn:name":"Samia",
    "gn:population":0,
    "gn:timezone":"Africa/Niamey",
    "iso:country":"NE",
    "name:ceb_x_preferred":[
        "Samia"
    ],
    "name:deu_x_preferred":[
        "Samia"
    ],
    "name:fra_x_preferred":[
        "Samia"
    ],
    "name:ita_x_preferred":[
        "Samia"
    ],
    "name:nld_x_preferred":[
        "Samia"
    ],
    "name:spa_x_preferred":[
        "Samia"
    ],
    "name:swe_x_preferred":[
        "Samia"
    ],
    "wof:name":"Samia",
    "wof:placetype":"locality"
},
  "geometry": {"coordinates":[4.05,19.35],"type":"Point"}
}