{
  "type": "Feature",
  "properties": {
    "gn:admin1_code":"2.0",
    "gn:asciiname":"Oyou Bezze Denga",
    "gn:country_code":"NE",
    "gn:dem":389,
    "gn:feature_class":"P",
    "gn:feature_code":"PPL",
    "gn:name":"Oyou Bezz\u00e9 Denga",
    "gn:population":0,
    "gn:timezone":"Africa/Niamey",
    "iso:country":"NE",
    "wof:name":"Oyou Bezze Denga",
    "wof:placetype":"locality"
},
  "geometry": {"coordinates":[13.28444,16.48194],"type":"Point"}
}